Workbook

Sheet CONCENTRADO
A1: CLAVE | B1: CONCEPTO | C1: SUBCLAVE | D1: CONCEPTO | E1: PRESUPUESTO | F1: ENERO | G1: FEBRERO | H1: MARZO | I1: ABRIL | J1: MAYO | K1: JUNIO | L1: JULIO | M1: AGOSTO | N1: SEPTIEMBRE | O1: OCTUBRE | P1: NOVIEMBRE | Q1: DICIEMBRE | R1: TOTAL ACUMULADO | S1: VARIACIÓN PRESUPUESTARÍA | T1: OBSERVACIONES
A2: MDE2025-001 | B2: DISEÑADORES BODEGA | C2: MDE2025-001 | D2: Diseñadores Bodega | F2: =IFERROR(SUMIF('ENE25'!E:E,CONCENTRADO!$C2,'ENE25'!F:F),"") -> 13900 | G2: =IFERROR(SUMIF('FEB25'!$E:$E,CONCENTRADO!$C2,'FEB25'!$F:$F),"") -> 25260.62 | H2: =IFERROR(SUMIF('MAR25'!$E:$E,CONCENTRADO!$C2,'MAR25'!$F:$F),"") -> 66007.76 | I2: =IFERROR(SUMIF('ABR25'!$E:$E,CONCENTRADO!$C2,'ABR25'!$F:$F),"") -> 42393.37 | J2: =IFERROR(SUMIF('MAY25'!$E:$E,CONCENTRADO!$C2,'MAY25'!$F:$F),"") -> 0 | K2: =IFERROR(SUMIF('JUN25'!$E:$E,CONCENTRADO!$C2,'JUN25'!$F:$F),"") -> 0 | L2: =IFERROR(SUMIF('JUL25'!$E:$E,CONCENTRADO!$C2,'JUL25'!$F:$F),"") -> 19500 | M2: =IFERROR(SUMIF('AGO25'!$E:$E,CONCENTRADO!$C2,'AGO25'!$F:$F),"") -> 0 | N2: =IFERROR(SUMIF('SEP25'!$E:$E,CONCENTRADO!$C2,'SEP25'!$F:$F),"") -> 206.03 | O2: =IFERROR(SUMIF('OCT25'!$E:$E,CONCENTRADO!$C2,'OCT25'!$F:$F),"") -> 1024.12 | P2: =IFERROR(SUMIF('NOV25'!$E:$E,CONCENTRADO!$C2,'NOV25'!$F:$F),"") -> 7256.03 | Q2: =IFERROR(SUMIF('DIC25'!$E:$E,CONCENTRADO!$C2,'DIC25'!$K:$K),"") -> 0 | R2: =SUM(K2:Q2) -> 27986.18 | S2: =$E2-$R2 -> -27986.18
A3: MDE2025-002 | B3: GASTOS FIJOS | C3: MDE2025-002A | D3: Servicio de recolección de basura y desechos industriales | F3: =IFERROR(SUMIF('ENE25'!E:E,CONCENTRADO!$C3,'ENE25'!F:F),"") -> 2650 | G3: =IFERROR(SUMIF('FEB25'!$E:$E,CONCENTRADO!$C3,'FEB25'!$F:$F),"") -> 2800 | H3: =IFERROR(SUMIF('MAR25'!$E:$E,CONCENTRADO!$C3,'MAR25'!$F:$F),"") -> 2800 | I3: =IFERROR(SUMIF('ABR25'!$E:$E,CONCENTRADO!$C3,'ABR25'!$F:$F),"") -> 2800 | J3: =IFERROR(SUMIF('MAY25'!$E:$E,CONCENTRADO!$C3,'MAY25'!$F:$F),"") -> 3500 | K3: =IFERROR(SUMIF('JUN25'!$E:$E,CONCENTRADO!$C3,'JUN25'!$F:$F),"") -> 2800 | L3: =IFERROR(SUMIF('JUL25'!$E:$E,CONCENTRADO!$C3,'JUL25'!$F:$F),"") -> 3500 | M3: =IFERROR(SUMIF('AGO25'!$E:$E,CONCENTRADO!$C3,'AGO25'!$F:$F),"") -> 2800 | N3: =IFERROR(SUMIF('SEP25'!$E:$E,CONCENTRADO!$C3,'SEP25'!$F:$F),"") -> 3000 | O3: =IFERROR(SUMIF('OCT25'!$E:$E,CONCENTRADO!$C3,'OCT25'!$F:$F),"") -> 3750 | P3: =IFERROR(SUMIF('NOV25'!$E:$E,CONCENTRADO!$C3,'NOV25'!$F:$F),"") -> 5300 | Q3: =IFERROR(SUMIF('DIC25'!$E:$E,CONCENTRADO!$C3,'DIC25'!$K:$K),"") -> 0 | R3: =SUM(K3:Q3) -> 21150 | S3: =$E3-$R3 -> -21150
C4: MDE2025-002B | D4: Agua embotellada | F4: =IFERROR(SUMIF('ENE25'!E:E,CONCENTRADO!$C4,'ENE25'!F:F),"") -> 475 | G4: =IFERROR(SUMIF('FEB25'!$E:$E,CONCENTRADO!$C4,'FEB25'!$F:$F),"") -> 473 | H4: =IFERROR(SUMIF('MAR25'!$E:$E,CONCENTRADO!$C4,'MAR25'!$F:$F),"") -> 1449 | I4: =IFERROR(SUMIF('ABR25'!$E:$E,CONCENTRADO!$C4,'ABR25'!$F:$F),"") -> 1590 | J4: =IFERROR(SUMIF('MAY25'!$E:$E,CONCENTRADO!$C4,'MAY25'!$F:$F),"") -> 1292 | K4: =IFERROR(SUMIF('JUN25'!$E:$E,CONCENTRADO!$C4,'JUN25'!$F:$F),"") -> 1400 | L4: =IFERROR(SUMIF('JUL25'!$E:$E,CONCENTRADO!$C4,'JUL25'!$F:$F),"") -> 1400 | M4: =IFERROR(SUMIF('AGO25'!$E:$E,CONCENTRADO!$C4,'AGO25'!$F:$F),"") -> 900 | N4: =IFERROR(SUMIF('SEP25'!$E:$E,CONCENTRADO!$C4,'SEP25'!$F:$F),"") -> 1550 | O4: =IFERROR(SUMIF('OCT25'!$E:$E,CONCENTRADO!$C4,'OCT25'!$F:$F),"") -> 1950 | P4: =IFERROR(SUMIF('NOV25'!$E:$E,CONCENTRADO!$C4,'NOV25'!$F:$F),"") -> 0 | Q4: =IFERROR(SUMIF('DIC25'!$E:$E,CONCENTRADO!$C4,'DIC25'!$K:$K),"") -> 0 | R4: =SUM(K4:Q4) -> 7200 | S4: =$E4-$R4 -> -7200
C5: MDE2025-002C | D5: Servicio de luz | F5: =IFERROR(SUMIF('ENE25'!E:E,CONCENTRADO!$C5,'ENE25'!F:F),"") -> 4903 | G5: =IFERROR(SUMIF('FEB25'!$E:$E,CONCENTRADO!$C5,'FEB25'!$F:$F),"") -> 7177 | H5: =IFERROR(SUMIF('MAR25'!$E:$E,CONCENTRADO!$C5,'MAR25'!$F:$F),"") -> 6994 | I5: =IFERROR(SUMIF('ABR25'!$E:$E,CONCENTRADO!$C5,'ABR25'!$F:$F),"") -> 8210 | J5: =IFERROR(SUMIF('MAY25'!$E:$E,CONCENTRADO!$C5,'MAY25'!$F:$F),"") -> 9753 | K5: =IFERROR(SUMIF('JUN25'!$E:$E,CONCENTRADO!$C5,'JUN25'!$F:$F),"") -> 10921 | L5: =IFERROR(SUMIF('JUL25'!$E:$E,CONCENTRADO!$C5,'JUL25'!$F:$F),"") -> 9165.52 | M5: =IFERROR(SUMIF('AGO25'!$E:$E,CONCENTRADO!$C5,'AGO25'!$F:$F),"") -> 0 | N5: =IFERROR(SUMIF('SEP25'!$E:$E,CONCENTRADO!$C5,'SEP25'!$F:$F),"") -> 0 | O5: =IFERROR(SUMIF('OCT25'!$E:$E,CONCENTRADO!$C5,'OCT25'!$F:$F),"") -> 1500 | P5: =IFERROR(SUMIF('NOV25'!$E:$E,CONCENTRADO!$C5,'NOV25'!$F:$F),"") -> 0 | Q5: =IFERROR(SUMIF('DIC25'!$E:$E,CONCENTRADO!$C5,'DIC25'!$K:$K),"") -> 0 | R5: =SUM(K5:Q5) -> 21586.52 | S5: =$E5-$R5 -> -21586.52
C6: MDE2025-002D | D6: Rentas | F6: =IFERROR(SUMIF('ENE25'!E:E,CONCENTRADO!$C6,'ENE25'!F:F),"") -> 167327.59 | G6: =IFERROR(SUMIF('FEB25'!$E:$E,CONCENTRADO!$C6,'FEB25'!$F:$F),"") -> 87327.59 | H6: =IFERROR(SUMIF('MAR25'!$E:$E,CONCENTRADO!$C6,'MAR25'!$F:$F),"") -> 87327.59 | I6: =IFERROR(SUMIF('ABR25'!$E:$E,CONCENTRADO!$C6,'ABR25'!$F:$F),"") -> 87327.59 | J6: =IFERROR(SUMIF('MAY25'!$E:$E,CONCENTRADO!$C6,'MAY25'!$F:$F),"") -> 20771.79 | K6: =IFERROR(SUMIF('JUN25'!$E:$E,CONCENTRADO!$C6,'JUN25'!$F:$F),"") -> 80000 | L6: =IFERROR(SUMIF('JUL25'!$E:$E,CONCENTRADO!$C6,'JUL25'!$F:$F),"") -> 80000 | M6: =IFERROR(SUMIF('AGO25'!$E:$E,CONCENTRADO!$C6,'AGO25'!$F:$F),"") -> 7327.59 | N6: =IFERROR(SUMIF('SEP25'!$E:$E,CONCENTRADO!$C6,'SEP25'!$F:$F),"") -> 7327.59 | O6: =IFERROR(SUMIF('OCT25'!$E:$E,CONCENTRADO!$C6,'OCT25'!$F:$F),"") -> 7327.59 | P6: =IFERROR(SUMIF('NOV25'!$E:$E,CONCENTRADO!$C6,'NOV25'!$F:$F),"") -> 7758.62 | Q6: =IFERROR(SUMIF('DIC25'!$E:$E,CONCENTRADO!$C6,'DIC25'!$K:$K),"") -> 0 | R6: =SUM(K6:Q6) -> 189741.39 | S6: =$E6-$R6 -> -189741.39
C7: MDE2025-002E | D7: Agua potable | F7: =IFERROR(SUMIF('ENE25'!E:E,CONCENTRADO!$C7,'ENE25'!F:F),"") -> 508.01 | G7: =IFERROR(SUMIF('FEB25'!$E:$E,CONCENTRADO!$C7,'FEB25'!$F:$F),"") -> 0 | H7: =IFERROR(SUMIF('MAR25'!$E:$E,CONCENTRADO!$C7,'MAR25'!$F:$F),"") -> 496 | I7: =IFERROR(SUMIF('ABR25'!$E:$E,CONCENTRADO!$C7,'ABR25'!$F:$F),"") -> 0 | J7: =IFERROR(SUMIF('MAY25'!$E:$E,CONCENTRADO!$C7,'MAY25'!$F:$F),"") -> 388.79 | K7: =IFERROR(SUMIF('JUN25'!$E:$E,CONCENTRADO!$C7,'JUN25'!$F:$F),"") -> 0 | L7: =IFERROR(SUMIF('JUL25'!$E:$E,CONCENTRADO!$C7,'JUL25'!$F:$F),"") -> 0 | M7: =IFERROR(SUMIF('AGO25'!$E:$E,CONCENTRADO!$C7,'AGO25'!$F:$F),"") -> 0 | N7: =IFERROR(SUMIF('SEP25'!$E:$E,CONCENTRADO!$C7,'SEP25'!$F:$F),"") -> 701 | O7: =IFERROR(SUMIF('OCT25'!$E:$E,CONCENTRADO!$C7,'OCT25'!$F:$F),"") -> 0 | P7: =IFERROR(SUMIF('NOV25'!$E:$E,CONCENTRADO!$C7,'NOV25'!$F:$F),"") -> 692 | Q7: =IFERROR(SUMIF('DIC25'!$E:$E,CONCENTRADO!$C7,'DIC25'!$K:$K),"") -> 0 | R7: =SUM(K7:Q7) -> 1393 | S7: =$E7-$R7 -> -1393
C8: MDE2025-002F | D8: Servicios telefónicos e internet | F8: =IFERROR(SUMIF('ENE25'!E:E,CONCENTRADO!$C8,'ENE25'!F:F),"") -> 22436 | G8: =IFERROR(SUMIF('FEB25'!$E:$E,CONCENTRADO!$C8,'FEB25'!$F:$F),"") -> 5791 | H8: =IFERROR(SUMIF('MAR25'!$E:$E,CONCENTRADO!$C8,'MAR25'!$F:$F),"") -> 5008.63 | I8: =IFERROR(SUMIF('ABR25'!$E:$E,CONCENTRADO!$C8,'ABR25'!$F:$F),"") -> 5570.58 | J8: =IFERROR(SUMIF('MAY25'!$E:$E,CONCENTRADO!$C8,'MAY25'!$F:$F),"") -> 5570.6 | K8: =IFERROR(SUMIF('JUN25'!$E:$E,CONCENTRADO!$C8,'JUN25'!$F:$F),"") -> 3111.38 | L8: =IFERROR(SUMIF('JUL25'!$E:$E,CONCENTRADO!$C8,'JUL25'!$F:$F),"") -> 8326 | M8: =IFERROR(SUMIF('AGO25'!$E:$E,CONCENTRADO!$C8,'AGO25'!$F:$F),"") -> 4299.62 | N8: =IFERROR(SUMIF('SEP25'!$E:$E,CONCENTRADO!$C8,'SEP25'!$F:$F),"") -> 12671 | O8: =IFERROR(SUMIF('OCT25'!$E:$E,CONCENTRADO!$C8,'OCT25'!$F:$F),"") -> 1878.8 | P8: =IFERROR(SUMIF('NOV25'!$E:$E,CONCENTRADO!$C8,'NOV25'!$F:$F),"") -> 7598 | Q8: =IFERROR(SUMIF('DIC25'!$E:$E,CONCENTRADO!$C8,'DIC25'!$K:$K),"") -> 0 | R8: =SUM(K8:Q8) -> 37884.8 | S8: =$E8-$R8 -> -37884.8
C9: MDE2025-002G | D9: Comisiones e intereses bancarios | F9: =IFERROR(SUMIF('ENE25'!E:E,CONCENTRADO!$C9,'ENE25'!F:F),"") -> 9389.01 | G9: =IFERROR(SUMIF('FEB25'!$E:$E,CONCENTRADO!$C9,'FEB25'!$F:$F),"") -> 0 | H9: =IFERROR(SUMIF('MAR25'!$E:$E,CONCENTRADO!$C9,'MAR25'!$F:$F),"") -> 0 | I9: =IFERROR(SUMIF('ABR25'!$E:$E,CONCENTRADO!$C9,'ABR25'!$F:$F),"") -> 0 | J9: =IFERROR(SUMIF('MAY25'!$E:$E,CONCENTRADO!$C9,'MAY25'!$F:$F),"") -> 520 | K9: =IFERROR(SUMIF('JUN25'!$E:$E,CONCENTRADO!$C9,'JUN25'!$F:$F),"") -> 520 | L9: =IFERROR(SUMIF('JUL25'!$E:$E,CONCENTRADO!$C9,'JUL25'!$F:$F),"") -> 520 | M9: =IFERROR(SUMIF('AGO25'!$E:$E,CONCENTRADO!$C9,'AGO25'!$F:$F),"") -> 0 | N9: =IFERROR(SUMIF('SEP25'!$E:$E,CONCENTRADO!$C9,'SEP25'!$F:$F),"") -> 4520 | O9: =IFERROR(SUMIF('OCT25'!$E:$E,CONCENTRADO!$C9,'OCT25'!$F:$F),"") -> 520 | P9: =IFERROR(SUMIF('NOV25'!$E:$E,CONCENTRADO!$C9,'NOV25'!$F:$F),"") -> 520 | Q9: =IFERROR(SUMIF('DIC25'!$E:$E,CONCENTRADO!$C9,'DIC25'!$K:$K),"") -> 0 | R9: =SUM(K9:Q9) -> 6600 | S9: =$E9-$R9 -> -6600
C10: MDE2025-002H | D10: Impuesto predial | F10: =IFERROR(SUMIF('ENE25'!E:E,CONCENTRADO!$C10,'ENE25'!F:F),"") -> 0 | G10: =IFERROR(SUMIF('FEB25'!$E:$E,CONCENTRADO!$C10,'FEB25'!$F:$F),"") -> 0 | H10: =IFERROR(SUMIF('MAR25'!$E:$E,CONCENTRADO!$C10,'MAR25'!$F:$F),"") -> 0 | I10: =IFERROR(SUMIF('ABR25'!$E:$E,CONCENTRADO!$C10,'ABR25'!$F:$F),"") -> 0 | J10: =IFERROR(SUMIF('MAY25'!$E:$E,CONCENTRADO!$C10,'MAY25'!$F:$F),"") -> 0 | K10: =IFERROR(SUMIF('JUN25'!$E:$E,CONCENTRADO!$C10,'JUN25'!$F:$F),"") -> 0 | L10: =IFERROR(SUMIF('JUL25'!$E:$E,CONCENTRADO!$C10,'JUL25'!$F:$F),"") -> 0 | M10: =IFERROR(SUMIF('AGO25'!$E:$E,CONCENTRADO!$C10,'AGO25'!$F:$F),"") -> 0 | N10: =IFERROR(SUMIF('SEP25'!$E:$E,CONCENTRADO!$C10,'SEP25'!$F:$F),"") -> 0 | O10: =IFERROR(SUMIF('OCT25'!$E:$E,CONCENTRADO!$C10,'OCT25'!$F:$F),"") -> 0 | P10: =IFERROR(SUMIF('NOV25'!$E:$E,CONCENTRADO!$C10,'NOV25'!$F:$F),"") -> 0 | Q10: =IFERROR(SUMIF('DIC25'!$E:$E,CONCENTRADO!$C10,'DIC25'!$K:$K),"") -> 0 | R10: =SUM(K10:Q10) -> 0 | S10: =$E10-$R10 -> 0
C11: MDE2025-002I | D11: Social media y web master | F11: =IFERROR(SUMIF('ENE25'!E:E,CONCENTRADO!$C11,'ENE25'!F:F),"") -> 8000 | G11: =IFERROR(SUMIF('FEB25'!$E:$E,CONCENTRADO!$C11,'FEB25'!$F:$F),"") -> 8000 | H11: =IFERROR(SUMIF('MAR25'!$E:$E,CONCENTRADO!$C11,'MAR25'!$F:$F),"") -> 8000 | I11: =IFERROR(SUMIF('ABR25'!$E:$E,CONCENTRADO!$C11,'ABR25'!$F:$F),"") -> 8000 | J11: =IFERROR(SUMIF('MAY25'!$E:$E,CONCENTRADO!$C11,'MAY25'!$F:$F),"") -> 8000 | K11: =IFERROR(SUMIF('JUN25'!$E:$E,CONCENTRADO!$C11,'JUN25'!$F:$F),"") -> 8000 | L11: =IFERROR(SUMIF('JUL25'!$E:$E,CONCENTRADO!$C11,'JUL25'!$F:$F),"") -> 8000 | M11: =IFERROR(SUMIF('AGO25'!$E:$E,CONCENTRADO!$C11,'AGO25'!$F:$F),"") -> 8599 | N11: =IFERROR(SUMIF('SEP25'!$E:$E,CONCENTRADO!$C11,'SEP25'!$F:$F),"") -> 8000 | O11: =IFERROR(SUMIF('OCT25'!$E:$E,CONCENTRADO!$C11,'OCT25'!$F:$F),"") -> 8000 | P11: =IFERROR(SUMIF('NOV25'!$E:$E,CONCENTRADO!$C11,'NOV25'!$F:$F),"") -> 8000 | Q11: =IFERROR(SUMIF('DIC25'!$E:$E,CONCENTRADO!$C11,'DIC25'!$K:$K),"") -> 0 | R11: =SUM(K11:Q11) -> 48599 | S11: =$E11-$R11 -> -48599
C12: MDE2025-002J | D12: Licencias y certificaciones | F12: =IFERROR(SUMIF('ENE25'!E:E,CONCENTRADO!$C12,'ENE25'!F:F),"") -> 615.63 | G12: =IFERROR(SUMIF('FEB25'!$E:$E,CONCENTRADO!$C12,'FEB25'!$F:$F),"") -> 615.63 | H12: =IFERROR(SUMIF('MAR25'!$E:$E,CONCENTRADO!$C12,'MAR25'!$F:$F),"") -> 610.78 | I12: =IFERROR(SUMIF('ABR25'!$E:$E,CONCENTRADO!$C12,'ABR25'!$F:$F),"") -> 594.78 | J12: =IFERROR(SUMIF('MAY25'!$E:$E,CONCENTRADO!$C12,'MAY25'!$F:$F),"") -> 5646.12 | K12: =IFERROR(SUMIF('JUN25'!$E:$E,CONCENTRADO!$C12,'JUN25'!$F:$F),"") -> 130956.64 | L12: =IFERROR(SUMIF('JUL25'!$E:$E,CONCENTRADO!$C12,'JUL25'!$F:$F),"") -> 20794.9 | M12: =IFERROR(SUMIF('AGO25'!$E:$E,CONCENTRADO!$C12,'AGO25'!$F:$F),"") -> 10966.18 | N12: =IFERROR(SUMIF('SEP25'!$E:$E,CONCENTRADO!$C12,'SEP25'!$F:$F),"") -> 34466.22 | O12: =IFERROR(SUMIF('OCT25'!$E:$E,CONCENTRADO!$C12,'OCT25'!$F:$F),"") -> 3280.77 | P12: =IFERROR(SUMIF('NOV25'!$E:$E,CONCENTRADO!$C12,'NOV25'!$F:$F),"") -> 987.47 | Q12: =IFERROR(SUMIF('DIC25'!$E:$E,CONCENTRADO!$C12,'DIC25'!$K:$K),"") -> 0 | R12: =SUM(K12:Q12) -> 201452.18 | S12: =$E12-$R12 -> -201452.18
C13: MDE2025-002K | D13: Vigilancia | F13: =IFERROR(SUMIF('ENE25'!E:E,CONCENTRADO!$C13,'ENE25'!F:F),"") -> 31050 | G13: =IFERROR(SUMIF('FEB25'!$E:$E,CONCENTRADO!$C13,'FEB25'!$F:$F),"") -> 31050 | H13: =IFERROR(SUMIF('MAR25'!$E:$E,CONCENTRADO!$C13,'MAR25'!$F:$F),"") -> 31050 | I13: =IFERROR(SUMIF('ABR25'!$E:$E,CONCENTRADO!$C13,'ABR25'!$F:$F),"") -> 31050 | J13: =IFERROR(SUMIF('MAY25'!$E:$E,CONCENTRADO!$C13,'MAY25'!$F:$F),"") -> 31199 | K13: =IFERROR(SUMIF('JUN25'!$E:$E,CONCENTRADO!$C13,'JUN25'!$F:$F),"") -> 15525 | L13: =IFERROR(SUMIF('JUL25'!$E:$E,CONCENTRADO!$C13,'JUL25'!$F:$F),"") -> 31050 | M13: =IFERROR(SUMIF('AGO25'!$E:$E,CONCENTRADO!$C13,'AGO25'!$F:$F),"") -> 31050 | N13: =IFERROR(SUMIF('SEP25'!$E:$E,CONCENTRADO!$C13,'SEP25'!$F:$F),"") -> 31050 | O13: =IFERROR(SUMIF('OCT25'!$E:$E,CONCENTRADO!$C13,'OCT25'!$F:$F),"") -> 34000 | P13: =IFERROR(SUMIF('NOV25'!$E:$E,CONCENTRADO!$C13,'NOV25'!$F:$F),"") -> 0 | Q13: =IFERROR(SUMIF('DIC25'!$E:$E,CONCENTRADO!$C13,'DIC25'!$K:$K),"") -> 0 | R13: =SUM(K13:Q13) -> 142675 | S13: =$E13-$R13 -> -142675
C14: MDE2025-002L | D14: Nómina semanal bodega | F14: =IFERROR(SUMIF('ENE25'!E:E,CONCENTRADO!$C14,'ENE25'!F:F),"") -> 516623.06 | G14: =IFERROR(SUMIF('FEB25'!$E:$E,CONCENTRADO!$C14,'FEB25'!$F:$F),"") -> 112188.63 | H14: =IFERROR(SUMIF('MAR25'!$E:$E,CONCENTRADO!$C14,'MAR25'!$F:$F),"") -> 133921.07 | I14: =IFERROR(SUMIF('ABR25'!$E:$E,CONCENTRADO!$C14,'ABR25'!$F:$F),"") -> 342431.74 | J14: =IFERROR(SUMIF('MAY25'!$E:$E,CONCENTRADO!$C14,'MAY25'!$F:$F),"") -> 101410.63 | K14: =IFERROR(SUMIF('JUN25'!$E:$E,CONCENTRADO!$C14,'JUN25'!$F:$F),"") -> 117811.71 | L14: =IFERROR(SUMIF('JUL25'!$E:$E,CONCENTRADO!$C14,'JUL25'!$F:$F),"") -> 121900.52 | M14: =IFERROR(SUMIF('AGO25'!$E:$E,CONCENTRADO!$C14,'AGO25'!$F:$F),"") -> 114562.92 | N14: =IFERROR(SUMIF('SEP25'!$E:$E,CONCENTRADO!$C14,'SEP25'!$F:$F),"") -> 132689.33 | O14: =IFERROR(SUMIF('OCT25'!$E:$E,CONCENTRADO!$C14,'OCT25'!$F:$F),"") -> 3920 | P14: =IFERROR(SUMIF('NOV25'!$E:$E,CONCENTRADO!$C14,'NOV25'!$F:$F),"") -> 0 | Q14: =IFERROR(SUMIF('DIC25'!$E:$E,CONCENTRADO!$C14,'DIC25'!$K:$K),"") -> 0 | R14: =SUM(K14:Q14) -> 490884.48 | S14: =$E14-$R14 -> -490884.48
C15: MDE2025-002M | D15: Carga social de nómina semanal | F15: =IFERROR(SUMIF('ENE25'!E:E,CONCENTRADO!$C15,'ENE25'!F:F),"") -> 0 | G15: =IFERROR(SUMIF('FEB25'!$E:$E,CONCENTRADO!$C15,'FEB25'!$F:$F),"") -> 0 | H15: =IFERROR(SUMIF('MAR25'!$E:$E,CONCENTRADO!$C15,'MAR25'!$F:$F),"") -> 0 | I15: =IFERROR(SUMIF('ABR25'!$E:$E,CONCENTRADO!$C15,'ABR25'!$F:$F),"") -> 0 | J15: =IFERROR(SUMIF('MAY25'!$E:$E,CONCENTRADO!$C15,'MAY25'!$F:$F),"") -> 0 | K15: =IFERROR(SUMIF('JUN25'!$E:$E,CONCENTRADO!$C15,'JUN25'!$F:$F),"") -> 0 | L15: =IFERROR(SUMIF('JUL25'!$E:$E,CONCENTRADO!$C15,'JUL25'!$F:$F),"") -> 0 | M15: =IFERROR(SUMIF('AGO25'!$E:$E,CONCENTRADO!$C15,'AGO25'!$F:$F),"") -> 0 | N15: =IFERROR(SUMIF('SEP25'!$E:$E,CONCENTRADO!$C15,'SEP25'!$F:$F),"") -> 0 | O15: =IFERROR(SUMIF('OCT25'!$E:$E,CONCENTRADO!$C15,'OCT25'!$F:$F),"") -> 0 | P15: =IFERROR(SUMIF('NOV25'!$E:$E,CONCENTRADO!$C15,'NOV25'!$F:$F),"") -> 0 | Q15: =IFERROR(SUMIF('DIC25'!$E:$E,CONCENTRADO!$C15,'DIC25'!$K:$K),"") -> 0 | R15: =SUM(K15:Q15) -> 0 | S15: =$E15-$R15 -> 0
... C20: MDE2025-002R | D20: Nómina en efectivo | F20: =IFERROR(SUMIF('ENE25'!E:E,CONCENTRADO!$C20,'ENE25'!F:F),"") -> 0 | G20: =IFERROR(SUMIF('FEB25'!$E:$E,CONCENTRADO!$C20,'FEB25'!$F:$F),"") -> 100000 | H20: =IFERROR(SUMIF('MAR25'!$E:$E,CONCENTRADO!$C20,'MAR25'!$F:$F),"") -> 0 | I20: =IFERROR(SUMIF('ABR25'!$E:$E,CONCENTRADO!$C20,'ABR25'!$F:$F),"") -> 0 | J20: =IFERROR(SUMIF('MAY25'!$E:$E,CONCENTRADO!$C20,'MAY25'!$F:$F),"") -> 300000 | K20: =IFERROR(SUMIF('JUN25'!$E:$E,CONCENTRADO!$C20,'JUN25'!$F:$F),"") -> 300000 | L20: =IFERROR(SUMIF('JUL25'!$E:$E,CONCENTRADO!$C20,'JUL25'!$F:$F),"") -> 0 | M20: =IFERROR(SUMIF('AGO25'!$E:$E,CONCENTRADO!$C20,'AGO25'!$F:$F),"") -> 0 | N20: =IFERROR(SUMIF('SEP25'!$E:$E,CONCENTRADO!$C20,'SEP25'!$F:$F),"") -> 352112.68 | O20: =IFERROR(SUMIF('OCT25'!$E:$E,CONCENTRADO!$C20,'OCT25'!$F:$F),"") -> 0 | P20: =IFERROR(SUMIF('NOV25'!$E:$E,CONCENTRADO!$C20,'NOV25'!$F:$F),"") -> 250000 | Q20: =IFERROR(SUMIF('DIC25'!$E:$E,CONCENTRADO!$C20,'DIC25'!$K:$K),"") -> 0 | R20: =SUM(K20:Q20) -> 902112.68 | S20: =$E20-$R20 -> -902112.68
F21: =IFERROR(SUMIF('ENE25'!E:E,CONCENTRADO!$C21,'ENE25'!F:F),"") -> 0 | G21: =IFERROR(SUMIF('FEB25'!$E:$E,CONCENTRADO!$C21,'FEB25'!$F:$F),"") -> 0 | H21: =IFERROR(SUMIF('MAR25'!$E:$E,CONCENTRADO!$C21,'MAR25'!$F:$F),"") -> 0 | I21: =IFERROR(SUMIF('ABR25'!$E:$E,CONCENTRADO!$C21,'ABR25'!$F:$F),"") -> 0 | J21: =IFERROR(SUMIF('MAY25'!$E:$E,CONCENTRADO!$C21,'MAY25'!$F:$F),"") -> 0 | K21: =IFERROR(SUMIF('JUN25'!$E:$E,CONCENTRADO!$C21,'JUN25'!$F:$F),"") -> 0 | L21: =IFERROR(SUMIF('JUL25'!$E:$E,CONCENTRADO!$C21,'JUL25'!$F:$F),"") -> 0 | M21: =IFERROR(SUMIF('AGO25'!$E:$E,CONCENTRADO!$C21,'AGO25'!$F:$F),"") -> 0 | N21: =IFERROR(SUMIF('SEP25'!$E:$E,CONCENTRADO!$C21,'SEP25'!$F:$F),"") -> 0 | O21: =IFERROR(SUMIF('OCT25'!$E:$E,CONCENTRADO!$C21,'OCT25'!$F:$F),"") -> 0 | P21: =IFERROR(SUMIF('NOV25'!$E:$E,CONCENTRADO!$C21,'NOV25'!$F:$F),"") -> 0 | Q21: =IFERROR(SUMIF('DIC25'!$E:$E,CONCENTRADO!$C21,'DIC25'!$K:$K),"") -> 0 | R21: =SUM(K21:Q21) -> 0 | S21: =$E21-$R21 -> 0
F22: =IFERROR(SUMIF('ENE25'!E:E,CONCENTRADO!$C22,'ENE25'!F:F),"") -> 0 | G22: =IFERROR(SUMIF('FEB25'!$E:$E,CONCENTRADO!$C22,'FEB25'!$F:$F),"") -> 0 | H22: =IFERROR(SUMIF('MAR25'!$E:$E,CONCENTRADO!$C22,'MAR25'!$F:$F),"") -> 0 | I22: =IFERROR(SUMIF('ABR25'!$E:$E,CONCENTRADO!$C22,'ABR25'!$F:$F),"") -> 0 | J22: =IFERROR(SUMIF('MAY25'!$E:$E,CONCENTRADO!$C22,'MAY25'!$F:$F),"") -> 0 | K22: =IFERROR(SUMIF('JUN25'!$E:$E,CONCENTRADO!$C22,'JUN25'!$F:$F),"") -> 0 | L22: =IFERROR(SUMIF('JUL25'!$E:$E,CONCENTRADO!$C22,'JUL25'!$F:$F),"") -> 0 | M22: =IFERROR(SUMIF('AGO25'!$E:$E,CONCENTRADO!$C22,'AGO25'!$F:$F),"") -> 0 | N22: =IFERROR(SUMIF('SEP25'!$E:$E,CONCENTRADO!$C22,'SEP25'!$F:$F),"") -> 0 | O22: =IFERROR(SUMIF('OCT25'!$E:$E,CONCENTRADO!$C22,'OCT25'!$F:$F),"") -> 0 | P22: =IFERROR(SUMIF('NOV25'!$E:$E,CONCENTRADO!$C22,'NOV25'!$F:$F),"") -> 0 | Q22: =IFERROR(SUMIF('DIC25'!$E:$E,CONCENTRADO!$C22,'DIC25'!$K:$K),"") -> 0 | R22: =SUM(K22:Q22) -> 0 | S22: =$E22-$R22 -> 0
F23: =IFERROR(SUMIF('ENE25'!E:E,CONCENTRADO!$C23,'ENE25'!F:F),"") -> 0 | G23: =IFERROR(SUMIF('FEB25'!$E:$E,CONCENTRADO!$C23,'FEB25'!$F:$F),"") -> 0 | H23: =IFERROR(SUMIF('MAR25'!$E:$E,CONCENTRADO!$C23,'MAR25'!$F:$F),"") -> 0 | I23: =IFERROR(SUMIF('ABR25'!$E:$E,CONCENTRADO!$C23,'ABR25'!$F:$F),"") -> 0 | J23: =IFERROR(SUMIF('MAY25'!$E:$E,CONCENTRADO!$C23,'MAY25'!$F:$F),"") -> 0 | K23: =IFERROR(SUMIF('JUN25'!$E:$E,CONCENTRADO!$C23,'JUN25'!$F:$F),"") -> 0 | L23: =IFERROR(SUMIF('JUL25'!$E:$E,CONCENTRADO!$C23,'JUL25'!$F:$F),"") -> 0 | M23: =IFERROR(SUMIF('AGO25'!$E:$E,CONCENTRADO!$C23,'AGO25'!$F:$F),"") -> 0 | N23: =IFERROR(SUMIF('SEP25'!$E:$E,CONCENTRADO!$C23,'SEP25'!$F:$F),"") -> 0 | O23: =IFERROR(SUMIF('OCT25'!$E:$E,CONCENTRADO!$C23,'OCT25'!$F:$F),"") -> 0 | P23: =IFERROR(SUMIF('NOV25'!$E:$E,CONCENTRADO!$C23,'NOV25'!$F:$F),"") -> 0 | Q23: =IFERROR(SUMIF('DIC25'!$E:$E,CONCENTRADO!$C23,'DIC25'!$K:$K),"") -> 0 | R23: =SUM(K23:Q23) -> 0 | S23: =$E23-$R23 -> 0
A24: MDE 2025-003 | B24: GASTOS VARIOS | C24: MDE2025-003A | D24: Papelería e insumos de limpieza | F24: =IFERROR(SUMIF('ENE25'!E:E,CONCENTRADO!$C24,'ENE25'!F:F),"") -> 50 | G24: =IFERROR(SUMIF('FEB25'!$E:$E,CONCENTRADO!$C24,'FEB25'!$F:$F),"") -> 6595.88 | H24: =IFERROR(SUMIF('MAR25'!$E:$E,CONCENTRADO!$C24,'MAR25'!$F:$F),"") -> 90 | I24: =IFERROR(SUMIF('ABR25'!$E:$E,CONCENTRADO!$C24,'ABR25'!$F:$F),"") -> 3052.66 | J24: =IFERROR(SUMIF('MAY25'!$E:$E,CONCENTRADO!$C24,'MAY25'!$F:$F),"") -> 5575.18 | K24: =IFERROR(SUMIF('JUN25'!$E:$E,CONCENTRADO!$C24,'JUN25'!$F:$F),"") -> 2141.31 | L24: =IFERROR(SUMIF('JUL25'!$E:$E,CONCENTRADO!$C24,'JUL25'!$F:$F),"") -> 11074.64 | M24: =IFERROR(SUMIF('AGO25'!$E:$E,CONCENTRADO!$C24,'AGO25'!$F:$F),"") -> 1363.03 | N24: =IFERROR(SUMIF('SEP25'!$E:$E,CONCENTRADO!$C24,'SEP25'!$F:$F),"") -> 4684.09 | O24: =IFERROR(SUMIF('OCT25'!$E:$E,CONCENTRADO!$C24,'OCT25'!$F:$F),"") -> 8284.5 | P24: =IFERROR(SUMIF('NOV25'!$E:$E,CONCENTRADO!$C24,'NOV25'!$F:$F),"") -> 10995.36 | Q24: =IFERROR(SUMIF('DIC25'!$E:$E,CONCENTRADO!$C24,'DIC25'!$K:$K),"") -> 0 | R24: =SUM(K24:Q24) -> 38542.93 | S24: =$E24-$R24 -> -38542.93
C25: MDE2025-003B | D25: Uniformes y EPP | F25: =IFERROR(SUMIF('ENE25'!E:E,CONCENTRADO!$C25,'ENE25'!F:F),"") -> 128 | G25: =IFERROR(SUMIF('FEB25'!$E:$E,CONCENTRADO!$C25,'FEB25'!$F:$F),"") -> 3175.49 | H25: =IFERROR(SUMIF('MAR25'!$E:$E,CONCENTRADO!$C25,'MAR25'!$F:$F),"") -> 1537.1 | I25: =IFERROR(SUMIF('ABR25'!$E:$E,CONCENTRADO!$C25,'ABR25'!$F:$F),"") -> 0 | J25: =IFERROR(SUMIF('MAY25'!$E:$E,CONCENTRADO!$C25,'MAY25'!$F:$F),"") -> 0 | K25: =IFERROR(SUMIF('JUN25'!$E:$E,CONCENTRADO!$C25,'JUN25'!$F:$F),"") -> 9897 | L25: =IFERROR(SUMIF('JUL25'!$E:$E,CONCENTRADO!$C25,'JUL25'!$F:$F),"") -> 4618.98 | M25: =IFERROR(SUMIF('AGO25'!$E:$E,CONCENTRADO!$C25,'AGO25'!$F:$F),"") -> 1189.65 | N25: =IFERROR(SUMIF('SEP25'!$E:$E,CONCENTRADO!$C25,'SEP25'!$F:$F),"") -> 111.2 | O25: =IFERROR(SUMIF('OCT25'!$E:$E,CONCENTRADO!$C25,'OCT25'!$F:$F),"") -> 0 | P25: =IFERROR(SUMIF('NOV25'!$E:$E,CONCENTRADO!$C25,'NOV25'!$F:$F),"") -> 10073 | Q25: =IFERROR(SUMIF('DIC25'!$E:$E,CONCENTRADO!$C25,'DIC25'!$K:$K),"") -> 0 | R25: =SUM(K25:Q25) -> 25889.83 | S25: =$E25-$R25 -> -25889.83
C26: MDE2025-003C | D26: Telefonía e internet | F26: =IFERROR(SUMIF('ENE25'!E:E,CONCENTRADO!$C26,'ENE25'!F:F),"") -> 1684.21 | G26: =IFERROR(SUMIF('FEB25'!$E:$E,CONCENTRADO!$C26,'FEB25'!$F:$F),"") -> 100 | H26: =IFERROR(SUMIF('MAR25'!$E:$E,CONCENTRADO!$C26,'MAR25'!$F:$F),"") -> 0 | I26: =IFERROR(SUMIF('ABR25'!$E:$E,CONCENTRADO!$C26,'ABR25'!$F:$F),"") -> 0 | J26: =IFERROR(SUMIF('MAY25'!$E:$E,CONCENTRADO!$C26,'MAY25'!$F:$F),"") -> 100 | K26: =IFERROR(SUMIF('JUN25'!$E:$E,CONCENTRADO!$C26,'JUN25'!$F:$F),"") -> 0 | L26: =IFERROR(SUMIF('JUL25'!$E:$E,CONCENTRADO!$C26,'JUL25'!$F:$F),"") -> 0 | M26: =IFERROR(SUMIF('AGO25'!$E:$E,CONCENTRADO!$C26,'AGO25'!$F:$F),"") -> 0 | N26: =IFERROR(SUMIF('SEP25'!$E:$E,CONCENTRADO!$C26,'SEP25'!$F:$F),"") -> 0 | O26: =IFERROR(SUMIF('OCT25'!$E:$E,CONCENTRADO!$C26,'OCT25'!$F:$F),"") -> 0 | P26: =IFERROR(SUMIF('NOV25'!$E:$E,CONCENTRADO!$C26,'NOV25'!$F:$F),"") -> 0 | Q26: =IFERROR(SUMIF('DIC25'!$E:$E,CONCENTRADO!$C26,'DIC25'!$K:$K),"") -> 0 | R26: =SUM(K26:Q26) -> 0 | S26: =$E26-$R26 -> 0
C27: MDE2025-003D | D27: Combustibles | F27: =IFERROR(SUMIF('ENE25'!E:E,CONCENTRADO!$C27,'ENE25'!F:F),"") -> 3231.5 | G27: =IFERROR(SUMIF('FEB25'!$E:$E,CONCENTRADO!$C27,'FEB25'!$F:$F),"") -> 1283.39 | H27: =IFERROR(SUMIF('MAR25'!$E:$E,CONCENTRADO!$C27,'MAR25'!$F:$F),"") -> 4432.08 | I27: =IFERROR(SUMIF('ABR25'!$E:$E,CONCENTRADO!$C27,'ABR25'!$F:$F),"") -> 2131.41 | J27: =IFERROR(SUMIF('MAY25'!$E:$E,CONCENTRADO!$C27,'MAY25'!$F:$F),"") -> 2711.62 | K27: =IFERROR(SUMIF('JUN25'!$E:$E,CONCENTRADO!$C27,'JUN25'!$F:$F),"") -> 819.22 | L27: =IFERROR(SUMIF('JUL25'!$E:$E,CONCENTRADO!$C27,'JUL25'!$F:$F),"") -> 5090.01 | M27: =IFERROR(SUMIF('AGO25'!$E:$E,CONCENTRADO!$C27,'AGO25'!$F:$F),"") -> 2899.81 | N27: =IFERROR(SUMIF('SEP25'!$E:$E,CONCENTRADO!$C27,'SEP25'!$F:$F),"") -> 5780.66 | O27: =IFERROR(SUMIF('OCT25'!$E:$E,CONCENTRADO!$C27,'OCT25'!$F:$F),"") -> 3284.13 | P27: =IFERROR(SUMIF('NOV25'!$E:$E,CONCENTRADO!$C27,'NOV25'!$F:$F),"") -> 288.44 | Q27: =IFERROR(SUMIF('DIC25'!$E:$E,CONCENTRADO!$C27,'DIC25'!$K:$K),"") -> 0 | R27: =SUM(K27:Q27) -> 18162.27 | S27: =$E27-$R27 -> -18162.27
C28: MDE2025-003F | D28: Farmacia/salud | F28: =IFERROR(SUMIF('ENE25'!E:E,CONCENTRADO!$C28,'ENE25'!F:F),"") -> 0 | G28: =IFERROR(SUMIF('FEB25'!$E:$E,CONCENTRADO!$C28,'FEB25'!$F:$F),"") -> 0 | H28: =IFERROR(SUMIF('MAR25'!$E:$E,CONCENTRADO!$C28,'MAR25'!$F:$F),"") -> 0 | I28: =IFERROR(SUMIF('ABR25'!$E:$E,CONCENTRADO!$C28,'ABR25'!$F:$F),"") -> 0 | J28: =IFERROR(SUMIF('MAY25'!$E:$E,CONCENTRADO!$C28,'MAY25'!$F:$F),"") -> 0 | K28: =IFERROR(SUMIF('JUN25'!$E:$E,CONCENTRADO!$C28,'JUN25'!$F:$F),"") -> 0 | L28: =IFERROR(SUMIF('JUL25'!$E:$E,CONCENTRADO!$C28,'JUL25'!$F:$F),"") -> 1052.69 | M28: =IFERROR(SUMIF('AGO25'!$E:$E,CONCENTRADO!$C28,'AGO25'!$F:$F),"") -> 566.01 | N28: =IFERROR(SUMIF('SEP25'!$E:$E,CONCENTRADO!$C28,'SEP25'!$F:$F),"") -> 55 | O28: =IFERROR(SUMIF('OCT25'!$E:$E,CONCENTRADO!$C28,'OCT25'!$F:$F),"") -> 0 | P28: =IFERROR(SUMIF('NOV25'!$E:$E,CONCENTRADO!$C28,'NOV25'!$F:$F),"") -> 230.5 | Q28: =IFERROR(SUMIF('DIC25'!$E:$E,CONCENTRADO!$C28,'DIC25'!$K:$K),"") -> 0 | R28: =SUM(K28:Q28) -> 1904.2 | S28: =$E28-$R28 -> -1904.2
C29: MDE2025-003H | D29: Alimentos y consumos | F29: =IFERROR(SUMIF('ENE25'!E:E,CONCENTRADO!$C29,'ENE25'!F:F),"") -> 279 | G29: =IFERROR(SUMIF('FEB25'!$E:$E,CONCENTRADO!$C29,'FEB25'!$F:$F),"") -> 0 | H29: =IFERROR(SUMIF('MAR25'!$E:$E,CONCENTRADO!$C29,'MAR25'!$F:$F),"") -> 0 | I29: =IFERROR(SUMIF('ABR25'!$E:$E,CONCENTRADO!$C29,'ABR25'!$F:$F),"") -> 0 | J29: =IFERROR(SUMIF('MAY25'!$E:$E,CONCENTRADO!$C29,'MAY25'!$F:$F),"") -> 1612.93 | K29: =IFERROR(SUMIF('JUN25'!$E:$E,CONCENTRADO!$C29,'JUN25'!$F:$F),"") -> 16228.96 | L29: =IFERROR(SUMIF('JUL25'!$E:$E,CONCENTRADO!$C29,'JUL25'!$F:$F),"") -> 0 | M29: =IFERROR(SUMIF('AGO25'!$E:$E,CONCENTRADO!$C29,'AGO25'!$F:$F),"") -> 0 | N29: =IFERROR(SUMIF('SEP25'!$E:$E,CONCENTRADO!$C29,'SEP25'!$F:$F),"") -> 0 | O29: =IFERROR(SUMIF('OCT25'!$E:$E,CONCENTRADO!$C29,'OCT25'!$F:$F),"") -> 0 | P29: =IFERROR(SUMIF('NOV25'!$E:$E,CONCENTRADO!$C29,'NOV25'!$F:$F),"") -> 0 | Q29: =IFERROR(SUMIF('DIC25'!$E:$E,CONCENTRADO!$C29,'DIC25'!$K:$K),"") -> 0 | R29: =SUM(K29:Q29) -> 16228.96 | S29: =$E29-$R29 -> -16228.96
C30: MDE2025-003I | D30: Hospedaje staff | F30: =IFERROR(SUMIF('ENE25'!E:E,CONCENTRADO!$C30,'ENE25'!F:F),"") -> 0 | G30: =IFERROR(SUMIF('FEB25'!$E:$E,CONCENTRADO!$C30,'FEB25'!$F:$F),"") -> 0 | H30: =IFERROR(SUMIF('MAR25'!$E:$E,CONCENTRADO!$C30,'MAR25'!$F:$F),"") -> 0 | I30: =IFERROR(SUMIF('ABR25'!$E:$E,CONCENTRADO!$C30,'ABR25'!$F:$F),"") -> 0 | J30: =IFERROR(SUMIF('MAY25'!$E:$E,CONCENTRADO!$C30,'MAY25'!$F:$F),"") -> 0 | K30: =IFERROR(SUMIF('JUN25'!$E:$E,CONCENTRADO!$C30,'JUN25'!$F:$F),"") -> 0 | L30: =IFERROR(SUMIF('JUL25'!$E:$E,CONCENTRADO!$C30,'JUL25'!$F:$F),"") -> 0 | M30: =IFERROR(SUMIF('AGO25'!$E:$E,CONCENTRADO!$C30,'AGO25'!$F:$F),"") -> 0 | N30: =IFERROR(SUMIF('SEP25'!$E:$E,CONCENTRADO!$C30,'SEP25'!$F:$F),"") -> 0 | O30: =IFERROR(SUMIF('OCT25'!$E:$E,CONCENTRADO!$C30,'OCT25'!$F:$F),"") -> 0 | P30: =IFERROR(SUMIF('NOV25'!$E:$E,CONCENTRADO!$C30,'NOV25'!$F:$F),"") -> 0 | Q30: =IFERROR(SUMIF('DIC25'!$E:$E,CONCENTRADO!$C30,'DIC25'!$K:$K),"") -> 0 | R30: =SUM(K30:Q30) -> 0 | S30: =$E30-$R30 -> 0
C31: MDE2025-003J | D31: Vuelos staff | F31: =IFERROR(SUMIF('ENE25'!E:E,CONCENTRADO!$C31,'ENE25'!F:F),"") -> 0 | G31: =IFERROR(SUMIF('FEB25'!$E:$E,CONCENTRADO!$C31,'FEB25'!$F:$F),"") -> 0 | H31: =IFERROR(SUMIF('MAR25'!$E:$E,CONCENTRADO!$C31,'MAR25'!$F:$F),"") -> 0 | I31: =IFERROR(SUMIF('ABR25'!$E:$E,CONCENTRADO!$C31,'ABR25'!$F:$F),"") -> 0 | J31: =IFERROR(SUMIF('MAY25'!$E:$E,CONCENTRADO!$C31,'MAY25'!$F:$F),"") -> 0 | K31: =IFERROR(SUMIF('JUN25'!$E:$E,CONCENTRADO!$C31,'JUN25'!$F:$F),"") -> 0 | L31: =IFERROR(SUMIF('JUL25'!$E:$E,CONCENTRADO!$C31,'JUL25'!$F:$F),"") -> 0 | M31: =IFERROR(SUMIF('AGO25'!$E:$E,CONCENTRADO!$C31,'AGO25'!$F:$F),"") -> 0 | N31: =IFERROR(SUMIF('SEP25'!$E:$E,CONCENTRADO!$C31,'SEP25'!$F:$F),"") -> 0 | O31: =IFERROR(SUMIF('OCT25'!$E:$E,CONCENTRADO!$C31,'OCT25'!$F:$F),"") -> 0 | P31: =IFERROR(SUMIF('NOV25'!$E:$E,CONCENTRADO!$C31,'NOV25'!$F:$F),"") -> 0 | Q31: =IFERROR(SUMIF('DIC25'!$E:$E,CONCENTRADO!$C31,'DIC25'!$K:$K),"") -> 0 | R31: =SUM(K31:Q31) -> 0 | S31: =$E31-$R31 -> 0
C32: MDE2025-003K | D32: Proyectos futuros | F32: =IFERROR(SUMIF('ENE25'!E:E,CONCENTRADO!$C32,'ENE25'!F:F),"") -> 73260.46 | G32: =IFERROR(SUMIF('FEB25'!$E:$E,CONCENTRADO!$C32,'FEB25'!$F:$F),"") -> 42000 | H32: =IFERROR(SUMIF('MAR25'!$E:$E,CONCENTRADO!$C32,'MAR25'!$F:$F),"") -> 0 | I32: =IFERROR(SUMIF('ABR25'!$E:$E,CONCENTRADO!$C32,'ABR25'!$F:$F),"") -> 400000 | J32: =IFERROR(SUMIF('MAY25'!$E:$E,CONCENTRADO!$C32,'MAY25'!$F:$F),"") -> 0 | K32: =IFERROR(SUMIF('JUN25'!$E:$E,CONCENTRADO!$C32,'JUN25'!$F:$F),"") -> 0 | L32: =IFERROR(SUMIF('JUL25'!$E:$E,CONCENTRADO!$C32,'JUL25'!$F:$F),"") -> 0 | M32: =IFERROR(SUMIF('AGO25'!$E:$E,CONCENTRADO!$C32,'AGO25'!$F:$F),"") -> 0 | N32: =IFERROR(SUMIF('SEP25'!$E:$E,CONCENTRADO!$C32,'SEP25'!$F:$F),"") -> 0 | O32: =IFERROR(SUMIF('OCT25'!$E:$E,CONCENTRADO!$C32,'OCT25'!$F:$F),"") -> 0 | P32: =IFERROR(SUMIF('NOV25'!$E:$E,CONCENTRADO!$C32,'NOV25'!$F:$F),"") -> 210000 | Q32: =IFERROR(SUMIF('DIC25'!$E:$E,CONCENTRADO!$C32,'DIC25'!$K:$K),"") -> 0 | R32: =SUM(K32:Q32) -> 210000 | S32: =$E32-$R32 -> -210000
C33: MDE2025-003L | D33: AMEX varios | F33: =IFERROR(SUMIF('ENE25'!E:E,CONCENTRADO!$C33,'ENE25'!F:F),"") -> 0 | G33: =IFERROR(SUMIF('FEB25'!$E:$E,CONCENTRADO!$C33,'FEB25'!$F:$F),"") -> 0 | H33: =IFERROR(SUMIF('MAR25'!$E:$E,CONCENTRADO!$C33,'MAR25'!$F:$F),"") -> 44555.01 | I33: =IFERROR(SUMIF('ABR25'!$E:$E,CONCENTRADO!$C33,'ABR25'!$F:$F),"") -> 11172.34 | J33: =IFERROR(SUMIF('MAY25'!$E:$E,CONCENTRADO!$C33,'MAY25'!$F:$F),"") -> 21934.28 | K33: =IFERROR(SUMIF('JUN25'!$E:$E,CONCENTRADO!$C33,'JUN25'!$F:$F),"") -> 0 | L33: =IFERROR(SUMIF('JUL25'!$E:$E,CONCENTRADO!$C33,'JUL25'!$F:$F),"") -> 23275.4 | M33: =IFERROR(SUMIF('AGO25'!$E:$E,CONCENTRADO!$C33,'AGO25'!$F:$F),"") -> 63777.87 | N33: =IFERROR(SUMIF('SEP25'!$E:$E,CONCENTRADO!$C33,'SEP25'!$F:$F),"") -> 8923.9 | O33: =IFERROR(SUMIF('OCT25'!$E:$E,CONCENTRADO!$C33,'OCT25'!$F:$F),"") -> 29832.01 | P33: =IFERROR(SUMIF('NOV25'!$E:$E,CONCENTRADO!$C33,'NOV25'!$F:$F),"") -> 0 | Q33: =IFERROR(SUMIF('DIC25'!$E:$E,CONCENTRADO!$C33,'DIC25'!$K:$K),"") -> 0 | R33: =SUM(K33:Q33) -> 125809.18 | S33: =$E33-$R33 -> -125809.18
F34: =IFERROR(SUMIF('ENE25'!E:E,CONCENTRADO!$C34,'ENE25'!F:F),"") -> 0 | G34: =IFERROR(SUMIF('FEB25'!$E:$E,CONCENTRADO!$C34,'FEB25'!$F:$F),"") -> 0 | H34: =IFERROR(SUMIF('MAR25'!$E:$E,CONCENTRADO!$C34,'MAR25'!$F:$F),"") -> 0 | I34: =IFERROR(SUMIF('ABR25'!$E:$E,CONCENTRADO!$C34,'ABR25'!$F:$F),"") -> 0 | J34: =IFERROR(SUMIF('MAY25'!$E:$E,CONCENTRADO!$C34,'MAY25'!$F:$F),"") -> 0 | K34: =IFERROR(SUMIF('JUN25'!$E:$E,CONCENTRADO!$C34,'JUN25'!$F:$F),"") -> 0 | L34: =IFERROR(SUMIF('JUL25'!$E:$E,CONCENTRADO!$C34,'JUL25'!$F:$F),"") -> 0 | M34: =IFERROR(SUMIF('AGO25'!$E:$E,CONCENTRADO!$C34,'AGO25'!$F:$F),"") -> 0 | N34: =IFERROR(SUMIF('SEP25'!$E:$E,CONCENTRADO!$C34,'SEP25'!$F:$F),"") -> 0 | O34: =IFERROR(SUMIF('OCT25'!$E:$E,CONCENTRADO!$C34,'OCT25'!$F:$F),"") -> 0 | P34: =IFERROR(SUMIF('NOV25'!$E:$E,CONCENTRADO!$C34,'NOV25'!$F:$F),"") -> 0 | Q34: =IFERROR(SUMIF('DIC25'!$E:$E,CONCENTRADO!$C34,'DIC25'!$K:$K),"") -> 0 | R34: =SUM(K34:Q34) -> 0 | S34: =$E34-$R34 -> 0
F35: =IFERROR(SUMIF('ENE25'!E:E,CONCENTRADO!$C35,'ENE25'!F:F),"") -> 0 | G35: =IFERROR(SUMIF('FEB25'!$E:$E,CONCENTRADO!$C35,'FEB25'!$F:$F),"") -> 0 | H35: =IFERROR(SUMIF('MAR25'!$E:$E,CONCENTRADO!$C35,'MAR25'!$F:$F),"") -> 0 | I35: =IFERROR(SUMIF('ABR25'!$E:$E,CONCENTRADO!$C35,'ABR25'!$F:$F),"") -> 0 | J35: =IFERROR(SUMIF('MAY25'!$E:$E,CONCENTRADO!$C35,'MAY25'!$F:$F),"") -> 0 | K35: =IFERROR(SUMIF('JUN25'!$E:$E,CONCENTRADO!$C35,'JUN25'!$F:$F),"") -> 0 | L35: =IFERROR(SUMIF('JUL25'!$E:$E,CONCENTRADO!$C35,'JUL25'!$F:$F),"") -> 0 | M35: =IFERROR(SUMIF('AGO25'!$E:$E,CONCENTRADO!$C35,'AGO25'!$F:$F),"") -> 0 | N35: =IFERROR(SUMIF('SEP25'!$E:$E,CONCENTRADO!$C35,'SEP25'!$F:$F),"") -> 0 | O35: =IFERROR(SUMIF('OCT25'!$E:$E,CONCENTRADO!$C35,'OCT25'!$F:$F),"") -> 0 | P35: =IFERROR(SUMIF('NOV25'!$E:$E,CONCENTRADO!$C35,'NOV25'!$F:$F),"") -> 0 | Q35: =IFERROR(SUMIF('DIC25'!$E:$E,CONCENTRADO!$C35,'DIC25'!$K:$K),"") -> 0 | R35: =SUM(K35:Q35) -> 0 | S35: =$E35-$R35 -> 0
F36: =IFERROR(SUMIF('ENE25'!E:E,CONCENTRADO!$C36,'ENE25'!F:F),"") -> 0 | G36: =IFERROR(SUMIF('FEB25'!$E:$E,CONCENTRADO!$C36,'FEB25'!$F:$F),"") -> 0 | H36: =IFERROR(SUMIF('MAR25'!$E:$E,CONCENTRADO!$C36,'MAR25'!$F:$F),"") -> 0 | I36: =IFERROR(SUMIF('ABR25'!$E:$E,CONCENTRADO!$C36,'ABR25'!$F:$F),"") -> 0 | J36: =IFERROR(SUMIF('MAY25'!$E:$E,CONCENTRADO!$C36,'MAY25'!$F:$F),"") -> 0 | K36: =IFERROR(SUMIF('JUN25'!$E:$E,CONCENTRADO!$C36,'JUN25'!$F:$F),"") -> 0 | L36: =IFERROR(SUMIF('JUL25'!$E:$E,CONCENTRADO!$C36,'JUL25'!$F:$F),"") -> 0 | M36: =IFERROR(SUMIF('AGO25'!$E:$E,CONCENTRADO!$C36,'AGO25'!$F:$F),"") -> 0 | N36: =IFERROR(SUMIF('SEP25'!$E:$E,CONCENTRADO!$C36,'SEP25'!$F:$F),"") -> 0 | O36: =IFERROR(SUMIF('OCT25'!$E:$E,CONCENTRADO!$C36,'OCT25'!$F:$F),"") -> 0 | P36: =IFERROR(SUMIF('NOV25'!$E:$E,CONCENTRADO!$C36,'NOV25'!$F:$F),"") -> 0 | Q36: =IFERROR(SUMIF('DIC25'!$E:$E,CONCENTRADO!$C36,'DIC25'!$K:$K),"") -> 0 | R36: =SUM(K36:Q36) -> 0 | S36: =$E36-$R36 -> 0
A37: MDE 2025-004 | B37: MATERIALES | C37: MDE2025-004 | D37: Pool de materiales | F37: =IFERROR(SUMIF('ENE25'!E:E,CONCENTRADO!$C37,'ENE25'!F:F),"") -> 192755.6 | G37: =IFERROR(SUMIF('FEB25'!$E:$E,CONCENTRADO!$C37,'FEB25'!$F:$F),"") -> 201664.38 | H37: =IFERROR(SUMIF('MAR25'!$E:$E,CONCENTRADO!$C37,'MAR25'!$F:$F),"") -> 444516.63 | I37: =IFERROR(SUMIF('ABR25'!$E:$E,CONCENTRADO!$C37,'ABR25'!$F:$F),"") -> 531090.22 | J37: =IFERROR(SUMIF('MAY25'!$E:$E,CONCENTRADO!$C37,'MAY25'!$F:$F),"") -> 550916.4 | K37: =IFERROR(SUMIF('JUN25'!$E:$E,CONCENTRADO!$C37,'JUN25'!$F:$F),"") -> 402093.47 | L37: =IFERROR(SUMIF('JUL25'!$E:$E,CONCENTRADO!$C37,'JUL25'!$F:$F),"") -> 682867.57 | M37: =IFERROR(SUMIF('AGO25'!$E:$E,CONCENTRADO!$C37,'AGO25'!$F:$F),"") -> 410964.49 | N37: =IFERROR(SUMIF('SEP25'!$E:$E,CONCENTRADO!$C37,'SEP25'!$F:$F),"") -> 572793.7 | O37: =IFERROR(SUMIF('OCT25'!$E:$E,CONCENTRADO!$C37,'OCT25'!$F:$F),"") -> 1232287.3 | P37: =IFERROR(SUMIF('NOV25'!$E:$E,CONCENTRADO!$C37,'NOV25'!$F:$F),"") -> 216526.54 | Q37: =IFERROR(SUMIF('DIC25'!$E:$E,CONCENTRADO!$C37,'DIC25'!$K:$K),"") -> 0 | R37: =SUM(K37:Q37) -> 3517533 | S37: =$E37-$R37 -> -3517533
C38: MDE2025-004A | D38: Materiales bodega | F38: =IFERROR(SUMIF('ENE25'!E:E,CONCENTRADO!$C38,'ENE25'!F:F),"") -> 223935.97 | G38: =IFERROR(SUMIF('FEB25'!$E:$E,CONCENTRADO!$C38,'FEB25'!$F:$F),"") -> 15934.35 | H38: =IFERROR(SUMIF('MAR25'!$E:$E,CONCENTRADO!$C38,'MAR25'!$F:$F),"") -> 644.03 | I38: =IFERROR(SUMIF('ABR25'!$E:$E,CONCENTRADO!$C38,'ABR25'!$F:$F),"") -> 7300 | J38: =IFERROR(SUMIF('MAY25'!$E:$E,CONCENTRADO!$C38,'MAY25'!$F:$F),"") -> 0 | K38: =IFERROR(SUMIF('JUN25'!$E:$E,CONCENTRADO!$C38,'JUN25'!$F:$F),"") -> 0 | L38: =IFERROR(SUMIF('JUL25'!$E:$E,CONCENTRADO!$C38,'JUL25'!$F:$F),"") -> 0 | M38: =IFERROR(SUMIF('AGO25'!$E:$E,CONCENTRADO!$C38,'AGO25'!$F:$F),"") -> 0 | N38: =IFERROR(SUMIF('SEP25'!$E:$E,CONCENTRADO!$C38,'SEP25'!$F:$F),"") -> 0 | O38: =IFERROR(SUMIF('OCT25'!$E:$E,CONCENTRADO!$C38,'OCT25'!$F:$F),"") -> 0 | P38: =IFERROR(SUMIF('NOV25'!$E:$E,CONCENTRADO!$C38,'NOV25'!$F:$F),"") -> 0 | Q38: =IFERROR(SUMIF('DIC25'!$E:$E,CONCENTRADO!$C38,'DIC25'!$K:$K),"") -> 0 | R38: =SUM(K38:Q38) -> 0 | S38: =$E38-$R38 -> 0
F39: =IFERROR(SUMIF('ENE25'!E:E,CONCENTRADO!$C39,'ENE25'!F:F),"") -> 0 | G39: =IFERROR(SUMIF('FEB25'!$E:$E,CONCENTRADO!$C39,'FEB25'!$F:$F),"") -> 0 | H39: =IFERROR(SUMIF('MAR25'!$E:$E,CONCENTRADO!$C39,'MAR25'!$F:$F),"") -> 0 | I39: =IFERROR(SUMIF('ABR25'!$E:$E,CONCENTRADO!$C39,'ABR25'!$F:$F),"") -> 0 | J39: =IFERROR(SUMIF('MAY25'!$E:$E,CONCENTRADO!$C39,'MAY25'!$F:$F),"") -> 0 | K39: =IFERROR(SUMIF('JUN25'!$E:$E,CONCENTRADO!$C39,'JUN25'!$F:$F),"") -> 0 | L39: =IFERROR(SUMIF('JUL25'!$E:$E,CONCENTRADO!$C39,'JUL25'!$F:$F),"") -> 0 | M39: =IFERROR(SUMIF('AGO25'!$E:$E,CONCENTRADO!$C39,'AGO25'!$F:$F),"") -> 0 | N39: =IFERROR(SUMIF('SEP25'!$E:$E,CONCENTRADO!$C39,'SEP25'!$F:$F),"") -> 0 | O39: =IFERROR(SUMIF('OCT25'!$E:$E,CONCENTRADO!$C39,'OCT25'!$F:$F),"") -> 0 | P39: =IFERROR(SUMIF('NOV25'!$E:$E,CONCENTRADO!$C39,'NOV25'!$F:$F),"") -> 0 | Q39: =IFERROR(SUMIF('DIC25'!$E:$E,CONCENTRADO!$C39,'DIC25'!$K:$K),"") -> 0 | R39: =SUM(K39:Q39) -> 0 | S39: =$E39-$R39 -> 0
A40: MDE2025-005 | C40: MDE2025-005 | D40: Fondeo para caja chica | F40: =IFERROR(SUMIF('ENE25'!E:E,CONCENTRADO!$C40,'ENE25'!F:F),"") -> 0 | G40: =IFERROR(SUMIF('FEB25'!$E:$E,CONCENTRADO!$C40,'FEB25'!$F:$F),"") -> 0 | H40: =IFERROR(SUMIF('MAR25'!$E:$E,CONCENTRADO!$C40,'MAR25'!$F:$F),"") -> 0 | I40: =IFERROR(SUMIF('ABR25'!$E:$E,CONCENTRADO!$C40,'ABR25'!$F:$F),"") -> 0 | J40: =IFERROR(SUMIF('MAY25'!$E:$E,CONCENTRADO!$C40,'MAY25'!$F:$F),"") -> 343371.88 | K40: =IFERROR(SUMIF('JUN25'!$E:$E,CONCENTRADO!$C40,'JUN25'!$F:$F),"") -> 457881.58 | L40: =IFERROR(SUMIF('JUL25'!$E:$E,CONCENTRADO!$C40,'JUL25'!$F:$F),"") -> 1472806.1 | M40: =IFERROR(SUMIF('AGO25'!$E:$E,CONCENTRADO!$C40,'AGO25'!$F:$F),"") -> 393518.17 | N40: =IFERROR(SUMIF('SEP25'!$E:$E,CONCENTRADO!$C40,'SEP25'!$F:$F),"") -> 0 | O40: =IFERROR(SUMIF('OCT25'!$E:$E,CONCENTRADO!$C40,'OCT25'!$F:$F),"") -> 0 | P40: =IFERROR(SUMIF('NOV25'!$E:$E,CONCENTRADO!$C40,'NOV25'!$F:$F),"") -> 0 | Q40: =IFERROR(SUMIF('DIC25'!$E:$E,CONCENTRADO!$C40,'DIC25'!$K:$K),"") -> 0 | R40: =SUM(K40:Q40) -> 2324205.8 | S40: =$E40-$R40 -> -2324205.8
F41: =IFERROR(SUMIF('ENE25'!E:E,CONCENTRADO!$C41,'ENE25'!F:F),"") -> 0 | G41: =IFERROR(SUMIF('FEB25'!$E:$E,CONCENTRADO!$C41,'FEB25'!$F:$F),"") -> 0 | H41: =IFERROR(SUMIF('MAR25'!$E:$E,CONCENTRADO!$C41,'MAR25'!$F:$F),"") -> 0 | I41: =IFERROR(SUMIF('ABR25'!$E:$E,CONCENTRADO!$C41,'ABR25'!$F:$F),"") -> 0 | J41: =IFERROR(SUMIF('MAY25'!$E:$E,CONCENTRADO!$C41,'MAY25'!$F:$F),"") -> 0 | K41: =IFERROR(SUMIF('JUN25'!$E:$E,CONCENTRADO!$C41,'JUN25'!$F:$F),"") -> 0 | L41: =IFERROR(SUMIF('JUL25'!$E:$E,CONCENTRADO!$C41,'JUL25'!$F:$F),"") -> 0 | M41: =IFERROR(SUMIF('AGO25'!$E:$E,CONCENTRADO!$C41,'AGO25'!$F:$F),"") -> 0 | N41: =IFERROR(SUMIF('SEP25'!$E:$E,CONCENTRADO!$C41,'SEP25'!$F:$F),"") -> 0 | O41: =IFERROR(SUMIF('OCT25'!$E:$E,CONCENTRADO!$C41,'OCT25'!$F:$F),"") -> 0 | P41: =IFERROR(SUMIF('NOV25'!$E:$E,CONCENTRADO!$C41,'NOV25'!$F:$F),"") -> 0 | Q41: =IFERROR(SUMIF('DIC25'!$E:$E,CONCENTRADO!$C41,'DIC25'!$K:$K),"") -> 0 | R41: =SUM(K41:Q41) -> 0 | S41: =$E41-$R41 -> 0
A42: MDE2025-006 | B42: LOGISTICA | C42: MDE2025-006A | D42: Servicio y mantenimiento de unidades de transporte | F42: =IFERROR(SUMIF('ENE25'!E:E,CONCENTRADO!$C42,'ENE25'!F:F),"") -> 20298.27 | G42: =IFERROR(SUMIF('FEB25'!$E:$E,CONCENTRADO!$C42,'FEB25'!$F:$F),"") -> 14880 | H42: =IFERROR(SUMIF('MAR25'!$E:$E,CONCENTRADO!$C42,'MAR25'!$F:$F),"") -> 85014 | I42: =IFERROR(SUMIF('ABR25'!$E:$E,CONCENTRADO!$C42,'ABR25'!$F:$F),"") -> 66405.55 | J42: =IFERROR(SUMIF('MAY25'!$E:$E,CONCENTRADO!$C42,'MAY25'!$F:$F),"") -> 80246.79 | K42: =IFERROR(SUMIF('JUN25'!$E:$E,CONCENTRADO!$C42,'JUN25'!$F:$F),"") -> 107430.51 | L42: =IFERROR(SUMIF('JUL25'!$E:$E,CONCENTRADO!$C42,'JUL25'!$F:$F),"") -> 85178.84 | M42: =IFERROR(SUMIF('AGO25'!$E:$E,CONCENTRADO!$C42,'AGO25'!$F:$F),"") -> 97790.03 | N42: =IFERROR(SUMIF('SEP25'!$E:$E,CONCENTRADO!$C42,'SEP25'!$F:$F),"") -> 43361.65 | O42: =IFERROR(SUMIF('OCT25'!$E:$E,CONCENTRADO!$C42,'OCT25'!$F:$F),"") -> 21876.1 | P42: =IFERROR(SUMIF('NOV25'!$E:$E,CONCENTRADO!$C42,'NOV25'!$F:$F),"") -> 12887 | Q42: =IFERROR(SUMIF('DIC25'!$E:$E,CONCENTRADO!$C42,'DIC25'!$K:$K),"") -> 0 | R42: =SUM(K42:Q42) -> 368524.13 | S42: =$E42-$R42 -> -368524.13
C43: MDE2025-006B | D43: Verificaciones y tenencias | F43: =IFERROR(SUMIF('ENE25'!E:E,CONCENTRADO!$C43,'ENE25'!F:F),"") -> 33143 | G43: =IFERROR(SUMIF('FEB25'!$E:$E,CONCENTRADO!$C43,'FEB25'!$F:$F),"") -> 1211 | H43: =IFERROR(SUMIF('MAR25'!$E:$E,CONCENTRADO!$C43,'MAR25'!$F:$F),"") -> 400 | I43: =IFERROR(SUMIF('ABR25'!$E:$E,CONCENTRADO!$C43,'ABR25'!$F:$F),"") -> 1650 | J43: =IFERROR(SUMIF('MAY25'!$E:$E,CONCENTRADO!$C43,'MAY25'!$F:$F),"") -> 2000 | K43: =IFERROR(SUMIF('JUN25'!$E:$E,CONCENTRADO!$C43,'JUN25'!$F:$F),"") -> 13034 | L43: =IFERROR(SUMIF('JUL25'!$E:$E,CONCENTRADO!$C43,'JUL25'!$F:$F),"") -> 3045 | M43: =IFERROR(SUMIF('AGO25'!$E:$E,CONCENTRADO!$C43,'AGO25'!$F:$F),"") -> 1559.15 | N43: =IFERROR(SUMIF('SEP25'!$E:$E,CONCENTRADO!$C43,'SEP25'!$F:$F),"") -> 0 | O43: =IFERROR(SUMIF('OCT25'!$E:$E,CONCENTRADO!$C43,'OCT25'!$F:$F),"") -> 0 | P43: =IFERROR(SUMIF('NOV25'!$E:$E,CONCENTRADO!$C43,'NOV25'!$F:$F),"") -> 0 | Q43: =IFERROR(SUMIF('DIC25'!$E:$E,CONCENTRADO!$C43,'DIC25'!$K:$K),"") -> 0 | R43: =SUM(K43:Q43) -> 17638.15 | S43: =$E43-$R43 -> -17638.15
C44: MDE2025-006C | D44: Gastos de transporte | F44: =IFERROR(SUMIF('ENE25'!E:E,CONCENTRADO!$C44,'ENE25'!F:F),"") -> 89234.25 | G44: =IFERROR(SUMIF('FEB25'!$E:$E,CONCENTRADO!$C44,'FEB25'!$F:$F),"") -> 900 | H44: =IFERROR(SUMIF('MAR25'!$E:$E,CONCENTRADO!$C44,'MAR25'!$F:$F),"") -> 69037.9 | I44: =IFERROR(SUMIF('ABR25'!$E:$E,CONCENTRADO!$C44,'ABR25'!$F:$F),"") -> 0 | J44: =IFERROR(SUMIF('MAY25'!$E:$E,CONCENTRADO!$C44,'MAY25'!$F:$F),"") -> 0 | K44: =IFERROR(SUMIF('JUN25'!$E:$E,CONCENTRADO!$C44,'JUN25'!$F:$F),"") -> 21747.21 | L44: =IFERROR(SUMIF('JUL25'!$E:$E,CONCENTRADO!$C44,'JUL25'!$F:$F),"") -> 0 | M44: =IFERROR(SUMIF('AGO25'!$E:$E,CONCENTRADO!$C44,'AGO25'!$F:$F),"") -> 0 | N44: =IFERROR(SUMIF('SEP25'!$E:$E,CONCENTRADO!$C44,'SEP25'!$F:$F),"") -> 0 | O44: =IFERROR(SUMIF('OCT25'!$E:$E,CONCENTRADO!$C44,'OCT25'!$F:$F),"") -> 0 | P44: =IFERROR(SUMIF('NOV25'!$E:$E,CONCENTRADO!$C44,'NOV25'!$F:$F),"") -> 0 | Q44: =IFERROR(SUMIF('DIC25'!$E:$E,CONCENTRADO!$C44,'DIC25'!$K:$K),"") -> 0 | R44: =SUM(K44:Q44) -> 21747.21 | S44: =$E44-$R44 -> -21747.21
C45: MDE2025-006D | D45: Peaje-caseta-tag | F45: =IFERROR(SUMIF('ENE25'!E:E,CONCENTRADO!$C45,'ENE25'!F:F),"") -> -23300.86 | G45: =IFERROR(SUMIF('FEB25'!$E:$E,CONCENTRADO!$C45,'FEB25'!$F:$F),"") -> 25157.76 | H45: =IFERROR(SUMIF('MAR25'!$E:$E,CONCENTRADO!$C45,'MAR25'!$F:$F),"") -> 5021.93 | I45: =IFERROR(SUMIF('ABR25'!$E:$E,CONCENTRADO!$C45,'ABR25'!$F:$F),"") -> 7019.39 | J45: =IFERROR(SUMIF('MAY25'!$E:$E,CONCENTRADO!$C45,'MAY25'!$F:$F),"") -> 15632.5 | K45: =IFERROR(SUMIF('JUN25'!$E:$E,CONCENTRADO!$C45,'JUN25'!$F:$F),"") -> 3044.88 | L45: =IFERROR(SUMIF('JUL25'!$E:$E,CONCENTRADO!$C45,'JUL25'!$F:$F),"") -> 32855.35 | M45: =IFERROR(SUMIF('AGO25'!$E:$E,CONCENTRADO!$C45,'AGO25'!$F:$F),"") -> 17427.09 | N45: =IFERROR(SUMIF('SEP25'!$E:$E,CONCENTRADO!$C45,'SEP25'!$F:$F),"") -> 3960.42 | O45: =IFERROR(SUMIF('OCT25'!$E:$E,CONCENTRADO!$C45,'OCT25'!$F:$F),"") -> 2769.03 | P45: =IFERROR(SUMIF('NOV25'!$E:$E,CONCENTRADO!$C45,'NOV25'!$F:$F),"") -> 95.69 | Q45: =IFERROR(SUMIF('DIC25'!$E:$E,CONCENTRADO!$C45,'DIC25'!$K:$K),"") -> 0 | R45: =SUM(K45:Q45) -> 60152.46 | S45: =$E45-$R45 -> -60152.46
C46: MDE2025-003E | D46: Estacionamiento y servicios de transporte | F46: =IFERROR(SUMIF('ENE25'!E:E,CONCENTRADO!$C46,'ENE25'!F:F),"") -> 1072.03 | G46: =IFERROR(SUMIF('FEB25'!$E:$E,CONCENTRADO!$C46,'FEB25'!$F:$F),"") -> 0 | H46: =IFERROR(SUMIF('MAR25'!$E:$E,CONCENTRADO!$C46,'MAR25'!$F:$F),"") -> 100 | I46: =IFERROR(SUMIF('ABR25'!$E:$E,CONCENTRADO!$C46,'ABR25'!$F:$F),"") -> 0 | J46: =IFERROR(SUMIF('MAY25'!$E:$E,CONCENTRADO!$C46,'MAY25'!$F:$F),"") -> 0 | K46: =IFERROR(SUMIF('JUN25'!$E:$E,CONCENTRADO!$C46,'JUN25'!$F:$F),"") -> 0 | L46: =IFERROR(SUMIF('JUL25'!$E:$E,CONCENTRADO!$C46,'JUL25'!$F:$F),"") -> 53 | M46: =IFERROR(SUMIF('AGO25'!$E:$E,CONCENTRADO!$C46,'AGO25'!$F:$F),"") -> 0 | N46: =IFERROR(SUMIF('SEP25'!$E:$E,CONCENTRADO!$C46,'SEP25'!$F:$F),"") -> 0 | O46: =IFERROR(SUMIF('OCT25'!$E:$E,CONCENTRADO!$C46,'OCT25'!$F:$F),"") -> 0 | P46: =IFERROR(SUMIF('NOV25'!$E:$E,CONCENTRADO!$C46,'NOV25'!$F:$F),"") -> 36 | Q46: =IFERROR(SUMIF('DIC25'!$E:$E,CONCENTRADO!$C46,'DIC25'!$K:$K),"") -> 0 | R46: =SUM(K46:Q46) -> 89 | S46: =$E46-$R46 -> -89
C47: MDE2025-006F | D47: Multas y asuntos legales | F47: =IFERROR(SUMIF('ENE25'!E:E,CONCENTRADO!$C47,'ENE25'!F:F),"") -> 0 | G47: =IFERROR(SUMIF('FEB25'!$E:$E,CONCENTRADO!$C47,'FEB25'!$F:$F),"") -> 0 | H47: =IFERROR(SUMIF('MAR25'!$E:$E,CONCENTRADO!$C47,'MAR25'!$F:$F),"") -> 0 | I47: =IFERROR(SUMIF('ABR25'!$E:$E,CONCENTRADO!$C47,'ABR25'!$F:$F),"") -> 0 | J47: =IFERROR(SUMIF('MAY25'!$E:$E,CONCENTRADO!$C47,'MAY25'!$F:$F),"") -> 0 | K47: =IFERROR(SUMIF('JUN25'!$E:$E,CONCENTRADO!$C47,'JUN25'!$F:$F),"") -> 0 | L47: =IFERROR(SUMIF('JUL25'!$E:$E,CONCENTRADO!$C47,'JUL25'!$F:$F),"") -> 0 | M47: =IFERROR(SUMIF('AGO25'!$E:$E,CONCENTRADO!$C47,'AGO25'!$F:$F),"") -> 1458 | N47: =IFERROR(SUMIF('SEP25'!$E:$E,CONCENTRADO!$C47,'SEP25'!$F:$F),"") -> 2500 | O47: =IFERROR(SUMIF('OCT25'!$E:$E,CONCENTRADO!$C47,'OCT25'!$F:$F),"") -> 0 | P47: =IFERROR(SUMIF('NOV25'!$E:$E,CONCENTRADO!$C47,'NOV25'!$F:$F),"") -> 0 | Q47: =IFERROR(SUMIF('DIC25'!$E:$E,CONCENTRADO!$C47,'DIC25'!$K:$K),"") -> 0 | R47: =SUM(K47:Q47) -> 3958 | S47: =$E47-$R47 -> -3958
C48: MDE2025-006G | D48: Maniobras externas | F48: =IFERROR(SUMIF('ENE25'!E:E,CONCENTRADO!$C48,'ENE25'!F:F),"") -> 0 | G48: =IFERROR(SUMIF('FEB25'!$E:$E,CONCENTRADO!$C48,'FEB25'!$F:$F),"") -> 0 | H48: =IFERROR(SUMIF('MAR25'!$E:$E,CONCENTRADO!$C48,'MAR25'!$F:$F),"") -> 0 | I48: =IFERROR(SUMIF('ABR25'!$E:$E,CONCENTRADO!$C48,'ABR25'!$F:$F),"") -> 400 | J48: =IFERROR(SUMIF('MAY25'!$E:$E,CONCENTRADO!$C48,'MAY25'!$F:$F),"") -> 3000 | K48: =IFERROR(SUMIF('JUN25'!$E:$E,CONCENTRADO!$C48,'JUN25'!$F:$F),"") -> 150 | L48: =IFERROR(SUMIF('JUL25'!$E:$E,CONCENTRADO!$C48,'JUL25'!$F:$F),"") -> 0 | M48: =IFERROR(SUMIF('AGO25'!$E:$E,CONCENTRADO!$C48,'AGO25'!$F:$F),"") -> 0 | N48: =IFERROR(SUMIF('SEP25'!$E:$E,CONCENTRADO!$C48,'SEP25'!$F:$F),"") -> 0 | O48: =IFERROR(SUMIF('OCT25'!$E:$E,CONCENTRADO!$C48,'OCT25'!$F:$F),"") -> 7500 | P48: =IFERROR(SUMIF('NOV25'!$E:$E,CONCENTRADO!$C48,'NOV25'!$F:$F),"") -> 0 | Q48: =IFERROR(SUMIF('DIC25'!$E:$E,CONCENTRADO!$C48,'DIC25'!$K:$K),"") -> 0 | R48: =SUM(K48:Q48) -> 7650 | S48: =$E48-$R48 -> -7650
C49: MDE2025-006H | D49: Combustible | F49: =IFERROR(SUMIF('ENE25'!E:E,CONCENTRADO!$C49,'ENE25'!F:F),"") -> 0 | G49: =IFERROR(SUMIF('FEB25'!$E:$E,CONCENTRADO!$C49,'FEB25'!$F:$F),"") -> 0 | H49: =IFERROR(SUMIF('MAR25'!$E:$E,CONCENTRADO!$C49,'MAR25'!$F:$F),"") -> 0 | I49: =IFERROR(SUMIF('ABR25'!$E:$E,CONCENTRADO!$C49,'ABR25'!$F:$F),"") -> 0 | J49: =IFERROR(SUMIF('MAY25'!$E:$E,CONCENTRADO!$C49,'MAY25'!$F:$F),"") -> 0 | K49: =IFERROR(SUMIF('JUN25'!$E:$E,CONCENTRADO!$C49,'JUN25'!$F:$F),"") -> 0 | L49: =IFERROR(SUMIF('JUL25'!$E:$E,CONCENTRADO!$C49,'JUL25'!$F:$F),"") -> 0 | M49: =IFERROR(SUMIF('AGO25'!$E:$E,CONCENTRADO!$C49,'AGO25'!$F:$F),"") -> 0 | N49: =IFERROR(SUMIF('SEP25'!$E:$E,CONCENTRADO!$C49,'SEP25'!$F:$F),"") -> 0 | O49: =IFERROR(SUMIF('OCT25'!$E:$E,CONCENTRADO!$C49,'OCT25'!$F:$F),"") -> 0 | P49: =IFERROR(SUMIF('NOV25'!$E:$E,CONCENTRADO!$C49,'NOV25'!$F:$F),"") -> 0 | Q49: =IFERROR(SUMIF('DIC25'!$E:$E,CONCENTRADO!$C49,'DIC25'!$K:$K),"") -> 0 | R49: =SUM(K49:Q49) -> 0 | S49: =$E49-$R49 -> 0
F50: =IFERROR(SUMIF('ENE25'!E:E,CONCENTRADO!$C50,'ENE25'!F:F),"") -> 0 | G50: =IFERROR(SUMIF('FEB25'!$E:$E,CONCENTRADO!$C50,'FEB25'!$F:$F),"") -> 0 | H50: =IFERROR(SUMIF('MAR25'!$E:$E,CONCENTRADO!$C50,'MAR25'!$F:$F),"") -> 0 | I50: =IFERROR(SUMIF('ABR25'!$E:$E,CONCENTRADO!$C50,'ABR25'!$F:$F),"") -> 0 | J50: =IFERROR(SUMIF('MAY25'!$E:$E,CONCENTRADO!$C50,'MAY25'!$F:$F),"") -> 0 | K50: =IFERROR(SUMIF('JUN25'!$E:$E,CONCENTRADO!$C50,'JUN25'!$F:$F),"") -> 0 | L50: =IFERROR(SUMIF('JUL25'!$E:$E,CONCENTRADO!$C50,'JUL25'!$F:$F),"") -> 0 | M50: =IFERROR(SUMIF('AGO25'!$E:$E,CONCENTRADO!$C50,'AGO25'!$F:$F),"") -> 0 | N50: =IFERROR(SUMIF('SEP25'!$E:$E,CONCENTRADO!$C50,'SEP25'!$F:$F),"") -> 0 | O50: =IFERROR(SUMIF('OCT25'!$E:$E,CONCENTRADO!$C50,'OCT25'!$F:$F),"") -> 0 | P50: =IFERROR(SUMIF('NOV25'!$E:$E,CONCENTRADO!$C50,'NOV25'!$F:$F),"") -> 0 | Q50: =IFERROR(SUMIF('DIC25'!$E:$E,CONCENTRADO!$C50,'DIC25'!$K:$K),"") -> 0 | R50: =SUM(K50:Q50) -> 0 | S50: =$E50-$R50 -> 0
F51: =IFERROR(SUMIF('ENE25'!E:E,CONCENTRADO!$C51,'ENE25'!F:F),"") -> 0 | G51: =IFERROR(SUMIF('FEB25'!$E:$E,CONCENTRADO!$C51,'FEB25'!$F:$F),"") -> 0 | H51: =IFERROR(SUMIF('MAR25'!$E:$E,CONCENTRADO!$C51,'MAR25'!$F:$F),"") -> 0 | I51: =IFERROR(SUMIF('ABR25'!$E:$E,CONCENTRADO!$C51,'ABR25'!$F:$F),"") -> 0 | J51: =IFERROR(SUMIF('MAY25'!$E:$E,CONCENTRADO!$C51,'MAY25'!$F:$F),"") -> 0 | K51: =IFERROR(SUMIF('JUN25'!$E:$E,CONCENTRADO!$C51,'JUN25'!$F:$F),"") -> 0 | L51: =IFERROR(SUMIF('JUL25'!$E:$E,CONCENTRADO!$C51,'JUL25'!$F:$F),"") -> 0 | M51: =IFERROR(SUMIF('AGO25'!$E:$E,CONCENTRADO!$C51,'AGO25'!$F:$F),"") -> 0 | N51: =IFERROR(SUMIF('SEP25'!$E:$E,CONCENTRADO!$C51,'SEP25'!$F:$F),"") -> 0 | O51: =IFERROR(SUMIF('OCT25'!$E:$E,CONCENTRADO!$C51,'OCT25'!$F:$F),"") -> 0 | P51: =IFERROR(SUMIF('NOV25'!$E:$E,CONCENTRADO!$C51,'NOV25'!$F:$F),"") -> 0 | Q51: =IFERROR(SUMIF('DIC25'!$E:$E,CONCENTRADO!$C51,'DIC25'!$K:$K),"") -> 0 | R51: =SUM(K51:Q51) -> 0 | S51: =$E51-$R51 -> 0
A52: MDE 2025-007 | B52: ACTIVOS FIJOS | C52: MDE2025-007A | D52: Equipo de transporte | F52: =IFERROR(SUMIF('ENE25'!E:E,CONCENTRADO!$C52,'ENE25'!F:F),"") -> 398800 | G52: =IFERROR(SUMIF('FEB25'!$E:$E,CONCENTRADO!$C52,'FEB25'!$F:$F),"") -> 0 | H52: =IFERROR(SUMIF('MAR25'!$E:$E,CONCENTRADO!$C52,'MAR25'!$F:$F),"") -> 0 | I52: =IFERROR(SUMIF('ABR25'!$E:$E,CONCENTRADO!$C52,'ABR25'!$F:$F),"") -> 0 | J52: =IFERROR(SUMIF('MAY25'!$E:$E,CONCENTRADO!$C52,'MAY25'!$F:$F),"") -> 274137.93 | K52: =IFERROR(SUMIF('JUN25'!$E:$E,CONCENTRADO!$C52,'JUN25'!$F:$F),"") -> 10000 | L52: =IFERROR(SUMIF('JUL25'!$E:$E,CONCENTRADO!$C52,'JUL25'!$F:$F),"") -> 0 | M52: =IFERROR(SUMIF('AGO25'!$E:$E,CONCENTRADO!$C52,'AGO25'!$F:$F),"") -> 0 | N52: =IFERROR(SUMIF('SEP25'!$E:$E,CONCENTRADO!$C52,'SEP25'!$F:$F),"") -> 0 | O52: =IFERROR(SUMIF('OCT25'!$E:$E,CONCENTRADO!$C52,'OCT25'!$F:$F),"") -> 15000 | P52: =IFERROR(SUMIF('NOV25'!$E:$E,CONCENTRADO!$C52,'NOV25'!$F:$F),"") -> 0 | Q52: =IFERROR(SUMIF('DIC25'!$E:$E,CONCENTRADO!$C52,'DIC25'!$K:$K),"") -> 0 | R52: =SUM(K52:Q52) -> 25000 | S52: =$E52-$R52 -> -25000
C53: MDE2025-007B | D53: Equipo de cómputo y telefonía | F53: =IFERROR(SUMIF('ENE25'!E:E,CONCENTRADO!$C53,'ENE25'!F:F),"") -> 7879 | G53: =IFERROR(SUMIF('FEB25'!$E:$E,CONCENTRADO!$C53,'FEB25'!$F:$F),"") -> 21417.26 | H53: =IFERROR(SUMIF('MAR25'!$E:$E,CONCENTRADO!$C53,'MAR25'!$F:$F),"") -> 42102.25 | I53: =IFERROR(SUMIF('ABR25'!$E:$E,CONCENTRADO!$C53,'ABR25'!$F:$F),"") -> 97128.67 | J53: =IFERROR(SUMIF('MAY25'!$E:$E,CONCENTRADO!$C53,'MAY25'!$F:$F),"") -> 144323.58 | K53: =IFERROR(SUMIF('JUN25'!$E:$E,CONCENTRADO!$C53,'JUN25'!$F:$F),"") -> 63979.02 | L53: =IFERROR(SUMIF('JUL25'!$E:$E,CONCENTRADO!$C53,'JUL25'!$F:$F),"") -> 47683.83 | M53: =IFERROR(SUMIF('AGO25'!$E:$E,CONCENTRADO!$C53,'AGO25'!$F:$F),"") -> 49535.05 | N53: =IFERROR(SUMIF('SEP25'!$E:$E,CONCENTRADO!$C53,'SEP25'!$F:$F),"") -> 16731.02 | O53: =IFERROR(SUMIF('OCT25'!$E:$E,CONCENTRADO!$C53,'OCT25'!$F:$F),"") -> 58646.92 | P53: =IFERROR(SUMIF('NOV25'!$E:$E,CONCENTRADO!$C53,'NOV25'!$F:$F),"") -> 0 | Q53: =IFERROR(SUMIF('DIC25'!$E:$E,CONCENTRADO!$C53,'DIC25'!$K:$K),"") -> 0 | R53: =SUM(K53:Q53) -> 236575.84 | S53: =$E53-$R53 -> -236575.84
C54: MDE2025-007C | D54: Maquinaria y herramientas | F54: =IFERROR(SUMIF('ENE25'!E:E,CONCENTRADO!$C54,'ENE25'!F:F),"") -> 2308.99 | G54: =IFERROR(SUMIF('FEB25'!$E:$E,CONCENTRADO!$C54,'FEB25'!$F:$F),"") -> 0 | H54: =IFERROR(SUMIF('MAR25'!$E:$E,CONCENTRADO!$C54,'MAR25'!$F:$F),"") -> 0 | I54: =IFERROR(SUMIF('ABR25'!$E:$E,CONCENTRADO!$C54,'ABR25'!$F:$F),"") -> 2020.98 | J54: =IFERROR(SUMIF('MAY25'!$E:$E,CONCENTRADO!$C54,'MAY25'!$F:$F),"") -> 53742.88 | K54: =IFERROR(SUMIF('JUN25'!$E:$E,CONCENTRADO!$C54,'JUN25'!$F:$F),"") -> 0 | L54: =IFERROR(SUMIF('JUL25'!$E:$E,CONCENTRADO!$C54,'JUL25'!$F:$F),"") -> 5065 | M54: =IFERROR(SUMIF('AGO25'!$E:$E,CONCENTRADO!$C54,'AGO25'!$F:$F),"") -> 62456.36 | N54: =IFERROR(SUMIF('SEP25'!$E:$E,CONCENTRADO!$C54,'SEP25'!$F:$F),"") -> 0 | O54: =IFERROR(SUMIF('OCT25'!$E:$E,CONCENTRADO!$C54,'OCT25'!$F:$F),"") -> 21000 | P54: =IFERROR(SUMIF('NOV25'!$E:$E,CONCENTRADO!$C54,'NOV25'!$F:$F),"") -> 5520.38 | Q54: =IFERROR(SUMIF('DIC25'!$E:$E,CONCENTRADO!$C54,'DIC25'!$K:$K),"") -> 0 | R54: =SUM(K54:Q54) -> 94041.74 | S54: =$E54-$R54 -> -94041.74
C55: MDE2025-007D | D55: Iluminación, audio y video | F55: =IFERROR(SUMIF('ENE25'!E:E,CONCENTRADO!$C55,'ENE25'!F:F),"") -> 19370.69 | G55: =IFERROR(SUMIF('FEB25'!$E:$E,CONCENTRADO!$C55,'FEB25'!$F:$F),"") -> 5671.55 | H55: =IFERROR(SUMIF('MAR25'!$E:$E,CONCENTRADO!$C55,'MAR25'!$F:$F),"") -> 0 | I55: =IFERROR(SUMIF('ABR25'!$E:$E,CONCENTRADO!$C55,'ABR25'!$F:$F),"") -> 0 | J55: =IFERROR(SUMIF('MAY25'!$E:$E,CONCENTRADO!$C55,'MAY25'!$F:$F),"") -> 6499 | K55: =IFERROR(SUMIF('JUN25'!$E:$E,CONCENTRADO!$C55,'JUN25'!$F:$F),"") -> 562.82 | L55: =IFERROR(SUMIF('JUL25'!$E:$E,CONCENTRADO!$C55,'JUL25'!$F:$F),"") -> 0 | M55: =IFERROR(SUMIF('AGO25'!$E:$E,CONCENTRADO!$C55,'AGO25'!$F:$F),"") -> 0 | N55: =IFERROR(SUMIF('SEP25'!$E:$E,CONCENTRADO!$C55,'SEP25'!$F:$F),"") -> 395.67 | O55: =IFERROR(SUMIF('OCT25'!$E:$E,CONCENTRADO!$C55,'OCT25'!$F:$F),"") -> 405.17 | P55: =IFERROR(SUMIF('NOV25'!$E:$E,CONCENTRADO!$C55,'NOV25'!$F:$F),"") -> 0 | Q55: =IFERROR(SUMIF('DIC25'!$E:$E,CONCENTRADO!$C55,'DIC25'!$K:$K),"") -> 0 | R55: =SUM(K55:Q55) -> 1363.66 | S55: =$E55-$R55 -> -1363.66
C56: MDE2025-007E | D56: Mobiliario y equipo de oficina | F56: =IFERROR(SUMIF('ENE25'!E:E,CONCENTRADO!$C56,'ENE25'!F:F),"") -> 10234.09 | G56: =IFERROR(SUMIF('FEB25'!$E:$E,CONCENTRADO!$C56,'FEB25'!$F:$F),"") -> 0 | H56: =IFERROR(SUMIF('MAR25'!$E:$E,CONCENTRADO!$C56,'MAR25'!$F:$F),"") -> 5799 | I56: =IFERROR(SUMIF('ABR25'!$E:$E,CONCENTRADO!$C56,'ABR25'!$F:$F),"") -> 0 | J56: =IFERROR(SUMIF('MAY25'!$E:$E,CONCENTRADO!$C56,'MAY25'!$F:$F),"") -> 0 | K56: =IFERROR(SUMIF('JUN25'!$E:$E,CONCENTRADO!$C56,'JUN25'!$F:$F),"") -> 0 | L56: =IFERROR(SUMIF('JUL25'!$E:$E,CONCENTRADO!$C56,'JUL25'!$F:$F),"") -> 0 | M56: =IFERROR(SUMIF('AGO25'!$E:$E,CONCENTRADO!$C56,'AGO25'!$F:$F),"") -> 8133.06 | N56: =IFERROR(SUMIF('SEP25'!$E:$E,CONCENTRADO!$C56,'SEP25'!$F:$F),"") -> 0 | O56: =IFERROR(SUMIF('OCT25'!$E:$E,CONCENTRADO!$C56,'OCT25'!$F:$F),"") -> 21419.91 | P56: =IFERROR(SUMIF('NOV25'!$E:$E,CONCENTRADO!$C56,'NOV25'!$F:$F),"") -> 0 | Q56: =IFERROR(SUMIF('DIC25'!$E:$E,CONCENTRADO!$C56,'DIC25'!$K:$K),"") -> 0 | R56: =SUM(K56:Q56) -> 29552.97 | S56: =$E56-$R56 -> -29552.97
C57: MDE2025-007F | D57: Aplicaciones digitales | F57: =IFERROR(SUMIF('ENE25'!E:E,CONCENTRADO!$C57,'ENE25'!F:F),"") -> 0 | G57: =IFERROR(SUMIF('FEB25'!$E:$E,CONCENTRADO!$C57,'FEB25'!$F:$F),"") -> 0 | H57: =IFERROR(SUMIF('MAR25'!$E:$E,CONCENTRADO!$C57,'MAR25'!$F:$F),"") -> 0 | I57: =IFERROR(SUMIF('ABR25'!$E:$E,CONCENTRADO!$C57,'ABR25'!$F:$F),"") -> 0 | J57: =IFERROR(SUMIF('MAY25'!$E:$E,CONCENTRADO!$C57,'MAY25'!$F:$F),"") -> 0 | K57: =IFERROR(SUMIF('JUN25'!$E:$E,CONCENTRADO!$C57,'JUN25'!$F:$F),"") -> 0 | L57: =IFERROR(SUMIF('JUL25'!$E:$E,CONCENTRADO!$C57,'JUL25'!$F:$F),"") -> 0 | M57: =IFERROR(SUMIF('AGO25'!$E:$E,CONCENTRADO!$C57,'AGO25'!$F:$F),"") -> 0 | N57: =IFERROR(SUMIF('SEP25'!$E:$E,CONCENTRADO!$C57,'SEP25'!$F:$F),"") -> 0 | O57: =IFERROR(SUMIF('OCT25'!$E:$E,CONCENTRADO!$C57,'OCT25'!$F:$F),"") -> 6000 | P57: =IFERROR(SUMIF('NOV25'!$E:$E,CONCENTRADO!$C57,'NOV25'!$F:$F),"") -> 0 | Q57: =IFERROR(SUMIF('DIC25'!$E:$E,CONCENTRADO!$C57,'DIC25'!$K:$K),"") -> 0 | R57: =SUM(K57:Q57) -> 6000 | S57: =$E57-$R57 -> -6000
C58: MDE2025-007G | D58: Certificaciones y uso de marca | F58: =IFERROR(SUMIF('ENE25'!E:E,CONCENTRADO!$C58,'ENE25'!F:F),"") -> 0 | G58: =IFERROR(SUMIF('FEB25'!$E:$E,CONCENTRADO!$C58,'FEB25'!$F:$F),"") -> 0 | H58: =IFERROR(SUMIF('MAR25'!$E:$E,CONCENTRADO!$C58,'MAR25'!$F:$F),"") -> 0 | I58: =IFERROR(SUMIF('ABR25'!$E:$E,CONCENTRADO!$C58,'ABR25'!$F:$F),"") -> 0 | J58: =IFERROR(SUMIF('MAY25'!$E:$E,CONCENTRADO!$C58,'MAY25'!$F:$F),"") -> 0 | K58: =IFERROR(SUMIF('JUN25'!$E:$E,CONCENTRADO!$C58,'JUN25'!$F:$F),"") -> 0 | L58: =IFERROR(SUMIF('JUL25'!$E:$E,CONCENTRADO!$C58,'JUL25'!$F:$F),"") -> 4623.38 | M58: =IFERROR(SUMIF('AGO25'!$E:$E,CONCENTRADO!$C58,'AGO25'!$F:$F),"") -> 0 | N58: =IFERROR(SUMIF('SEP25'!$E:$E,CONCENTRADO!$C58,'SEP25'!$F:$F),"") -> 0 | O58: =IFERROR(SUMIF('OCT25'!$E:$E,CONCENTRADO!$C58,'OCT25'!$F:$F),"") -> 0 | P58: =IFERROR(SUMIF('NOV25'!$E:$E,CONCENTRADO!$C58,'NOV25'!$F:$F),"") -> 0 | Q58: =IFERROR(SUMIF('DIC25'!$E:$E,CONCENTRADO!$C58,'DIC25'!$K:$K),"") -> 0 | R58: =SUM(K58:Q58) -> 4623.38 | S58: =$E58-$R58 -> -4623.38
C59: MDE2025-007H | D59: Herramientas Daniela A. | F59: =IFERROR(SUMIF('ENE25'!E:E,CONCENTRADO!$C59,'ENE25'!F:F),"") -> 0 | G59: =IFERROR(SUMIF('FEB25'!$E:$E,CONCENTRADO!$C59,'FEB25'!$F:$F),"") -> 0 | H59: =IFERROR(SUMIF('MAR25'!$E:$E,CONCENTRADO!$C59,'MAR25'!$F:$F),"") -> 0 | I59: =IFERROR(SUMIF('ABR25'!$E:$E,CONCENTRADO!$C59,'ABR25'!$F:$F),"") -> 0 | J59: =IFERROR(SUMIF('MAY25'!$E:$E,CONCENTRADO!$C59,'MAY25'!$F:$F),"") -> 0 | K59: =IFERROR(SUMIF('JUN25'!$E:$E,CONCENTRADO!$C59,'JUN25'!$F:$F),"") -> 1787.93 | L59: =IFERROR(SUMIF('JUL25'!$E:$E,CONCENTRADO!$C59,'JUL25'!$F:$F),"") -> 0 | M59: =IFERROR(SUMIF('AGO25'!$E:$E,CONCENTRADO!$C59,'AGO25'!$F:$F),"") -> 0 | N59: =IFERROR(SUMIF('SEP25'!$E:$E,CONCENTRADO!$C59,'SEP25'!$F:$F),"") -> 0 | O59: =IFERROR(SUMIF('OCT25'!$E:$E,CONCENTRADO!$C59,'OCT25'!$F:$F),"") -> 0 | P59: =IFERROR(SUMIF('NOV25'!$E:$E,CONCENTRADO!$C59,'NOV25'!$F:$F),"") -> 0 | Q59: =IFERROR(SUMIF('DIC25'!$E:$E,CONCENTRADO!$C59,'DIC25'!$K:$K),"") -> 0 | R59: =SUM(K59:Q59) -> 1787.93 | S59: =$E59-$R59 -> -1787.93
C60: MDE2025-007I | D60: Edificios | F60: =IFERROR(SUMIF('ENE25'!E:E,CONCENTRADO!$C60,'ENE25'!F:F),"") -> 164222.81 | G60: =IFERROR(SUMIF('FEB25'!$E:$E,CONCENTRADO!$C60,'FEB25'!$F:$F),"") -> 69705.92 | H60: =IFERROR(SUMIF('MAR25'!$E:$E,CONCENTRADO!$C60,'MAR25'!$F:$F),"") -> 50535.54 | I60: =IFERROR(SUMIF('ABR25'!$E:$E,CONCENTRADO!$C60,'ABR25'!$F:$F),"") -> 71832.45 | J60: =IFERROR(SUMIF('MAY25'!$E:$E,CONCENTRADO!$C60,'MAY25'!$F:$F),"") -> 106898.73 | K60: =IFERROR(SUMIF('JUN25'!$E:$E,CONCENTRADO!$C60,'JUN25'!$F:$F),"") -> 70175.44 | L60: =IFERROR(SUMIF('JUL25'!$E:$E,CONCENTRADO!$C60,'JUL25'!$F:$F),"") -> 69848.6 | M60: =IFERROR(SUMIF('AGO25'!$E:$E,CONCENTRADO!$C60,'AGO25'!$F:$F),"") -> 27443.68 | N60: =IFERROR(SUMIF('SEP25'!$E:$E,CONCENTRADO!$C60,'SEP25'!$F:$F),"") -> 23400 | O60: =IFERROR(SUMIF('OCT25'!$E:$E,CONCENTRADO!$C60,'OCT25'!$F:$F),"") -> 10000 | P60: =IFERROR(SUMIF('NOV25'!$E:$E,CONCENTRADO!$C60,'NOV25'!$F:$F),"") -> 0 | Q60: =IFERROR(SUMIF('DIC25'!$E:$E,CONCENTRADO!$C60,'DIC25'!$K:$K),"") -> 0 | R60: =SUM(K60:Q60) -> 200867.72 | S60: =$E60-$R60 -> -200867.72
C61: MDE2025-007J | D61: Seguridad | F61: =IFERROR(SUMIF('ENE25'!E:E,CONCENTRADO!$C61,'ENE25'!F:F),"") -> 0 | G61: =IFERROR(SUMIF('FEB25'!$E:$E,CONCENTRADO!$C61,'FEB25'!$F:$F),"") -> 0 | H61: =IFERROR(SUMIF('MAR25'!$E:$E,CONCENTRADO!$C61,'MAR25'!$F:$F),"") -> 0 | I61: =IFERROR(SUMIF('ABR25'!$E:$E,CONCENTRADO!$C61,'ABR25'!$F:$F),"") -> 0 | J61: =IFERROR(SUMIF('MAY25'!$E:$E,CONCENTRADO!$C61,'MAY25'!$F:$F),"") -> 0 | K61: =IFERROR(SUMIF('JUN25'!$E:$E,CONCENTRADO!$C61,'JUN25'!$F:$F),"") -> 0 | L61: =IFERROR(SUMIF('JUL25'!$E:$E,CONCENTRADO!$C61,'JUL25'!$F:$F),"") -> 0 | M61: =IFERROR(SUMIF('AGO25'!$E:$E,CONCENTRADO!$C61,'AGO25'!$F:$F),"") -> 23980 | N61: =IFERROR(SUMIF('SEP25'!$E:$E,CONCENTRADO!$C61,'SEP25'!$F:$F),"") -> 0 | O61: =IFERROR(SUMIF('OCT25'!$E:$E,CONCENTRADO!$C61,'OCT25'!$F:$F),"") -> 0 | P61: =IFERROR(SUMIF('NOV25'!$E:$E,CONCENTRADO!$C61,'NOV25'!$F:$F),"") -> 0 | Q61: =IFERROR(SUMIF('DIC25'!$E:$E,CONCENTRADO!$C61,'DIC25'!$K:$K),"") -> 0 | R61: =SUM(K61:Q61) -> 23980 | S61: =$E61-$R61 -> -23980
F62: =IFERROR(SUMIF('ENE25'!E:E,CONCENTRADO!$C62,'ENE25'!F:F),"") -> 0 | G62: =IFERROR(SUMIF('FEB25'!$E:$E,CONCENTRADO!$C62,'FEB25'!$F:$F),"") -> 0 | H62: =IFERROR(SUMIF('MAR25'!$E:$E,CONCENTRADO!$C62,'MAR25'!$F:$F),"") -> 0 | I62: =IFERROR(SUMIF('ABR25'!$E:$E,CONCENTRADO!$C62,'ABR25'!$F:$F),"") -> 0 | J62: =IFERROR(SUMIF('MAY25'!$E:$E,CONCENTRADO!$C62,'MAY25'!$F:$F),"") -> 0 | K62: =IFERROR(SUMIF('JUN25'!$E:$E,CONCENTRADO!$C62,'JUN25'!$F:$F),"") -> 0 | L62: =IFERROR(SUMIF('JUL25'!$E:$E,CONCENTRADO!$C62,'JUL25'!$F:$F),"") -> 0 | M62: =IFERROR(SUMIF('AGO25'!$E:$E,CONCENTRADO!$C62,'AGO25'!$F:$F),"") -> 0 | N62: =IFERROR(SUMIF('SEP25'!$E:$E,CONCENTRADO!$C62,'SEP25'!$F:$F),"") -> 0 | O62: =IFERROR(SUMIF('OCT25'!$E:$E,CONCENTRADO!$C62,'OCT25'!$F:$F),"") -> 0 | P62: =IFERROR(SUMIF('NOV25'!$E:$E,CONCENTRADO!$C62,'NOV25'!$F:$F),"") -> 0 | Q62: =IFERROR(SUMIF('DIC25'!$E:$E,CONCENTRADO!$C62,'DIC25'!$K:$K),"") -> 0 | R62: =SUM(K62:Q62) -> 0 | S62: =$E62-$R62 -> 0
F63: =IFERROR(SUMIF('ENE25'!E:E,CONCENTRADO!$C63,'ENE25'!F:F),"") -> 0 | G63: =IFERROR(SUMIF('FEB25'!$E:$E,CONCENTRADO!$C63,'FEB25'!$F:$F),"") -> 0 | H63: =IFERROR(SUMIF('MAR25'!$E:$E,CONCENTRADO!$C63,'MAR25'!$F:$F),"") -> 0 | I63: =IFERROR(SUMIF('ABR25'!$E:$E,CONCENTRADO!$C63,'ABR25'!$F:$F),"") -> 0 | J63: =IFERROR(SUMIF('MAY25'!$E:$E,CONCENTRADO!$C63,'MAY25'!$F:$F),"") -> 0 | K63: =IFERROR(SUMIF('JUN25'!$E:$E,CONCENTRADO!$C63,'JUN25'!$F:$F),"") -> 0 | L63: =IFERROR(SUMIF('JUL25'!$E:$E,CONCENTRADO!$C63,'JUL25'!$F:$F),"") -> 0 | M63: =IFERROR(SUMIF('AGO25'!$E:$E,CONCENTRADO!$C63,'AGO25'!$F:$F),"") -> 0 | N63: =IFERROR(SUMIF('SEP25'!$E:$E,CONCENTRADO!$C63,'SEP25'!$F:$F),"") -> 0 | O63: =IFERROR(SUMIF('OCT25'!$E:$E,CONCENTRADO!$C63,'OCT25'!$F:$F),"") -> 0 | P63: =IFERROR(SUMIF('NOV25'!$E:$E,CONCENTRADO!$C63,'NOV25'!$F:$F),"") -> 0 | Q63: =IFERROR(SUMIF('DIC25'!$E:$E,CONCENTRADO!$C63,'DIC25'!$K:$K),"") -> 0 | R63: =SUM(K63:Q63) -> 0 | S63: =$E63-$R63 -> 0
F64: =IFERROR(SUMIF('ENE25'!E:E,CONCENTRADO!$C64,'ENE25'!F:F),"") -> 0 | G64: =IFERROR(SUMIF('FEB25'!$E:$E,CONCENTRADO!$C64,'FEB25'!$F:$F),"") -> 0 | H64: =IFERROR(SUMIF('MAR25'!$E:$E,CONCENTRADO!$C64,'MAR25'!$F:$F),"") -> 0 | I64: =IFERROR(SUMIF('ABR25'!$E:$E,CONCENTRADO!$C64,'ABR25'!$F:$F),"") -> 0 | J64: =IFERROR(SUMIF('MAY25'!$E:$E,CONCENTRADO!$C64,'MAY25'!$F:$F),"") -> 0 | K64: =IFERROR(SUMIF('JUN25'!$E:$E,CONCENTRADO!$C64,'JUN25'!$F:$F),"") -> 0 | L64: =IFERROR(SUMIF('JUL25'!$E:$E,CONCENTRADO!$C64,'JUL25'!$F:$F),"") -> 0 | M64: =IFERROR(SUMIF('AGO25'!$E:$E,CONCENTRADO!$C64,'AGO25'!$F:$F),"") -> 0 | N64: =IFERROR(SUMIF('SEP25'!$E:$E,CONCENTRADO!$C64,'SEP25'!$F:$F),"") -> 0 | O64: =IFERROR(SUMIF('OCT25'!$E:$E,CONCENTRADO!$C64,'OCT25'!$F:$F),"") -> 0 | P64: =IFERROR(SUMIF('NOV25'!$E:$E,CONCENTRADO!$C64,'NOV25'!$F:$F),"") -> 0 | Q64: =IFERROR(SUMIF('DIC25'!$E:$E,CONCENTRADO!$C64,'DIC25'!$K:$K),"") -> 0 | R64: =SUM(K64:Q64) -> 0 | S64: =$E64-$R64 -> 0
A65: MDE 2025-008 | B65: EVENTOS INTERNOS | C65: MDE2025-008A | D65: Cursos y capacitaciones | F65: =IFERROR(SUMIF('ENE25'!E:E,CONCENTRADO!$C65,'ENE25'!F:F),"") -> 0 | G65: =IFERROR(SUMIF('FEB25'!$E:$E,CONCENTRADO!$C65,'FEB25'!$F:$F),"") -> 0 | H65: =IFERROR(SUMIF('MAR25'!$E:$E,CONCENTRADO!$C65,'MAR25'!$F:$F),"") -> 10330.86 | I65: =IFERROR(SUMIF('ABR25'!$E:$E,CONCENTRADO!$C65,'ABR25'!$F:$F),"") -> 0 | J65: =IFERROR(SUMIF('MAY25'!$E:$E,CONCENTRADO!$C65,'MAY25'!$F:$F),"") -> 0 | K65: =IFERROR(SUMIF('JUN25'!$E:$E,CONCENTRADO!$C65,'JUN25'!$F:$F),"") -> 0 | L65: =IFERROR(SUMIF('JUL25'!$E:$E,CONCENTRADO!$C65,'JUL25'!$F:$F),"") -> 0 | M65: =IFERROR(SUMIF('AGO25'!$E:$E,CONCENTRADO!$C65,'AGO25'!$F:$F),"") -> 0 | N65: =IFERROR(SUMIF('SEP25'!$E:$E,CONCENTRADO!$C65,'SEP25'!$F:$F),"") -> 0 | O65: =IFERROR(SUMIF('OCT25'!$E:$E,CONCENTRADO!$C65,'OCT25'!$F:$F),"") -> 0 | P65: =IFERROR(SUMIF('NOV25'!$E:$E,CONCENTRADO!$C65,'NOV25'!$F:$F),"") -> 0 | Q65: =IFERROR(SUMIF('DIC25'!$E:$E,CONCENTRADO!$C65,'DIC25'!$K:$K),"") -> 0 | R65: =SUM(K65:Q65) -> 0 | S65: =$E65-$R65 -> 0
C66: MDE2025-008B | D66: Regalos y Patrocinios Clientes | F66: =IFERROR(SUMIF('ENE25'!E:E,CONCENTRADO!$C66,'ENE25'!F:F),"") -> 41918.9 | G66: =IFERROR(SUMIF('FEB25'!$E:$E,CONCENTRADO!$C66,'FEB25'!$F:$F),"") -> 7000 | H66: =IFERROR(SUMIF('MAR25'!$E:$E,CONCENTRADO!$C66,'MAR25'!$F:$F),"") -> 1654.79 | I66: =IFERROR(SUMIF('ABR25'!$E:$E,CONCENTRADO!$C66,'ABR25'!$F:$F),"") -> 1612.27 | J66: =IFERROR(SUMIF('MAY25'!$E:$E,CONCENTRADO!$C66,'MAY25'!$F:$F),"") -> 0 | K66: =IFERROR(SUMIF('JUN25'!$E:$E,CONCENTRADO!$C66,'JUN25'!$F:$F),"") -> 7512.78 | L66: =IFERROR(SUMIF('JUL25'!$E:$E,CONCENTRADO!$C66,'JUL25'!$F:$F),"") -> 0 | M66: =IFERROR(SUMIF('AGO25'!$E:$E,CONCENTRADO!$C66,'AGO25'!$F:$F),"") -> 0 | N66: =IFERROR(SUMIF('SEP25'!$E:$E,CONCENTRADO!$C66,'SEP25'!$F:$F),"") -> 25000 | O66: =IFERROR(SUMIF('OCT25'!$E:$E,CONCENTRADO!$C66,'OCT25'!$F:$F),"") -> 25000 | P66: =IFERROR(SUMIF('NOV25'!$E:$E,CONCENTRADO!$C66,'NOV25'!$F:$F),"") -> 961.18 | Q66: =IFERROR(SUMIF('DIC25'!$E:$E,CONCENTRADO!$C66,'DIC25'!$K:$K),"") -> 0 | R66: =SUM(K66:Q66) -> 58473.96 | S66: =$E66-$R66 -> -58473.96
F67: =IFERROR(SUMIF('ENE25'!E:E,CONCENTRADO!$C67,'ENE25'!F:F),"") -> 0 | G67: =IFERROR(SUMIF('FEB25'!$E:$E,CONCENTRADO!$C67,'FEB25'!$F:$F),"") -> 0 | H67: =IFERROR(SUMIF('MAR25'!$E:$E,CONCENTRADO!$C67,'MAR25'!$F:$F),"") -> 0 | I67: =IFERROR(SUMIF('ABR25'!$E:$E,CONCENTRADO!$C67,'ABR25'!$F:$F),"") -> 0 | J67: =IFERROR(SUMIF('MAY25'!$E:$E,CONCENTRADO!$C67,'MAY25'!$F:$F),"") -> 0 | K67: =IFERROR(SUMIF('JUN25'!$E:$E,CONCENTRADO!$C67,'JUN25'!$F:$F),"") -> 0 | L67: =IFERROR(SUMIF('JUL25'!$E:$E,CONCENTRADO!$C67,'JUL25'!$F:$F),"") -> 0 | M67: =IFERROR(SUMIF('AGO25'!$E:$E,CONCENTRADO!$C67,'AGO25'!$F:$F),"") -> 0 | N67: =IFERROR(SUMIF('SEP25'!$E:$E,CONCENTRADO!$C67,'SEP25'!$F:$F),"") -> 0 | O67: =IFERROR(SUMIF('OCT25'!$E:$E,CONCENTRADO!$C67,'OCT25'!$F:$F),"") -> 0 | P67: =IFERROR(SUMIF('NOV25'!$E:$E,CONCENTRADO!$C67,'NOV25'!$F:$F),"") -> 0 | Q67: =IFERROR(SUMIF('DIC25'!$E:$E,CONCENTRADO!$C67,'DIC25'!$K:$K),"") -> 0 | R67: =SUM(K67:Q67) -> 0 | S67: =$E67-$R67 -> 0
A68: MDE 2025-009 | B68: MANTENIMIENTO | C68: MDE2025-009A | D68: Insumos para mantenimiento bodega | F68: =IFERROR(SUMIF('ENE25'!E:E,CONCENTRADO!$C68,'ENE25'!F:F),"") -> 20444.6 | G68: =IFERROR(SUMIF('FEB25'!$E:$E,CONCENTRADO!$C68,'FEB25'!$F:$F),"") -> 12823.63 | H68: =IFERROR(SUMIF('MAR25'!$E:$E,CONCENTRADO!$C68,'MAR25'!$F:$F),"") -> 6754.66 | I68: =IFERROR(SUMIF('ABR25'!$E:$E,CONCENTRADO!$C68,'ABR25'!$F:$F),"") -> 16545.95 | J68: =IFERROR(SUMIF('MAY25'!$E:$E,CONCENTRADO!$C68,'MAY25'!$F:$F),"") -> 2418.7 | K68: =IFERROR(SUMIF('JUN25'!$E:$E,CONCENTRADO!$C68,'JUN25'!$F:$F),"") -> 1109.1 | L68: =IFERROR(SUMIF('JUL25'!$E:$E,CONCENTRADO!$C68,'JUL25'!$F:$F),"") -> 775.08 | M68: =IFERROR(SUMIF('AGO25'!$E:$E,CONCENTRADO!$C68,'AGO25'!$F:$F),"") -> 4951.16 | N68: =IFERROR(SUMIF('SEP25'!$E:$E,CONCENTRADO!$C68,'SEP25'!$F:$F),"") -> 2031.89 | O68: =IFERROR(SUMIF('OCT25'!$E:$E,CONCENTRADO!$C68,'OCT25'!$F:$F),"") -> 0 | P68: =IFERROR(SUMIF('NOV25'!$E:$E,CONCENTRADO!$C68,'NOV25'!$F:$F),"") -> 0 | Q68: =IFERROR(SUMIF('DIC25'!$E:$E,CONCENTRADO!$C68,'DIC25'!$K:$K),"") -> 0 | R68: =SUM(K68:Q68) -> 8867.23 | S68: =$E68-$R68 -> -8867.23
C69: MDE2025-009B | D69: Mantenimiento y reparación varios | F69: =IFERROR(SUMIF('ENE25'!E:E,CONCENTRADO!$C69,'ENE25'!F:F),"") -> 26715.55 | G69: =IFERROR(SUMIF('FEB25'!$E:$E,CONCENTRADO!$C69,'FEB25'!$F:$F),"") -> 10900 | H69: =IFERROR(SUMIF('MAR25'!$E:$E,CONCENTRADO!$C69,'MAR25'!$F:$F),"") -> 39181.35 | I69: =IFERROR(SUMIF('ABR25'!$E:$E,CONCENTRADO!$C69,'ABR25'!$F:$F),"") -> 7846.68 | J69: =IFERROR(SUMIF('MAY25'!$E:$E,CONCENTRADO!$C69,'MAY25'!$F:$F),"") -> 17982.73 | K69: =IFERROR(SUMIF('JUN25'!$E:$E,CONCENTRADO!$C69,'JUN25'!$F:$F),"") -> 43339.66 | L69: =IFERROR(SUMIF('JUL25'!$E:$E,CONCENTRADO!$C69,'JUL25'!$F:$F),"") -> 23867.3 | M69: =IFERROR(SUMIF('AGO25'!$E:$E,CONCENTRADO!$C69,'AGO25'!$F:$F),"") -> 14312.24 | N69: =IFERROR(SUMIF('SEP25'!$E:$E,CONCENTRADO!$C69,'SEP25'!$F:$F),"") -> 57491.73 | O69: =IFERROR(SUMIF('OCT25'!$E:$E,CONCENTRADO!$C69,'OCT25'!$F:$F),"") -> 66714.3 | P69: =IFERROR(SUMIF('NOV25'!$E:$E,CONCENTRADO!$C69,'NOV25'!$F:$F),"") -> 0 | Q69: =IFERROR(SUMIF('DIC25'!$E:$E,CONCENTRADO!$C69,'DIC25'!$K:$K),"") -> 0 | R69: =SUM(K69:Q69) -> 205725.23 | S69: =$E69-$R69 -> -205725.23
C70: MDE2025-009C | D70: Renta de adicionales (cimbra, andamios, etc.) | F70: =IFERROR(SUMIF('ENE25'!E:E,CONCENTRADO!$C70,'ENE25'!F:F),"") -> 0 | G70: =IFERROR(SUMIF('FEB25'!$E:$E,CONCENTRADO!$C70,'FEB25'!$F:$F),"") -> 0 | H70: =IFERROR(SUMIF('MAR25'!$E:$E,CONCENTRADO!$C70,'MAR25'!$F:$F),"") -> 0 | I70: =IFERROR(SUMIF('ABR25'!$E:$E,CONCENTRADO!$C70,'ABR25'!$F:$F),"") -> 0 | J70: =IFERROR(SUMIF('MAY25'!$E:$E,CONCENTRADO!$C70,'MAY25'!$F:$F),"") -> 0 | K70: =IFERROR(SUMIF('JUN25'!$E:$E,CONCENTRADO!$C70,'JUN25'!$F:$F),"") -> 0 | L70: =IFERROR(SUMIF('JUL25'!$E:$E,CONCENTRADO!$C70,'JUL25'!$F:$F),"") -> 45307.57 | M70: =IFERROR(SUMIF('AGO25'!$E:$E,CONCENTRADO!$C70,'AGO25'!$F:$F),"") -> 0 | N70: =IFERROR(SUMIF('SEP25'!$E:$E,CONCENTRADO!$C70,'SEP25'!$F:$F),"") -> 0 | O70: =IFERROR(SUMIF('OCT25'!$E:$E,CONCENTRADO!$C70,'OCT25'!$F:$F),"") -> 0 | P70: =IFERROR(SUMIF('NOV25'!$E:$E,CONCENTRADO!$C70,'NOV25'!$F:$F),"") -> 0 | Q70: =IFERROR(SUMIF('DIC25'!$E:$E,CONCENTRADO!$C70,'DIC25'!$K:$K),"") -> 0 | R70: =SUM(K70:Q70) -> 45307.57 | S70: =$E70-$R70 -> -45307.57
F71: =IFERROR(SUMIF('ENE25'!E:E,CONCENTRADO!$C71,'ENE25'!F:F),"") -> 0 | G71: =IFERROR(SUMIF('FEB25'!$E:$E,CONCENTRADO!$C71,'FEB25'!$F:$F),"") -> 0 | H71: =IFERROR(SUMIF('MAR25'!$E:$E,CONCENTRADO!$C71,'MAR25'!$F:$F),"") -> 0 | I71: =IFERROR(SUMIF('ABR25'!$E:$E,CONCENTRADO!$C71,'ABR25'!$F:$F),"") -> 0 | J71: =IFERROR(SUMIF('MAY25'!$E:$E,CONCENTRADO!$C71,'MAY25'!$F:$F),"") -> 0 | K71: =IFERROR(SUMIF('JUN25'!$E:$E,CONCENTRADO!$C71,'JUN25'!$F:$F),"") -> 0 | L71: =IFERROR(SUMIF('JUL25'!$E:$E,CONCENTRADO!$C71,'JUL25'!$F:$F),"") -> 0 | M71: =IFERROR(SUMIF('AGO25'!$E:$E,CONCENTRADO!$C71,'AGO25'!$F:$F),"") -> 0 | N71: =IFERROR(SUMIF('SEP25'!$E:$E,CONCENTRADO!$C71,'SEP25'!$F:$F),"") -> 0 | O71: =IFERROR(SUMIF('OCT25'!$E:$E,CONCENTRADO!$C71,'OCT25'!$F:$F),"") -> 0 | P71: =IFERROR(SUMIF('NOV25'!$E:$E,CONCENTRADO!$C71,'NOV25'!$F:$F),"") -> 0 | Q71: =IFERROR(SUMIF('DIC25'!$E:$E,CONCENTRADO!$C71,'DIC25'!$K:$K),"") -> 0 | R71: =SUM(K71:Q71) -> 0 | S71: =$E71-$R71 -> 0
A72: TOK2025-001 | B72: TOKA | C72: TOK2025-001A | D72: Gastos Toka | F72: =IFERROR(SUMIF('ENE25'!E:E,CONCENTRADO!$C72,'ENE25'!F:F),"") -> 0 | G72: =IFERROR(SUMIF('FEB25'!$E:$E,CONCENTRADO!$C72,'FEB25'!$F:$F),"") -> 0 | H72: =IFERROR(SUMIF('MAR25'!$E:$E,CONCENTRADO!$C72,'MAR25'!$F:$F),"") -> 0 | I72: =IFERROR(SUMIF('ABR25'!$E:$E,CONCENTRADO!$C72,'ABR25'!$F:$F),"") -> 0 | J72: =IFERROR(SUMIF('MAY25'!$E:$E,CONCENTRADO!$C72,'MAY25'!$F:$F),"") -> 800 | K72: =IFERROR(SUMIF('JUN25'!$E:$E,CONCENTRADO!$C72,'JUN25'!$F:$F),"") -> 0 | L72: =IFERROR(SUMIF('JUL25'!$E:$E,CONCENTRADO!$C72,'JUL25'!$F:$F),"") -> 0 | M72: =IFERROR(SUMIF('AGO25'!$E:$E,CONCENTRADO!$C72,'AGO25'!$F:$F),"") -> 0 | N72: =IFERROR(SUMIF('SEP25'!$E:$E,CONCENTRADO!$C72,'SEP25'!$F:$F),"") -> 0 | O72: =IFERROR(SUMIF('OCT25'!$E:$E,CONCENTRADO!$C72,'OCT25'!$F:$F),"") -> 0 | P72: =IFERROR(SUMIF('NOV25'!$E:$E,CONCENTRADO!$C72,'NOV25'!$F:$F),"") -> 3750 | Q72: =IFERROR(SUMIF('DIC25'!$E:$E,CONCENTRADO!$C72,'DIC25'!$K:$K),"") -> 0 | R72: =SUM(K72:Q72) -> 3750 | S72: =$E72-$R72 -> -3750
C73: TOK2025-001B | D73: Combustible Toka | F73: =IFERROR(SUMIF('ENE25'!E:E,CONCENTRADO!$C73,'ENE25'!F:F),"") -> 400 | G73: =IFERROR(SUMIF('FEB25'!$E:$E,CONCENTRADO!$C73,'FEB25'!$F:$F),"") -> 0 | H73: =IFERROR(SUMIF('MAR25'!$E:$E,CONCENTRADO!$C73,'MAR25'!$F:$F),"") -> 0 | I73: =IFERROR(SUMIF('ABR25'!$E:$E,CONCENTRADO!$C73,'ABR25'!$F:$F),"") -> 0 | J73: =IFERROR(SUMIF('MAY25'!$E:$E,CONCENTRADO!$C73,'MAY25'!$F:$F),"") -> 500 | K73: =IFERROR(SUMIF('JUN25'!$E:$E,CONCENTRADO!$C73,'JUN25'!$F:$F),"") -> 0 | L73: =IFERROR(SUMIF('JUL25'!$E:$E,CONCENTRADO!$C73,'JUL25'!$F:$F),"") -> 0 | M73: =IFERROR(SUMIF('AGO25'!$E:$E,CONCENTRADO!$C73,'AGO25'!$F:$F),"") -> 0 | N73: =IFERROR(SUMIF('SEP25'!$E:$E,CONCENTRADO!$C73,'SEP25'!$F:$F),"") -> 1400 | O73: =IFERROR(SUMIF('OCT25'!$E:$E,CONCENTRADO!$C73,'OCT25'!$F:$F),"") -> 0 | P73: =IFERROR(SUMIF('NOV25'!$E:$E,CONCENTRADO!$C73,'NOV25'!$F:$F),"") -> 2250 | Q73: =IFERROR(SUMIF('DIC25'!$E:$E,CONCENTRADO!$C73,'DIC25'!$K:$K),"") -> 0 | R73: =SUM(K73:Q73) -> 3650 | S73: =$E73-$R73 -> -3650
C74: TOK2025-001C | D74: Comisiones Toka | F74: =IFERROR(SUMIF('ENE25'!E:E,CONCENTRADO!$C74,'ENE25'!F:F),"") -> 348 | G74: =IFERROR(SUMIF('FEB25'!$E:$E,CONCENTRADO!$C74,'FEB25'!$F:$F),"") -> 1200 | H74: =IFERROR(SUMIF('MAR25'!$E:$E,CONCENTRADO!$C74,'MAR25'!$F:$F),"") -> 800 | I74: =IFERROR(SUMIF('ABR25'!$E:$E,CONCENTRADO!$C74,'ABR25'!$F:$F),"") -> 1826.5 | J74: =IFERROR(SUMIF('MAY25'!$E:$E,CONCENTRADO!$C74,'MAY25'!$F:$F),"") -> 1441.92 | K74: =IFERROR(SUMIF('JUN25'!$E:$E,CONCENTRADO!$C74,'JUN25'!$F:$F),"") -> 1892 | L74: =IFERROR(SUMIF('JUL25'!$E:$E,CONCENTRADO!$C74,'JUL25'!$F:$F),"") -> 780 | M74: =IFERROR(SUMIF('AGO25'!$E:$E,CONCENTRADO!$C74,'AGO25'!$F:$F),"") -> 1300 | N74: =IFERROR(SUMIF('SEP25'!$E:$E,CONCENTRADO!$C74,'SEP25'!$F:$F),"") -> 0 | O74: =IFERROR(SUMIF('OCT25'!$E:$E,CONCENTRADO!$C74,'OCT25'!$F:$F),"") -> 7819.2 | P74: =IFERROR(SUMIF('NOV25'!$E:$E,CONCENTRADO!$C74,'NOV25'!$F:$F),"") -> 0 | Q74: =IFERROR(SUMIF('DIC25'!$E:$E,CONCENTRADO!$C74,'DIC25'!$K:$K),"") -> 0 | R74: =SUM(K74:Q74) -> 11791.2 | S74: =$E74-$R74 -> -11791.2
D77: TOTALES | E77: =SUM(E2:E74) -> 0 | F77: =SUM(F2:F74) -> 2086743.4 | G77: =SUM(G2:G74) -> 1381340.2 | H77: =SUM(H2:H74) -> 1553929.3 | I77: =SUM(I2:I74) -> 2215727.1 | J77: =SUM(J2:J74) -> 2594923 | K77: =SUM(K2:K74) -> 2400596.6 | L77: =SUM(L2:L74) -> 3378879.3 | ... R77: =SUM(R2:R74) -> 11734887
D79: CONFIRMACIÓN DETALLADO | F79: =SUM('ENE25'!$F:$F) -> 2086743.4 | G79: =SUM('FEB25'!$F:$F) -> 1381340.2 | H79: =SUM('MAR25'!$F:$F) -> 1553929.3 | I79: =SUM('ABR25'!$F:$F) -> 2215727.1 | J79: =SUM('MAY25'!$F:$F) -> 2594923 | K79: =SUM('JUN25'!$F:$F) -> 2400596.6 | L79: =SUM('JUL25'!$F:$F) -> 3378879.3 | M79: =SUM('AGO25'!$F:$F) -> 1909092 | N79: =SUM('SEP25'!$F:$F) -> 1672603.3 | O79: =SUM('OCT25'!$F:$F) -> 1604989.8 | P79: =SUM('NOV25'!$F:$F) -> 768726.21 | Q79: =SUM('DIC25'!$F:$F) -> 0
D81: DIFERENCIA | F81: =F77-F79 -> 0 | G81: =G77-G79 -> 0 | H81: =H77-H79 -> 0 | I81: =I77-I79 -> 0 | J81: =J77-J79 -> 0 | K81: =K77-K79 -> 0 | L81: =L77-L79 -> 0 | M81: =M77-M79 -> 0 | ... Q81: =Q77-Q79 -> 0

Sheet CUENTAS
A1: SUBCUENTA | B1: CUENTA | C1: CLAVE | G1: FORMA DE PAGO
A2: DISEÑADORES BODEGA | B2: DISEÑOS | C2: MDE2025-001 | G2: KUSPIT SP´S
A3: SERVICIO DE RECOLECCION DE BASURA Y DESECHOS INDUSTRIALES | B3: GASTOS FIJOS | C3: MDE2025-002A | G3: SANTANDER - SUBCUENTA
A4: AGUA EMBOTELLADA | B4: GASTOS FIJOS | C4: MDE2025-002B | G4: TARJETA SANTANDER
A5: SERVICIO DE LUZ | B5: GASTOS FIJOS | C5: MDE2025-002C | G5: AMEX
A6: RENTAS | B6: GASTOS FIJOS | C6: MDE2025-002D | G6: EFECTIVO
A7: AGUA POTABLE | B7: GASTOS FIJOS | C7: MDE2025-002E | G7: BBVA
A8: SERVICIOS TELEFÓNICOS E INTERNET | B8: GASTOS FIJOS | C8: MDE2025-002F | G8: CAJA CHICA
A9: COMISIONES E INTERESES BANCARIOS | B9: GASTOS FIJOS | C9: MDE2025-002G | G9: TOKA - COMBUSTIBLES
A10: IMPUESTO PREDIAL | B10: GASTOS FIJOS | C10: MDE2025-002H | G10: TOKA - CONNECT
A11: SOCIAL MEDIA Y WEB MASTER | B11: GASTOS FIJOS | C11: MDE2025-002I | G11: SANTANDER SELECT - ENRIQUE
A12: LICENCIAS Y CERTIFICACIONES | B12: GASTOS FIJOS | C12: MDE2025-002J | G12: TOKA - TELEVIA
... A16: COMISIÓN DE NÓMINA SEMANAL | B16: GASTOS FIJOS | C16: MDE2025-002N | G16: ****
A17: NÓMINA QUINCENAL FIJA | B17: GASTOS FIJOS | C17: MDE2025-002O
A18: COMISIÓN DE NÓMINA QUINCENAL | B18: GASTOS FIJOS | C18: MDE2025-002P
A19: PRÉSTAMOS PERSONALES | B19: GASTOS FIJOS | C19: MDE2025-002Q
A20: NÓMINA EN EFECTIVO | B20: GASTOS FIJOS | C20: MDE2025-002R
A21: PAPELERÍA E INSUMOS DE LIMPIEZA | B21: GASTOS VARIOS | C21: MDE2025-003A
A22: UNIFORMES Y EPP | B22: GASTOS VARIOS | C22: MDE2025-003B
A23: TELEFONÍA E INTERNET | B23: GASTOS VARIOS | C23: MDE2025-003C
A24: COMBUSTIBLE | B24: GASTOS VARIOS | C24: MDE2025-003D
A25: FARMACIA/SALUD | B25: GASTOS VARIOS | C25: MDE2025-003F
A26: ALIMENTOS Y CONSUMOS | B26: GASTOS VARIOS | C26: MDE2025-003H
A27: HOSPEDAJE STAFF | B27: GASTOS VARIOS | C27: MDE2025-003I
A28: VUELOS STAFF | B28: GASTOS VARIOS | C28: MDE2025-003J
... A59: COMISIONES TOKA | B59: TOKA | C59: TOK2025-001C

Sheet ENE25
A1: PROVEEDOR | B1: CONCEPTO | C1: SUBCUENTA | D1: CUENTA | E1: CLAVE | F1: SUBTOTAL | G1: IVA | H1: TOTAL | I1: VALIDACIÓN | J1: FORMA DE PAGO | K1: EJECUTIVO | L1: STATUS | M1: FECHA | N1: FACTURA
A2: JOSE E ZEPEDA BURGOS | B2: REEMBOLSO COMPRA DISCO DURO / AMEX PLATINO | C2: EQUIPO DE CÓMPUTO Y TELEFONÍA | D2: =IFERROR(VLOOKUP($C2,CUENTAS[],2,0),"") -> ACTIVOS FIJOS | E2: =IFERROR(VLOOKUP($C2,CUENTAS[],3,0),"") -> MDE2025-007B | F2: 1580 | G2: 0 | H2: 1580 | I2: =IFERROR(IF(F2+G2<>H2,"REVISAR","CORRECTO"),"") -> CORRECTO | J2: KUSPIT SP´S | K2: ALEXIS/LESLIE | L2: PAGADO | M2: 45659 | N2: COMPROBANTE
A3: VIDAL ESTRADA | B3: COMPRA DE MATERIAL DE PLOMERIA | C3: INSUMOS PARA MANTENIMIENTO BODEGA | D3: =IFERROR(VLOOKUP($C3,CUENTAS[],2,0),"") -> MANTENIMIENTO | E3: =IFERROR(VLOOKUP($C3,CUENTAS[],3,0),"") -> MDE2025-009A | F3: 3799.14 | G3: 607.86 | H3: 4407 | I3: =+IF(F3+G3<>H3,"REVISAR","CORRECTO") -> CORRECTO | J3: KUSPIT SP´S | K3: ALEJANDRA | L3: PAGADO | M3: 45659 | N3: FACT13287
A4: DEKOMADERA SA DE CV | B4: COMPRA DE MATERIALES QUE YA ESTAN EN CIERRES DA198638,DA199206,DA201123 ,DA199634.DA200074,DA200512,DA202792,DA203155, DA204491 | C4: MATERIALES BODEGA | D4: =IFERROR(VLOOKUP($C4,CUENTAS[],2,0),"") -> MATERIALES | E4: =IFERROR(VLOOKUP($C4,CUENTAS[],3,0),"") -> MDE2025-004A | F4: 30000 | G4: 0 | H4: 30000 | I4: =+IF(F4+G4<>H4,"REVISAR","CORRECTO") -> CORRECTO | J4: KUSPIT SP´S | K4: ALEJANDRA | L4: PAGADO | M4: 45659 | N4: DA-30551
A5: UNALANA PAY | B5: COMISIONES BANCARIOS | C5: COMISIONES E INTERESES BANCARIOS | D5: =IFERROR(VLOOKUP($C5,CUENTAS[],2,0),"") -> GASTOS FIJOS | E5: =IFERROR(VLOOKUP($C5,CUENTAS[],3,0),"") -> MDE2025-002G | F5: 1379.31 | G5: 220.69 | H5: 1600 | I5: =+IF(F5+G5<>H5,"REVISAR","CORRECTO") -> CORRECTO | J5: KUSPIT SP´S | K5: KAWIR | L5: PAGADO | M5: 45659 | N5: PENDIENTE
A6: EVODIO DE JESUS GOMEZ | B6: PAGO MANO DE OBRA TRABAJO NUEVAS OFICINAS - EVODIO DE JESUS | C6: EDIFICIOS | D6: =IFERROR(VLOOKUP($C6,CUENTAS[],2,0),"") -> ACTIVOS FIJOS | E6: =IFERROR(VLOOKUP($C6,CUENTAS[],3,0),"") -> MDE2025-007I | F6: 3500 | G6: 0 | H6: 3500 | I6: =+IF(F6+G6<>H6,"REVISAR","CORRECTO") -> CORRECTO | J6: KUSPIT SP´S | K6: CAROLINA | L6: PAGADO | M6: 45660 | N6: N/A
A7: TIRSO DE JESUS DE LA CRUZ | B7: PAGO MANO DE OBRA TRABAJO NUEVAS OFICINAS - TIRSO DE JESUS | C7: EDIFICIOS | D7: =IFERROR(VLOOKUP($C7,CUENTAS[],2,0),"") -> ACTIVOS FIJOS | E7: =IFERROR(VLOOKUP($C7,CUENTAS[],3,0),"") -> MDE2025-007I | F7: 3200 | G7: 0 | H7: 3200 | I7: =+IF(F7+G7<>H7,"REVISAR","CORRECTO") -> CORRECTO | J7: KUSPIT SP´S | K7: CAROLINA | L7: PAGADO | M7: 45660 | N7: N/A
A8: BENITO AVILA DIAZ | B8: PAGO MANO DE OBRA - OFICINAS NUEVAS | C8: EDIFICIOS | D8: =IFERROR(VLOOKUP($C8,CUENTAS[],2,0),"") -> ACTIVOS FIJOS | E8: =IFERROR(VLOOKUP($C8,CUENTAS[],3,0),"") -> MDE2025-007I | F8: 5000 | G8: 0 | H8: 5000 | I8: =+IF(F8+G8<>H8,"REVISAR","CORRECTO") -> CORRECTO | J8: KUSPIT SP´S | K8: ENRIQUE | L8: PAGADO | M8: 45660 | N8: N/A
A9: UNALANA PAY | B9: COMISIONES BANCARIOS | C9: COMISIONES E INTERESES BANCARIOS | D9: =IFERROR(VLOOKUP($C9,CUENTAS[],2,0),"") -> GASTOS FIJOS | E9: =IFERROR(VLOOKUP($C9,CUENTAS[],3,0),"") -> MDE2025-002G | F9: 120 | G9: 0 | H9: 120 | I9: =+IF(F9+G9<>H9,"REVISAR","CORRECTO") -> CORRECTO | J9: KUSPIT SP´S | K9: KAWIR | L9: PAGADO | M9: 45660 | N9: NOMINA
A10: UNALANAPAY | B10: COMISIONES BANCARIAS | C10: COMISIONES E INTERESES BANCARIOS | D10: =IFERROR(VLOOKUP($C10,CUENTAS[],2,0),"") -> GASTOS FIJOS | E10: =IFERROR(VLOOKUP($C10,CUENTAS[],3,0),"") -> MDE2025-002G | F10: 689.66 | G10: 110.34 | H10: 800 | I10: =+IF(F10+G10<>H10,"REVISAR","CORRECTO") -> CORRECTO | J10: KUSPIT SP´S | K10: KAWIR | L10: PAGADO | M10: 45664 | N10: COMISIONES
A11: LUIS ANTONIO GARDUÑO TAPIA | B11: MO - TRABAJO PORTON BODEGA | C11: MANTENIMIENTO Y REPARACIÓN VARIOS | D11: =IFERROR(VLOOKUP($C11,CUENTAS[],2,0),"") -> MANTENIMIENTO | E11: =IFERROR(VLOOKUP($C11,CUENTAS[],3,0),"") -> MDE2025-009B | F11: 700 | G11: 0 | H11: 700 | I11: =+IF(F11+G11<>H11,"REVISAR","CORRECTO") -> CORRECTO | J11: KUSPIT SP´S | K11: ENRIQUE | L11: PAGADO | M11: 45665 | N11: N/A
A12: VICTOR AARON RODRIGUEZ MIRANDA | B12: DISEÑO Y RENDER PARA STAND ALEN 6X3 MTS - CAMBIO EXPO WALMART 2025 | C12: DISEÑADORES BODEGA | D12: =IFERROR(VLOOKUP($C12,CUENTAS[],2,0),"") -> DISEÑOS | E12: =IFERROR(VLOOKUP($C12,CUENTAS[],3,0),"") -> MDE2025-001 | F12: 6900 | G12: 281.52 | H12: 7181.52 | I12: =+IF(F12+G12<>H12,"REVISAR","CORRECTO") -> CORRECTO | J12: KUSPIT SP´S | K12: LESLIE | L12: PAGADO | M12: 45665 | N12: FACT 465
A13: RICARDO MONTENEGRO | B13: AFINACION MOTOR BALEROS FRENOS ALINEACION Y BALANCEO - JEEP | C13: SERVICIO Y MANTENIMIENTO DE UNIDADES DE TRANSPORTE | D13: =IFERROR(VLOOKUP($C13,CUENTAS[],2,0),"") -> LOGÍSTICA | E13: =IFERROR(VLOOKUP($C13,CUENTAS[],3,0),"") -> MDE2025-006A | F13: 4100 | G13: 656 | H13: 4756 | I13: =+IF(F13+G13<>H13,"REVISAR","CORRECTO") -> CORRECTO | J13: KUSPIT SP´S | K13: FERNANDO | L13: PAGADO | M13: 45665 | N13: FACT61842
A14: NORMA ELENA BURGOS REYES | B14: RENTA BODEGA DICIEMBRE 2024 | C14: RENTAS | D14: =IFERROR(VLOOKUP($C14,CUENTAS[],2,0),"") -> GASTOS FIJOS | E14: =IFERROR(VLOOKUP($C14,CUENTAS[],3,0),"") -> MDE2025-002D | F14: 80000 | G14: 0 | H14: 80000 | I14: =+IF(F14+G14<>H14,"REVISAR","CORRECTO") -> CORRECTO | J14: KUSPIT SP´S | K14: NAYELI | L14: PAGADO | M14: 45665 | N14: N/A
... A36: MARIANA GONZALEZ VARA | B36: PAGO MENSUAL SOCIAL MEDIA MES DE ENERO 2025 | C36: SOCIAL MEDIA Y WEB MASTER | D36: =IFERROR(VLOOKUP($C36,CUENTAS[],2,0),"") -> GASTOS FIJOS | E36: =IFERROR(VLOOKUP($C36,CUENTAS[],3,0),"") -> MDE2025-002I | F36: 8000 | G36: 0 | H36: 8000 | I36: =+IF(F36+G36<>H36,"REVISAR","CORRECTO") -> CORRECTO | J36: KUSPIT SP´S | K36: NAYELI | L36: PAGADO | M36: 45672 | N36: N/A
A37: Toka internacional S.A.P.I. de C.V. | B37: 2372615 | C37: COMISIONES TOKA | D37: =IFERROR(VLOOKUP($C37,CUENTAS[],2,0),"") -> TOKA | E37: =IFERROR(VLOOKUP($C37,CUENTAS[],3,0),"") -> TOK2025-001C | F37: 348 | G37: 0 | H37: 348 | I37: =+IF(F37+G37<>H37,"REVISAR","CORRECTO") -> CORRECTO | J37: KUSPIT SP´S | K37: NAYELI | L37: PAGADO | M37: 45672 | N37: FACTURA
A38: UNALANAPAY | B38: COMISIONES BANCARIAS | C38: COMISIONES E INTERESES BANCARIOS | D38: =IFERROR(VLOOKUP($C38,CUENTAS[],2,0),"") -> GASTOS FIJOS | E38: =IFERROR(VLOOKUP($C38,CUENTAS[],3,0),"") -> MDE2025-002G | F38: 172.41 | G38: 27.59 | H38: 200 | I38: =+IF(F38+G38<>H38,"REVISAR","CORRECTO") -> CORRECTO | J38: KUSPIT SP´S | K38: KAWIR | L38: PAGADO | M38: 45672 | N38: COMISIONES
A39: VICTOR MANUEL RUIZ ZARATE | B39: REEMBOLSO COMPRA DE 10 TAQUETE ARPON Y TORNILLOS PARA ZAGUÁN 13/ENE/25 | C39: INSUMOS PARA MANTENIMIENTO BODEGA | D39: =IFERROR(VLOOKUP($C39,CUENTAS[],2,0),"") -> MANTENIMIENTO | E39: =IFERROR(VLOOKUP($C39,CUENTAS[],3,0),"") -> MDE2025-009A | F39: 340 | G39: 0 | H39: 340 | I39: =+IF(F39+G39<>H39,"REVISAR","CORRECTO") -> CORRECTO | J39: KUSPIT SP´S | K39: CAROLINA | L39: PAGADO | M39: 45673 | N39: COMPROBANTE
A40: SECRETARIA DE FINANZAS | B40: TENENCIA 2025 - NAVISTAR INTERNATION CHASIS CABINA MV CUMMINS ISB6.7 197/214/239/242/279/280/289HP | C40: VERIFICACIONES Y TENENCIAS | D40: =IFERROR(VLOOKUP($C40,CUENTAS[],2,0),"") -> LOGÍSTICA | E40: =IFERROR(VLOOKUP($C40,CUENTAS[],3,0),"") -> MDE2025-006B | F40: 6051 | G40: 0 | H40: 6051 | I40: =+IF(F40+G40<>H40,"REVISAR","CORRECTO") -> CORRECTO | J40: KUSPIT SP´S | K40: FERNANDO | L40: PAGADO | M40: 45674 | N40: COMPROBANTE
A41: SECRETARIA DE FINANZAS | B41: TENENCIA 2025 - FORD RANGER T/M CREW CAB XLT 2.5L 4CIL 4A TELA/PIEL | C41: VERIFICACIONES Y TENENCIAS | D41: =IFERROR(VLOOKUP($C41,CUENTAS[],2,0),"") -> LOGÍSTICA | E41: =IFERROR(VLOOKUP($C41,CUENTAS[],3,0),"") -> MDE2025-006B | F41: 917 | G41: 0 | H41: 917 | I41: =+IF(F41+G41<>H41,"REVISAR","CORRECTO") -> CORRECTO | J41: KUSPIT SP´S | K41: FERNANDO | L41: PAGADO | M41: 45674 | N41: COMPROBANTE
A42: VOCCOPO SA DE CV | B42: SERVICIO TELEFONICO ENERO 2025 | C42: TELEFONÍA E INTERNET | D42: =IFERROR(VLOOKUP($C42,CUENTAS[],2,0),"") -> GASTOS VARIOS | E42: =IFERROR(VLOOKUP($C42,CUENTAS[],3,0),"") -> MDE2025-003C | F42: 1598 | G42: 0 | H42: 1598 | I42: =+IF(F42+G42<>H42,"REVISAR","CORRECTO") -> CORRECTO | J42: KUSPIT SP´S | K42: NAYELI | L42: PAGADO | M42: 45673 | N42: N/A
A43: COVARRUBIAS LAMA YAJAIRA ALEJANDRA | B43: COMPRA DE LLANTAS PARA MUEBLES MUESTRA BOSCH Y LAVANDERIA | C43: INSUMOS PARA MANTENIMIENTO BODEGA | D43: =IFERROR(VLOOKUP($C43,CUENTAS[],2,0),"") -> MANTENIMIENTO | E43: =IFERROR(VLOOKUP($C43,CUENTAS[],3,0),"") -> MDE2025-009A | F43: 279.32 | G43: 44.69 | H43: 324.01 | I43: =+IF(F43+G43<>H43,"REVISAR","CORRECTO") -> CORRECTO | J43: KUSPIT SP´S | K43: ALEJANDRA | L43: PAGADO | M43: 45673 | N43: 64358
A44: VICTOR MANUEL RUIZ ZARATE | B44: REEMBOLSO COMPRA DE 2 PZ DE RODAJA GIRATORIA TRACTOR Y 2 PZ DE RODAJA FIJA TRACTOR DE 4" 15ENE25 | C44: INSUMOS PARA MANTENIMIENTO BODEGA | D44: =IFERROR(VLOOKUP($C44,CUENTAS[],2,0),"") -> MANTENIMIENTO | E44: =IFERROR(VLOOKUP($C44,CUENTAS[],3,0),"") -> MDE2025-009A | F44: 580 | G44: 0 | H44: 580 | I44: =+IF(F44+G44<>H44,"REVISAR","CORRECTO") -> CORRECTO | J44: KUSPIT SP´S | K44: CAROLINA | L44: PAGADO | M44: 45673 | N44: COMPROBANTE
A45: VICTOR MANUEL RUIZ ZARATE | B45: REEMBOLSO COMPRA DE XRO ROLLO MALLA 6-6-6-6 15ENE25 | C45: INSUMOS PARA MANTENIMIENTO BODEGA | D45: =IFERROR(VLOOKUP($C45,CUENTAS[],2,0),"") -> MANTENIMIENTO | E45: =IFERROR(VLOOKUP($C45,CUENTAS[],3,0),"") -> MDE2025-009A | F45: 3024.83 | G45: 483.97 | H45: 3508.8 | I45: =+IF(F45+G45<>H45,"REVISAR","CORRECTO") -> CORRECTO | J45: KUSPIT SP´S | K45: CAROLINA | L45: PAGADO | M45: 45673 | N45: FACT T360365
A46: COVARRUBIAS LAMA YAJAIRA ALEJANDRA | B46: COMPRA DE CLAVOS Y SAPO BAÑO | C46: INSUMOS PARA MANTENIMIENTO BODEGA | D46: =IFERROR(VLOOKUP($C46,CUENTAS[],2,0),"") -> MANTENIMIENTO | E46: =IFERROR(VLOOKUP($C46,CUENTAS[],3,0),"") -> MDE2025-009A | F46: 301.72 | G46: 48.28 | H46: 350 | I46: =+IF(F46+G46<>H46,"REVISAR","CORRECTO") -> CORRECTO | J46: KUSPIT SP´S | K46: ALEJANDRA | L46: PAGADO | M46: 45673 | N46: 13314
A47: JOSE E ZEPEDA BURGOS | B47: PAGO A BENITO POR REPARACIÓN DEL PORTÓN | C47: MANTENIMIENTO Y REPARACIÓN VARIOS | D47: =IFERROR(VLOOKUP($C47,CUENTAS[],2,0),"") -> MANTENIMIENTO | E47: =IFERROR(VLOOKUP($C47,CUENTAS[],3,0),"") -> MDE2025-009B | F47: 4000 | G47: 0 | H47: 4000 | I47: =+IF(F47+G47<>H47,"REVISAR","CORRECTO") -> CORRECTO | J47: KUSPIT SP´S | K47: LESLIE | L47: PAGADO | M47: 45673 | N47: N/A
A48: JOSE E ZEPEDA BURGOS | B48: ASFALTO ENTRADA BODEGA | C48: MANTENIMIENTO Y REPARACIÓN VARIOS | D48: =IFERROR(VLOOKUP($C48,CUENTAS[],2,0),"") -> MANTENIMIENTO | E48: =IFERROR(VLOOKUP($C48,CUENTAS[],3,0),"") -> MDE2025-009B | F48: 10000 | G48: 0 | H48: 10000 | I48: =+IF(F48+G48<>H48,"REVISAR","CORRECTO") -> CORRECTO | J48: KUSPIT SP´S | K48: LESLIE | L48: PAGADO | M48: 45673 | N48: N/A
A49: BENITO AVILA DIAZ | B49: PAGO DE MANO DE OBRA CONSTRUCCION DE OFICINAS | C49: EDIFICIOS | D49: =IFERROR(VLOOKUP($C49,CUENTAS[],2,0),"") -> ACTIVOS FIJOS | E49: =IFERROR(VLOOKUP($C49,CUENTAS[],3,0),"") -> MDE2025-007I | F49: 20000 | G49: 0 | H49: 20000 | I49: =+IF(F49+G49<>H49,"REVISAR","CORRECTO") -> CORRECTO | J49: KUSPIT SP´S | K49: ENRIQUE | L49: PAGADO | M49: 45673 | N49: N/A
A50: LUIS ANTONIO GARDUÑO TAPIA | B50: PAGO MANO DE OBRA - CONSTRUCCION OFICINAS | C50: EDIFICIOS | D50: =IFERROR(VLOOKUP($C50,CUENTAS[],2,0),"") -> ACTIVOS FIJOS | E50: =IFERROR(VLOOKUP($C50,CUENTAS[],3,0),"") -> MDE2025-007I | F50: 2000 | G50: 0 | H50: 2000 | I50: =+IF(F50+G50<>H50,"REVISAR","CORRECTO") -> CORRECTO | J50: KUSPIT SP´S | K50: ENRIQUE | L50: PAGADO | M50: 45673 | N50: N/A
A51: UNALANAPAY | B51: COMISIONES BANCARIAS | C51: COMISIONES E INTERESES BANCARIOS | D51: =IFERROR(VLOOKUP($C51,CUENTAS[],2,0),"") -> GASTOS FIJOS | E51: =IFERROR(VLOOKUP($C51,CUENTAS[],3,0),"") -> MDE2025-002G | F51: 1863.84 | G51: 298.22 | H51: 2162.06 | I51: =+IF(F51+G51<>H51,"REVISAR","CORRECTO") -> CORRECTO | J51: KUSPIT SP´S | K51: KAWIR | L51: PAGADO | M51: 45673 | N51: COMISIONES
A52: CINDY PINEDA VAZQUEZ | B52: SALDO 50% TAPIZADO DE SILLAS | C52: MOBILIARIO Y EQUIPO DE OFICINA | D52: =IFERROR(VLOOKUP($C52,CUENTAS[],2,0),"") -> ACTIVOS FIJOS | E52: =IFERROR(VLOOKUP($C52,CUENTAS[],3,0),"") -> MDE2025-007E | F52: 7543.1 | G52: 1206.9 | H52: 8750 | I52: =+IF(F52+G52<>H52,"REVISAR","CORRECTO") -> CORRECTO | J52: KUSPIT SP´S | K52: ANGIE | L52: PAGADO | M52: 45674 | N52: FAC PENDIENTE
A53: ANGIE PEREZ | B53: REEMBOLSO COMPRA DE TAPETE - VIGILANCIA | C53: INSUMOS PARA MANTENIMIENTO BODEGA | D53: =IFERROR(VLOOKUP($C53,CUENTAS[],2,0),"") -> MANTENIMIENTO | E53: =IFERROR(VLOOKUP($C53,CUENTAS[],3,0),"") -> MDE2025-009A | F53: 188.79 | G53: 30.21 | H53: 219 | I53: =+IF(F53+G53<>H53,"REVISAR","CORRECTO") -> CORRECTO | J53: KUSPIT SP´S | K53: ANGIE | L53: PAGADO | M53: 45674 | N53: FACT89602
A54: ANGIE PEREZ | B54: REEMBOLSO COMPRA DE MESA- VIGILANCIA | C54: INSUMOS PARA MANTENIMIENTO BODEGA | D54: =IFERROR(VLOOKUP($C54,CUENTAS[],2,0),"") -> MANTENIMIENTO | E54: =IFERROR(VLOOKUP($C54,CUENTAS[],3,0),"") -> MDE2025-009A | F54: 688.8 | G54: 110.2 | H54: 799 | I54: =+IF(F54+G54<>H54,"REVISAR","CORRECTO") -> CORRECTO | J54: KUSPIT SP´S | K54: ANGIE | L54: PAGADO | M54: 45674 | N54: FACT 3465099
A55: EVODIO DE JESUS GOMEZ | B55: PAGO MANO DE OBRA TRABAJO NUEVAS OFICINAS | C55: EDIFICIOS | D55: =IFERROR(VLOOKUP($C55,CUENTAS[],2,0),"") -> ACTIVOS FIJOS | E55: =IFERROR(VLOOKUP($C55,CUENTAS[],3,0),"") -> MDE2025-007I | F55: 3500 | G55: 0 | H55: 3500 | I55: =+IF(F55+G55<>H55,"REVISAR","CORRECTO") -> CORRECTO | J55: KUSPIT SP´S | K55: NAYELI | L55: PAGADO | M55: 45674 | N55: N/A
A56: TIRSO DE JESUS DE LA CRUZ | B56: PAGO MANO DE OBRA TRABAJO NUEVAS OFICINAS | C56: EDIFICIOS | D56: =IFERROR(VLOOKUP($C56,CUENTAS[],2,0),"") -> ACTIVOS FIJOS | E56: =IFERROR(VLOOKUP($C56,CUENTAS[],3,0),"") -> MDE2025-007I | F56: 3200 | G56: 0 | H56: 3200 | I56: =+IF(F56+G56<>H56,"REVISAR","CORRECTO") -> CORRECTO | J56: KUSPIT SP´S | K56: NAYELI | L56: PAGADO | M56: 45674 | N56: N/A
A57: ALBERTO SUÁREZ JIMENEZ | B57: MANO DE OBRA - PROYECTOS FUTUROS 2025 | C57: PROYECTOS FUTUROS | D57: =IFERROR(VLOOKUP($C57,CUENTAS[],2,0),"") -> GASTOS VARIOS | E57: =IFERROR(VLOOKUP($C57,CUENTAS[],3,0),"") -> MDE2025-003K | F57: 10000 | G57: 0 | H57: 10000 | I57: =+IF(F57+G57<>H57,"REVISAR","CORRECTO") -> CORRECTO | J57: KUSPIT SP´S | K57: ENRIQUE | L57: PAGADO | M57: 45674 | N57: N/A
A58: GUILLERMO SUÁREZ JIMENEZ | B58: MANO DE OBRA - PROYECTOS FUTUROS 2025 | C58: PROYECTOS FUTUROS | D58: =IFERROR(VLOOKUP($C58,CUENTAS[],2,0),"") -> GASTOS VARIOS | E58: =IFERROR(VLOOKUP($C58,CUENTAS[],3,0),"") -> MDE2025-003K | F58: 10000 | G58: 0 | H58: 10000 | I58: =+IF(F58+G58<>H58,"REVISAR","CORRECTO") -> CORRECTO | J58: KUSPIT SP´S | K58: ENRIQUE | L58: PAGADO | M58: 45674 | N58: N/A
... A85: RICARDO MONTENEGRO | B85: PAGO POR SUSTITUCIÓN DE BATERIA Y SISTEMA DE ARRANQUE - MALIBÚ | C85: SERVICIO Y MANTENIMIENTO DE UNIDADES DE TRANSPORTE | D85: =IFERROR(VLOOKUP($C85,CUENTAS[],2,0),"") -> LOGÍSTICA | E85: =IFERROR(VLOOKUP($C85,CUENTAS[],3,0),"") -> MDE2025-006A | F85: 3970 | G85: 635.2 | H85: 4605.2 | I85: =+IF(F85+G85<>H85,"REVISAR","CORRECTO") -> CORRECTO | J85: KUSPIT SP´S | K85: FERNANDO | L85: PAGADO | M85: 45686 | N85: PENDIENTE
A86: Operadora Concesionaria Mexiquense SA de CV | B86: Contratación servicio flotilla MADE_3933411 - Garantia | C86: PEAJE-CASETA-TAG | D86: =IFERROR(VLOOKUP($C86,CUENTAS[],2,0),"") -> LOGÍSTICA | E86: =IFERROR(VLOOKUP($C86,CUENTAS[],3,0),"") -> MDE2025-006D | F86: -25000 | G86: 0 | H86: -25000 | I86: =+IF(F86+G86<>H86,"REVISAR","CORRECTO") -> CORRECTO | J86: KUSPIT SP´S | K86: FERNANDO | L86: PAGADO | M86: 45686 | N86: PENDIENTE / DEVOLUCION | P86: $ 25,000 DEVOLUCIÓN
A87: 365 INTELIGENCIA EN SEGURIDAD PRIVADA | B87: SERVICIO DE VIGILNCIA DEL 16 AL 31 DE ENERO 2025 | C87: VIGILANCIA | D87: =IFERROR(VLOOKUP($C87,CUENTAS[],2,0),"") -> GASTOS FIJOS | E87: =IFERROR(VLOOKUP($C87,CUENTAS[],3,0),"") -> MDE2025-002K | F87: 15525 | G87: 2484 | H87: 18009 | I87: =+IF(F87+G87<>H87,"REVISAR","CORRECTO") -> CORRECTO | J87: KUSPIT SP´S | K87: PRISCILA | L87: PAGADO | M87: 45686 | N87: 486
A88: Toka internacional S.A.P.I. de C.V. | B88: 2387957 | C88: COMBUSTIBLE TOKA | D88: =IFERROR(VLOOKUP($C88,CUENTAS[],2,0),"") -> TOKA | E88: =IFERROR(VLOOKUP($C88,CUENTAS[],3,0),"") -> TOK2025-001B | F88: 400 | G88: 64 | H88: 464 | I88: =+IF(F88+G88<>H88,"REVISAR","CORRECTO") -> CORRECTO | J88: KUSPIT SP´S | K88: NAYELI | L88: PAGADO | M88: 45686 | N88: FACTURA
A89: VIDEOSTAFF S.A. de C.V. | B89: Switcher para Streaming FeelWorld LIVEPRO L4 Series: L4A2400988 | C89: ILUMINACIÓN, AUDIO Y VIDEO | D89: =IFERROR(VLOOKUP($C89,CUENTAS[],2,0),"") -> ACTIVOS FIJOS | E89: =IFERROR(VLOOKUP($C89,CUENTAS[],3,0),"") -> MDE2025-007D | F89: 11370.69 | G89: 1819.31 | H89: 13190 | I89: =+IF(F89+G89<>H89,"REVISAR","CORRECTO") -> CORRECTO | J89: KUSPIT SP´S | K89: ELISA | L89: PAGADO | M89: 45686 | N89: FA24603
A90: COVARRUBIAS LAMA YAJAIRA ALEJANDRA | B90: COMPRA DE MADERA PARA APLANADO | C90: MANTENIMIENTO Y REPARACIÓN VARIOS | D90: =IFERROR(VLOOKUP($C90,CUENTAS[],2,0),"") -> MANTENIMIENTO | E90: =IFERROR(VLOOKUP($C90,CUENTAS[],3,0),"") -> MDE2025-009B | F90: 1015.55 | G90: 162.49 | H90: 1178.04 | I90: =+IF(F90+G90<>H90,"REVISAR","CORRECTO") -> CORRECTO | J90: KUSPIT SP´S | K90: ALEJANDRA | L90: PAGADO | M90: 45686 | N90: COMPROBANTES
A91: INTERCONTINENTAL SERVICES TLC | B91: BOLIGRAFO MADE | C91: REGALOS Y PATROCINIOS CLIENTES | D91: =IFERROR(VLOOKUP($C91,CUENTAS[],2,0),"") -> EVENTOS INTERNOS | E91: =IFERROR(VLOOKUP($C91,CUENTAS[],3,0),"") -> MDE2025-008B | F91: 3700 | G91: 592 | H91: 4292 | I91: =+IF(F91+G91<>H91,"REVISAR","CORRECTO") -> CORRECTO | J91: KUSPIT SP´S | K91: JAVIER | L91: PAGADO | M91: 45686 | N91: A_3596
A92: VICTOR MANUEL RUIZ ZARATE | B92: REEMBOLSO COMPRA TAQUETES, PIJAS - BODEGA 21ENE25 | C92: INSUMOS PARA MANTENIMIENTO BODEGA | D92: =IFERROR(VLOOKUP($C92,CUENTAS[],2,0),"") -> MANTENIMIENTO | E92: =IFERROR(VLOOKUP($C92,CUENTAS[],3,0),"") -> MDE2025-009A | F92: 132 | G92: 0 | H92: 132 | I92: =+IF(F92+G92<>H92,"REVISAR","CORRECTO") -> CORRECTO | J92: KUSPIT SP´S | K92: PRISCILA | L92: PAGADO | M92: 45686 | N92: COMPROBANTES
A93: JOSE E ZEPEDA BURGOS | B93: REEMBOLSO (2 PARES DE GUANTES,1 PAR CANDADOS,18 AMARTIGUADOR PARA PUERTA) 29/ENE/25 VICTOR RUIZ | C93: INSUMOS PARA MANTENIMIENTO BODEGA | D93: =IFERROR(VLOOKUP($C93,CUENTAS[],2,0),"") -> MANTENIMIENTO | E93: =IFERROR(VLOOKUP($C93,CUENTAS[],3,0),"") -> MDE2025-009A | F93: 500 | G93: 0 | H93: 500 | I93: =+IF(F93+G93<>H93,"REVISAR","CORRECTO") -> CORRECTO | J93: KUSPIT SP´S | K93: PRISCILA | L93: PAGADO | M93: 45687 | N93: COMPROBANTE
A94: JOSE E ZEPEDA BURGOS | B94: REEMBOLSO MATERIAL PLOMERIA OFICINAS NUEVAS - AMEX PLAT | C94: EDIFICIOS | D94: =IFERROR(VLOOKUP($C94,CUENTAS[],2,0),"") -> ACTIVOS FIJOS | E94: =IFERROR(VLOOKUP($C94,CUENTAS[],3,0),"") -> MDE2025-007I | F94: 4820.17 | G94: 0 | H94: 4820.17 | I94: =+IF(F94+G94<>H94,"REVISAR","CORRECTO") -> CORRECTO | J94: KUSPIT SP´S | K94: NAYELI | L94: PAGADO | M94: 45687 | N94: COMPROBANTE
A95: SECRETARIA DE FINANZAS | B95: TENENCIA, PLACAS Y TARJETA CIRCULACION DOLPHIN ELECTRICO 2025 | C95: VERIFICACIONES Y TENENCIAS | D95: =IFERROR(VLOOKUP($C95,CUENTAS[],2,0),"") -> LOGÍSTICA | E95: =IFERROR(VLOOKUP($C95,CUENTAS[],3,0),"") -> MDE2025-006B | F95: 1445 | G95: 0 | H95: 1445 | I95: =+IF(F95+G95<>H95,"REVISAR","CORRECTO") -> CORRECTO | J95: KUSPIT SP´S | K95: FERNANDO | L95: PAGADO | M95: 45692 | N95: COMPROBANTE
A96: VIDAL ESTRADA | B96: COMPRA DE MATERIALES PVC PARA CONSTRUCCION DE OFICINAS NUEVAS | C96: EDIFICIOS | D96: =IFERROR(VLOOKUP($C96,CUENTAS[],2,0),"") -> ACTIVOS FIJOS | E96: =IFERROR(VLOOKUP($C96,CUENTAS[],3,0),"") -> MDE2025-007I | F96: 4261 | G96: 0 | H96: 4261 | I96: =+IF(F96+G96<>H96,"REVISAR","CORRECTO") -> CORRECTO | J96: KUSPIT SP´S | K96: ALEJANDRA | L96: PAGADO | M96: 45688 | N96: COT508
A97: FERNANDO BECERRIL | B97: REEMBOLSO CASETAS PEDRO GOMEZ 30JUN25 - REVISION HYUNDAI | C97: PEAJE-CASETA-TAG | D97: =IFERROR(VLOOKUP($C97,CUENTAS[],2,0),"") -> LOGÍSTICA | E97: =IFERROR(VLOOKUP($C97,CUENTAS[],3,0),"") -> MDE2025-006D | F97: 199.14 | G97: 31.86 | H97: 231 | I97: =+IF(F97+G97<>H97,"REVISAR","CORRECTO") -> CORRECTO | J97: KUSPIT SP´S | K97: FERNANDO | L97: PAGADO | M97: 45688 | N97: COMPROBANTE
A98: EVODIO DE JESUS GOMEZ | B98: PAGO MANO DE OBRA TRABAJO NUEVAS OFICINAS | C98: EDIFICIOS | D98: =IFERROR(VLOOKUP($C98,CUENTAS[],2,0),"") -> ACTIVOS FIJOS | E98: =IFERROR(VLOOKUP($C98,CUENTAS[],3,0),"") -> MDE2025-007I | F98: 3500 | G98: 0 | H98: 3500 | I98: =+IF(F98+G98<>H98,"REVISAR","CORRECTO") -> CORRECTO | J98: KUSPIT SP´S | K98: NAYELI | L98: PAGADO | M98: 45688 | N98: N/A
A99: TIRSO DE JESUS DE LA CRUZ | B99: PAGO MANO DE OBRA TRABAJO NUEVAS OFICINAS | C99: EDIFICIOS | D99: =IFERROR(VLOOKUP($C99,CUENTAS[],2,0),"") -> ACTIVOS FIJOS | E99: =IFERROR(VLOOKUP($C99,CUENTAS[],3,0),"") -> MDE2025-007I | F99: 3200 | G99: 0 | H99: 3200 | I99: =+IF(F99+G99<>H99,"REVISAR","CORRECTO") -> CORRECTO | J99: KUSPIT SP´S | K99: NAYELI | L99: PAGADO | M99: 45688 | N99: N/A
A100: VICTOR MANUEL RUIZ ZARATE | B100: REEMBOLSO CADENAS Y CANDADOS PARA ALMACEN | C100: INSUMOS PARA MANTENIMIENTO BODEGA | D100: =IFERROR(VLOOKUP($C100,CUENTAS[],2,0),"") -> MANTENIMIENTO | E100: =IFERROR(VLOOKUP($C100,CUENTAS[],3,0),"") -> MDE2025-009A | F100: 370.69 | G100: 59.31 | H100: 430 | I100: =+IF(F100+G100<>H100,"REVISAR","CORRECTO") -> CORRECTO | J100: KUSPIT SP´S | K100: NAYELI | L100: PAGADO | M100: 45688 | N100: 2801
A101: ESTEFANY VICTORIA ROCHA | B101: FINIQUITO | C101: NÓMINA QUINCENAL FIJA | D101: =IFERROR(VLOOKUP($C101,CUENTAS[],2,0),"") -> GASTOS FIJOS | E101: =IFERROR(VLOOKUP($C101,CUENTAS[],3,0),"") -> MDE2025-002O | F101: 1869.86 | G101: 0 | H101: 1869.86 | I101: =+IF(F101+G101<>H101,"REVISAR","CORRECTO") -> CORRECTO | J101: KUSPIT SP´S | K101: ANGIE | L101: PAGADO | M101: 45688 | N101: N/A
A102: OSCAR SUÁREZ JIMENEZ | B102: MANO DE OBRA - PROYECTOS FUTUROS | C102: PROYECTOS FUTUROS | D102: =IFERROR(VLOOKUP($C102,CUENTAS[],2,0),"") -> GASTOS VARIOS | E102: =IFERROR(VLOOKUP($C102,CUENTAS[],3,0),"") -> MDE2025-003K | F102: 8000 | G102: 0 | H102: 8000 | I102: =+IF(F102+G102<>H102,"REVISAR","CORRECTO") -> CORRECTO | J102: KUSPIT SP´S | K102: ENRIQUE | L102: PAGADO | M102: 45688 | N102: N/A
A103: ALBERTO SUÁREZ JIMENEZ | B103: MANO DE OBRA - PROYECTOS FUTUROS | C103: PROYECTOS FUTUROS | D103: =IFERROR(VLOOKUP($C103,CUENTAS[],2,0),"") -> GASTOS VARIOS | E103: =IFERROR(VLOOKUP($C103,CUENTAS[],3,0),"") -> MDE2025-003K | F103: 8000 | G103: 0 | H103: 8000 | I103: =+IF(F103+G103<>H103,"REVISAR","CORRECTO") -> CORRECTO | J103: KUSPIT SP´S | K103: ENRIQUE | L103: PAGADO | M103: 45688 | N103: N/A
A104: GUILLERMO SUÁREZ JIMENEZ | B104: MANO DE OBRA - PROYECTOS FUTUROS | C104: PROYECTOS FUTUROS | D104: =IFERROR(VLOOKUP($C104,CUENTAS[],2,0),"") -> GASTOS VARIOS | E104: =IFERROR(VLOOKUP($C104,CUENTAS[],3,0),"") -> MDE2025-003K | F104: 8000 | G104: 0 | H104: 8000 | I104: =+IF(F104+G104<>H104,"REVISAR","CORRECTO") -> CORRECTO | J104: KUSPIT SP´S | K104: ENRIQUE | L104: PAGADO | M104: 45688 | N104: N/A
A105: ALEJANDRO SUÁREZ JIMENEZ | B105: MANO DE OBRA - PROYECTOS FUTUROS | C105: PROYECTOS FUTUROS | D105: =IFERROR(VLOOKUP($C105,CUENTAS[],2,0),"") -> GASTOS VARIOS | E105: =IFERROR(VLOOKUP($C105,CUENTAS[],3,0),"") -> MDE2025-003K | F105: 8000 | G105: 0 | H105: 8000 | I105: =+IF(F105+G105<>H105,"REVISAR","CORRECTO") -> CORRECTO | J105: KUSPIT SP´S | K105: ENRIQUE | L105: PAGADO | M105: 45688 | N105: N/A
A106: JOSE E ZEPEDA BURGOS | B106: REEMBOLSO EUROELECTRICA - OFICINAS NUEVAS | C106: EDIFICIOS | D106: =IFERROR(VLOOKUP($C106,CUENTAS[],2,0),"") -> ACTIVOS FIJOS | E106: =IFERROR(VLOOKUP($C106,CUENTAS[],3,0),"") -> MDE2025-007I | F106: 12056.15 | G106: 0 | H106: 12056.15 | I106: =+IF(F106+G106<>H106,"REVISAR","CORRECTO") -> CORRECTO | J106: KUSPIT SP´S | K106: ENRIQUE | L106: PAGADO | M106: 45688 | N106: COMPROBANTE
A107: JULIO SERRANO | B107: COMPRA DE MONITOR | C107: ILUMINACIÓN, AUDIO Y VIDEO | D107: =IFERROR(VLOOKUP($C107,CUENTAS[],2,0),"") -> ACTIVOS FIJOS | E107: =IFERROR(VLOOKUP($C107,CUENTAS[],3,0),"") -> MDE2025-007D | F107: 8000 | G107: 0 | H107: 8000 | I107: =+IF(F107+G107<>H107,"REVISAR","CORRECTO") -> CORRECTO | J107: KUSPIT SP´S | K107: LESLIE | L107: PAGADO | M107: 45688 | N107: N/A
A108: SECRETARIA DE FINANZAS | B108: TENENCIA 2025 - HYUNDAI EX8 CHASIS CABINA 2 ejes, DIESEL, 4500-9500Kg PBV | C108: VERIFICACIONES Y TENENCIAS | D108: =IFERROR(VLOOKUP($C108,CUENTAS[],2,0),"") -> LOGÍSTICA | E108: =IFERROR(VLOOKUP($C108,CUENTAS[],3,0),"") -> MDE2025-006B | F108: 6035 | G108: 0 | H108: 6035 | I108: =+IF(F108+G108<>H108,"REVISAR","CORRECTO") -> CORRECTO | J108: KUSPIT SP´S | K108: FERNANDO | L108: PAGADO | M108: 45688 | N108: COMPROBANTE
A109: FERNANDO BECERRIL | B109: REEMBOLSO DE CASETAS - BFM, HEIZ, RBM /FERNANDO BECERRIL | C109: COMBUSTIBLE | D109: =IFERROR(VLOOKUP($C109,CUENTAS[],2,0),"") -> GASTOS VARIOS | E109: =IFERROR(VLOOKUP($C109,CUENTAS[],3,0),"") -> MDE2025-003D | F109: 420 | G109: 0 | H109: 420 | I109: =+IF(F109+G109<>H109,"REVISAR","CORRECTO") -> CORRECTO | J109: KUSPIT SP´S | K109: FERNANDO | L109: PAGADO | M109: 45667 | N109: COMPROBANTE
A110: FERNANDO BECERRIL | B110: REEMBOLSO DE CASETAS Y VERIFICACION TOYOTA FERNANDO BECERRIL | C110: ESTACIONAMIENTO Y SERVICIOS DE TRANSPORTE | D110: =IFERROR(VLOOKUP($C110,CUENTAS[],2,0),"") -> LOGÍSTICA | E110: =IFERROR(VLOOKUP($C110,CUENTAS[],3,0),"") -> MDE2025-003E | F110: 750 | G110: 0 | H110: 750 | I110: =+IF(F110+G110<>H110,"REVISAR","CORRECTO") -> CORRECTO | J110: KUSPIT SP´S | K110: FERNANDO | L110: PAGADO | M110: 45672 | N110: COMPROBANTE
A111: FERNANDO BECERRIL | B111: REEMBOLSO DE CASETAS, TALACHAS MULTAS Y COMBUSTIBLE | C111: SERVICIO Y MANTENIMIENTO DE UNIDADES DE TRANSPORTE | D111: =IFERROR(VLOOKUP($C111,CUENTAS[],2,0),"") -> LOGÍSTICA | E111: =IFERROR(VLOOKUP($C111,CUENTAS[],3,0),"") -> MDE2025-006A | F111: 380 | G111: 0 | H111: 380 | I111: =+IF(F111+G111<>H111,"REVISAR","CORRECTO") -> CORRECTO | J111: KUSPIT SP´S | K111: FERNANDO | L111: PAGADO | M111: 45315 | N111: COMPROBANTES
A112: SUAREZ | B112: PAGO MANO DE OBRA REJA CUARTO COMPRESOR | C112: MANTENIMIENTO Y REPARACIÓN VARIOS | D112: =IFERROR(VLOOKUP($C112,CUENTAS[],2,0),"") -> MANTENIMIENTO | E112: =IFERROR(VLOOKUP($C112,CUENTAS[],3,0),"") -> MDE2025-009B | F112: 6000 | G112: 0 | H112: 6000 | I112: =+IF(F112+G112<>H112,"REVISAR","CORRECTO") -> CORRECTO | J112: KUSPIT SP´S | K112: ENRIQUE | L112: PAGADO | M112: 45660 | N112: N/A
... A121: JOSE E ZEPEDA BURGOS | B121: REGALOS CLIENTES | C121: REGALOS Y PATROCINIOS CLIENTES | D121: =IFERROR(VLOOKUP($C121,CUENTAS[],2,0),"") -> EVENTOS INTERNOS | E121: =IFERROR(VLOOKUP($C121,CUENTAS[],3,0),"") -> MDE2025-008B | F121: 8581.05 | G121: 0 | H121: 8581.05 | I121: =+IF(F121+G121<>H121,"REVISAR","CORRECTO") -> CORRECTO | J121: AMEX | K121: LESLIE | L121: PAGADO | M121: 45692 | N121: PENDIENTE
A122: JOSE E ZEPEDA BURGOS | B122: SERVICIO TOYOTA | C122: SERVICIO Y MANTENIMIENTO DE UNIDADES DE TRANSPORTE | D122: =IFERROR(VLOOKUP($C122,CUENTAS[],2,0),"") -> LOGÍSTICA | E122: =IFERROR(VLOOKUP($C122,CUENTAS[],3,0),"") -> MDE2025-006A | F122: 11848.27 | G122: 1895.73 | H122: 13744 | I122: =+IF(F122+G122<>H122,"REVISAR","CORRECTO") -> CORRECTO | J122: AMEX | K122: ENRIQUE | L122: PAGADO | M122: 45692 | N122: 289618
A123: JOSE E ZEPEDA BURGOS | B123: LICENCIA SHUTTERSTOCK | C123: LICENCIAS Y CERTIFICACIONES | D123: =IFERROR(VLOOKUP($C123,CUENTAS[],2,0),"") -> GASTOS FIJOS | E123: =IFERROR(VLOOKUP($C123,CUENTAS[],3,0),"") -> MDE2025-002J | F123: 615.63 | G123: 0 | H123: 615.63 | I123: =+IF(F123+G123<>H123,"REVISAR","CORRECTO") -> CORRECTO | J123: AMEX | K123: JAVIER MENA | L123: PAGADO | M123: 45692 | N123: RECIBO
A124: JOSE E ZEPEDA BURGOS | B124: OPENPAY*STARLINK CIUDAD DE MEXIC | C124: SERVICIOS TELEFÓNICOS E INTERNET | D124: =IFERROR(VLOOKUP($C124,CUENTAS[],2,0),"") -> GASTOS FIJOS | E124: =IFERROR(VLOOKUP($C124,CUENTAS[],3,0),"") -> MDE2025-002F | F124: 3148 | G124: 0 | H124: 3148 | I124: =+IF(F124+G124<>H124,"REVISAR","CORRECTO") -> CORRECTO | J124: AMEX | K124: PRISCILA | L124: PAGADO | M124: 45692 | N124: PENDIENTE
A125: JOSE E ZEPEDA BURGOS | B125: MATERIALES PARA CONSTRUCCION OFICINAS NUEVAS | C125: EDIFICIOS | D125: =IFERROR(VLOOKUP($C125,CUENTAS[],2,0),"") -> ACTIVOS FIJOS | E125: =IFERROR(VLOOKUP($C125,CUENTAS[],3,0),"") -> MDE2025-007I | F125: 3839.46 | G125: 614.31 | H125: 4453.77 | I125: =+IF(F125+G125<>H125,"REVISAR","CORRECTO") -> CORRECTO | J125: AMEX | K125: ARIADNA | L125: PAGADO | M125: 45722 | N125: XBA60007
A126: JOSE E ZEPEDA BURGOS | B126: COMPRA DE CELULAR ALEJANDRA COVARRUBIAS | C126: EQUIPO DE CÓMPUTO Y TELEFONÍA | D126: =IFERROR(VLOOKUP($C126,CUENTAS[],2,0),"") -> ACTIVOS FIJOS | E126: =IFERROR(VLOOKUP($C126,CUENTAS[],3,0),"") -> MDE2025-007B | F126: 6299 | G126: 0 | H126: 6299 | I126: =+IF(F126+G126<>H126,"REVISAR","CORRECTO") -> CORRECTO | J126: AMEX | K126: JESSICA | L126: PAGADO | M126: 45722 | N126: INVOICE
A127: GASOL EST MULATA 3488 | B127: COMPRA DE REGALOS CLIENTES | C127: COMBUSTIBLE | D127: =IFERROR(VLOOKUP($C127,CUENTAS[],2,0),"") -> GASTOS VARIOS | E127: =IFERROR(VLOOKUP($C127,CUENTAS[],3,0),"") -> MDE2025-003D | F127: 346.14 | G127: 53.86 | H127: 400 | I127: =+IF(F127+G127<>H127,"REVISAR","CORRECTO") -> CORRECTO | J127: TOKA COMBUSTIBLES | K127: EDUARDO | L127: PAGADO | M127: 45673 | N127: W231834
A128: MULTISERVS DUAL | B128: MOV VARIOS | C128: COMBUSTIBLE | D128: =IFERROR(VLOOKUP($C128,CUENTAS[],2,0),"") -> GASTOS VARIOS | E128: =IFERROR(VLOOKUP($C128,CUENTAS[],3,0),"") -> MDE2025-003D | F128: 432.68 | G128: 67.32 | H128: 500 | I128: =+IF(F128+G128<>H128,"REVISAR","CORRECTO") -> CORRECTO | J128: TOKA COMBUSTIBLES | K128: EDUARDO | L128: PAGADO | M128: 45664 | N128: W230941
A129: GAS LEVET 3 | B129: COMPRAS MISCELANEAS | C129: COMBUSTIBLE | D129: =IFERROR(VLOOKUP($C129,CUENTAS[],2,0),"") -> GASTOS VARIOS | E129: =IFERROR(VLOOKUP($C129,CUENTAS[],3,0),"") -> MDE2025-003D | F129: 432.68 | G129: 67.32 | H129: 500 | I129: =+IF(F129+G129<>H129,"REVISAR","CORRECTO") -> CORRECTO | J129: TOKA COMBUSTIBLES | K129: EDUARDO | L129: PAGADO | M129: 45680 | N129: 6410 ALVT
A130: GASOL MOBIL METEPEC | B130: ENRIQUE ZEPEDA | C130: COMBUSTIBLE | D130: =IFERROR(VLOOKUP($C130,CUENTAS[],2,0),"") -> GASTOS VARIOS | E130: =IFERROR(VLOOKUP($C130,CUENTAS[],3,0),"") -> MDE2025-003D | F130: 1000 | G130: 0 | H130: 1000 | I130: =+IF(F130+G130<>H130,"REVISAR","CORRECTO") -> CORRECTO | J130: TOKA COMBUSTIBLES | K130: ENRIQUE | L130: PAGADO | M130: 45680 | N130: SIN FACT
A131: AUTOMOTRIZ HF | B131: CUMBRES METEPEC ROGELIO V | C131: COMBUSTIBLE | D131: =IFERROR(VLOOKUP($C131,CUENTAS[],2,0),"") -> GASTOS VARIOS | E131: =IFERROR(VLOOKUP($C131,CUENTAS[],3,0),"") -> MDE2025-003D | F131: 600 | G131: 0 | H131: 600 | I131: =+IF(F131+G131<>H131,"REVISAR","CORRECTO") -> CORRECTO | J131: TOKA COMBUSTIBLES | K131: ROGELIO V | L131: PAGADO | M131: 45687 | N131: SIN FACT
A132: AT&T | B132: CHIP ATT PARA ADMON | C132: TELEFONÍA E INTERNET | D132: =IFERROR(VLOOKUP($C132,CUENTAS[],2,0),"") -> GASTOS VARIOS | E132: =IFERROR(VLOOKUP($C132,CUENTAS[],3,0),"") -> MDE2025-003C | F132: 86.21 | G132: 13.79 | H132: 100 | I132: =+IF(F132+G132<>H132,"REVISAR","CORRECTO") -> CORRECTO | J132: CAJA CHICA | K132: NAYELI | L132: PAGADO | M132: 45659 | N132: SIN FACT
A133: LAVANDERIA SEÑOR BURBUJA | B133: SERV LAVANDERIA UNIFORMES | C133: UNIFORMES Y EPP | D133: =IFERROR(VLOOKUP($C133,CUENTAS[],2,0),"") -> GASTOS VARIOS | E133: =IFERROR(VLOOKUP($C133,CUENTAS[],3,0),"") -> MDE2025-003B | F133: 128 | G133: 0 | H133: 128 | I133: =+IF(F133+G133<>H133,"REVISAR","CORRECTO") -> CORRECTO | J133: CAJA CHICA | K133: ALEJANDRA | L133: PAGADO | M133: 45659 | N133: T1793
A134: PROMOTORA Y ADMINISTRADORA DE CARRETERAS | B134: CASETAS PEDRO 02ENE25 / MOV MADE | C134: ESTACIONAMIENTO Y SERVICIOS DE TRANSPORTE | D134: =IFERROR(VLOOKUP($C134,CUENTAS[],2,0),"") -> LOGÍSTICA | E134: =IFERROR(VLOOKUP($C134,CUENTAS[],3,0),"") -> MDE2025-003E | F134: 181.03 | G134: 28.97 | H134: 210 | I134: =+IF(F134+G134<>H134,"REVISAR","CORRECTO") -> CORRECTO | J134: CAJA CHICA | K134: PEDRO | L134: PAGADO | M134: 45659 | N134: FACT 9056487
... A151: PROMETOR | B151: 5 DISCO DE CORTE | C151: INSUMOS PARA MANTENIMIENTO BODEGA | D151: =IFERROR(VLOOKUP($C151,CUENTAS[],2,0),"") -> MANTENIMIENTO | E151: =IFERROR(VLOOKUP($C151,CUENTAS[],3,0),"") -> MDE2025-009A | F151: 442.93 | G151: 0 | H151: 442.93 | I151: =+IF(F151+G151<>H151,"REVISAR","CORRECTO") -> CORRECTO | J151: CAJA CHICA | K151: NAYELI | L151: PAGADO | M151: 45687 | N151: NV38645
A152: KAWIR GRUPO SA DE CV | B152: NOMINA SEMANAL DEL 20 AL 26ENE25 | C152: NÓMINA SEMANAL BODEGA | D152: =IFERROR(VLOOKUP($C152,CUENTAS[],2,0),"") -> GASTOS FIJOS | E152: =IFERROR(VLOOKUP($C152,CUENTAS[],3,0),"") -> MDE2025-002L | F152: =+H152 -> 30461.2 | G152: 0 | H152: 30461.2 | I152: =+IF(F152+G152<>H152,"REVISAR","CORRECTO") -> CORRECTO | J152: KUSPIT SP´S | K152: ANGIE | L152: PAGADO | M152: 45684 | N152: N/A
A153: KAWIR GRUPO SA DE CV | B153: NOMINA SEMANAL DEL 13 AL 19ENE25 | C153: NÓMINA SEMANAL BODEGA | D153: =IFERROR(VLOOKUP($C153,CUENTAS[],2,0),"") -> GASTOS FIJOS | E153: =IFERROR(VLOOKUP($C153,CUENTAS[],3,0),"") -> MDE2025-002L | F153: =+H153 -> 31018.14 | G153: 0 | H153: 31018.14 | I153: =+IF(F153+G153<>H153,"REVISAR","CORRECTO") -> CORRECTO | J153: KUSPIT SP´S | K153: ANGIE | L153: PAGADO | M153: 45677 | N153: N/A
A154: KAWIR GRUPO SA DE CV | B154: NOMINA SEMANAL DEL 6 AL 12 ENE25 | C154: NÓMINA SEMANAL BODEGA | D154: =IFERROR(VLOOKUP($C154,CUENTAS[],2,0),"") -> GASTOS FIJOS | E154: =IFERROR(VLOOKUP($C154,CUENTAS[],3,0),"") -> MDE2025-002L | F154: =+H154 -> 29724.66 | G154: 0 | H154: 29724.66 | I154: =+IF(F154+G154<>H154,"REVISAR","CORRECTO") -> CORRECTO | J154: KUSPIT SP´S | K154: ANGIE | L154: PAGADO | M154: 45670 | N154: N/A
A155: KAWIR GRUPO SA DE CV | B155: NOMINA SEMANAL DEL 30DIC24 AL 05ENE25 | C155: NÓMINA SEMANAL BODEGA | D155: =IFERROR(VLOOKUP($C155,CUENTAS[],2,0),"") -> GASTOS FIJOS | E155: =IFERROR(VLOOKUP($C155,CUENTAS[],3,0),"") -> MDE2025-002L | F155: =+H155 -> 32785.06 | G155: 0 | H155: 32785.06 | I155: =+IF(F155+G155<>H155,"REVISAR","CORRECTO") -> CORRECTO | J155: KUSPIT SP´S | K155: ANGIE | L155: PAGADO | M155: 45670 | N155: N/A
A156: KAWIR GRUPO SA DE CV | B156: NOMINA QUINCENAL 1-15ENE25 FISCAL | C156: NÓMINA SEMANAL BODEGA | D156: =IFERROR(VLOOKUP($C156,CUENTAS[],2,0),"") -> GASTOS FIJOS | E156: =IFERROR(VLOOKUP($C156,CUENTAS[],3,0),"") -> MDE2025-002L | F156: =+H156 -> 49909.8 | G156: 0 | H156: 49909.8 | I156: =+IF(F156+G156<>H156,"REVISAR","CORRECTO") -> CORRECTO | J156: KUSPIT SP´S | K156: ANGIE | L156: PAGADO | M156: 45672 | N156: N/A
A157: KAWIR GRUPO SA DE CV | B157: NOMINA QUINCENAL 1-15ENE25 ASIMILADOS | C157: NÓMINA SEMANAL BODEGA | D157: =IFERROR(VLOOKUP($C157,CUENTAS[],2,0),"") -> GASTOS FIJOS | E157: =IFERROR(VLOOKUP($C157,CUENTAS[],3,0),"") -> MDE2025-002L | F157: =+H157 -> 119852.2 | G157: 0 | H157: 119852.2 | I157: =+IF(F157+G157<>H157,"REVISAR","CORRECTO") -> CORRECTO | J157: KUSPIT SP´S | K157: ANGIE | L157: PAGADO | M157: 45672 | N157: N/A
A158: KAWIR GRUPO SA DE CV | B158: DESC PRESTAMOS 1-15ENE25 | C158: PRÉSTAMOS PERSONALES | D158: =IFERROR(VLOOKUP($C158,CUENTAS[],2,0),"") -> GASTOS FIJOS | E158: =IFERROR(VLOOKUP($C158,CUENTAS[],3,0),"") -> MDE2025-002Q | F158: =+H158 -> -1750 | G158: 0 | H158: -1750 | I158: =+IF(F158+G158<>H158,"REVISAR","CORRECTO") -> CORRECTO | J158: KUSPIT SP´S | K158: ANGIE | L158: PAGADO | M158: 45672 | N158: N/A
A159: KAWIR GRUPO SA DE CV | B159: NOMINA QUINCENAL 16 AL 31ENE25 FISCAL | C159: NÓMINA SEMANAL BODEGA | D159: =IFERROR(VLOOKUP($C159,CUENTAS[],2,0),"") -> GASTOS FIJOS | E159: =IFERROR(VLOOKUP($C159,CUENTAS[],3,0),"") -> MDE2025-002L | F159: =+H159 -> 49406.52 | G159: 0 | H159: 49406.52 | I159: =+IF(F159+G159<>H159,"REVISAR","CORRECTO") -> CORRECTO | J159: KUSPIT SP´S | K159: ANGIE | L159: PAGADO | M159: 45672 | N159: N/A
A160: KAWIR GRUPO SA DE CV | B160: NOMINA QUINCENAL ASIMILADOS 16 AL 31ENE25 | C160: NÓMINA SEMANAL BODEGA | D160: =IFERROR(VLOOKUP($C160,CUENTAS[],2,0),"") -> GASTOS FIJOS | E160: =IFERROR(VLOOKUP($C160,CUENTAS[],3,0),"") -> MDE2025-002L | F160: =+H160 -> 133105.48 | G160: 0 | H160: 133105.48 | I160: =+IF(F160+G160<>H160,"REVISAR","CORRECTO") -> CORRECTO | J160: KUSPIT SP´S | K160: ANGIE | L160: PAGADO | M160: 45672 | N160: N/A
A161: KAWIR GRUPO SA DE CV | B161: DESC PRESTAMOS 16 AL 31ENE25 | C161: PRÉSTAMOS PERSONALES | D161: =IFERROR(VLOOKUP($C161,CUENTAS[],2,0),"") -> GASTOS FIJOS | E161: =IFERROR(VLOOKUP($C161,CUENTAS[],3,0),"") -> MDE2025-002Q | F161: =+H161 -> -1750 | G161: 0 | H161: -1750 | I161: =+IF(F161+G161<>H161,"REVISAR","CORRECTO") -> CORRECTO | J161: KUSPIT SP´S | K161: ANGIE | L161: PAGADO | M161: 45672 | N161: N/A
A162: JESSICA GARCIA | B162: COMPLEMENTO DE NOMINA - DESC IMPROCEDENTE | C162: NÓMINA SEMANAL BODEGA | D162: =IFERROR(VLOOKUP($C162,CUENTAS[],2,0),"") -> GASTOS FIJOS | E162: =IFERROR(VLOOKUP($C162,CUENTAS[],3,0),"") -> MDE2025-002L | F162: 500 | G162: 0 | H162: 500 | I162: =+IF(F162+G162<>H162,"REVISAR","CORRECTO") -> CORRECTO | J162: KUSPIT SP´S | K162: ANGIE | L162: PAGADO | M162: 45674 | N162: N/A
A163: CAROLINA ABIGAIL GARCIA MEDINA | B163: PAGO FINIQUITO | C163: NÓMINA QUINCENAL FIJA | D163: =IFERROR(VLOOKUP($C163,CUENTAS[],2,0),"") -> GASTOS FIJOS | E163: =IFERROR(VLOOKUP($C163,CUENTAS[],3,0),"") -> MDE2025-002O | F163: 2082.19 | G163: 0 | H163: 2082.19 | I163: =+IF(F163+G163<>H163,"REVISAR","CORRECTO") -> CORRECTO | J163: KUSPIT SP´S | K163: ANGIE | L163: PAGADO | M163: 45674 | N163: N/A
N172: SUBTOTAL | O172: =+SUM(F:F) -> 2086743.4
N173: IVA | O173: =+SUM(G:G) -> 51303.57
N174: TOTAL GTO NO IMP. | O174: =+SUM(H:H) -> 2138047 | P174: =O174-O173-O172 -> 0
O175: =IF(P174<>0,"REVISAR CAPTURA","")

Sheet FEB25
A1: PROVEEDOR | B1: CONCEPTO | C1: SUBCUENTA | D1: CUENTA | E1: CLAVE | F1: SUBTOTAL | G1: IVA | H1: TOTAL | I1: VALIDACIÓN | J1: FORMA DE PAGO | K1: EJECUTIVO | L1: STATUS | M1: FECHA | N1: FACTURA
A2: VICTOR MANUEL RUIZ ZARATE | B2: REEMBOLSO CHAVETA INOXIDABLE - BODEGA | C2: INSUMOS PARA MANTENIMIENTO BODEGA | D2: =IFERROR(VLOOKUP($C2,CUENTAS[],2,0),"") -> MANTENIMIENTO | E2: =IFERROR(VLOOKUP($C2,CUENTAS[],3,0),"") -> MDE2025-009A | F2: 12.93 | G2: 2.07 | H2: 15 | I2: =IFERROR(IF(F2+G2<>H2,"REVISAR","CORRECTO"),"") -> CORRECTO | J2: KUSPIT SP´S | K2: NAYELI | L2: PAGADO | M2: 45693 | N2: 2692
A3: VIDAL ESTRADA | B3: COMPRA DE MATERIAL PARA DRENAJE DE OFICINAS NUEVAS | C3: EDIFICIOS | D3: =IFERROR(VLOOKUP($C3,CUENTAS[],2,0),"") -> ACTIVOS FIJOS | E3: =IFERROR(VLOOKUP($C3,CUENTAS[],3,0),"") -> MDE2025-007I | F3: 3187 | G3: 0 | H3: 3187 | I3: =IFERROR(IF(F3+G3<>H3,"REVISAR","CORRECTO"),"") -> CORRECTO | J3: KUSPIT SP´S | K3: ALEJANDRA | L3: PAGADO | M3: 45693 | N3: COT0339
A4: MARIA NANCY QUEZADA HERNANDEZ | B4: COMPRA DE 1/2 TONELADA DE CEMENTO PARA OFICINAS NUEVAS | C4: EDIFICIOS | D4: =IFERROR(VLOOKUP($C4,CUENTAS[],2,0),"") -> ACTIVOS FIJOS | E4: =IFERROR(VLOOKUP($C4,CUENTAS[],3,0),"") -> MDE2025-007I | F4: 3000 | G4: 0 | H4: 3000 | I4: =IFERROR(IF(F4+G4<>H4,"REVISAR","CORRECTO"),"") -> CORRECTO | J4: KUSPIT SP´S | K4: ALEJANDRA | L4: PAGADO | M4: 45693 | N4: PENDIENTE
A5: ECONOCOMEX INTERNACIONAL SA DE CV | B5: TAMBO DE THINNER PARA BODEGA | C5: POOL DE MATERIALES | D5: =IFERROR(VLOOKUP($C5,CUENTAS[],2,0),"") -> MATERIALES | E5: =IFERROR(VLOOKUP($C5,CUENTAS[],3,0),"") -> MDE2025-004 | F5: 5061.21 | G5: 809.79 | H5: 5871 | I5: =IFERROR(IF(F5+G5<>H5,"REVISAR","CORRECTO"),"") -> CORRECTO | J5: KUSPIT SP´S | K5: ALEJANDRA | L5: PAGADO | M5: 45693 | N5: F34462
A6: JOSE E ZEPEDA BURGOS | B6: REEMBOLSO MO LUIS ELECTRICO - OFICINAS NUEVAS 03FEB25 | C6: EDIFICIOS | D6: =IFERROR(VLOOKUP($C6,CUENTAS[],2,0),"") -> ACTIVOS FIJOS | E6: =IFERROR(VLOOKUP($C6,CUENTAS[],3,0),"") -> MDE2025-007I | F6: 4000 | G6: 0 | H6: 4000 | I6: =IFERROR(IF(F6+G6<>H6,"REVISAR","CORRECTO"),"") -> CORRECTO | J6: KUSPIT SP´S | K6: NAYELI | L6: PAGADO | M6: 45693 | N6: COMPROBANTE
A7: JOSE E ZEPEDA BURGOS | B7: REEMBOLSO MO DANIEL ARELLANO - PROYECTOS FUTUROS 31ENE25 | C7: PROYECTOS FUTUROS | D7: =IFERROR(VLOOKUP($C7,CUENTAS[],2,0),"") -> GASTOS VARIOS | E7: =IFERROR(VLOOKUP($C7,CUENTAS[],3,0),"") -> MDE2025-003K | F7: 10000 | G7: 0 | H7: 10000 | I7: =IFERROR(IF(F7+G7<>H7,"REVISAR","CORRECTO"),"") -> CORRECTO | J7: KUSPIT SP´S | K7: NAYELI | L7: PAGADO | M7: 45693 | N7: COMPROBANTE
A8: JOSE E ZEPEDA BURGOS | B8: REEMBOLSO MANTENIMIENTO HIACE- LOGISTICA | C8: SERVICIO Y MANTENIMIENTO DE UNIDADES DE TRANSPORTE | D8: =IFERROR(VLOOKUP($C8,CUENTAS[],2,0),"") -> LOGÍSTICA | E8: =IFERROR(VLOOKUP($C8,CUENTAS[],3,0),"") -> MDE2025-006A | F8: 8800 | G8: 0 | H8: 8800 | I8: =IFERROR(IF(F8+G8<>H8,"REVISAR","CORRECTO"),"") -> CORRECTO | J8: KUSPIT SP´S | K8: PRISCILA | L8: PAGADO | M8: 45693 | N8: COMPROBANTE
A9: COVARRUBIAS LAMA YAJAIRA ALEJANDRA | B9: REEMBOLSO DE PILAS PARA LASER 05FEB25 | C9: PAPELERÍA E INSUMOS DE LIMPIEZA | D9: =IFERROR(VLOOKUP($C9,CUENTAS[],2,0),"") -> GASTOS VARIOS | E9: =IFERROR(VLOOKUP($C9,CUENTAS[],3,0),"") -> MDE2025-003A | F9: 120.26 | G9: 19.24 | H9: 139.5 | I9: =IFERROR(IF(F9+G9<>H9,"REVISAR","CORRECTO"),"") -> CORRECTO | J9: KUSPIT SP´S | K9: ALEJANDRA | L9: PAGADO | M9: 45695 | N9: FAC 05102
A10: EVODIO DE JESUS GOMEZ | B10: PAGO MANO DE OBRA TRABAJO NUEVAS OFICINAS | C10: EDIFICIOS | D10: =IFERROR(VLOOKUP($C10,CUENTAS[],2,0),"") -> ACTIVOS FIJOS | E10: =IFERROR(VLOOKUP($C10,CUENTAS[],3,0),"") -> MDE2025-007I | F10: 3500 | G10: 0 | H10: 3500 | I10: =IFERROR(IF(F10+G10<>H10,"REVISAR","CORRECTO"),"") -> CORRECTO | J10: KUSPIT SP´S | K10: PRISCILA | L10: PAGADO | M10: 45695 | N10: NA
A11: TIRSO DE JESUS DE LA CRUZ | B11: PAGO MANO DE OBRA TRABAJO NUEVAS OFICINAS | C11: EDIFICIOS | D11: =IFERROR(VLOOKUP($C11,CUENTAS[],2,0),"") -> ACTIVOS FIJOS | E11: =IFERROR(VLOOKUP($C11,CUENTAS[],3,0),"") -> MDE2025-007I | F11: 3200 | G11: 0 | H11: 3200 | I11: =IFERROR(IF(F11+G11<>H11,"REVISAR","CORRECTO"),"") -> CORRECTO | J11: KUSPIT SP´S | K11: PRISCILA | L11: PAGADO | M11: 45695 | N11: NA
A12: VICTOR HUGO MARTINEZ GONZALEZ | B12: MO POR DRENAJE $4500, BOMBA $1800Y $800 TINACO | C12: MANTENIMIENTO Y REPARACIÓN VARIOS | D12: =IFERROR(VLOOKUP($C12,CUENTAS[],2,0),"") -> MANTENIMIENTO | E12: =IFERROR(VLOOKUP($C12,CUENTAS[],3,0),"") -> MDE2025-009B | F12: 7100 | G12: 0 | H12: 7100 | I12: =IFERROR(IF(F12+G12<>H12,"REVISAR","CORRECTO"),"") -> CORRECTO | J12: KUSPIT SP´S | K12: ENRIQUE | L12: PAGADO | M12: 45695 | N12: NA
A13: Toka internacional S.A.P.I. de C.V. | B13: 2402243 | C13: COMISIONES TOKA | D13: =IFERROR(VLOOKUP($C13,CUENTAS[],2,0),"") -> TOKA | E13: =IFERROR(VLOOKUP($C13,CUENTAS[],3,0),"") -> TOK2025-001C | F13: 400 | G13: 64 | H13: 464 | I13: =IFERROR(IF(F13+G13<>H13,"REVISAR","CORRECTO"),"") -> CORRECTO | J13: KUSPIT SP´S | K13: NAYELI | L13: PAGADO | M13: 45699 | N13: PREFACTURA
A14: LUIS ANTONIO GARDUÑO TAPIA | B14: PAGO MANO DE OBRA - CONSTRUCCION OFICINAS | C14: MANTENIMIENTO Y REPARACIÓN VARIOS | D14: =IFERROR(VLOOKUP($C14,CUENTAS[],2,0),"") -> MANTENIMIENTO | E14: =IFERROR(VLOOKUP($C14,CUENTAS[],3,0),"") -> MDE2025-009B | F14: 1500 | G14: 0 | H14: 1500 | I14: =IFERROR(IF(F14+G14<>H14,"REVISAR","CORRECTO"),"") -> CORRECTO | J14: KUSPIT SP´S | K14: ENRIQUE | L14: PAGADO | M14: 45698 | N14: N/A
A15: Operadora Concesionaria Mexiquense SA de CV | B15: REFERENCIA POR DEPÓSITO EN FONDE DE GARANTÍA | C15: PEAJE-CASETA-TAG | D15: =IFERROR(VLOOKUP($C15,CUENTAS[],2,0),"") -> LOGÍSTICA | E15: =IFERROR(VLOOKUP($C15,CUENTAS[],3,0),"") -> MDE2025-006D | F15: 25000 | G15: 0 | H15: 25000 | I15: =IFERROR(IF(F15+G15<>H15,"REVISAR","CORRECTO"),"") -> CORRECTO | J15: KUSPIT SP´S | K15: FERNANDO | L15: PAGADO | M15: 45698 | N15: N/A
A16: PAULA OLIVIA MOLINA HERNANDEZ | B16: SOPORTE TECNICO | C16: DISEÑADORES BODEGA | D16: =IFERROR(VLOOKUP($C16,CUENTAS[],2,0),"") -> DISEÑOS | E16: =IFERROR(VLOOKUP($C16,CUENTAS[],3,0),"") -> MDE2025-001 | F16: 12096.87 | G16: 1960 | H16: 14056.87 | I16: =IFERROR(IF(F16+G16<>H16,"REVISAR","CORRECTO"),"") -> CORRECTO | J16: KUSPIT SP´S | K16: ENRIQUE | L16: PAGADO | M16: 45699 | N16: B0C15F
A17: 365 INTELIGENCIA EN SEGURIDAD PRIVADA | B17: SERVICIO DE VIGILANCIA DEL 1 AL 15FEB25 | C17: VIGILANCIA | D17: =IFERROR(VLOOKUP($C17,CUENTAS[],2,0),"") -> GASTOS FIJOS | E17: =IFERROR(VLOOKUP($C17,CUENTAS[],3,0),"") -> MDE2025-002K | F17: 15525 | G17: 2484 | H17: 18009 | I17: =IFERROR(IF(F17+G17<>H17,"REVISAR","CORRECTO"),"") -> CORRECTO | J17: KUSPIT SP´S | K17: PRISCILA | L17: PAGADO | M17: 45699 | N17: FAC 510
A18: DAVID CORTES ARROYO | B18: GESTORIA PLACAS BYD | C18: GASTOS DE TRANSPORTE | D18: =IFERROR(VLOOKUP($C18,CUENTAS[],2,0),"") -> LOGÍSTICA | E18: =IFERROR(VLOOKUP($C18,CUENTAS[],3,0),"") -> MDE2025-006C | F18: 900 | G18: 0 | H18: 900 | I18: =IFERROR(IF(F18+G18<>H18,"REVISAR","CORRECTO"),"") -> CORRECTO | J18: KUSPIT SP´S | K18: FERNANDO | L18: PAGADO | M18: 45699 | N18: COMPROBANTE
A19: VIDAL ESTRADA | B19: PAGO RENTA DE CASA SUAREZ FEBRERO 25 | C19: RENTAS | D19: =IFERROR(VLOOKUP($C19,CUENTAS[],2,0),"") -> GASTOS FIJOS | E19: =IFERROR(VLOOKUP($C19,CUENTAS[],3,0),"") -> MDE2025-002D | F19: 7327.59 | G19: 1172.41 | H19: 8500 | I19: =IFERROR(IF(F19+G19<>H19,"REVISAR","CORRECTO"),"") -> CORRECTO | J19: KUSPIT SP´S | K19: NAYELI | L19: PAGADO | M19: 45699 | N19: FAC13391
A20: VICTOR MANUEL RUIZ ZARATE | B20: REEMBOLSO COMPRAS 1 TINACO, 1 LIMPIADOR PVC 07FEB25- BODEGA | C20: POOL DE MATERIALES | D20: =IFERROR(VLOOKUP($C20,CUENTAS[],2,0),"") -> MATERIALES | E20: =IFERROR(VLOOKUP($C20,CUENTAS[],3,0),"") -> MDE2025-004 | F20: 3551.72 | G20: 568.28 | H20: 4120 | I20: =IFERROR(IF(F20+G20<>H20,"REVISAR","CORRECTO"),"") -> CORRECTO | J20: KUSPIT SP´S | K20: PRISCILA | L20: PAGADO | M20: 45699 | N20: FACT 2818
A21: VICTOR MANUEL RUIZ ZARATE | B21: REEMBOLSO COMPRAS TAQUETE, TORNILLOS, ETC- 07FEB25-BODEGA | C21: POOL DE MATERIALES | D21: =IFERROR(VLOOKUP($C21,CUENTAS[],2,0),"") -> MATERIALES | E21: =IFERROR(VLOOKUP($C21,CUENTAS[],3,0),"") -> MDE2025-004 | F21: 1508.03 | G21: 241.29 | H21: 1749.32 | I21: =IFERROR(IF(F21+G21<>H21,"REVISAR","CORRECTO"),"") -> CORRECTO | J21: KUSPIT SP´S | K21: PRISCILA | L21: PAGADO | M21: 45699 | N21: A18544
A22: SEGRA MEX | B22: COMPRA DE CABEZALES, CARTUCHO DE MANTENIMIENTO PLOTTER 700 | C22: MATERIALES BODEGA | D22: =IFERROR(VLOOKUP($C22,CUENTAS[],2,0),"") -> MATERIALES | E22: =IFERROR(VLOOKUP($C22,CUENTAS[],3,0),"") -> MDE2025-004A | F22: 15934.35 | G22: 2549.5 | H22: 18483.85 | I22: =IFERROR(IF(F22+G22<>H22,"REVISAR","CORRECTO"),"") -> CORRECTO | J22: KUSPIT SP´S | K22: ALEJANDRA | L22: PAGADO | M22: 45701 | N22: COT 1949
A23: MARIA NANCY QUEZADA HERNANDEZ | B23: COMPRA DE 1/2 TONELADA DE CEMENTO Y 5 BULTOS MÁS PARA OFICINAS NUEVAS | C23: EDIFICIOS | D23: =IFERROR(VLOOKUP($C23,CUENTAS[],2,0),"") -> ACTIVOS FIJOS | E23: =IFERROR(VLOOKUP($C23,CUENTAS[],3,0),"") -> MDE2025-007I | F23: 3750 | G23: 0 | H23: 3750 | I23: =IFERROR(IF(F23+G23<>H23,"REVISAR","CORRECTO"),"") -> CORRECTO | J23: KUSPIT SP´S | K23: ALEJANDRA | L23: PAGADO | M23: 45701 | N23: COMPROBANTE
A24: JUAN JOSE BALDERAS CHAVEZ | B24: PATROCINIOS | C24: REGALOS Y PATROCINIOS CLIENTES | D24: =IFERROR(VLOOKUP($C24,CUENTAS[],2,0),"") -> EVENTOS INTERNOS | E24: =IFERROR(VLOOKUP($C24,CUENTAS[],3,0),"") -> MDE2025-008B | F24: 577 | G24: 0 | H24: 577 | I24: =IFERROR(IF(F24+G24<>H24,"REVISAR","CORRECTO"),"") -> CORRECTO | J24: KUSPIT SP´S | K24: ENRIQUE | L24: PAGADO | M24: 45701 | N24: N/A
A25: ECONOCOMEX INTERNACIONAL SA DE CV | B25: COMPRA DE LACAS PARA MUEBLES BOSCH SHOW ROMM, PHOTO OPP ULKRO, LACAS DE FOREO POLANCO Y MATERIAL BODEGA | C25: POOL DE MATERIALES | D25: =IFERROR(VLOOKUP($C25,CUENTAS[],2,0),"") -> MATERIALES | E25: =IFERROR(VLOOKUP($C25,CUENTAS[],3,0),"") -> MDE2025-004 | F25: 8793.11 | G25: 1406.89 | H25: 10200 | I25: =IFERROR(IF(F25+G25<>H25,"REVISAR","CORRECTO"),"") -> CORRECTO | J25: KUSPIT SP´S | K25: ALEJANDRA | L25: PAGADO | M25: 45701 | N25: F34494
... A66: TIRSO DE JESUS DE LA CRUZ | B66: PAGO MANO DE OBRA TRABAJO NUEVAS OFICINAS | C66: EDIFICIOS | D66: =IFERROR(VLOOKUP($C66,CUENTAS[],2,0),"") -> ACTIVOS FIJOS | E66: =IFERROR(VLOOKUP($C66,CUENTAS[],3,0),"") -> MDE2025-007I | F66: 3200 | G66: 0 | H66: 3200 | I66: =IFERROR(IF(F66+G66<>H66,"REVISAR","CORRECTO"),"") -> CORRECTO | J66: KUSPIT SP´S | K66: PRISCILA | L66: PAGADO | M66: 45716 | N66: N/A
A67: Toka internacional S.A.P.I. de C.V. | B67: 2423578 | C67: COMISIONES TOKA | D67: =IFERROR(VLOOKUP($C67,CUENTAS[],2,0),"") -> TOKA | E67: =IFERROR(VLOOKUP($C67,CUENTAS[],3,0),"") -> TOK2025-001C | F67: 500 | G67: 80 | H67: 580 | I67: =IFERROR(IF(F67+G67<>H67,"REVISAR","CORRECTO"),"") -> CORRECTO | J67: KUSPIT SP´S | K67: NAYELI | L67: PAGADO | M67: 45716 | N67: PREFACTURA
A68: Toka internacional S.A.P.I. de C.V. | B68: 2423539 | C68: COMISIONES TOKA | D68: =IFERROR(VLOOKUP($C68,CUENTAS[],2,0),"") -> TOKA | E68: =IFERROR(VLOOKUP($C68,CUENTAS[],3,0),"") -> TOK2025-001C | F68: 300 | G68: 48 | H68: 348 | I68: =IFERROR(IF(F68+G68<>H68,"REVISAR","CORRECTO"),"") -> CORRECTO | J68: KUSPIT SP´S | K68: NAYELI | L68: PAGADO | M68: 45716 | N68: PREFACTURA
A69: ANGEL GUADALUPE ALBARRAN PEREA | B69: 50% ALUMINIO PARA VENTANAS OFICINAS NUEVAS | C69: EDIFICIOS | D69: =IFERROR(VLOOKUP($C69,CUENTAS[],2,0),"") -> ACTIVOS FIJOS | E69: =IFERROR(VLOOKUP($C69,CUENTAS[],3,0),"") -> MDE2025-007I | F69: 11500 | G69: 0 | H69: 11500 | I69: =IFERROR(IF(F69+G69<>H69,"REVISAR","CORRECTO"),"") -> CORRECTO | J69: KUSPIT SP´S | K69: ENRIQUE | L69: PAGADO | M69: 45716 | N69: N/A
A70: OSCAR SUÁREZ JIMENEZ | B70: MANO DE OBRA- LETREROS BOSCH | C70: PROYECTOS FUTUROS | D70: =IFERROR(VLOOKUP($C70,CUENTAS[],2,0),"") -> GASTOS VARIOS | E70: =IFERROR(VLOOKUP($C70,CUENTAS[],3,0),"") -> MDE2025-003K | F70: 8000 | G70: 0 | H70: 8000 | I70: =IFERROR(IF(F70+G70<>H70,"REVISAR","CORRECTO"),"") -> CORRECTO | J70: KUSPIT SP´S | K70: PRISCILA | L70: PAGADO | M70: 45702 | N70: N/A
A71: ALBERTO SUÁREZ JIMENEZ | B71: MANO DE OBRA- LETREROS BOSCH | C71: PROYECTOS FUTUROS | D71: =IFERROR(VLOOKUP($C71,CUENTAS[],2,0),"") -> GASTOS VARIOS | E71: =IFERROR(VLOOKUP($C71,CUENTAS[],3,0),"") -> MDE2025-003K | F71: 8000 | G71: 0 | H71: 8000 | I71: =IFERROR(IF(F71+G71<>H71,"REVISAR","CORRECTO"),"") -> CORRECTO | J71: KUSPIT SP´S | K71: PRISCILA | L71: PAGADO | M71: 45702 | N71: N/A
A72: GUILLERMO SUÁREZ JIMENEZ | B72: MANO DE OBRA- LETREROS BOSCH | C72: PROYECTOS FUTUROS | D72: =IFERROR(VLOOKUP($C72,CUENTAS[],2,0),"") -> GASTOS VARIOS | E72: =IFERROR(VLOOKUP($C72,CUENTAS[],3,0),"") -> MDE2025-003K | F72: 8000 | G72: 0 | H72: 8000 | I72: =IFERROR(IF(F72+G72<>H72,"REVISAR","CORRECTO"),"") -> CORRECTO | J72: KUSPIT SP´S | K72: PRISCILA | L72: PAGADO | M72: 45702 | N72: N/A
A73: ALEJANDRO SUÁREZ JIMENEZ | B73: MANO DE OBRA- LETREROS BOSCH | C73: PROYECTOS FUTUROS | D73: =IFERROR(VLOOKUP($C73,CUENTAS[],2,0),"") -> GASTOS VARIOS | E73: =IFERROR(VLOOKUP($C73,CUENTAS[],3,0),"") -> MDE2025-003K | F73: 8000 | G73: 0 | H73: 8000 | I73: =IFERROR(IF(F73+G73<>H73,"REVISAR","CORRECTO"),"") -> CORRECTO | J73: KUSPIT SP´S | K73: PRISCILA | L73: PAGADO | M73: 45702 | N73: N/A
A74: FERNANDO BECERRIL | B74: ROLLO DE PLAYO 18 CALIBRE 80 | C74: POOL DE MATERIALES | D74: =IFERROR(VLOOKUP($C74,CUENTAS[],2,0),"") -> MATERIALES | E74: =IFERROR(VLOOKUP($C74,CUENTAS[],3,0),"") -> MDE2025-004 | F74: 1600 | G74: 0 | H74: 1600 | I74: =IFERROR(IF(F74+G74<>H74,"REVISAR","CORRECTO"),"") -> CORRECTO | J74: ALMACEN | K74: ARIADNA | P74: REVISAR CON NAYE
A75: ALEJANDRA COVARRUBIAS | B75: GUANTE TEJIDO NYLON #7 | C75: UNIFORMES Y EPP | D75: =IFERROR(VLOOKUP($C75,CUENTAS[],2,0),"") -> GASTOS VARIOS | E75: =IFERROR(VLOOKUP($C75,CUENTAS[],3,0),"") -> MDE2025-003B | F75: 39.66 | G75: 0 | H75: 39.66 | I75: =IFERROR(IF(F75+G75<>H75,"REVISAR","CORRECTO"),"") -> CORRECTO | J75: ALMACEN | K75: ARIADNA
A76: ALEJANDRA COVARRUBIAS | B76: GUANTE TEJIDO NYLON #8 | C76: UNIFORMES Y EPP | D76: =IFERROR(VLOOKUP($C76,CUENTAS[],2,0),"") -> GASTOS VARIOS | E76: =IFERROR(VLOOKUP($C76,CUENTAS[],3,0),"") -> MDE2025-003B | F76: 19.83 | G76: 0 | H76: 19.83 | I76: =IFERROR(IF(F76+G76<>H76,"REVISAR","CORRECTO"),"") -> CORRECTO | J76: ALMACEN | K76: ARIADNA
A77: JOSE E ZEPEDA BURGOS | B77: MUEBLES PARA BAÑOS OFICINAS NUEVAS | C77: EDIFICIOS | D77: =IFERROR(VLOOKUP($C77,CUENTAS[],2,0),"") -> ACTIVOS FIJOS | E77: =IFERROR(VLOOKUP($C77,CUENTAS[],3,0),"") -> MDE2025-007I | F77: 18668.92 | G77: 2987.03 | H77: 21655.95 | I77: =IFERROR(IF(F77+G77<>H77,"REVISAR","CORRECTO"),"") -> CORRECTO | J77: AMEX | K77: ANGIE | L77: PENDIENTE | N77: 316-164685
A78: JOSE E ZEPEDA BURGOS | B78: LICENCIA SHUTTERSTOCK | C78: LICENCIAS Y CERTIFICACIONES | D78: =IFERROR(VLOOKUP($C78,CUENTAS[],2,0),"") -> GASTOS FIJOS | E78: =IFERROR(VLOOKUP($C78,CUENTAS[],3,0),"") -> MDE2025-002J | F78: 615.63 | G78: 0 | H78: 615.63 | I78: =IFERROR(IF(F78+G78<>H78,"REVISAR","CORRECTO"),"") -> CORRECTO | J78: AMEX | K78: JAVIER MENA | L78: PENDIENTE | N78: RECIBO
A79: JOSE E ZEPEDA BURGOS | B79: COMPRA DE CELULAR . | C79: EQUIPO DE CÓMPUTO Y TELEFONÍA | D79: =IFERROR(VLOOKUP($C79,CUENTAS[],2,0),"") -> ACTIVOS FIJOS | E79: =IFERROR(VLOOKUP($C79,CUENTAS[],3,0),"") -> MDE2025-007B | F79: 10708.63 | G79: 1713.37 | H79: 12422 | I79: =IFERROR(IF(F79+G79<>H79,"REVISAR","CORRECTO"),"") -> CORRECTO | J79: AMEX | K79: JESSICA | L79: PENDIENTE | N79: A287356B
A80: JOSE E ZEPEDA BURGOS | B80: COMPRA DE CELULAR COMPRAS ARIANA | C80: EQUIPO DE CÓMPUTO Y TELEFONÍA | D80: =IFERROR(VLOOKUP($C80,CUENTAS[],2,0),"") -> ACTIVOS FIJOS | E80: =IFERROR(VLOOKUP($C80,CUENTAS[],3,0),"") -> MDE2025-007B | F80: 10708.63 | G80: 1713.37 | H80: 12422 | I80: =IFERROR(IF(F80+G80<>H80,"REVISAR","CORRECTO"),"") -> CORRECTO | J80: AMEX | K80: JESSICA | L80: PENDIENTE | N80: 89DE8231OCCA
A81: JOSE E ZEPEDA BURGOS | B81: PAGO ANTENA DE INTERNET | C81: SERVICIOS TELEFÓNICOS E INTERNET | D81: =IFERROR(VLOOKUP($C81,CUENTAS[],2,0),"") -> GASTOS FIJOS | E81: =IFERROR(VLOOKUP($C81,CUENTAS[],3,0),"") -> MDE2025-002F | F81: 3148 | G81: 0 | H81: 3148 | I81: =IFERROR(IF(F81+G81<>H81,"REVISAR","CORRECTO"),"") -> CORRECTO | J81: AMEX | K81: ENRIQUE | L81: PENDIENTE | N81: N/A
A82: JOSE E ZEPEDA BURGOS | B82: PAGO ANTENA DE INTERNET | C82: SERVICIOS TELEFÓNICOS E INTERNET | D82: =IFERROR(VLOOKUP($C82,CUENTAS[],2,0),"") -> GASTOS FIJOS | E82: =IFERROR(VLOOKUP($C82,CUENTAS[],3,0),"") -> MDE2025-002F | F82: 1045 | G82: 0 | H82: 1045 | I82: =IFERROR(IF(F82+G82<>H82,"REVISAR","CORRECTO"),"") -> CORRECTO | J82: AMEX | K82: ENRIQUE | L82: PENDIENTE | N82: N/A
A83: GAS PORTOMARIN LERMA | B83: COMBUSTILBE EZ | C83: COMBUSTIBLE | D83: =IFERROR(VLOOKUP($C83,CUENTAS[],2,0),"") -> GASTOS VARIOS | E83: =IFERROR(VLOOKUP($C83,CUENTAS[],3,0),"") -> MDE2025-003D | F83: 1283.39 | G83: 0 | H83: 1283.39 | I83: =IFERROR(IF(F83+G83<>H83,"REVISAR","CORRECTO"),"") -> CORRECTO | J83: TOKA | K83: ENRIQUE Z | L83: PAGADO | M83: 45701 | N83: SIN FACT
A84: OPERADORA CONCESIONARIA MEXIQUENSE | B84: PEAJES EDUARDO - UNIDAD DE EZP 13FEB25 | C84: PEAJE-CASETA-TAG | D84: =IFERROR(VLOOKUP($C84,CUENTAS[],2,0),"") -> LOGÍSTICA | E84: =IFERROR(VLOOKUP($C84,CUENTAS[],3,0),"") -> MDE2025-006D | F84: 157.76 | G84: 25.24 | H84: 183 | I84: =IFERROR(IF(F84+G84<>H84,"REVISAR","CORRECTO"),"") -> CORRECTO | J84: TAG TELEVIA | K84: EDUARDO | L84: PAGADO | M84: 45716 | N84: FAC21430
A85: SOLICITUD DE EFECTIVO | B85: PAGO NOMINA EFECTIVO | C85: NÓMINA EN EFECTIVO | D85: =IFERROR(VLOOKUP($C85,CUENTAS[],2,0),"") -> GASTOS FIJOS | E85: =IFERROR(VLOOKUP($C85,CUENTAS[],3,0),"") -> MDE2025-002R | F85: 100000 | G85: 0 | H85: 100000 | I85: =IFERROR(IF(F85+G85<>H85,"REVISAR","CORRECTO"),"") -> CORRECTO | J85: KUSPIT SP´S | K85: ENRIQUE | L85: PAGADO | M85: 45707 | N85: N/A
A86: FERRELU | B86: ABRAZADERA, CONECTOR Y EMPAQUE PARA MANGUERA | C86: INSUMOS PARA MANTENIMIENTO BODEGA | D86: =IFERROR(VLOOKUP($C86,CUENTAS[],2,0),"") -> MANTENIMIENTO | E86: =IFERROR(VLOOKUP($C86,CUENTAS[],3,0),"") -> MDE2025-009A | F86: 29 | G86: 0 | H86: 29 | I86: =IFERROR(IF(F86+G86<>H86,"REVISAR","CORRECTO"),"") -> CORRECTO | J86: EFECTIVO | K86: OSVALDO | L86: PAGADO | M86: 45699 | N86: SIN FACT
A87: FERRELU | B87: ADAPTADOR Y ABRAZADERA SIN FIN | C87: INSUMOS PARA MANTENIMIENTO BODEGA | D87: =IFERROR(VLOOKUP($C87,CUENTAS[],2,0),"") -> MANTENIMIENTO | E87: =IFERROR(VLOOKUP($C87,CUENTAS[],3,0),"") -> MDE2025-009A | F87: 22 | G87: 0 | H87: 22 | I87: =IFERROR(IF(F87+G87<>H87,"REVISAR","CORRECTO"),"") -> CORRECTO | J87: EFECTIVO | K87: OSVALDO | L87: PAGADO | M87: 45698 | N87: SIN FACT
A88: PAPELERIA LA ECONOMICA | B88: LIBRETA, AGENDA Y POSTIT | C88: PAPELERÍA E INSUMOS DE LIMPIEZA | D88: =IFERROR(VLOOKUP($C88,CUENTAS[],2,0),"") -> GASTOS VARIOS | E88: =IFERROR(VLOOKUP($C88,CUENTAS[],3,0),"") -> MDE2025-003A | F88: 265 | G88: 0 | H88: 265 | I88: =IFERROR(IF(F88+G88<>H88,"REVISAR","CORRECTO"),"") -> CORRECTO | J88: EFECTIVO | K88: NAYELI | L88: PAGADO | M88: 45704 | N88: SIN FACT
A89: BRANDON AGUILAR | B89: RECOLECCION BASURA AL 06FEB25 | C89: SERVICIO DE RECOLECCION DE BASURA Y DESECHOS INDUSTRIALES | D89: =IFERROR(VLOOKUP($C89,CUENTAS[],2,0),"") -> GASTOS FIJOS | E89: =IFERROR(VLOOKUP($C89,CUENTAS[],3,0),"") -> MDE2025-002A | F89: 700 | G89: 0 | H89: 700 | I89: =IFERROR(IF(F89+G89<>H89,"REVISAR","CORRECTO"),"") -> CORRECTO | J89: EFECTIVO | K89: NAYELI | L89: PAGADO | M89: 45694 | N89: VALE
A90: BRANDON AGUILAR | B90: RECOLECCION BASURA AL 13FEB25 | C90: SERVICIO DE RECOLECCION DE BASURA Y DESECHOS INDUSTRIALES | D90: =IFERROR(VLOOKUP($C90,CUENTAS[],2,0),"") -> GASTOS FIJOS | E90: =IFERROR(VLOOKUP($C90,CUENTAS[],3,0),"") -> MDE2025-002A | F90: 700 | G90: 0 | H90: 700 | I90: =IFERROR(IF(F90+G90<>H90,"REVISAR","CORRECTO"),"") -> CORRECTO | J90: EFECTIVO | K90: NAYELI | L90: PAGADO | M90: 45701 | N90: VALE
A91: BRANDON AGUILAR | B91: RECOLECCION BASURA AL 20FEB25 | C91: SERVICIO DE RECOLECCION DE BASURA Y DESECHOS INDUSTRIALES | D91: =IFERROR(VLOOKUP($C91,CUENTAS[],2,0),"") -> GASTOS FIJOS | E91: =IFERROR(VLOOKUP($C91,CUENTAS[],3,0),"") -> MDE2025-002A | F91: 700 | G91: 0 | H91: 700 | I91: =IFERROR(IF(F91+G91<>H91,"REVISAR","CORRECTO"),"") -> CORRECTO | J91: EFECTIVO | K91: NAYELI | L91: PAGADO | M91: 45708 | N91: VALE
A92: VIDAL EUGENIO ESTRADA LARA | B92: LLAVE DE PASO 1/2 PARA BOMBA AGUA | C92: INSUMOS PARA MANTENIMIENTO BODEGA | D92: =IFERROR(VLOOKUP($C92,CUENTAS[],2,0),"") -> MANTENIMIENTO | E92: =IFERROR(VLOOKUP($C92,CUENTAS[],3,0),"") -> MDE2025-009A | F92: 107.76 | G92: 17.24 | H92: 125 | I92: =IFERROR(IF(F92+G92<>H92,"REVISAR","CORRECTO"),"") -> CORRECTO | J92: EFECTIVO | K92: OSVALDO | L92: PAGADO | M92: 45708 | N92: F13414
A93: AT&T | B93: RECARGA CEL ADMON2 | C93: TELEFONÍA E INTERNET | D93: =IFERROR(VLOOKUP($C93,CUENTAS[],2,0),"") -> GASTOS VARIOS | E93: =IFERROR(VLOOKUP($C93,CUENTAS[],3,0),"") -> MDE2025-003C | F93: 100 | G93: 0 | H93: 100 | I93: =IFERROR(IF(F93+G93<>H93,"REVISAR","CORRECTO"),"") -> CORRECTO | J93: EFECTIVO | K93: NAYELI | L93: PAGADO | M93: 45708 | N93: COMPROBANTE
A94: DON LOLO | B94: 30CM DE PVC, CODO Y COPLE PARA BOMBA AGUA | C94: INSUMOS PARA MANTENIMIENTO BODEGA | D94: =IFERROR(VLOOKUP($C94,CUENTAS[],2,0),"") -> MANTENIMIENTO | E94: =IFERROR(VLOOKUP($C94,CUENTAS[],3,0),"") -> MDE2025-009A | F94: 29 | G94: 0 | H94: 29 | I94: =IFERROR(IF(F94+G94<>H94,"REVISAR","CORRECTO"),"") -> CORRECTO | J94: EFECTIVO | K94: OSVALDO | L94: PAGADO | M94: 45707 | N94: NV0686
... A97: BRANDON AGUILAR | B97: RECOLECCION BASURA AL 27FEB25 | C97: SERVICIO DE RECOLECCION DE BASURA Y DESECHOS INDUSTRIALES | D97: =IFERROR(VLOOKUP($C97,CUENTAS[],2,0),"") -> GASTOS FIJOS | E97: =IFERROR(VLOOKUP($C97,CUENTAS[],3,0),"") -> MDE2025-002A | F97: 700 | G97: 0 | H97: 700 | I97: =IFERROR(IF(F97+G97<>H97,"REVISAR","CORRECTO"),"") -> CORRECTO | J97: EFECTIVO | K97: NAYELI | L97: PAGADO | M97: 45715 | N97: VALE
A98: NOMINA QUINCENAL | B98: DEL 1 AL 15 FEB25 | C98: NÓMINA QUINCENAL FIJA | D98: =IFERROR(VLOOKUP($C98,CUENTAS[],2,0),"") -> GASTOS FIJOS | E98: =IFERROR(VLOOKUP($C98,CUENTAS[],3,0),"") -> MDE2025-002O | F98: 49406.52 | G98: 0 | H98: 49406.52 | I98: =IFERROR(IF(F98+G98<>H98,"REVISAR","CORRECTO"),"") -> CORRECTO | J98: KUSPIT SP´S
A99: NOMINA QUINCENAL | B99: DEL 1 AL 15 FEB25 | C99: NÓMINA QUINCENAL FIJA | D99: =IFERROR(VLOOKUP($C99,CUENTAS[],2,0),"") -> GASTOS FIJOS | E99: =IFERROR(VLOOKUP($C99,CUENTAS[],3,0),"") -> MDE2025-002O | F99: 132405.52 | G99: 0 | H99: 132405.52 | I99: =IFERROR(IF(F99+G99<>H99,"REVISAR","CORRECTO"),"") -> CORRECTO | J99: KUSPIT SP´S
A100: YAIR CRESENCIO PEREZ MONTES DE OCA | B100: COMPLEMENTO DE NOMINA DEL 27ENERO AL 02FEB25 | C100: NÓMINA SEMANAL BODEGA | D100: =IFERROR(VLOOKUP($C100,CUENTAS[],2,0),"") -> GASTOS FIJOS | E100: =IFERROR(VLOOKUP($C100,CUENTAS[],3,0),"") -> MDE2025-002L | F100: 1000 | G100: 0 | H100: 1000 | I100: =IFERROR(IF(F100+G100<>H100,"REVISAR","CORRECTO"),"") -> CORRECTO | J100: KUSPIT SP´S | K100: ANGIE | L100: PAGADO | M100: 45695 | N100: NA
A101: KAWIR GRUPO SA DE CV | B101: NOMINA SEMANAL DEL 27ENE AL 02FEB25 | C101: NÓMINA SEMANAL BODEGA | D101: =IFERROR(VLOOKUP($C101,CUENTAS[],2,0),"") -> GASTOS FIJOS | E101: =IFERROR(VLOOKUP($C101,CUENTAS[],3,0),"") -> MDE2025-002L | F101: 29042.28 | G101: 0 | H101: 29042.28 | I101: =IFERROR(IF(F101+G101<>H101,"REVISAR","CORRECTO"),"") -> CORRECTO | J101: KUSPIT SP´S | K101: ANGIE | L101: PAGADO | M101: 45691 | N101: N/A
A102: KAWIR GRUPO SA DE CV | B102: NOMINA SEMANAL DEL 3 AL 9FEB25 | C102: NÓMINA SEMANAL BODEGA | D102: =IFERROR(VLOOKUP($C102,CUENTAS[],2,0),"") -> GASTOS FIJOS | E102: =IFERROR(VLOOKUP($C102,CUENTAS[],3,0),"") -> MDE2025-002L | F102: 19376.85 | G102: 0 | H102: 19376.85 | I102: =IFERROR(IF(F102+G102<>H102,"REVISAR","CORRECTO"),"") -> CORRECTO | J102: KUSPIT SP´S | K102: ANGIE | L102: PAGADO | M102: 45698 | N102: N/A
A103: KAWIR GRUPO SA DE CV | B103: NOMINA SEMANAL DEL 10 AL 16FEB25 | C103: NÓMINA SEMANAL BODEGA | D103: =IFERROR(VLOOKUP($C103,CUENTAS[],2,0),"") -> GASTOS FIJOS | E103: =IFERROR(VLOOKUP($C103,CUENTAS[],3,0),"") -> MDE2025-002L | F103: 30894.84 | G103: 0 | H103: 30894.84 | I103: =IFERROR(IF(F103+G103<>H103,"REVISAR","CORRECTO"),"") -> CORRECTO | J103: KUSPIT SP´S | K103: ANGIE | L103: PAGADO | M103: 45705 | N103: N/A
A104: KAWIR GRUPO SA DE CV | B104: NOMINA SEMANAL DEL 17 AL 23FEB25 | C104: NÓMINA SEMANAL BODEGA | D104: =IFERROR(VLOOKUP($C104,CUENTAS[],2,0),"") -> GASTOS FIJOS | E104: =IFERROR(VLOOKUP($C104,CUENTAS[],3,0),"") -> MDE2025-002L | F104: 27449.73 | G104: 0 | H104: 27449.73 | I104: =IFERROR(IF(F104+G104<>H104,"REVISAR","CORRECTO"),"") -> CORRECTO | J104: KUSPIT SP´S | K104: ANGIE | L104: PAGADO | M104: 45712 | N104: N/A
A105: KAWIR GRUPO SA DE CV | B105: NOMINA FISCAL DEL 1 AL 15FEB25 | C105: NÓMINA QUINCENAL FIJA | D105: =IFERROR(VLOOKUP($C105,CUENTAS[],2,0),"") -> GASTOS FIJOS | E105: =IFERROR(VLOOKUP($C105,CUENTAS[],3,0),"") -> MDE2025-002O | F105: 49406.52 | G105: 0 | H105: 49406.52 | I105: =IFERROR(IF(F105+G105<>H105,"REVISAR","CORRECTO"),"") -> CORRECTO | J105: KUSPIT SP´S | K105: ANGIE | L105: PAGADO | M105: 45703 | N105: N/A
A106: KAWIR GRUPO SA DE CV | B106: NOMINA ASIMILADOS QUINC 1 AL 15FEB25 | C106: NÓMINA QUINCENAL FIJA | D106: =IFERROR(VLOOKUP($C106,CUENTAS[],2,0),"") -> GASTOS FIJOS | E106: =IFERROR(VLOOKUP($C106,CUENTAS[],3,0),"") -> MDE2025-002O | F106: 132405.52 | G106: 0 | H106: 132405.52 | I106: =IFERROR(IF(F106+G106<>H106,"REVISAR","CORRECTO"),"") -> CORRECTO | J106: KUSPIT SP´S | K106: ANGIE | L106: PAGADO | M106: 45703 | N106: N/A
A107: KAWIR GRUPO SA DE CV | B107: DESC PRESTAMOS 1 AL 15FEB25 | C107: PRÉSTAMOS PERSONALES | D107: =IFERROR(VLOOKUP($C107,CUENTAS[],2,0),"") -> GASTOS FIJOS | E107: =IFERROR(VLOOKUP($C107,CUENTAS[],3,0),"") -> MDE2025-002Q | F107: -1850 | G107: 0 | H107: -1850 | I107: =IFERROR(IF(F107+G107<>H107,"REVISAR","CORRECTO"),"") -> CORRECTO | J107: KUSPIT SP´S | K107: ANGIE | L107: PAGADO | M107: 45703 | N107: N/A
A108: KAWIR GRUPO SA DE CV | B108: NOMINA FISCAL DEL 16 AL 28FEB25 | C108: NÓMINA QUINCENAL FIJA | D108: =IFERROR(VLOOKUP($C108,CUENTAS[],2,0),"") -> GASTOS FIJOS | E108: =IFERROR(VLOOKUP($C108,CUENTAS[],3,0),"") -> MDE2025-002O | F108: 49406.52 | G108: 0 | H108: 49406.52 | I108: =IFERROR(IF(F108+G108<>H108,"REVISAR","CORRECTO"),"") -> CORRECTO | J108: KUSPIT SP´S | K108: ANGIE | L108: PAGADO | M108: 45716 | N108: N/A
A109: KAWIR GRUPO SA DE CV | B109: NOMINA ASIMILADOS QUINC 16AL 28FEB25 | C109: NÓMINA QUINCENAL FIJA | D109: =IFERROR(VLOOKUP($C109,CUENTAS[],2,0),"") -> GASTOS FIJOS | E109: =IFERROR(VLOOKUP($C109,CUENTAS[],3,0),"") -> MDE2025-002O | F109: 142605.48 | G109: 0 | H109: 142605.48 | I109: =IFERROR(IF(F109+G109<>H109,"REVISAR","CORRECTO"),"") -> CORRECTO | J109: KUSPIT SP´S | K109: ANGIE | L109: PAGADO | M109: 45716 | N109: N/A
A110: KAWIR GRUPO SA DE CV | B110: DESC PRESTAMOS 16 AL 28FEB25 | C110: PRÉSTAMOS PERSONALES | D110: =IFERROR(VLOOKUP($C110,CUENTAS[],2,0),"") -> GASTOS FIJOS | E110: =IFERROR(VLOOKUP($C110,CUENTAS[],3,0),"") -> MDE2025-002Q | F110: -7750 | G110: 0 | H110: -7750 | I110: =IFERROR(IF(F110+G110<>H110,"REVISAR","CORRECTO"),"") -> CORRECTO | J110: KUSPIT SP´S | K110: ANGIE | L110: PAGADO | M110: 45716 | N110: N/A
A111: KAWIR GRUPO SA DE CV | B111: NOMINA QUINCENAL EXTRAS DEL 16 AL 28FEB25 | C111: PRÉSTAMOS PERSONALES | D111: =IFERROR(VLOOKUP($C111,CUENTAS[],2,0),"") -> GASTOS FIJOS | E111: =IFERROR(VLOOKUP($C111,CUENTAS[],3,0),"") -> MDE2025-002Q | F111: 6000 | G111: 0 | H111: 6000 | I111: =IFERROR(IF(F111+G111<>H111,"REVISAR","CORRECTO"),"") -> CORRECTO | J111: KUSPIT SP´S | K111: ANGIE | L111: PAGADO | M111: 45716 | N111: N/A
... A114: FREDY RICO DOTOR | B114: PAGO FINIQUITO | C114: NÓMINA SEMANAL BODEGA | D114: =IFERROR(VLOOKUP($C114,CUENTAS[],2,0),"") -> GASTOS FIJOS | E114: =IFERROR(VLOOKUP($C114,CUENTAS[],3,0),"") -> MDE2025-002L | F114: 4424.93 | G114: 0 | H114: 4424.93 | I114: =IFERROR(IF(F114+G114<>H114,"REVISAR","CORRECTO"),"") -> CORRECTO | J114: KUSPIT SP´S | K114: ANGIE | L114: PAGADO | M114: 45708 | N114: N/A
N117: SUBTOTAL | O117: =+SUM(F:F) -> 1381340.2
N118: IVA | O118: =+SUM(G:G) -> 36658.82
N119: TOTAL GTO NO IMP. | O119: =+SUM(H:H) -> 1417999 | P119: =O119-O118-O117 -> 0
O120: =IF(P119<>0,"REVISAR CAPTURA","")

Sheet MAR25
A1: PROVEEDOR | B1: CONCEPTO | C1: SUBCUENTA | D1: CUENTA | E1: CLAVE | F1: SUBTOTAL | G1: IVA | H1: TOTAL | I1: VALIDACIÓN | J1: FORMA DE PAGO | K1: EJECUTIVO | L1: STATUS | M1: FECHA | N1: FACTURA
A2: MARIO GERARDO MORENO RODRIGUEZ | B2: PROPUESTA CREATIVA EN LICITACIÓN BROWN FORMAN | C2: DISEÑADORES BODEGA | D2: =IFERROR(VLOOKUP($C2,CUENTAS[],2,0),"") -> DISEÑOS | E2: =IFERROR(VLOOKUP($C2,CUENTAS[],3,0),"") -> MDE2025-001 | F2: 40000 | G2: 0 | H2: 40000 | I2: =IFERROR(IF(F2+G2<>H2,"REVISAR","CORRECTO"),"") -> CORRECTO | J2: KUSPIT SP´S | K2: LESLIE | L2: PAGADO | M2: 45720 | N2: N/A
A3: MARIO GERARDO MORENO RODRIGUEZ | B3: RENDER EN LICITACIÓN HEINZ HOSPITALITY | C3: DISEÑADORES BODEGA | D3: =IFERROR(VLOOKUP($C3,CUENTAS[],2,0),"") -> DISEÑOS | E3: =IFERROR(VLOOKUP($C3,CUENTAS[],3,0),"") -> MDE2025-001 | F3: 8000 | G3: 0 | H3: 8000 | I3: =IFERROR(IF(F3+G3<>H3,"REVISAR","CORRECTO"),"") -> CORRECTO | J3: KUSPIT SP´S | K3: LESLIE | L3: PAGADO | M3: 45720 | N3: N/A
A4: ENRIQUE VELEZ JIMENEZ | B4: BOLETO DE AVION COPA AIRLINES/ DEL 24 AL 30 DE MARZO/ MEX PTY MEX/ LESLIE FLORES/ BK2MCE | C4: CURSOS Y CAPACITACIONES | D4: =IFERROR(VLOOKUP($C4,CUENTAS[],2,0),"") -> EVENTOS INTERNOS | E4: =IFERROR(VLOOKUP($C4,CUENTAS[],3,0),"") -> MDE2025-008A | F4: 10330.86 | G4: 1652.94 | H4: 11983.8 | I4: =IFERROR(IF(F4+G4<>H4,"REVISAR","CORRECTO"),"") -> CORRECTO | J4: KUSPIT SP´S | K4: ELISA | L4: PAGADO | M4: 45720 | N4: C29158A
A5: ENRIQUE CRUZ CARDEÑA | B5: PAGO DISEÑO PALLETS KLENEEX KIMBERLY | C5: DISEÑADORES BODEGA | D5: =IFERROR(VLOOKUP($C5,CUENTAS[],2,0),"") -> DISEÑOS | E5: =IFERROR(VLOOKUP($C5,CUENTAS[],3,0),"") -> MDE2025-001 | F5: 3800 | G5: 0 | H5: 3800 | I5: =IFERROR(IF(F5+G5<>H5,"REVISAR","CORRECTO"),"") -> CORRECTO | J5: KUSPIT SP´S | K5: JESSICA | L5: PAGADO | M5: 45720 | N5: COT WHATS
A6: ELISA DANIELA NAVA TERAN | B6: REEMBOLSO PAGO A DISEÑADOR (GARRA DE PELUCHES ALEN) | C6: DISEÑADORES BODEGA | D6: =IFERROR(VLOOKUP($C6,CUENTAS[],2,0),"") -> DISEÑOS | E6: =IFERROR(VLOOKUP($C6,CUENTAS[],3,0),"") -> MDE2025-001 | F6: 500 | G6: 0 | H6: 500 | I6: =IFERROR(IF(F6+G6<>H6,"REVISAR","CORRECTO"),"") -> CORRECTO | J6: KUSPIT SP´S | K6: ELISA NAVA | L6: PAGADO | M6: 45720 | N6: REF-0702250
A7: ART TEGNOLOGIA SA DE CV | B7: COMPRA DE BROCAS DE 1/8 + ENVIO | C7: POOL DE MATERIALES | D7: =IFERROR(VLOOKUP($C7,CUENTAS[],2,0),"") -> MATERIALES | E7: =IFERROR(VLOOKUP($C7,CUENTAS[],3,0),"") -> MDE2025-004 | F7: 3538.46 | G7: 566.15 | H7: 4104.61 | I7: =IFERROR(IF(F7+G7<>H7,"REVISAR","CORRECTO"),"") -> CORRECTO | J7: KUSPIT SP´S | K7: ARIADNA | L7: PAGADO | M7: 45720 | N7: COT. 43104
A8: ECONOCOMEX SA DE CV | B8: COMPRA DE FELPAS GRANDES, CHICAS ,VINIMEX 1LT CLASICA | C8: POOL DE MATERIALES | D8: =IFERROR(VLOOKUP($C8,CUENTAS[],2,0),"") -> MATERIALES | E8: =IFERROR(VLOOKUP($C8,CUENTAS[],3,0),"") -> MDE2025-004 | F8: 2048.88 | G8: 327.82 | H8: 2376.7 | I8: =IFERROR(IF(F8+G8<>H8,"REVISAR","CORRECTO"),"") -> CORRECTO | J8: KUSPIT SP´S | K8: ARIADNA | L8: PAGADO | M8: 45720 | N8: COT COMEX
A9: VICTOR MANUEL RUIZ ZARATE | B9: REEMBOLSO DE JUEGO DE PUNTAS PARA TALADRO- 28FEB25 | C9: POOL DE MATERIALES | D9: =IFERROR(VLOOKUP($C9,CUENTAS[],2,0),"") -> MATERIALES | E9: =IFERROR(VLOOKUP($C9,CUENTAS[],3,0),"") -> MDE2025-004 | F9: 103.45 | G9: 16.55 | H9: 120 | I9: =IFERROR(IF(F9+G9<>H9,"REVISAR","CORRECTO"),"") -> CORRECTO | J9: KUSPIT SP´S | K9: PRISCILA | L9: PAGADO | M9: 45720 | N9: FAC- 13447
A10: VICTOR MANUEL RUIZ ZARATE | B10: REEMBOLSO DE VINIL ESPEJO PLATA 92CM- 28FEB25 | C10: POOL DE MATERIALES | D10: =IFERROR(VLOOKUP($C10,CUENTAS[],2,0),"") -> MATERIALES | E10: =IFERROR(VLOOKUP($C10,CUENTAS[],3,0),"") -> MDE2025-004 | F10: 220 | G10: 0 | H10: 220 | I10: =IFERROR(IF(F10+G10<>H10,"REVISAR","CORRECTO"),"") -> CORRECTO | J10: KUSPIT SP´S | K10: PRISCILA | L10: PAGADO | M10: 45720 | N10: N- 24034
A11: VICTOR MANUEL RUIZ ZARATE | B11: REEMBOLSO DE MASKING TAPE AZUL, TESA 4934 CINTA DOS CARAS, CINTA DUCTOS GRIS, SHURTAPE CINTA DE DUCTOS NEGRA- 28FEB25 | C11: POOL DE MATERIALES | D11: =IFERROR(VLOOKUP($C11,CUENTAS[],2,0),"") -> MATERIALES | E11: =IFERROR(VLOOKUP($C11,CUENTAS[],3,0),"") -> MDE2025-004 | F11: 3705.17 | G11: 592.83 | H11: 4298 | I11: =IFERROR(IF(F11+G11<>H11,"REVISAR","CORRECTO"),"") -> CORRECTO | J11: KUSPIT SP´S | K11: PRISCILA | L11: PAGADO | M11: 45720 | N11: F10387
A12: VICTOR MANUEL RUIZ ZARATE | B12: REEMBOLSO DE BATERIAS ALCALINAS AAA- 03MARZO25 | C12: POOL DE MATERIALES | D12: =IFERROR(VLOOKUP($C12,CUENTAS[],2,0),"") -> MATERIALES | E12: =IFERROR(VLOOKUP($C12,CUENTAS[],3,0),"") -> MDE2025-004 | F12: 306.03 | G12: 48.96 | H12: 354.99 | I12: =IFERROR(IF(F12+G12<>H12,"REVISAR","CORRECTO"),"") -> CORRECTO | J12: KUSPIT SP´S | K12: PRISCILA | L12: PAGADO | M12: 45720 | N12: FAC 47797
A13: DAVID CARLOS PEREZ FLORES | B13: TUBO CAÑTALIZADOR ROJO,RESANADOR, ESMALTES EN AGUA | C13: POOL DE MATERIALES | D13: =IFERROR(VLOOKUP($C13,CUENTAS[],2,0),"") -> MATERIALES | E13: =IFERROR(VLOOKUP($C13,CUENTAS[],3,0),"") -> MDE2025-004 | F13: 7535 | G13: 1205.6 | H13: 8740.6 | I13: =IFERROR(IF(F13+G13<>H13,"REVISAR","CORRECTO"),"") -> CORRECTO | J13: KUSPIT SP´S | K13: ARIADNA | L13: PAGADO | M13: 45720 | N13: FAC VARIAS
... A17: VICTOR MANUEL RUIZ ZARATE | B17: REEMBOLSO DE PLAYO, FUENTE 12V- 26FEB25 | C17: POOL DE MATERIALES | D17: =IFERROR(VLOOKUP($C17,CUENTAS[],2,0),"") -> MATERIALES | E17: =IFERROR(VLOOKUP($C17,CUENTAS[],3,0),"") -> MDE2025-004 | F17: 2625 | G17: 0 | H17: 2625 | I17: =IFERROR(IF(F17+G17<>H17,"REVISAR","CORRECTO"),"") -> CORRECTO | J17: KUSPIT SP´S | K17: PRISCILA | L17: PAGADO | M17: 45720 | N17: TICKET- 20515
A18: VICTOR MANUEL RUIZ ZARATE | B18: REEMBOLSO DE PAR DE CORDONES- 28FEB25 | C18: POOL DE MATERIALES | D18: =IFERROR(VLOOKUP($C18,CUENTAS[],2,0),"") -> MATERIALES | E18: =IFERROR(VLOOKUP($C18,CUENTAS[],3,0),"") -> MDE2025-004 | F18: 50 | G18: 0 | H18: 50 | I18: =IFERROR(IF(F18+G18<>H18,"REVISAR","CORRECTO"),"") -> CORRECTO | J18: KUSPIT SP´S | K18: PRISCILA | L18: PAGADO | M18: 45720 | N18: 464
A19: VICTOR MANUEL RUIZ ZARATE | B19: REEMBOLSO DE LAMINA DE ACR 240X120 6MM, LAMINA DE ACR 240X120 Z-2 3MM- 27FEB25 | C19: POOL DE MATERIALES | D19: =IFERROR(VLOOKUP($C19,CUENTAS[],2,0),"") -> MATERIALES | E19: =IFERROR(VLOOKUP($C19,CUENTAS[],3,0),"") -> MDE2025-004 | F19: 4070 | G19: 651.2 | H19: 4721.2 | I19: =IFERROR(IF(F19+G19<>H19,"REVISAR","CORRECTO"),"") -> CORRECTO | J19: KUSPIT SP´S | K19: PRISCILA | L19: PAGADO | M19: 45720 | N19: A-13508
A20: VICTOR MANUEL RUIZ ZARATE | B20: REEMBOLSO DE BICOLAM ROJO/BLANCO 1.5MM 60X120CM- 26FEB25 | C20: POOL DE MATERIALES | D20: =IFERROR(VLOOKUP($C20,CUENTAS[],2,0),"") -> MATERIALES | E20: =IFERROR(VLOOKUP($C20,CUENTAS[],3,0),"") -> MDE2025-004 | F20: 2974.14 | G20: 475.86 | H20: 3450 | I20: =IFERROR(IF(F20+G20<>H20,"REVISAR","CORRECTO"),"") -> CORRECTO | J20: KUSPIT SP´S | K20: PRISCILA | L20: PAGADO | M20: 45720 | N20: DA-217848
A21: VICTOR MANUEL RUIZ ZARATE | B21: REEMBOLSO DE 2 PLASTICO PARA CANCELERIA OPALEN 2.7MM - 26FEB25 | C21: POOL DE MATERIALES | D21: =IFERROR(VLOOKUP($C21,CUENTAS[],2,0),"") -> MATERIALES | E21: =IFERROR(VLOOKUP($C21,CUENTAS[],3,0),"") -> MDE2025-004 | F21: 1370.69 | G21: 219.31 | H21: 1590 | I21: =IFERROR(IF(F21+G21<>H21,"REVISAR","CORRECTO"),"") -> CORRECTO | J21: KUSPIT SP´S | K21: PRISCILA | L21: PAGADO | M21: 45720 | N21: DA-217788
A22: CARLOS FERNANDO BECERRIL VILCHIS | B22: MTTO RANGER: AJUSTE DE MOTOR, REP DE VENTILADOR Y AFINACION COMPLETA | C22: SERVICIO Y MANTENIMIENTO DE UNIDADES DE TRANSPORTE | D22: =IFERROR(VLOOKUP($C22,CUENTAS[],2,0),"") -> LOGÍSTICA | E22: =IFERROR(VLOOKUP($C22,CUENTAS[],3,0),"") -> MDE2025-006A | F22: 19613.2 | G22: 3138.11 | H22: 22751.31 | I22: =IFERROR(IF(F22+G22<>H22,"REVISAR","CORRECTO"),"") -> CORRECTO | J22: KUSPIT SP´S | K22: FERNANDO | L22: PAGADO | M22: 45720 | N22: COT04797
A23: VIDAL ESTRADA | B23: PAGO RENTA DE CASA SUAREZ MARZO25 | C23: RENTAS | D23: =IFERROR(VLOOKUP($C23,CUENTAS[],2,0),"") -> GASTOS FIJOS | E23: =IFERROR(VLOOKUP($C23,CUENTAS[],3,0),"") -> MDE2025-002D | F23: 7327.59 | G23: 1172.41 | H23: 8500 | I23: =IFERROR(IF(F23+G23<>H23,"REVISAR","CORRECTO"),"") -> CORRECTO | J23: KUSPIT SP´S | K23: NAYELI | L23: PAGADO | M23: 45722 | N23: FAC 13463
A24: LUIS DANIEL GALICIA DE GANTE | B24: RESPIVERSO STAND | C24: DISEÑADORES BODEGA | D24: =IFERROR(VLOOKUP($C24,CUENTAS[],2,0),"") -> DISEÑOS | E24: =IFERROR(VLOOKUP($C24,CUENTAS[],3,0),"") -> MDE2025-001 | F24: 10000 | G24: 1600 | H24: 11600 | I24: =IFERROR(IF(F24+G24<>H24,"REVISAR","CORRECTO"),"") -> CORRECTO | J24: KUSPIT SP´S | K24: JAVIER MENA | L24: PAGADO | M24: 45722 | N24: FAC
A25: Toka internacional S.A.P.I. de C.V. | B25: 2434580 | C25: COMISIONES TOKA | D25: =IFERROR(VLOOKUP($C25,CUENTAS[],2,0),"") -> TOKA | E25: =IFERROR(VLOOKUP($C25,CUENTAS[],3,0),"") -> TOK2025-001C | F25: 300 | G25: 48 | H25: 348 | I25: =IFERROR(IF(F25+G25<>H25,"REVISAR","CORRECTO"),"") -> CORRECTO | J25: KUSPIT SP´S | K25: NAYELI | L25: PAGADO | M25: 45722 | N25: PREFACTURA
A26: ANGEL GUADALUPE ALBARRAN PEREA | B26: 50% SALDO ALUMINIO PARA VENTANAS OFICINAS NUEVAS | C26: EDIFICIOS | D26: =IFERROR(VLOOKUP($C26,CUENTAS[],2,0),"") -> ACTIVOS FIJOS | E26: =IFERROR(VLOOKUP($C26,CUENTAS[],3,0),"") -> MDE2025-007I | F26: 11500 | G26: 0 | H26: 11500 | I26: =IFERROR(IF(F26+G26<>H26,"REVISAR","CORRECTO"),"") -> CORRECTO | J26: KUSPIT SP´S | K26: ENRIQUE | L26: PAGADO | M26: 45723 | N26: N/A
A27: EVODIO DE JESUS GOMEZ | B27: PAGO MANO DE OBRA TRABAJO NUEVAS OFICINAS | C27: EDIFICIOS | D27: =IFERROR(VLOOKUP($C27,CUENTAS[],2,0),"") -> ACTIVOS FIJOS | E27: =IFERROR(VLOOKUP($C27,CUENTAS[],3,0),"") -> MDE2025-007I | F27: 3500 | G27: 0 | H27: 3500 | I27: =IFERROR(IF(F27+G27<>H27,"REVISAR","CORRECTO"),"") -> CORRECTO | J27: KUSPIT SP´S | K27: PRISCILA | L27: PAGADO | M27: 45723 | N27: N/A
A28: TIRSO DE JESUS DE LA CRUZ | B28: PAGO MANO DE OBRA TRABAJO NUEVAS OFICINAS | C28: EDIFICIOS | D28: =IFERROR(VLOOKUP($C28,CUENTAS[],2,0),"") -> ACTIVOS FIJOS | E28: =IFERROR(VLOOKUP($C28,CUENTAS[],3,0),"") -> MDE2025-007I | F28: 3200 | G28: 0 | H28: 3200 | I28: =IFERROR(IF(F28+G28<>H28,"REVISAR","CORRECTO"),"") -> CORRECTO | J28: KUSPIT SP´S | K28: PRISCILA | L28: PAGADO | M28: 45723 | N28: N/A
A29: BENITO AVILA DIAZ | B29: FAB DE CASA PARA PERROS | C29: MANTENIMIENTO Y REPARACIÓN VARIOS | D29: =IFERROR(VLOOKUP($C29,CUENTAS[],2,0),"") -> MANTENIMIENTO | E29: =IFERROR(VLOOKUP($C29,CUENTAS[],3,0),"") -> MDE2025-009B | F29: 2500 | G29: 0 | H29: 2500 | I29: =IFERROR(IF(F29+G29<>H29,"REVISAR","CORRECTO"),"") -> CORRECTO | J29: KUSPIT SP´S | K29: ENRIQUE | L29: PAGADO | M29: 45723 | N29: N/A
A30: LUIS ANTONIO GARDUÑO TAPIA | B30: MANO DE OBRA - INSTALACION ELECTRICA A CAJA ADIDAS | C30: MANTENIMIENTO Y REPARACIÓN VARIOS | D30: =IFERROR(VLOOKUP($C30,CUENTAS[],2,0),"") -> MANTENIMIENTO | E30: =IFERROR(VLOOKUP($C30,CUENTAS[],3,0),"") -> MDE2025-009B | F30: 1200 | G30: 0 | H30: 1200 | I30: =IFERROR(IF(F30+G30<>H30,"REVISAR","CORRECTO"),"") -> CORRECTO | J30: KUSPIT SP´S | K30: ENRIQUE | L30: PAGADO | M30: 45723 | N30: N/A
A31: LUIS ANTONIO GARDUÑO TAPIA | B31: MANO DE OBRA - DESMONTAJE DE MOTOR COMPRESOR | C31: MANTENIMIENTO Y REPARACIÓN VARIOS | D31: =IFERROR(VLOOKUP($C31,CUENTAS[],2,0),"") -> MANTENIMIENTO | E31: =IFERROR(VLOOKUP($C31,CUENTAS[],3,0),"") -> MDE2025-009B | F31: 300 | G31: 0 | H31: 300 | I31: =IFERROR(IF(F31+G31<>H31,"REVISAR","CORRECTO"),"") -> CORRECTO | J31: KUSPIT SP´S | K31: ENRIQUE | L31: PAGADO | M31: 45723 | N31: N/A
A32: LUIS ANTONIO GARDUÑO TAPIA | B32: MANO DE OBRA - REVISION Y AJUSTE DE HIDRO | C32: MANTENIMIENTO Y REPARACIÓN VARIOS | D32: =IFERROR(VLOOKUP($C32,CUENTAS[],2,0),"") -> MANTENIMIENTO | E32: =IFERROR(VLOOKUP($C32,CUENTAS[],3,0),"") -> MDE2025-009B | F32: 300 | G32: 0 | H32: 300 | I32: =IFERROR(IF(F32+G32<>H32,"REVISAR","CORRECTO"),"") -> CORRECTO | J32: KUSPIT SP´S | K32: ENRIQUE | L32: PAGADO | M32: 45723 | N32: N/A
A33: LUIS ANTONIO GARDUÑO TAPIA | B33: MANO DE OBRA - INSTALACION ELECTRICA OFICINAS NUEVAS | C33: EDIFICIOS | D33: =IFERROR(VLOOKUP($C33,CUENTAS[],2,0),"") -> ACTIVOS FIJOS | E33: =IFERROR(VLOOKUP($C33,CUENTAS[],3,0),"") -> MDE2025-007I | F33: 2000 | G33: 0 | H33: 2000 | I33: =IFERROR(IF(F33+G33<>H33,"REVISAR","CORRECTO"),"") -> CORRECTO | J33: KUSPIT SP´S | K33: ENRIQUE | L33: PAGADO | M33: 45723 | N33: N/A
A34: TOMAS SANABRIA ESCUTIA | B34: COMPRA DE ROLLO DE TELA NEGRA | C34: POOL DE MATERIALES | D34: =IFERROR(VLOOKUP($C34,CUENTAS[],2,0),"") -> MATERIALES | E34: =IFERROR(VLOOKUP($C34,CUENTAS[],3,0),"") -> MDE2025-004 | F34: 1050 | G34: 168 | H34: 1218 | I34: =IFERROR(IF(F34+G34<>H34,"REVISAR","CORRECTO"),"") -> CORRECTO | J34: KUSPIT SP´S | K34: ARIADNA | L34: PAGADO | M34: 45727 | N34: COT390
A35: JESSYCA VERÒNICA EZQUERRO DOMINGUEZ | B35: MOCK UPS UNIFORMES MADE | C35: UNIFORMES Y EPP | D35: =IFERROR(VLOOKUP($C35,CUENTAS[],2,0),"") -> GASTOS VARIOS | E35: =IFERROR(VLOOKUP($C35,CUENTAS[],3,0),"") -> MDE2025-003B | F35: 1500 | G35: 0 | H35: 1500 | I35: =IFERROR(IF(F35+G35<>H35,"REVISAR","CORRECTO"),"") -> CORRECTO | J35: KUSPIT SP´S | K35: ELISA NAVA | L35: PAGADO | M35: 45727 | N35: COT
A36: NORA LIZ PINEDA PEREZ | B36: COMPRA DE PLAYO 18" Y GUANTES TEJIDOS DE NYLON #7, #8 Y #9 - 14FEB25 | C36: POOL DE MATERIALES | D36: =IFERROR(VLOOKUP($C36,CUENTAS[],2,0),"") -> MATERIALES | E36: =IFERROR(VLOOKUP($C36,CUENTAS[],3,0),"") -> MDE2025-004 | F36: 1897.45 | G36: 303.59 | H36: 2201.04 | I36: =IFERROR(IF(F36+G36<>H36,"REVISAR","CORRECTO"),"") -> CORRECTO | J36: KUSPIT SP´S | K36: NAYELI | L36: PAGADO | M36: 45727 | N36: A 3448
A37: ELISA DANIELA NAVA TERAN | B37: REEMBOLSO COMPRA BOWL PARA MUESTRA "SABORMEX" | C37: DISEÑADORES BODEGA | D37: =IFERROR(VLOOKUP($C37,CUENTAS[],2,0),"") -> DISEÑOS | E37: =IFERROR(VLOOKUP($C37,CUENTAS[],3,0),"") -> MDE2025-001 | F37: 125 | G37: 0 | H37: 125 | I37: =IFERROR(IF(F37+G37<>H37,"REVISAR","CORRECTO"),"") -> CORRECTO | J37: KUSPIT SP´S | K37: ELISA NAVA | L37: PAGADO | M37: 45727 | N37: COMPROBANTE
... A55: QUALITAS COMPAÑÍA DE SEGUROS, SA DE CV | B55: PAGO SEGURO GREAT WALL MOTORS | C55: GASTOS DE TRANSPORTE | D55: =IFERROR(VLOOKUP($C55,CUENTAS[],2,0),"") -> LOGÍSTICA | E55: =IFERROR(VLOOKUP($C55,CUENTAS[],3,0),"") -> MDE2025-006C | F55: 18771.52 | G55: 3003.44 | H55: 21774.96 | I55: =IFERROR(IF(F55+G55<>H55,"REVISAR","CORRECTO"),"") -> CORRECTO | J55: KUSPIT SP´S | K55: FERNANDO | L55: PAGADO | M55: 45730 | N55: POL47246
A56: Toka internacional S.A.P.I. de C.V. | B56: 2443289 | C56: COMISIONES TOKA | D56: =IFERROR(VLOOKUP($C56,CUENTAS[],2,0),"") -> TOKA | E56: =IFERROR(VLOOKUP($C56,CUENTAS[],3,0),"") -> TOK2025-001C | F56: 200 | G56: 32 | H56: 232 | I56: =IFERROR(IF(F56+G56<>H56,"REVISAR","CORRECTO"),"") -> CORRECTO | J56: KUSPIT SP´S | K56: NAYELI | L56: PAGADO | M56: 45730 | N56: PENDIENTE
A57: Toka internacional S.A.P.I. de C.V. | B57: 2441983 | C57: COMISIONES TOKA | D57: =IFERROR(VLOOKUP($C57,CUENTAS[],2,0),"") -> TOKA | E57: =IFERROR(VLOOKUP($C57,CUENTAS[],3,0),"") -> TOK2025-001C | F57: 300 | G57: 48 | H57: 348 | I57: =IFERROR(IF(F57+G57<>H57,"REVISAR","CORRECTO"),"") -> CORRECTO | J57: KUSPIT SP´S | K57: NAYELI | L57: PAGADO | M57: 45730 | N57: PENDIENTE
A58: RICARDO MONTENEGRO | B58: PAGO POR SUSTITUCIÓN KIT CLUTCH, REPARACIÓN DE CAJA - RANGER | C58: SERVICIO Y MANTENIMIENTO DE UNIDADES DE TRANSPORTE | D58: =IFERROR(VLOOKUP($C58,CUENTAS[],2,0),"") -> LOGÍSTICA | E58: =IFERROR(VLOOKUP($C58,CUENTAS[],3,0),"") -> MDE2025-006A | F58: 8060 | G58: 1289.6 | H58: 9349.6 | I58: =IFERROR(IF(F58+G58<>H58,"REVISAR","CORRECTO"),"") -> CORRECTO | J58: KUSPIT SP´S | K58: FERNANDO | L58: PAGADO | M58: 45734 | N58: FOL-00000
A59: ECONOCOMEX SA DE CV | B59: 3L POLYFORM BARNIZ 11000 MAT, 1L POLYFORM CATALIZADOR 250, 4L POLYFORM SOLVENTE P/POLIURETANO - 13/03/2025 | C59: POOL DE MATERIALES | D59: =IFERROR(VLOOKUP($C59,CUENTAS[],2,0),"") -> MATERIALES | E59: =IFERROR(VLOOKUP($C59,CUENTAS[],3,0),"") -> MDE2025-004 | F59: 4712.93 | G59: 754.07 | H59: 5467 | I59: =IFERROR(IF(F59+G59<>H59,"REVISAR","CORRECTO"),"") -> CORRECTO | J59: KUSPIT SP´S | K59: ARIADNA | L59: PAGADO | M59: 45734 | N59: COT04903
A60: DISTRIBUIDORA SAGARO DE MEXICO | B60: 5 ROLLOS VINIL ORACAL WHITE , TRANSFER DE PAPEL | C60: POOL DE MATERIALES | D60: =IFERROR(VLOOKUP($C60,CUENTAS[],2,0),"") -> MATERIALES | E60: =IFERROR(VLOOKUP($C60,CUENTAS[],3,0),"") -> MDE2025-004 | F60: 22252.12 | G60: 3560.34 | H60: 25812.46 | I60: =IFERROR(IF(F60+G60<>H60,"REVISAR","CORRECTO"),"") -> CORRECTO | J60: KUSPIT SP´S | K60: ARIADNA | L60: PAGADO | M60: 45734 | N60: COT-16222
A61: DEKOMADERA SA DE CV | B61: COMPRA DE 3 PZAS BROCA CARBURO PF- 535, 4PZAS BROCA CARBURO PF-535-2 - 27 FEB25 | C61: POOL DE MATERIALES | D61: =IFERROR(VLOOKUP($C61,CUENTAS[],2,0),"") -> MATERIALES | E61: =IFERROR(VLOOKUP($C61,CUENTAS[],3,0),"") -> MDE2025-004 | F61: 1878.5 | G61: 0 | H61: 1878.5 | I61: =IFERROR(IF(F61+G61<>H61,"REVISAR","CORRECTO"),"") -> CORRECTO | J61: KUSPIT SP´S | K61: PRISCILA | L61: PAGADO | M61: 45734 | N61: DA-217720
A62: DEKOMADERA SA DE CV | B62: COMPRA DE RESANALACK RINO 1 L - 27FEB25 | C62: POOL DE MATERIALES | D62: =IFERROR(VLOOKUP($C62,CUENTAS[],2,0),"") -> MATERIALES | E62: =IFERROR(VLOOKUP($C62,CUENTAS[],3,0),"") -> MDE2025-004 | F62: 1849.68 | G62: 0 | H62: 1849.68 | I62: =IFERROR(IF(F62+G62<>H62,"REVISAR","CORRECTO"),"") -> CORRECTO | J62: KUSPIT SP´S | K62: PRISCILA | L62: PAGADO | M62: 45734 | N62: DA-217677
A63: VICTOR MANUEL RUIZ ZARATE | B63: REEMBOLSO DE COMPRAS MATERIALES: CABLE ESTAÑO Y NEON FLEX, TIRA LED | C63: POOL DE MATERIALES | D63: =IFERROR(VLOOKUP($C63,CUENTAS[],2,0),"") -> MATERIALES | E63: =IFERROR(VLOOKUP($C63,CUENTAS[],3,0),"") -> MDE2025-004 | F63: 22973.13 | G63: 0 | H63: 22973.13 | I63: =IFERROR(IF(F63+G63<>H63,"REVISAR","CORRECTO"),"") -> CORRECTO | J63: KUSPIT SP´S | K63: NAYELI | L63: PAGADO | M63: 45734 | N63: C259032, FAC839
A64: MADERAMEX | B64: 35 TABLAS DE 20CM, 2 TABLAS DE TRIPLAY DE 15MM DE PRIMERA | C64: POOL DE MATERIALES | D64: =IFERROR(VLOOKUP($C64,CUENTAS[],2,0),"") -> MATERIALES | E64: =IFERROR(VLOOKUP($C64,CUENTAS[],3,0),"") -> MDE2025-004 | F64: 13288 | G64: 0 | H64: 13288 | I64: =IFERROR(IF(F64+G64<>H64,"REVISAR","CORRECTO"),"") -> CORRECTO | J64: KUSPIT SP´S | K64: ARIADNA | L64: PAGADO | M64: 45734 | N64: COT-01
A65: QUALITAS COMPAÑÍA DE SEGUROS, SA DE CV | B65: PAGO SEGURO RABON EQ INTERNATIONAL MV607 27FEB25 AL 27FEB26 | C65: GASTOS DE TRANSPORTE | D65: =IFERROR(VLOOKUP($C65,CUENTAS[],2,0),"") -> LOGÍSTICA | E65: =IFERROR(VLOOKUP($C65,CUENTAS[],3,0),"") -> MDE2025-006C | F65: 50266.38 | G65: 8042.62 | H65: 58309 | I65: =IFERROR(IF(F65+G65<>H65,"REVISAR","CORRECTO"),"") -> CORRECTO | J65: KUSPIT SP´S | K65: FERNANDO | L65: PAGADO | M65: 45734 | N65: POL47167
A66: JOSE E ZEPEDA BURGOS | B66: REEMBOLSO COMPRA DE MATERIALES - VICTOR R 15MZO25 | C66: POOL DE MATERIALES | D66: =IFERROR(VLOOKUP($C66,CUENTAS[],2,0),"") -> MATERIALES | E66: =IFERROR(VLOOKUP($C66,CUENTAS[],3,0),"") -> MDE2025-004 | F66: 3200 | G66: 0 | H66: 3200 | I66: =IFERROR(IF(F66+G66<>H66,"REVISAR","CORRECTO"),"") -> CORRECTO | J66: KUSPIT SP´S | K66: NAYELI | L66: PAGADO | M66: 45734 | N66: COMPROBANTE
A67: JOSE E ZEPEDA BURGOS | B67: REEMBOLSO COMPRA DE MATERIALES - VICTOR R 14MZO25 | C67: POOL DE MATERIALES | D67: =IFERROR(VLOOKUP($C67,CUENTAS[],2,0),"") -> MATERIALES | E67: =IFERROR(VLOOKUP($C67,CUENTAS[],3,0),"") -> MDE2025-004 | F67: 40000 | G67: 0 | H67: 40000 | I67: =IFERROR(IF(F67+G67<>H67,"REVISAR","CORRECTO"),"") -> CORRECTO | J67: KUSPIT SP´S | K67: NAYELI | L67: PAGADO | M67: 45734 | N67: COMPROBANTE
A68: GRUPO ROLANS SA DE CV | B68: 50 LLANTAS CON FRENO. 50 LLANTAS SIN FRENO COLOR NEGRO | C68: POOL DE MATERIALES | D68: =IFERROR(VLOOKUP($C68,CUENTAS[],2,0),"") -> MATERIALES | E68: =IFERROR(VLOOKUP($C68,CUENTAS[],3,0),"") -> MDE2025-004 | F68: 4397 | G68: 703.52 | H68: 5100.52 | I68: =IFERROR(IF(F68+G68<>H68,"REVISAR","CORRECTO"),"") -> CORRECTO | J68: KUSPIT SP´S | K68: ARIADNA | L68: PAGADO | M68: 45735 | N68: TOL-65219
A69: PESA TECNOLOGIA | B69: CINTA VERDE, TESA DOBLE CARA, CINTAS DE DUCTOS GRIS, CINTA NEGRA,CINTA MASKING | C69: POOL DE MATERIALES | D69: =IFERROR(VLOOKUP($C69,CUENTAS[],2,0),"") -> MATERIALES | E69: =IFERROR(VLOOKUP($C69,CUENTAS[],3,0),"") -> MDE2025-004 | F69: 25446.54 | G69: 4071.46 | H69: 29518 | I69: =IFERROR(IF(F69+G69<>H69,"REVISAR","CORRECTO"),"") -> CORRECTO | J69: KUSPIT SP´S | K69: ARIADNA | L69: PAGADO | M69: 45735 | N69: COT5142
... A108: LUIS ANTONIO GARDUÑO TAPIA | B108: MANO DE OBRA OFICINAS NUEVAS | C108: EDIFICIOS | D108: =IFERROR(VLOOKUP($C108,CUENTAS[],2,0),"") -> ACTIVOS FIJOS | E108: =IFERROR(VLOOKUP($C108,CUENTAS[],3,0),"") -> MDE2025-007I | F108: 3000 | G108: 0 | H108: 3000 | I108: =IFERROR(IF(F108+G108<>H108,"REVISAR","CORRECTO"),"") -> CORRECTO | J108: KUSPIT SP´S | K108: ENRIQUE | L108: PAGADO | M108: 45744 | N108: N/A
A109: ALMACEN | B109: 2 PARES GUANTES HYFLEX #7 SERGIO Y PEDRO | C109: UNIFORMES Y EPP | D109: =IFERROR(VLOOKUP($C109,CUENTAS[],2,0),"") -> GASTOS VARIOS | E109: =IFERROR(VLOOKUP($C109,CUENTAS[],3,0),"") -> MDE2025-003B | F109: 37.1 | G109: 2.56 | H109: 39.66 | I109: =IFERROR(IF(F109+G109<>H109,"REVISAR","CORRECTO"),"") -> CORRECTO | J109: ALMACEN | K109: MARTIN | L109: PAGADO | M109: 45719
A110: ALMACEN | B110: 1 CUTHER GRANDE, 1 CUTTHER CH, 1 FELPA | C110: INSUMOS PARA MANTENIMIENTO BODEGA | D110: =IFERROR(VLOOKUP($C110,CUENTAS[],2,0),"") -> MANTENIMIENTO | E110: =IFERROR(VLOOKUP($C110,CUENTAS[],3,0),"") -> MDE2025-009A | F110: 51.53 | G110: 8.24 | H110: 59.77 | I110: =IFERROR(IF(F110+G110<>H110,"REVISAR","CORRECTO"),"") -> CORRECTO | J110: ALMACEN | K110: ALEJANDRA | L110: PAGADO | M110: 45719
A111: ALMACEN | B111: HOJA DE MDF DE 6MM | C111: SERVICIO Y MANTENIMIENTO DE UNIDADES DE TRANSPORTE | D111: =IFERROR(VLOOKUP($C111,CUENTAS[],2,0),"") -> LOGÍSTICA | E111: =IFERROR(VLOOKUP($C111,CUENTAS[],3,0),"") -> MDE2025-006A | F111: 203.06 | G111: 32.49 | H111: 235.55 | I111: =IFERROR(IF(F111+G111<>H111,"REVISAR","CORRECTO"),"") -> CORRECTO | J111: ALMACEN | K111: MARTIN | L111: PAGADO | M111: 45736
A112: ALMACEN | B112: LIJA NEGRA DE 120 | C112: INSUMOS PARA MANTENIMIENTO BODEGA | D112: =IFERROR(VLOOKUP($C112,CUENTAS[],2,0),"") -> MANTENIMIENTO | E112: =IFERROR(VLOOKUP($C112,CUENTAS[],3,0),"") -> MDE2025-009A | F112: 9.14 | G112: 0.86 | H112: 10 | I112: =IFERROR(IF(F112+G112<>H112,"REVISAR","CORRECTO"),"") -> CORRECTO | J112: ALMACEN | K112: MARTIN | L112: PAGADO | M112: 45736
A113: ALMACEN | B113: CINCHOS 50 PIEZAS SPORTIKA | C113: MATERIALES BODEGA | D113: =IFERROR(VLOOKUP($C113,CUENTAS[],2,0),"") -> MATERIALES | E113: =IFERROR(VLOOKUP($C113,CUENTAS[],3,0),"") -> MDE2025-004A | F113: 325.87 | G113: 52.13 | H113: 378 | I113: =IFERROR(IF(F113+G113<>H113,"REVISAR","CORRECTO"),"") -> CORRECTO | J113: ALMACEN | K113: MARTIN | L113: PAGADO | M113: 45737
A114: ALMACEN | B114: CINTA GAFER, CINTA DE AISLAR, FELPA CHICA SPORTIKA | C114: MATERIALES BODEGA | D114: =IFERROR(VLOOKUP($C114,CUENTAS[],2,0),"") -> MATERIALES | E114: =IFERROR(VLOOKUP($C114,CUENTAS[],3,0),"") -> MDE2025-004A | F114: 154.38 | G114: 24.7 | H114: 179.08 | I114: =IFERROR(IF(F114+G114<>H114,"REVISAR","CORRECTO"),"") -> CORRECTO | J114: ALMACEN | K114: MARTIN | L114: PAGADO | M114: 45737
A115: ALMACEN | B115: PINTURA VINILICA NEGRA SPORTIKA 1LT | C115: MATERIALES BODEGA | D115: =IFERROR(VLOOKUP($C115,CUENTAS[],2,0),"") -> MATERIALES | E115: =IFERROR(VLOOKUP($C115,CUENTAS[],3,0),"") -> MDE2025-004A | F115: 163.78 | G115: 26.16 | H115: 189.94 | I115: =IFERROR(IF(F115+G115<>H115,"REVISAR","CORRECTO"),"") -> CORRECTO | J115: ALMACEN | K115: MARTIN | L115: PAGADO | M115: 45737
A116: ALMACEN | B116: FELPA GRANDE,BROCCHA DE 2" OFICINAS NUEVAS | C116: EDIFICIOS | D116: =IFERROR(VLOOKUP($C116,CUENTAS[],2,0),"") -> ACTIVOS FIJOS | E116: =IFERROR(VLOOKUP($C116,CUENTAS[],3,0),"") -> MDE2025-007I | F116: 78.64 | G116: 12.58 | H116: 91.22 | I116: =IFERROR(IF(F116+G116<>H116,"REVISAR","CORRECTO"),"") -> CORRECTO | J116: ALMACEN | K116: MARTIN | L116: PAGADO | M116: 45798
A117: ALMACEN | B117: 1 CUBETA DE PINTURA VINILICA BLANCA OFICINAS NUEVAS | C117: EDIFICIOS | D117: =IFERROR(VLOOKUP($C117,CUENTAS[],2,0),"") -> ACTIVOS FIJOS | E117: =IFERROR(VLOOKUP($C117,CUENTAS[],3,0),"") -> MDE2025-007I | F117: 3106.9 | G117: 497.1 | H117: 3604 | I117: =IFERROR(IF(F117+G117<>H117,"REVISAR","CORRECTO"),"") -> CORRECTO | J117: ALMACEN | K117: MARTIN | L117: PAGADO | M117: 45798
A118: ALMACEN | B118: CUTTER GRANDE PARA DISEÑO | C118: INSUMOS PARA MANTENIMIENTO BODEGA | D118: =IFERROR(VLOOKUP($C118,CUENTAS[],2,0),"") -> MANTENIMIENTO | E118: =IFERROR(VLOOKUP($C118,CUENTAS[],3,0),"") -> MDE2025-009A | F118: 14.83 | G118: 0.86 | H118: 15.69 | I118: =IFERROR(IF(F118+G118<>H118,"REVISAR","CORRECTO"),"") -> CORRECTO | J118: ALMACEN | K118: CESAR | L118: PAGADO | M118: 45798
A119: ALMACEN | B119: FELPA CHICA CASA PERROS | C119: INSUMOS PARA MANTENIMIENTO BODEGA | D119: =IFERROR(VLOOKUP($C119,CUENTAS[],2,0),"") -> MANTENIMIENTO | E119: =IFERROR(VLOOKUP($C119,CUENTAS[],3,0),"") -> MDE2025-009A | F119: 30.6 | G119: 4.9 | H119: 35.5 | I119: =IFERROR(IF(F119+G119<>H119,"REVISAR","CORRECTO"),"") -> CORRECTO | J119: ALMACEN | K119: MARTIN | L119: PAGADO | M119: 45742
A120: ALMACEN | B120: PIJA 2" CASA DE PERRO 100 | C120: INSUMOS PARA MANTENIMIENTO BODEGA | D120: =IFERROR(VLOOKUP($C120,CUENTAS[],2,0),"") -> MANTENIMIENTO | E120: =IFERROR(VLOOKUP($C120,CUENTAS[],3,0),"") -> MDE2025-009A | F120: 14.3 | G120: 2.2 | H120: 16.5 | I120: =IFERROR(IF(F120+G120<>H120,"REVISAR","CORRECTO"),"") -> CORRECTO | J120: ALMACEN | K120: MARTIN | L120: PAGADO | M120: 45742
A121: ALMACEN | B121: PIJA 1 1/2 CASA PEROOS 100 | C121: INSUMOS PARA MANTENIMIENTO BODEGA | D121: =IFERROR(VLOOKUP($C121,CUENTAS[],2,0),"") -> MANTENIMIENTO | E121: =IFERROR(VLOOKUP($C121,CUENTAS[],3,0),"") -> MDE2025-009A | F121: 17.85 | G121: 2.85 | H121: 20.7 | I121: =IFERROR(IF(F121+G121<>H121,"REVISAR","CORRECTO"),"") -> CORRECTO | J121: ALMACEN | K121: MARTIN | L121: PAGADO | M121: 45742 | N121: .
A122: ALMACEN | B122: LIJA CON VELCRO GRADO 60 3 CASA PERROS | C122: INSUMOS PARA MANTENIMIENTO BODEGA | D122: =IFERROR(VLOOKUP($C122,CUENTAS[],2,0),"") -> MANTENIMIENTO | E122: =IFERROR(VLOOKUP($C122,CUENTAS[],3,0),"") -> MDE2025-009A | F122: 30.25 | G122: 4.85 | H122: 35.1 | I122: =IFERROR(IF(F122+G122<>H122,"REVISAR","CORRECTO"),"") -> CORRECTO | J122: ALMACEN | K122: MARTIN | L122: PAGADO | M122: 45742
A123: ALMACEN | B123: LIJA CON VELCRO GRADO 80 2 CASA PERROS | C123: INSUMOS PARA MANTENIMIENTO BODEGA | D123: =IFERROR(VLOOKUP($C123,CUENTAS[],2,0),"") -> MANTENIMIENTO | E123: =IFERROR(VLOOKUP($C123,CUENTAS[],3,0),"") -> MDE2025-009A | F123: 17.46 | G123: 2.8 | H123: 20.26 | I123: =IFERROR(IF(F123+G123<>H123,"REVISAR","CORRECTO"),"") -> CORRECTO | J123: ALMACEN | K123: MARTIN | L123: PAGADO | M123: 45742
B124: GUANTES HYFLEX 7 Y 8 | C124: INSUMOS PARA MANTENIMIENTO BODEGA | D124: =IFERROR(VLOOKUP($C124,CUENTAS[],2,0),"") -> MANTENIMIENTO | E124: =IFERROR(VLOOKUP($C124,CUENTAS[],3,0),"") -> MDE2025-009A | F124: 34.5 | G124: 5.5 | H124: 40 | I124: =IFERROR(IF(F124+G124<>H124,"REVISAR","CORRECTO"),"") -> CORRECTO | J124: ALMACEN | K124: MARTIN | L124: PAGADO | M124: 45744
A125: FERRECSA | B125: CLAVOS, BANDA PRECAUCION, SIERRA P/MADERA, LIJAS, GRAPAS, SEGUETAS, KOLA LOKA, PUNTA DE CRUZ | C125: POOL DE MATERIALES | D125: =IFERROR(VLOOKUP($C125,CUENTAS[],2,0),"") -> MATERIALES | E125: =IFERROR(VLOOKUP($C125,CUENTAS[],3,0),"") -> MDE2025-004 | F125: 17533.44 | G125: 2805.36 | H125: 20338.8 | I125: =IFERROR(IF(F125+G125<>H125,"REVISAR","CORRECTO"),"") -> CORRECTO | J125: BBVA | K125: VICTOR RUIZ | L125: PAGADO | M125: 45729 | N125: D749696
A126: FERRECSA | B126: 4 SIERRAS PARA MADERA 10/80 DIENTES DEWALT | C126: POOL DE MATERIALES | D126: =IFERROR(VLOOKUP($C126,CUENTAS[],2,0),"") -> MATERIALES | E126: =IFERROR(VLOOKUP($C126,CUENTAS[],3,0),"") -> MDE2025-004 | F126: 2662.08 | G126: 425.93 | H126: 3088.01 | I126: =IFERROR(IF(F126+G126<>H126,"REVISAR","CORRECTO"),"") -> CORRECTO | J126: BBVA | K126: VICTOR RUIZ | L126: PAGADO | M126: 45729 | N126: D749705
A127: NOVELSA | B127: 1 ROLLO DE POLYFORM 1M X 105 X 1/8# | C127: POOL DE MATERIALES | D127: =IFERROR(VLOOKUP($C127,CUENTAS[],2,0),"") -> MATERIALES | E127: =IFERROR(VLOOKUP($C127,CUENTAS[],3,0),"") -> MDE2025-004 | F127: 586.35 | G127: 93.82 | H127: 680.17 | I127: =IFERROR(IF(F127+G127<>H127,"REVISAR","CORRECTO"),"") -> CORRECTO | J127: BBVA | K127: VICTOR RUIZ | L127: PAGADO | M127: 45730 | N127: DT86807
A128: NOVELSA | B128: 160 ESQUIN-K2X2 CAL 160 Y 1 ROLLO POLYFORM | C128: POOL DE MATERIALES | D128: =IFERROR(VLOOKUP($C128,CUENTAS[],2,0),"") -> MATERIALES | E128: =IFERROR(VLOOKUP($C128,CUENTAS[],3,0),"") -> MDE2025-004 | F128: 2795.95 | G128: 447.35 | H128: 3243.3 | I128: =IFERROR(IF(F128+G128<>H128,"REVISAR","CORRECTO"),"") -> CORRECTO | J128: BBVA | K128: VICTOR RUIZ | L128: PAGADO | M128: 45730 | N128: DT-89796
A129: COMERCIALIZADORA NAVJAM | B129: ARANDELAS GAL 5/16, TUERCAS GAL 5/16X18H Y TORNILLOS GAL CUERDA CORR | C129: POOL DE MATERIALES | D129: =IFERROR(VLOOKUP($C129,CUENTAS[],2,0),"") -> MATERIALES | E129: =IFERROR(VLOOKUP($C129,CUENTAS[],3,0),"") -> MDE2025-004 | F129: 169.38 | G129: 27.1 | H129: 196.48 | I129: =IFERROR(IF(F129+G129<>H129,"REVISAR","CORRECTO"),"") -> CORRECTO | J129: BBVA | K129: VICTOR RUIZ | L129: PAGADO | M129: 45730 | N129: NM20779
A130: DON LOLO | B130: 2 JGO PINCEL PRETUL Y 1KG CLAVO ESTÁNDAR | C130: POOL DE MATERIALES | D130: =IFERROR(VLOOKUP($C130,CUENTAS[],2,0),"") -> MATERIALES | E130: =IFERROR(VLOOKUP($C130,CUENTAS[],3,0),"") -> MDE2025-004 | F130: 137.93 | G130: 22.07 | H130: 160 | I130: =IFERROR(IF(F130+G130<>H130,"REVISAR","CORRECTO"),"") -> CORRECTO | J130: BBVA | K130: VICTOR RUIZ | L130: PAGADO | M130: 45730 | N130: F2898
A131: EUROELECTRICA | B131: CABLE DUPLEX, CONTACTOS, TOMA CORRIENTE, CABLE USO RUDO, TERMINAL TIPO ESPADA CINTA DE AISLAR, PLACA PARA RECEPTACULO, CAJA CHALUPA | C131: POOL DE MATERIALES | D131: =IFERROR(VLOOKUP($C131,CUENTAS[],2,0),"") -> MATERIALES | E131: =IFERROR(VLOOKUP($C131,CUENTAS[],3,0),"") -> MDE2025-004 | F131: 12311.58 | G131: 1969.85 | H131: 14281.43 | I131: =IFERROR(IF(F131+G131<>H131,"REVISAR","CORRECTO"),"") -> CORRECTO | J131: BBVA | K131: VICTOR RUIZ | L131: PAGADO | M131: 45730 | N131: XFA78022
A132: ECONOCOMEX | B132: MASKINTG AZUL, MASKING 3M | C132: POOL DE MATERIALES | D132: =IFERROR(VLOOKUP($C132,CUENTAS[],2,0),"") -> MATERIALES | E132: =IFERROR(VLOOKUP($C132,CUENTAS[],3,0),"") -> MDE2025-004 | F132: 606.89 | G132: 97.11 | H132: 704 | I132: =IFERROR(IF(F132+G132<>H132,"REVISAR","CORRECTO"),"") -> CORRECTO | J132: BBVA | K132: VICTOR RUIZ | L132: PAGADO | M132: 45730 | N132: AEBE16259
A133: MADEKO | B133: 1 CERRADURA FERKY NS RECAMARA BOLA CILINDRICA | C133: POOL DE MATERIALES | D133: =IFERROR(VLOOKUP($C133,CUENTAS[],2,0),"") -> MATERIALES | E133: =IFERROR(VLOOKUP($C133,CUENTAS[],3,0),"") -> MDE2025-004 | F133: 233.36 | G133: 37.34 | H133: 270.7 | I133: =IFERROR(IF(F133+G133<>H133,"REVISAR","CORRECTO"),"") -> CORRECTO | J133: BBVA | K133: VICTOR RUIZ | L133: PAGADO | M133: 45730 | N133: MDK6179
A134: JOSE E ZEPEDA BURGOS | B134: BBVA RETAIL | C134: MANTENIMIENTO Y REPARACIÓN VARIOS | D134: =IFERROR(VLOOKUP($C134,CUENTAS[],2,0),"") -> MANTENIMIENTO | E134: =IFERROR(VLOOKUP($C134,CUENTAS[],3,0),"") -> MDE2025-009B | F134: 514.54 | G134: 82.33 | H134: 596.87 | I134: =IFERROR(IF(F134+G134<>H134,"REVISAR","CORRECTO"),"") -> CORRECTO | J134: AMEX | K134: ENRIQUE | L134: PAGADO | M134: 45750 | N134: FAA316132792
A135: JOSE E ZEPEDA BURGOS | B135: GERSA METEPEC EM | C135: MANTENIMIENTO Y REPARACIÓN VARIOS | D135: =IFERROR(VLOOKUP($C135,CUENTAS[],2,0),"") -> MANTENIMIENTO | E135: =IFERROR(VLOOKUP($C135,CUENTAS[],3,0),"") -> MDE2025-009B | F135: 4154.76 | G135: 664.76 | H135: 4819.52 | I135: =IFERROR(IF(F135+G135<>H135,"REVISAR","CORRECTO"),"") -> CORRECTO | J135: AMEX | K135: ENRIQUE | L135: PAGADO | M135: 45750 | N135: FA-31685780021
A136: JOSE E ZEPEDA BURGOS | B136: BBVA RETAIL | C136: MANTENIMIENTO Y REPARACIÓN VARIOS | D136: =IFERROR(VLOOKUP($C136,CUENTAS[],2,0),"") -> MANTENIMIENTO | E136: =IFERROR(VLOOKUP($C136,CUENTAS[],3,0),"") -> MDE2025-009B | F136: 19433.21 | G136: 0 | H136: 19433.21 | I136: =IFERROR(IF(F136+G136<>H136,"REVISAR","CORRECTO"),"") -> CORRECTO | J136: AMEX | K136: ENRIQUE | L136: PAGADO | M136: 45747 | N136: RBO 316-166343
... A139: JOSE E ZEPEDA BURGOS | B139: GERSA METEPEC EM | C139: MANTENIMIENTO Y REPARACIÓN VARIOS | D139: =IFERROR(VLOOKUP($C139,CUENTAS[],2,0),"") -> MANTENIMIENTO | E139: =IFERROR(VLOOKUP($C139,CUENTAS[],3,0),"") -> MDE2025-009B | F139: 10278.84 | G139: 1644.61 | H139: 11923.45 | I139: =IFERROR(IF(F139+G139<>H139,"REVISAR","CORRECTO"),"") -> CORRECTO | J139: AMEX | K139: ENRIQUE | L139: PAGADO | M139: 45747 | N139: 316-86177825
A140: JOSE E ZEPEDA BURGOS | B140: OPENPAY*STARLINK CIUDAD DE MEXIC | C140: SERVICIOS TELEFÓNICOS E INTERNET | D140: =IFERROR(VLOOKUP($C140,CUENTAS[],2,0),"") -> GASTOS FIJOS | E140: =IFERROR(VLOOKUP($C140,CUENTAS[],3,0),"") -> MDE2025-002F | F140: 3148 | G140: 0 | H140: 3148 | I140: =IFERROR(IF(F140+G140<>H140,"REVISAR","CORRECTO"),"") -> CORRECTO | J140: AMEX | K140: ENRIQUE | L140: PAGADO | M140: 45750
A141: JOSE E ZEPEDA BURGOS | B141: AMAZON MX MARKETPLACE*A MEXICO CITY | C141: SERVICIOS TELEFÓNICOS E INTERNET | D141: =IFERROR(VLOOKUP($C141,CUENTAS[],2,0),"") -> GASTOS FIJOS | E141: =IFERROR(VLOOKUP($C141,CUENTAS[],3,0),"") -> MDE2025-002F | F141: -1.11 | G141: 0 | H141: -1.11 | I141: =IFERROR(IF(F141+G141<>H141,"REVISAR","CORRECTO"),"") -> CORRECTO | J141: AMEX | L141: PAGADO
A142: JOSE E ZEPEDA BURGOS | B142: AMAZON MX MARKETPLACE*A MEXICO CITY | C142: SERVICIOS TELEFÓNICOS E INTERNET | D142: =IFERROR(VLOOKUP($C142,CUENTAS[],2,0),"") -> GASTOS FIJOS | E142: =IFERROR(VLOOKUP($C142,CUENTAS[],3,0),"") -> MDE2025-002F | F142: -0.74 | G142: 0 | H142: -0.74 | I142: =IFERROR(IF(F142+G142<>H142,"REVISAR","CORRECTO"),"") -> CORRECTO | J142: AMEX | L142: PAGADO
A143: JOSE E ZEPEDA BURGOS | B143: AMAZON MX MARKETPLACE*A MEXICO CITY | C143: SERVICIOS TELEFÓNICOS E INTERNET | D143: =IFERROR(VLOOKUP($C143,CUENTAS[],2,0),"") -> GASTOS FIJOS | E143: =IFERROR(VLOOKUP($C143,CUENTAS[],3,0),"") -> MDE2025-002F | F143: -0.74 | G143: 0 | H143: -0.74 | I143: =IFERROR(IF(F143+G143<>H143,"REVISAR","CORRECTO"),"") -> CORRECTO | J143: AMEX | L143: PAGADO
A144: JOSE E ZEPEDA BURGOS | B144: MERCADO LIBRE MEXICO | C144: SERVICIOS TELEFÓNICOS E INTERNET | D144: =IFERROR(VLOOKUP($C144,CUENTAS[],2,0),"") -> GASTOS FIJOS | E144: =IFERROR(VLOOKUP($C144,CUENTAS[],3,0),"") -> MDE2025-002F | F144: -89 | G144: 0 | H144: -89 | I144: =IFERROR(IF(F144+G144<>H144,"REVISAR","CORRECTO"),"") -> CORRECTO | J144: AMEX | L144: PAGADO
A145: MA LORETO ALTAMIRANO B | B145: RAPPI*RAPPI MEXICO MEXICO CITY | C145: SERVICIOS TELEFÓNICOS E INTERNET | D145: =IFERROR(VLOOKUP($C145,CUENTAS[],2,0),"") -> GASTOS FIJOS | E145: =IFERROR(VLOOKUP($C145,CUENTAS[],3,0),"") -> MDE2025-002F | F145: -180 | G145: 0 | H145: -180 | I145: =IFERROR(IF(F145+G145<>H145,"REVISAR","CORRECTO"),"") -> CORRECTO | J145: AMEX | L145: PAGADO
A146: MA LORETO ALTAMIRANO B | B146: RAPPI*RAPPI MEXICO MEXICO CITY | C146: SERVICIOS TELEFÓNICOS E INTERNET | D146: =IFERROR(VLOOKUP($C146,CUENTAS[],2,0),"") -> GASTOS FIJOS | E146: =IFERROR(VLOOKUP($C146,CUENTAS[],3,0),"") -> MDE2025-002F | F146: -54.83 | G146: 0 | H146: -54.83 | I146: =IFERROR(IF(F146+G146<>H146,"REVISAR","CORRECTO"),"") -> CORRECTO | J146: AMEX | L146: PAGADO
A147: OSCAR A CAZARES HERRERA | B147: VIAGOGO EVENT TICKETS GENEVA | C147: SERVICIOS TELEFÓNICOS E INTERNET | D147: =IFERROR(VLOOKUP($C147,CUENTAS[],2,0),"") -> GASTOS FIJOS | E147: =IFERROR(VLOOKUP($C147,CUENTAS[],3,0),"") -> MDE2025-002F | F147: -173.28 | G147: 0 | H147: -173.28 | I147: =IFERROR(IF(F147+G147<>H147,"REVISAR","CORRECTO"),"") -> CORRECTO | J147: AMEX | L147: PAGADO
A148: JOSE E ZEPEDA BURGOS | B148: SALDO A FAVOR | C148: SERVICIOS TELEFÓNICOS E INTERNET | D148: =IFERROR(VLOOKUP($C148,CUENTAS[],2,0),"") -> GASTOS FIJOS | E148: =IFERROR(VLOOKUP($C148,CUENTAS[],3,0),"") -> MDE2025-002F | F148: -282.67 | G148: 0 | H148: -282.67 | I148: =IFERROR(IF(F148+G148<>H148,"REVISAR","CORRECTO"),"") -> CORRECTO | J148: AMEX | L148: PAGADO
A149: JOSE E ZEPEDA BURGOS | B149: APPLE STORE R740 R740 MEXICO CITY | C149: EQUIPO DE CÓMPUTO Y TELEFONÍA | D149: =IFERROR(VLOOKUP($C149,CUENTAS[],2,0),"") -> ACTIVOS FIJOS | E149: =IFERROR(VLOOKUP($C149,CUENTAS[],3,0),"") -> MDE2025-007B | F149: 7649.67 | G149: 0 | H149: 7649.67 | I149: =IFERROR(IF(F149+G149<>H149,"REVISAR","CORRECTO"),"") -> CORRECTO | J149: AMEX | K149: ENRIQUE | L149: PAGADO | M149: 45750
A150: JOSE E ZEPEDA BURGOS | B150: OPENPAY*STARLINK CIUDAD DE MEXIC | C150: SERVICIOS TELEFÓNICOS E INTERNET | D150: =IFERROR(VLOOKUP($C150,CUENTAS[],2,0),"") -> GASTOS FIJOS | E150: =IFERROR(VLOOKUP($C150,CUENTAS[],3,0),"") -> MDE2025-002F | F150: 1045 | G150: 0 | H150: 1045 | I150: =IFERROR(IF(F150+G150<>H150,"REVISAR","CORRECTO"),"") -> CORRECTO | J150: AMEX | K150: ENRIQUE | L150: PAGADO | M150: 45750
A151: OSCAR A CAZARES HERRERA | B151: MONTO POR CANCELACIÒN DE PAGOS DIFERIDOS | C151: AMEX VARIOS | D151: =IFERROR(VLOOKUP($C151,CUENTAS[],2,0),"") -> GASTOS VARIOS | E151: =IFERROR(VLOOKUP($C151,CUENTAS[],3,0),"") -> MDE2025-003L | F151: 33382.66 | G151: 0 | H151: 33382.66 | I151: =IFERROR(IF(F151+G151<>H151,"REVISAR","CORRECTO"),"") -> CORRECTO | J151: AMEX | K151: SALDO DIFERIDO CANCELADO | L151: PAGADO | M151: 45750
A152: OSCAR A CAZARES HERRERA | B152: COMISIÓN POR PLAN DE PAGOS DIFERIDOS | C152: AMEX VARIOS | D152: =IFERROR(VLOOKUP($C152,CUENTAS[],2,0),"") -> GASTOS VARIOS | E152: =IFERROR(VLOOKUP($C152,CUENTAS[],3,0),"") -> MDE2025-003L | F152: 1663.65 | G152: 0 | H152: 1663.65 | I152: =IFERROR(IF(F152+G152<>H152,"REVISAR","CORRECTO"),"") -> CORRECTO | J152: AMEX | K152: MONTO QUE SE PAGO A SALDO DIFERIDO | L152: PAGADO | M152: 45750
A153: OSCAR A CAZARES HERRERA | B153: IVA APLICABLE | C153: AMEX VARIOS | D153: =IFERROR(VLOOKUP($C153,CUENTAS[],2,0),"") -> GASTOS VARIOS | E153: =IFERROR(VLOOKUP($C153,CUENTAS[],3,0),"") -> MDE2025-003L | F153: 266.18 | G153: 0 | H153: 266.18 | I153: =IFERROR(IF(F153+G153<>H153,"REVISAR","CORRECTO"),"") -> CORRECTO | J153: AMEX | K153: MONTO QUE SE PAGO A SALDO DIFERIDO | L153: PAGADO | M153: 45750
A154: OSCAR A CAZARES HERRERA | B154: PLAN DE PAGOS DIFERIDOS | C154: AMEX VARIOS | D154: =IFERROR(VLOOKUP($C154,CUENTAS[],2,0),"") -> GASTOS VARIOS | E154: =IFERROR(VLOOKUP($C154,CUENTAS[],3,0),"") -> MDE2025-003L | F154: 9242.52 | G154: 0 | H154: 9242.52 | I154: =IFERROR(IF(F154+G154<>H154,"REVISAR","CORRECTO"),"") -> CORRECTO | J154: AMEX | K154: MONTO QUE SE PAGO A SALDO DIFERIDO | L154: PAGADO | M154: 45750
A155: YAEL ESTRADA QUEZADA | B155: COMPRA DE CAUTIN DE LAPIZ - 04MARZO25 | C155: POOL DE MATERIALES | D155: =IFERROR(VLOOKUP($C155,CUENTAS[],2,0),"") -> MATERIALES | E155: =IFERROR(VLOOKUP($C155,CUENTAS[],3,0),"") -> MDE2025-004 | F155: 129.31 | G155: 20.69 | H155: 150 | I155: =IFERROR(IF(F155+G155<>H155,"REVISAR","CORRECTO"),"") -> CORRECTO | J155: TOKA CONNECT | K155: VICTOR RUIZ | L155: PAGADO | M155: 45720 | N155: F2875
A156: DISTRIBUIDORA DE INSUMOS GRAFICOS DE TOLUCA | B156: COMPRA DE 5 PLACAS COLOR AZUL CON FELPA- 03MAR25 | C156: POOL DE MATERIALES | D156: =IFERROR(VLOOKUP($C156,CUENTAS[],2,0),"") -> MATERIALES | E156: =IFERROR(VLOOKUP($C156,CUENTAS[],3,0),"") -> MDE2025-004 | F156: 150 | G156: 0 | H156: 150 | I156: =IFERROR(IF(F156+G156<>H156,"REVISAR","CORRECTO"),"") -> CORRECTO | J156: TOKA CONNECT | K156: VICTOR RUIZ | L156: PAGADO | M156: 45719 | N156: NO. 24089
A157: TECNOLOGIA APLICADA INDUSTRIAL Y AUTOMOTRIZ SA DE CV | B157: COMPRA DE 10 CINTA DOS CARAS 2X25 MTS - 03MAR25 | C157: POOL DE MATERIALES | D157: =IFERROR(VLOOKUP($C157,CUENTAS[],2,0),"") -> MATERIALES | E157: =IFERROR(VLOOKUP($C157,CUENTAS[],3,0),"") -> MDE2025-004 | F157: 3068.97 | G157: 491.03 | H157: 3560 | I157: =IFERROR(IF(F157+G157<>H157,"REVISAR","CORRECTO"),"") -> CORRECTO | J157: TOKA CONNECT | K157: VICTOR RUIZ | L157: PAGADO | M157: 45719 | N157: F10433
A158: ANDRES PEÑA GONZALES (RUUPER) | B158: COMPRA DE CINTA PVC, CINTA DOBLE CARA, CUTTER 18 MM, ESTUCHE CON 1O CUCHILLAS, CINTA DE DUCTOS-03MAR25 | C158: POOL DE MATERIALES | D158: =IFERROR(VLOOKUP($C158,CUENTAS[],2,0),"") -> MATERIALES | E158: =IFERROR(VLOOKUP($C158,CUENTAS[],3,0),"") -> MDE2025-004 | F158: 1500.7 | G158: 240.11 | H158: 1740.81 | I158: =IFERROR(IF(F158+G158<>H158,"REVISAR","CORRECTO"),"") -> CORRECTO | J158: TOKA CONNECT | K158: VICTOR RUIZ | L158: PAGADO | M158: 45719 | N158: CA-19871
A159: YAEL ESTRADA QUEZADA | B159: COMPRA DE 8 GARRAFONES DE AGUA | C159: AGUA EMBOTELLADA | D159: =IFERROR(VLOOKUP($C159,CUENTAS[],2,0),"") -> GASTOS FIJOS | E159: =IFERROR(VLOOKUP($C159,CUENTAS[],3,0),"") -> MDE2025-002B | F159: 440 | G159: 0 | H159: 440 | I159: =IFERROR(IF(F159+G159<>H159,"REVISAR","CORRECTO"),"") -> CORRECTO | J159: TOKA CONNECT | K159: VICTOR RUIZ | L159: PAGADO | M159: 45720 | N159: NOTA 0586
A160: YAEL ESTRADA QUEZADA | B160: COMPRA DE 20COSTALES | C160: INSUMOS PARA MANTENIMIENTO BODEGA | D160: =IFERROR(VLOOKUP($C160,CUENTAS[],2,0),"") -> MANTENIMIENTO | E160: =IFERROR(VLOOKUP($C160,CUENTAS[],3,0),"") -> MDE2025-009A | F160: 200 | G160: 0 | H160: 200 | I160: =IFERROR(IF(F160+G160<>H160,"REVISAR","CORRECTO"),"") -> CORRECTO | J160: TOKA CONNECT | K160: VICTOR RUIZ | L160: PAGADO | M160: 45720 | N160: NOTA 0586
...

Sheet ABR25
A1: PROVEEDOR | B1: CONCEPTO | C1: SUBCUENTA | D1: CUENTA | E1: CLAVE | F1: SUBTOTAL | G1: IVA | H1: TOTAL | I1: VALIDACIÓN | J1: FORMA DE PAGO | K1: EJECUTIVO | L1: STATUS | M1: FECHA | N1: FACTURA
A2: CARLOS FERNANDO BECERRIL VILCHIS | B2: MTTO RANGER: 20% - AJUSTE DE MOTOR, REP DE VENTILADOR Y AFINACION COMPLETA - PAGO 3 | C2: SERVICIO Y MANTENIMIENTO DE UNIDADES DE TRANSPORTE | D2: =IFERROR(VLOOKUP($C2,CUENTAS[],2,0),"") -> LOGÍSTICA | E2: =IFERROR(VLOOKUP($C2,CUENTAS[],3,0),"") -> MDE2025-006A | F2: 19613.2 | G2: 3138.11 | H2: 22751.31 | I2: =IFERROR(IF(F2+G2<>H2,"REVISAR","CORRECTO"),"") -> CORRECTO | J2: KUSPIT SP´S | K2: FERNANDO | L2: PAGADO | M2: 45749 | N2: FAC03962
A3: NORA LIZ PINEDA PEREZ | B3: COMPRA DE SOPORTE SACROLUMBAR CON TERCER CINTURON CH, M, G - 07MAR25 - CREDITO | C3: POOL DE MATERIALES | D3: =IFERROR(VLOOKUP($C3,CUENTAS[],2,0),"") -> MATERIALES | E3: =IFERROR(VLOOKUP($C3,CUENTAS[],3,0),"") -> MDE2025-004 | F3: 1846.6 | G3: 295.46 | H3: 2142.06 | I3: =IFERROR(IF(F3+G3<>H3,"REVISAR","CORRECTO"),"") -> CORRECTO | J3: KUSPIT SP´S | K3: PRISCILA | L3: PAGADO | M3: 45749 | N3: A3602
A4: DEKOMADERA SA DE CV | B4: COMPRA DE CERRADURA, BROCHA MAMEY, PUNTA IMANTADA, PUNTA PHILLIPS - 3MAR25 DA218030 , JALADERA SOARMA, SEGUETA BOSH, PUNTA PHILLIPS- 5MAR25 DA218408 | C4: POOL DE MATERIALES | D4: =IFERROR(VLOOKUP($C4,CUENTAS[],2,0),"") -> MATERIALES | E4: =IFERROR(VLOOKUP($C4,CUENTAS[],3,0),"") -> MDE2025-004 | F4: 3328.67 | G4: 532.59 | H4: 3861.26 | I4: =IFERROR(IF(F4+G4<>H4,"REVISAR","CORRECTO"),"") -> CORRECTO | J4: KUSPIT SP´S | K4: PRISCILA | L4: PAGADO | M4: 45749 | N4: TK DA218408 Y DA218030- FAC DA32054
A5: VICTOR MANUEL RUIZ ZARATE | B5: REEMBOLSO DE COMPRAS MATERIAL OFICINAS NUEVAS - 28MAR25 | C5: EDIFICIOS | D5: =IFERROR(VLOOKUP($C5,CUENTAS[],2,0),"") -> ACTIVOS FIJOS | E5: =IFERROR(VLOOKUP($C5,CUENTAS[],3,0),"") -> MDE2025-007I | F5: 8907.59 | G5: 1426.81 | H5: 10334.4 | I5: =IFERROR(IF(F5+G5<>H5,"REVISAR","CORRECTO"),"") -> CORRECTO | J5: KUSPIT SP´S | K5: PRISCILA | L5: PAGADO | M5: 45749 | N5: XFA78513
A6: VICTOR MANUEL RUIZ ZARATE | B6: REEMBOLSO DE COMPRAS MATERIALES EMPAQUE LONA, KIT BASICO DE REFACCIONES, PISTOLA KRAYAMA, RESPIRADOR MEDIA CARA SIN FILTRO, FILTROS 3M NIOSH, PIJA FIJADORA, TUERCA PARA MADERA, TORNILLO, PUNTA PARA TALADRO, RONDANA | C6: POOL DE MATERIALES | D6: =IFERROR(VLOOKUP($C6,CUENTAS[],2,0),"") -> MATERIALES | E6: =IFERROR(VLOOKUP($C6,CUENTAS[],3,0),"") -> MDE2025-004 | F6: 6299.56 | G6: 1007.93 | H6: 7307.49 | I6: =IFERROR(IF(F6+G6<>H6,"REVISAR","CORRECTO"),"") -> CORRECTO | J6: KUSPIT SP´S | K6: PRISCILA | L6: PAGADO | M6: 45749 | N6: VARIAS
A7: ECONOCOMEX SA DE CV | B7: LACAS AUTOMOTIVAS CAFE | C7: POOL DE MATERIALES | D7: =IFERROR(VLOOKUP($C7,CUENTAS[],2,0),"") -> MATERIALES | E7: =IFERROR(VLOOKUP($C7,CUENTAS[],3,0),"") -> MDE2025-004 | F7: 7429.48 | G7: 1188.72 | H7: 8618.2 | I7: =IFERROR(IF(F7+G7<>H7,"REVISAR","CORRECTO"),"") -> CORRECTO | J7: KUSPIT SP´S | K7: ARIADNA | L7: PAGADO | M7: 45749 | N7: COT-006
A8: MARIA NANCY QUEZADA HERNANDEZ | B8: /COMPRA DE 30 BULTOS DE MORTERO, 10 BULTOS DE CEMENTO - 28MAR25 | C8: INSUMOS PARA MANTENIMIENTO BODEGA | D8: =IFERROR(VLOOKUP($C8,CUENTAS[],2,0),"") -> MANTENIMIENTO | E8: =IFERROR(VLOOKUP($C8,CUENTAS[],3,0),"") -> MDE2025-009A | F8: 6340 | G8: 0 | H8: 6340 | I8: =IFERROR(IF(F8+G8<>H8,"REVISAR","CORRECTO"),"") -> CORRECTO | J8: KUSPIT SP´S | K8: NAYELI | L8: PAGADO | M8: 45750 | N8: NV13
A9: DISTRIBUIDOR PAPELERO DE TOLUCA SA DE CV | B9: MOUSE,REGISTRADORES,REGLAS,ENGRAPADORAS | C9: PAPELERÍA E INSUMOS DE LIMPIEZA | D9: =IFERROR(VLOOKUP($C9,CUENTAS[],2,0),"") -> GASTOS VARIOS | E9: =IFERROR(VLOOKUP($C9,CUENTAS[],3,0),"") -> MDE2025-003A | F9: 1884.06 | G9: 301.44 | H9: 2185.5 | I9: =IFERROR(IF(F9+G9<>H9,"REVISAR","CORRECTO"),"") -> CORRECTO | J9: KUSPIT SP´S | K9: ARIADNA | L9: PAGADO | M9: 45750 | N9: COT-178653
A10: BRANDON YAIR AGUILAR DIAZ | B10: 4 VIAJES DE RECOLECCION DE BASURA - ABRIL25 | C10: SERVICIO DE RECOLECCION DE BASURA Y DESECHOS INDUSTRIALES | D10: =IFERROR(VLOOKUP($C10,CUENTAS[],2,0),"") -> GASTOS FIJOS | E10: =IFERROR(VLOOKUP($C10,CUENTAS[],3,0),"") -> MDE2025-002A | F10: 2800 | G10: 0 | H10: 2800 | I10: =IFERROR(IF(F10+G10<>H10,"REVISAR","CORRECTO"),"") -> CORRECTO | J10: KUSPIT SP´S | K10: PRISCILA | L10: PAGADO | M10: 45750 | N10: N/A
A11: JOSE E ZEPEDA BURGOS | B11: REEMBOLSO COMPRA DE MATERIALES VARIOS- VICTOR RUIZ 02/04/25 | C11: MATERIALES BODEGA | D11: =IFERROR(VLOOKUP($C11,CUENTAS[],2,0),"") -> MATERIALES | E11: =IFERROR(VLOOKUP($C11,CUENTAS[],3,0),"") -> MDE2025-004A | F11: 3200 | G11: 0 | H11: 3200 | I11: =IFERROR(IF(F11+G11<>H11,"REVISAR","CORRECTO"),"") -> CORRECTO | J11: KUSPIT SP´S | K11: NAYELI | L11: PAGADO | M11: 45750 | N11: COMPROBANTE
A12: JOSE E ZEPEDA BURGOS | B12: REEMBOLSO COMPRA DE MATERIALES VARIOS- VICTOR RUIZ 02/04/25 | C12: MATERIALES BODEGA | D12: =IFERROR(VLOOKUP($C12,CUENTAS[],2,0),"") -> MATERIALES | E12: =IFERROR(VLOOKUP($C12,CUENTAS[],3,0),"") -> MDE2025-004A | F12: 2400 | G12: 0 | H12: 2400 | I12: =IFERROR(IF(F12+G12<>H12,"REVISAR","CORRECTO"),"") -> CORRECTO | J12: KUSPIT SP´S | K12: NAYELI | L12: PAGADO | M12: 45750 | N12: COMPROBANTE
A13: JOSE E ZEPEDA BURGOS | B13: REEMBOLSO COMPRA DE MATERIALES VARIOS- VICTOR RUIZ 02/04/25 | C13: MATERIALES BODEGA | D13: =IFERROR(VLOOKUP($C13,CUENTAS[],2,0),"") -> MATERIALES | E13: =IFERROR(VLOOKUP($C13,CUENTAS[],3,0),"") -> MDE2025-004A | F13: 1700 | G13: 0 | H13: 1700 | I13: =IFERROR(IF(F13+G13<>H13,"REVISAR","CORRECTO"),"") -> CORRECTO | J13: KUSPIT SP´S | K13: NAYELI | L13: PAGADO | M13: 45750 | N13: COMPROBANTE
... A24: FERNANDO BECERRIL | B24: REEMBOLSO PAGO DE TALACHAS MANTENIMIENTO - 03ABR25 | C24: SERVICIO Y MANTENIMIENTO DE UNIDADES DE TRANSPORTE | D24: =IFERROR(VLOOKUP($C24,CUENTAS[],2,0),"") -> LOGÍSTICA | E24: =IFERROR(VLOOKUP($C24,CUENTAS[],3,0),"") -> MDE2025-006A | F24: 400 | G24: 0 | H24: 400 | I24: =IFERROR(IF(F24+G24<>H24,"REVISAR","CORRECTO"),"") -> CORRECTO | J24: KUSPIT SP´S | K24: FERNANDO | L24: PAGADO | M24: 45755 | N24: COMPROBANTE
A25: VIDAL ESTRADA | B25: PAGO RENTA DE CASA SUAREZ ABRIL2025 | C25: RENTAS | D25: =IFERROR(VLOOKUP($C25,CUENTAS[],2,0),"") -> GASTOS FIJOS | E25: =IFERROR(VLOOKUP($C25,CUENTAS[],3,0),"") -> MDE2025-002D | F25: 7327.59 | G25: 1172.41 | H25: 8500 | I25: =IFERROR(IF(F25+G25<>H25,"REVISAR","CORRECTO"),"") -> CORRECTO | J25: KUSPIT SP´S | K25: NAYELI | L25: PAGADO | M25: 45755 | N25: 13550
A26: MARIANA GONZALEZ VARA | B26: PAGO MENSUAL SOCIAL MEDIA MES DE ABRIL 2025 | C26: SOCIAL MEDIA Y WEB MASTER | D26: =IFERROR(VLOOKUP($C26,CUENTAS[],2,0),"") -> GASTOS FIJOS | E26: =IFERROR(VLOOKUP($C26,CUENTAS[],3,0),"") -> MDE2025-002I | F26: 8000 | G26: 0 | H26: 8000 | I26: =IFERROR(IF(F26+G26<>H26,"REVISAR","CORRECTO"),"") -> CORRECTO | J26: KUSPIT SP´S | K26: NAYELI | L26: PAGADO | M26: 45755 | N26: N/A
A27: JOSE E ZEPEDA BURGOS | B27: REEMBOLSO POR COMPRA DE PAPELERIA - 03ABR25 | C27: REGALOS Y PATROCINIOS CLIENTES | D27: =IFERROR(VLOOKUP($C27,CUENTAS[],2,0),"") -> EVENTOS INTERNOS | E27: =IFERROR(VLOOKUP($C27,CUENTAS[],3,0),"") -> MDE2025-008B | F27: 288 | G27: 0 | H27: 288 | I27: =IFERROR(IF(F27+G27<>H27,"REVISAR","CORRECTO"),"") -> CORRECTO | J27: KUSPIT SP´S | K27: NAYELI | L27: PAGADO | M27: 45755 | N27: COMPROBANTE
A28: Toka internacional S.A.P.I. de C.V. | B28: 2463196 | C28: COMISIONES TOKA | D28: =IFERROR(VLOOKUP($C28,CUENTAS[],2,0),"") -> TOKA | E28: =IFERROR(VLOOKUP($C28,CUENTAS[],3,0),"") -> TOK2025-001C | F28: 500 | G28: 80 | H28: 580 | I28: =IFERROR(IF(F28+G28<>H28,"REVISAR","CORRECTO"),"") -> CORRECTO | J28: KUSPIT SP´S | K28: NAYELI | L28: PAGADO | M28: 45750 | N28: PF837393
A29: Toka internacional S.A.P.I. de C.V. | B29: 2471773 | C29: COMISIONES TOKA | D29: =IFERROR(VLOOKUP($C29,CUENTAS[],2,0),"") -> TOKA | E29: =IFERROR(VLOOKUP($C29,CUENTAS[],3,0),"") -> TOK2025-001C | F29: 500 | G29: 80 | H29: 580 | I29: =IFERROR(IF(F29+G29<>H29,"REVISAR","CORRECTO"),"") -> CORRECTO | J29: KUSPIT SP´S | K29: NAYELI | L29: PAGADO | M29: 45756 | N29: 42025
A30: DEKOMADERA SA DE CV | B30: COMPRA BROCAS, BISAGRA DA219959 / CUBRECANTO Y BROCAS DA219439 | C30: POOL DE MATERIALES | D30: =IFERROR(VLOOKUP($C30,CUENTAS[],2,0),"") -> MATERIALES | E30: =IFERROR(VLOOKUP($C30,CUENTAS[],3,0),"") -> MDE2025-004 | F30: 4285.76 | G30: 685.72 | H30: 4971.48 | I30: =IFERROR(IF(F30+G30<>H30,"REVISAR","CORRECTO"),"") -> CORRECTO | J30: KUSPIT SP´S | K30: NAYELI | L30: PAGADO | M30: 45757 | N30: FAC-DA31969-TICKETS
A31: VICTOR MANUEL RUIZ ZARATE | B31: REEMBOLSO POR COMPRA DE 2 CANDADOS HERMEX, 1 PINZA PUNTA - 07ABR25 | C31: POOL DE MATERIALES | D31: =IFERROR(VLOOKUP($C31,CUENTAS[],2,0),"") -> MATERIALES | E31: =IFERROR(VLOOKUP($C31,CUENTAS[],3,0),"") -> MDE2025-004 | F31: 379.31 | G31: 60.69 | H31: 440 | I31: =IFERROR(IF(F31+G31<>H31,"REVISAR","CORRECTO"),"") -> CORRECTO | J31: KUSPIT SP´S | K31: PRISCILA | L31: PAGADO | M31: 45757 | N31: FAC 2945
A32: JOSE E ZEPEDA BURGOS | B32: REEMBOLSO COMPRA DE FORMAICA - 08ABR25 ANDREY NUNEZ | C32: EDIFICIOS | D32: =IFERROR(VLOOKUP($C32,CUENTAS[],2,0),"") -> ACTIVOS FIJOS | E32: =IFERROR(VLOOKUP($C32,CUENTAS[],3,0),"") -> MDE2025-007I | F32: 9181 | G32: 0 | H32: 9181 | I32: =IFERROR(IF(F32+G32<>H32,"REVISAR","CORRECTO"),"") -> CORRECTO | J32: KUSPIT SP´S | K32: NAYELI | L32: PAGADO | M32: 45757 | N32: COMPROBANTE
A33: EVODIO DE JESUS GOMEZ | B33: PAGO MANO DE OBRA - CONSTRUCCION DE OFICINAS NUEVAS | C33: EDIFICIOS | D33: =IFERROR(VLOOKUP($C33,CUENTAS[],2,0),"") -> ACTIVOS FIJOS | E33: =IFERROR(VLOOKUP($C33,CUENTAS[],3,0),"") -> MDE2025-007I | F33: 3500 | G33: 0 | H33: 3500 | I33: =IFERROR(IF(F33+G33<>H33,"REVISAR","CORRECTO"),"") -> CORRECTO | J33: KUSPIT SP´S | K33: NAYELI | L33: PAGADO | M33: 45758 | N33: N/A
A34: TIRSO DE JESUS DE LA CRUZ | B34: PAGO MANO DE OBRA - CONSTRUCCION DE OFICINAS NUEVAS | C34: EDIFICIOS | D34: =IFERROR(VLOOKUP($C34,CUENTAS[],2,0),"") -> ACTIVOS FIJOS | E34: =IFERROR(VLOOKUP($C34,CUENTAS[],3,0),"") -> MDE2025-007I | F34: 2773.34 | G34: 0 | H34: 2773.34 | I34: =IFERROR(IF(F34+G34<>H34,"REVISAR","CORRECTO"),"") -> CORRECTO | J34: KUSPIT SP´S | K34: NAYELI | L34: PAGADO | M34: 45758 | N34: N/A
A35: PAULA OLIVIA MOLINA HERNANDEZ | B35: SOPORTE TECNICO 01ABRIL2025 | C35: DISEÑADORES BODEGA | D35: =IFERROR(VLOOKUP($C35,CUENTAS[],2,0),"") -> DISEÑOS | E35: =IFERROR(VLOOKUP($C35,CUENTAS[],3,0),"") -> MDE2025-001 | F35: 42393.37 | G35: 6868.8 | H35: 49262.17 | I35: =IFERROR(IF(F35+G35<>H35,"REVISAR","CORRECTO"),"") -> CORRECTO | J35: KUSPIT SP´S | K35: NAYELI | L35: PAGADO | M35: 45762 | N35: FAC 511B5
A36: 365 INTELIGENCIA EN SEGURIDAD PRIVADA | B36: SERVICIO DE VIGILANCIA DEL 1 AL 15 ABRIL25 | C36: VIGILANCIA | D36: =IFERROR(VLOOKUP($C36,CUENTAS[],2,0),"") -> GASTOS FIJOS | E36: =IFERROR(VLOOKUP($C36,CUENTAS[],3,0),"") -> MDE2025-002K | F36: 15525 | G36: 2484 | H36: 18009 | I36: =IFERROR(IF(F36+G36<>H36,"REVISAR","CORRECTO"),"") -> CORRECTO | J36: KUSPIT SP´S | K36: FERNANDO | L36: PAGADO | M36: 45762 | N36: F624
A37: ERIKA IDALID SALAZAR RODRIGUEZ | B37: PISO LAMINADO CHOCOLATE 17 MM | C37: POOL DE MATERIALES | D37: =IFERROR(VLOOKUP($C37,CUENTAS[],2,0),"") -> MATERIALES | E37: =IFERROR(VLOOKUP($C37,CUENTAS[],3,0),"") -> MDE2025-004 | F37: 7426 | G37: 0 | H37: 7426 | I37: =IFERROR(IF(F37+G37<>H37,"REVISAR","CORRECTO"),"") -> CORRECTO | J37: KUSPIT SP´S | K37: PRISCILA | L37: PAGADO | M37: 45762 | N37: COT-008
A38: ECONOCOMEX SA DE CV | B38: 11,000 , BARNIZ BRILLANTE 1 LITR0 | C38: POOL DE MATERIALES | D38: =IFERROR(VLOOKUP($C38,CUENTAS[],2,0),"") -> MATERIALES | E38: =IFERROR(VLOOKUP($C38,CUENTAS[],3,0),"") -> MDE2025-004 | F38: 1432.2 | G38: 0 | H38: 1432.2 | I38: =IFERROR(IF(F38+G38<>H38,"REVISAR","CORRECTO"),"") -> CORRECTO | J38: KUSPIT SP´S | K38: ARIADNA | L38: PAGADO | M38: 45762 | N38: COT009
A39: ECONOCOMEX SA DE CV | B39: LACAS AUTOMOTIVA AZUL VERDE FIUSHA | C39: POOL DE MATERIALES | D39: =IFERROR(VLOOKUP($C39,CUENTAS[],2,0),"") -> MATERIALES | E39: =IFERROR(VLOOKUP($C39,CUENTAS[],3,0),"") -> MDE2025-004 | F39: 1846 | G39: 0 | H39: 1846 | I39: =IFERROR(IF(F39+G39<>H39,"REVISAR","CORRECTO"),"") -> CORRECTO | J39: KUSPIT SP´S | K39: ARIADNA | L39: PAGADO | M39: 45762 | N39: COT-011
A40: CARLOS FERNANDO BECERRIL VILCHIS | B40: 20% MTT CLUTCH, RECTIFICADO DE VOLANTE, AFINACION, FRENOS, ESCAPE INTERNATIONAL BCO - PAGO 3 | C40: SERVICIO Y MANTENIMIENTO DE UNIDADES DE TRANSPORTE | D40: =IFERROR(VLOOKUP($C40,CUENTAS[],2,0),"") -> LOGÍSTICA | E40: =IFERROR(VLOOKUP($C40,CUENTAS[],3,0),"") -> MDE2025-006A | F40: 13893.32 | G40: 0 | H40: 13893.32 | I40: =IFERROR(IF(F40+G40<>H40,"REVISAR","CORRECTO"),"") -> CORRECTO | J40: KUSPIT SP´S | K40: NAYELI | L40: PAGADO | M40: 45762 | N40: COT04903
A41: FERNANDO BECERRIL | B41: PERMISO DE CIRCULACION ABRIL Y MAYO POER | C41: VERIFICACIONES Y TENENCIAS | D41: =IFERROR(VLOOKUP($C41,CUENTAS[],2,0),"") -> LOGÍSTICA | E41: =IFERROR(VLOOKUP($C41,CUENTAS[],3,0),"") -> MDE2025-006B | F41: 150 | G41: 0 | H41: 150 | I41: =IFERROR(IF(F41+G41<>H41,"REVISAR","CORRECTO"),"") -> CORRECTO | J41: KUSPIT SP´S | K41: FERNANDO | L41: PAGADO | M41: 45757 | N41: COMPROBANTE
... A75: PABELLON INGENIERIA DEL COLOR Y SUMINISTROS | B75: COMPRA DE PASTA AUTOMITVA STOCK MATERIALES | C75: POOL DE MATERIALES | D75: =IFERROR(VLOOKUP($C75,CUENTAS[],2,0),"") -> MATERIALES | E75: =IFERROR(VLOOKUP($C75,CUENTAS[],3,0),"") -> MDE2025-004 | F75: 5136.3 | G75: 0 | H75: 5136.3 | I75: =IFERROR(IF(F75+G75<>H75,"REVISAR","CORRECTO"),"") -> CORRECTO | J75: KUSPIT SP´S | K75: ARIADNA | L75: PAGADO | M75: 45771 | N75: CPT-3648
A76: Toka internacional S.A.P.I. de C.V. | B76: 2484749 | C76: COMISIONES TOKA | D76: =IFERROR(VLOOKUP($C76,CUENTAS[],2,0),"") -> TOKA | E76: =IFERROR(VLOOKUP($C76,CUENTAS[],3,0),"") -> TOK2025-001C | F76: 300 | G76: 48 | H76: 348 | I76: =IFERROR(IF(F76+G76<>H76,"REVISAR","CORRECTO"),"") -> CORRECTO | J76: KUSPIT SP´S | K76: NAYELI | L76: PAGADO | M76: 45770 | N76: PF1312322
A77: JOSE E ZEPEDA BURGOS | B77: REEMBOLSO COMPRA DE MATERIALES VICTOR RUIZ - 23ABRIL25 | C77: POOL DE MATERIALES | D77: =IFERROR(VLOOKUP($C77,CUENTAS[],2,0),"") -> MATERIALES | E77: =IFERROR(VLOOKUP($C77,CUENTAS[],3,0),"") -> MDE2025-004 | F77: 2000 | G77: 0 | H77: 2000 | I77: =IFERROR(IF(F77+G77<>H77,"REVISAR","CORRECTO"),"") -> CORRECTO | J77: KUSPIT SP´S | K77: NAYELI | L77: PAGADO | M77: 45772 | N77: COMPROBANTE
A78: JOSE E ZEPEDA BURGOS | B78: REEMBOLSO COMPRA DE REPUESTOS PARA PISTOLAS DE PINTURA SAYER - 23ABR25 VICTOR RUIZ | C78: POOL DE MATERIALES | D78: =IFERROR(VLOOKUP($C78,CUENTAS[],2,0),"") -> MATERIALES | E78: =IFERROR(VLOOKUP($C78,CUENTAS[],3,0),"") -> MDE2025-004 | F78: 2985 | G78: 0 | H78: 2985 | I78: =IFERROR(IF(F78+G78<>H78,"REVISAR","CORRECTO"),"") -> CORRECTO | J78: KUSPIT SP´S | K78: NAYELI | L78: PAGADO | M78: 45772 | N78: COMPROBANTE
A79: JOSE E ZEPEDA BURGOS | B79: REEMBOLSO DE 2 PTR DE 1X1 CAL 14 - VICTOR RUIZ 24/04/25 | C79: POOL DE MATERIALES | D79: =IFERROR(VLOOKUP($C79,CUENTAS[],2,0),"") -> MATERIALES | E79: =IFERROR(VLOOKUP($C79,CUENTAS[],3,0),"") -> MDE2025-004 | F79: 441.1 | G79: 0 | H79: 441.1 | I79: =IFERROR(IF(F79+G79<>H79,"REVISAR","CORRECTO"),"") -> CORRECTO | J79: KUSPIT SP´S | K79: NAYELI | L79: PAGADO | M79: 45772 | N79: COMPROBANTE
A80: DISTRIBUIDORA SAGARO SA DE CV | B80: 5 ROLLOS DE VINIL BLANCO MATE RECORTE | C80: POOL DE MATERIALES | D80: =IFERROR(VLOOKUP($C80,CUENTAS[],2,0),"") -> MATERIALES | E80: =IFERROR(VLOOKUP($C80,CUENTAS[],3,0),"") -> MDE2025-004 | F80: 20997.44 | G80: 3359.59 | H80: 24357.03 | I80: =IFERROR(IF(F80+G80<>H80,"REVISAR","CORRECTO"),"") -> CORRECTO | J80: KUSPIT SP´S | K80: ARIADNA | L80: PAGADO | M80: 45772 | N80: SUR25079
A81: EVODIO DE JESUS GOMEZ | B81: PAGO MANO DE OBRA - CONSTRUCCION DE OFICINAS | C81: MANTENIMIENTO Y REPARACIÓN VARIOS | D81: =IFERROR(VLOOKUP($C81,CUENTAS[],2,0),"") -> MANTENIMIENTO | E81: =IFERROR(VLOOKUP($C81,CUENTAS[],3,0),"") -> MDE2025-009B | F81: 3500 | G81: 0 | H81: 3500 | I81: =IFERROR(IF(F81+G81<>H81,"REVISAR","CORRECTO"),"") -> CORRECTO | J81: KUSPIT SP´S | K81: NAYELI | L81: PAGADO | M81: 45772 | N81: N/A
A82: TIRSO DE JESUS DE LA CRUZ | B82: PAGO MANO DE OBRA - CONSTRUCCION DE OFICINAS | C82: MANTENIMIENTO Y REPARACIÓN VARIOS | D82: =IFERROR(VLOOKUP($C82,CUENTAS[],2,0),"") -> MANTENIMIENTO | E82: =IFERROR(VLOOKUP($C82,CUENTAS[],3,0),"") -> MDE2025-009B | F82: 2346.68 | G82: 0 | H82: 2346.68 | I82: =IFERROR(IF(F82+G82<>H82,"REVISAR","CORRECTO"),"") -> CORRECTO | J82: KUSPIT SP´S | K82: NAYELI | L82: PAGADO | M82: 45772 | N82: N/A
A83: BENITO AVILA DIAZ | B83: PAGO DE RACK PARA CAMIONETAS - LOGISTICA | C83: SERVICIO Y MANTENIMIENTO DE UNIDADES DE TRANSPORTE | D83: =IFERROR(VLOOKUP($C83,CUENTAS[],2,0),"") -> LOGÍSTICA | E83: =IFERROR(VLOOKUP($C83,CUENTAS[],3,0),"") -> MDE2025-006A | F83: 5000 | G83: 0 | H83: 5000 | I83: =IFERROR(IF(F83+G83<>H83,"REVISAR","CORRECTO"),"") -> CORRECTO | J83: KUSPIT SP´S | K83: ENRIQUE | L83: PAGADO | M83: 45772 | N83: N/A
