Workbook

Sheet RESUMEN CIERRE INTERNO
A1: CIERRE INTERNO
E2: CLIENTE: | F2: =C13 -> DOTERRA
E3: CLAVE EVENTO | F3: DOT2025-003 | G3: =F3 -> DOT2025-003
E4: FECHAS DEL EVENTO: | F4: JULIO- DIC
E5: SEDE:
E6: CIUDAD:
E7: ASESOR TERRESTRE:
E8: VENDEDOR DE GRUPOS:
A11: INGRESOS
A12: Status | B12: No. Factura | C12: Proveedor / Razón Social | D12: Concepto | E12: Otra Moneda | F12: Sub-Total | G12: I.V.A | H12: Monto a Pagar
A13: PAGADO | B13: 7981 | C13: DOTERRA | D13: CONVENCIÓN DOTERRA 2025 ANTICIPO | F13: 1671642.5 | G13: =F13*16% -> 267462.8 | H13: =SUM(F13:G13) -> 1939105.3
A14: PAGADO | B14: 8070 | C14: DOTERRA | D14: CONVENCIÓN DOTERRA 2025 FINIQUITO | F14: =2052301.58/1.16 -> 1769225.5 | G14: =F14*16% -> 283076.08 | H14: =SUM(F14:G14) -> 2052301.6
A15: PAGADO | B15: 8069 | C15: DOTERRA | D15: CONVENCIÓN DOTERRA 2025 FEE | F15: =399149.69/1.16 -> 344094.56 | G15: =F15*16% -> 55055.13 | H15: =SUM(F15:G15) -> 399149.69
F16: 0 | G16: =F16*16% -> 0 | H16: =SUM(F16:G16) -> 0
A18: TOTAL INGRESOS | F18: =SUM($F$13:$F$16) -> 3784962.6 | G18: =SUM($G$13:$G$16) -> 605594.01 | H18: =SUM($H$13:$H$16) -> 4390556.6
A20: RESUMEN EGRESOS
A21: Concepto | B21: Sub-Total | C21: I.V.A | D21: Total | E21: Porcentaje
A22: ='SP´S'!A5 -> SP´S | B22: ='SP´S'!F138 -> 826051.73 | C22: ='SP´S'!G138 -> 33622.658 | D22: ='SP´S'!H138 -> 859674.39 | E22: =D22/$B$32 -> 0.2271289
A23: ='COMBUSTIBLE PEAJE'!A5 -> COMBUSTIBLE / PEAJE | B23: ='COMBUSTIBLE PEAJE'!F36 -> 26427.59 | C23: ='COMBUSTIBLE PEAJE'!G36 -> 3923.1908 | D23: ='COMBUSTIBLE PEAJE'!H36 -> 30350.781 | E23: =D23/$B$32 -> 0.0080187797
A24: =RH!A5 -> RH | B24: =RH!F31 -> 40552.09 | C24: =RH!G31 -> 0 | D24: =RH!H31 -> 40552.09 | E24: =D24/$B$32 -> 0.010714
A25: =MATERIALES!A5 -> MATERIALES | B25: =MATERIALES!H175 -> 411968.91 | C25: =MATERIALES!I175 -> 65915.026 | D25: =MATERIALES!J175 -> 477883.94 | E25: =D25/$B$32 -> 0.12625856
A26: =PROVISIONES!A7 -> PROVISIONES | B26: =PROVISIONES!C53 -> 1500970.6 | C26: =PROVISIONES!D53 -> 0 | D26: =PROVISIONES!E53 -> 1500970.6 | E26: =D26/$B$32 -> 0.39656156
A28: TOTAL EGRESOS | B28: =SUM($B$22:$B$26) -> 2805971 | C28: =SUM($C$22:$C$26) -> 103460.87 | D28: =SUM($D$22:$D$26) -> 2909431.8 | E28: =SUM($E$22:$E$26) -> 0.7686818
A30: RESUMEN UTILIDAD
A31: CONCEPTO | B31: MONTO | C31: PORCENTAJE
A32: SUMA DE INGRESOS | B32: =F18 -> 3784962.6 | C32: =SUM(C33:C35) -> 1
A33: SUMA DE EGRESOS | B33: =B28 -> 2805971 | C33: =B33/$B$32 -> 0.74134708
A35: UTILIDAD | B35: =B32-(SUM(B33)) -> 978991.6 | C35: =B35/B32 -> 0.25865292
A612: PAGADO
A613: PENDIENTE

Sheet SP´S
A5: SP´S
A6: Status | B6: Método de Pago | C6: No. Factura | D6: Proveedor / Razón Social | E6: Concepto | F6: Sub-Total | G6: I.V.A | H6: Monto a Pagar | I6: Fecha de Pago | J6: SP S | K6: FLUJO
A7: PAGADO | B7: TRANSFERENCIA | C7: TICKET | D7: JESSICA GARCIA GONZALEZ | E7: ESTACIONAMIENTO CITIBANAMEX SCOUTING DOTERRA | F7: 160 | G7: 0 | H7: =SUM(F7:G7) -> 160 | I7: 45839 | J7: SI | K7: SI
A8: PAGADO | B8: TRANSFERENCIA | C8: N/A | D8: ALBERTO SUÁREZ JIMENEZ | E8: MO TRABAJOS DOTERRA | F8: 20000 | G8: 0 | H8: =F8+G8 -> 20000 | I8: 45919 | J8: SI | K8: SI
A9: PAGADO | B9: TRANSFERENCIA | C9: N/A | D9: GUILLERMO SUAREZ JIMENEZ | E9: MO TRABAJOS DOTERRA | F9: 20000 | G9: 0 | H9: =F9+G9 -> 20000 | I9: 45919 | J9: SI | K9: SI
A10: PAGADO | B10: TRANSFERENCIA | C10: N/A | D10: OSCAR SUAREZ JIMENEZ | E10: MO TRABAJOS DOTERRA | F10: 20000 | G10: 0 | H10: =F10+G10 -> 20000 | I10: 45919 | J10: SI | K10: SI
A11: PAGADO | B11: SANTANDER | C11: N/A | D11: ALEJANDRO SUÁREZ JIMENEZ | E11: MO TRABAJOS DOTERRA | F11: 20000 | G11: 0 | H11: =F11+G11 -> 20000 | I11: 45922 | J11: SI | K11: STD
A12: PAGADO | B12: TRANSFERENCIA | C12: 4EC7CCE1 | D12: JESUS SANCHEZ GALICIA | E12: 50% ANTICIPO VOLUMETRICO EN FIBRA DE VIDRIO 60X36CM CONVENCION DOTERRA | F12: 13450 | G12: =F12*16% -> 2152 | H12: =SUM(F12:G12) -> 15602 | I12: 45925 | J12: SI | K12: SI
A13: PAGADO | B13: AMEX | C13: COMPROBANTE | D13: JOSE E ZEPEDA BURGOS | E13: AMAZON MX MARKETPLACE*A MEXICO CITY08 oct 2025 | F13: 436.05 | G13: 0 | H13: =SUM(F13:G13) -> 436.05 | I13: 45957 | L13: TB EZ SANTANDER-AMEX $250,135.11 PROYECTOS VARIOS
A14: PAGADO | B14: AMEX | C14: COMPROBANTE | D14: JOSE E ZEPEDA BURGOS | E14: AMAZON MX MARKETPLACE*A MEXICO CITY | F14: 1476 | G14: 0 | H14: =SUM(F14:G14) -> 1476 | I14: 45957 | L14: TB EZ SANTANDER-AMEX $250,135.11 PROYECTOS VARIOS
A15: PAGADO | B15: SANTANDER | C15: N/A | D15: JUANA GARAY MONROY | E15: ANTICIPO HECHURA DE CORTINAS | F15: 2750 | G15: 0 | H15: =SUM(F15:G15) -> 2750 | I15: 45945 | J15: SI
A16: PAGADO | B16: SANTANDER | C16: PENDIENTE | D16: ERICK AXEL ESPINOZA HERNANDEZ | E16: ANTICIPO PERFORMANCE | F16: 25000 | G16: 0 | H16: =SUM(F16:G16) -> 25000 | I16: 45945 | J16: SI
A17: PAGADO | B17: TRANSFERENCIA | C17: COMPROBANTE | D17: MARIO GERARDO MORENO RODRIGUEZ | E17: RENDER DOTERRA CONVENCION LATAM 2025 | F17: 45000 | G17: 0 | H17: =SUM(F17:G17) -> 45000 | I17: 45874 | J17: SI | K17: SI
A18: PAGADO | B18: TRANSFERENCIA | C18: F0778D64 | D18: INNOVACION VERDE | E18: PAGO PLANTAS CONVENCION DOTERRA | F18: 5820 | G18: 0 | H18: =SUM(F18:G18) -> 5820 | I18: 45946 | J18: SI
A19: PAGADO | B19: TRANSFERENCIA | C19: F1B27410 | D19: IVAN EDUARDO MORENO | E19: ANTICIPO DEL 50% DE IMPRESORAS CONVENCION DOTERRA | F19: 12639.95 | G19: 2296 | H19: =SUM(F19:G19) -> 14935.95 | I19: 45946 | J19: SI
A20: PAGADO | B20: TRANSFERENCIA | C20: COT WHATS | D20: RAUL ALEJANDRO LEZAMA | E20: ANTICIPO DEL 50% DE RADIOS PARA CLIENTE CONVECION DOTERRA | F20: 3870 | G20: 0 | H20: =SUM(F20:G20) -> 3870 | I20: 45946 | J20: SI
A21: PAGADO | B21: SANTANDER | C21: COT WHATS | D21: MARIA DE LOURDES PASTRANA PEREZ | E21: ANTICIPO DEL 50% CABINA DE FOTOS CONVENCION DOTERRA | F21: 2000 | G21: 0 | H21: =SUM(F21:G21) -> 2000 | I21: 45947 | J21: SI
A22: PAGADO | B22: SANTANDER | C22: COT KS000745 | D22: TIENDA MERCADAZO S.A DE C.V | E22: PAGO DE MAQUINA SMOOTHIE DOTERRA | F22: 22198 | G22: 0 | H22: =SUM(F22:G22) -> 22198 | I22: PROCESO | J22: SI
A23: PAGADO | B23: AMEX | C23: PENDIENTE | D23: JOSE E ZEPEDA BURGOS | E23: MERCADO LIBRE MEXICO/18 oct 2025 | F23: 14000 | G23: 0 | H23: =SUM(F23:G23) -> 14000 | I23: 45957 | L23: TB EZ SANTANDER-AMEX $250,135.11 PROYECTOS VARIOS
A24: PAGADO | B24: AMEX | C24: PENDIENTE | D24: JOSE E ZEPEDA BURGOS | E24: MERCADO LIBRE MEXICO/26 oct 2025 | F24: -14000 | G24: 0 | H24: =SUM(F24:G24) -> -14000 | I24: 45957 | L24: TB EZ SANTANDER-AMEX $250,135.11 PROYECTOS VARIOS
A25: PAGADO | B25: AMEX | C25: PENDIENTE | D25: JOSE E ZEPEDA BURGOS | E25: MERCADO LIBRE MEXICO/18 oct 2025 | F25: 21999 | G25: 0 | H25: =SUM(F25:G25) -> 21999 | I25: 45957 | L25: TB EZ SANTANDER-AMEX $250,135.11 PROYECTOS VARIOS
A26: PAGADO | B26: AMEX | C26: PENDIENTE | D26: JOSE E ZEPEDA BURGOS | E26: MERCADO LIBRE MEXICO/23 oct 2025 | F26: -21999 | G26: 0 | H26: =SUM(F26:G26) -> -21999 | I26: 45957 | L26: TB EZ SANTANDER-AMEX $250,135.11 PROYECTOS VARIOS
A27: PAGADO | B27: AMEX | C27: COMPROBANTE | D27: JOSE E ZEPEDA BURGOS | E27: AMAZON MX MARKETPLACE*A MEXICO CITY/17 oct 2025 | F27: 819.94 | G27: 0 | H27: =SUM(F27:G27) -> 819.94 | I27: 45957 | L27: TB EZ SANTANDER-AMEX $250,135.11 PROYECTOS VARIOS
A28: PAGADO | B28: TRANSFERENCIA | C28: COMPROBANTE | D28: CREATIVO RED CARPET ESTUDIO SA DE CV | E28: RENTA DE MOBILIARIO CONVENCION DOTERRA | F28: 25803 | G28: =F28*16% -> 4128.48 | H28: =SUM(F28:G28) -> 29931.48 | I28: 45951 | J28: SI
A29: PAGADO | B29: TRANSFERENCIA | C29: COMPROBANTE | D29: LINO GUTIERREZ LOPEZ | E29: PAGO CHOFER EXTERNO LINO Y SAID- MONTAJE DOTERRA 20OCT25 | F29: 2600 | G29: 0 | H29: =SUM(F29:G29) -> 2600 | I29: 45951 | J29: SI
A30: PAGADO | B30: TRANSFERENCIA | C30: COMPROBANTE | D30: EDGAR OCTAVIO ALVARADO | E30: PAGO 5 MANIOBRISTAS 20OCT25 - 500 C/U DOTERRA | F30: 2500 | G30: 0 | H30: =SUM(F30:G30) -> 2500 | I30: 45951 | J30: SI
A31: PAGADO | B31: SANTANDER | C31: COMPROBANTE | D31: ANGIE LIZEL PEREZ GUERRA | E31: PAGO DE REEMBOLSO MACETAS 21OCT25 | F31: 1300 | G31: 0 | H31: =SUM(F31:G31) -> 1300 | I31: 45951 | J31: SI
A32: PAGADO | B32: SANTANDER | C32: N/A | D32: JUANA GARAY MONROY | E32: ANTICIPO HECHURA DE CORTINAS 2 | F32: 2750 | G32: 0 | H32: =SUM(F32:G32) -> 2750 | I32: 45951 | J32: SI
A33: PAGADO | B33: SANTANDER | C33: N/A | D33: JUANA GARAY MONROY | E33: FINIQUITO HECHURA DE CORTINAS 21OCT25 | F33: 2750 | G33: 0 | H33: =SUM(F33:G33) -> 2750 | I33: 45951 | J33: SI
A34: PAGADO | B34: SANTANDER | C34: SOLICITUD | D34: ROGELIO VILCHIS | E34: VIATICOS MONTAJE 21OCT25 DOTERRA | F34: 300 | G34: 0 | H34: =SUM(F34:G34) -> 300 | I34: 45951 | J34: SI
A35: PAGADO | B35: SANTANDER | C35: SOLICITUD | D35: DAVID CHACON | E35: VIATICOS MONTAJE 21OCT25 DOTERRA | F35: 300 | G35: 0 | H35: =SUM(F35:G35) -> 300 | I35: 45951 | J35: SI
A36: PAGADO | B36: AMEX | C36: COMPROBANTE | D36: JOSE E ZEPEDA BURGOS | E36: AMAZON MX MARKETPLACE*A MEXICO CITY/19 oct 2025 | F36: 1969.16 | G36: 0 | H36: =SUM(F36:G36) -> 1969.16 | I36: 45957 | L36: TB EZ SANTANDER-AMEX $250,135.11 PROYECTOS VARIOS
A37: PAGADO | B37: AMEX | C37: COMPROBANTE | D37: JOSE E ZEPEDA BURGOS | E37: AMAZON MX MARKETPLACE*A MEXICO CITY/17 oct 2025 | F37: 507.68 | G37: 0 | H37: =SUM(F37:G37) -> 507.68 | I37: 45957 | L37: TB EZ SANTANDER-AMEX $250,135.11 PROYECTOS VARIOS
A38: PAGADO | B38: TRANSFERENCIA | C38: COT WHATS | D38: RAUL ALEJANDRO LEZAMA | E38: LIQUIDACION DE RADIOS PARA CLIENTE CONVECION DOTERRA | F38: 3870 | G38: 0 | H38: =SUM(F38:G38) -> 3870 | I38: 45952 | J38: SI
A39: PAGADO | B39: TRANSFERENCIA | C39: 6366 | D39: DESARROLLO CREATIVO EN PUBLICIDAD Y MARKETING | E39: PAGO DE BANDERAS CONVENCION DOTERRA | F39: 35700 | G39: =F39*16% -> 5712 | H39: =SUM(F39:G39) -> 41412 | I39: 45952 | J39: SI
A40: PAGADO | B40: TRANSFERENCIA | C40: COMPROBANTE | D40: LINO GUTIÉRREZ LOPEZ | E40: PAGO CHOFER EXTERNO LINO MONTAJE DOTERRA 20OCT25 | F40: 1300 | G40: 0 | H40: =SUM(F40:G40) -> 1300 | I40: 45952 | J40: SI
A41: PAGADO | B41: TRANSFERENCIA | C41: COMPROBANTE | D41: LINO GUTIÉRREZ LOPEZ | E41: PAGO CHOFER EXTERNO SAID MONTAJE DOTERRA 20OCT25 | F41: 1300 | G41: 0 | H41: =SUM(F41:G41) -> 1300 | I41: 45952 | J41: SI
A42: PAGADO | B42: TRANSFERENCIA | C42: COMPROBANTE | D42: LINO GUTIÉRREZ LOPEZ | E42: PAGO CHOFER EXTERNO BRAYAN MONTAJE DOTERRA 20OCT25 | F42: 1300 | G42: 0 | H42: =SUM(F42:G42) -> 1300 | I42: 45952 | J42: SI
A43: PAGADO | B43: TRANSFERENCIA | C43: COT WHATS | D43: MARIA DE LA LUZ TAPIA SANTAMARIA | E43: ARREGLO FLORAL CONVENCION DOTERRA | F43: 1380 | G43: 0 | H43: =SUM(F43:G43) -> 1380 | I43: 45952 | J43: SI
A44: PAGADO | B44: TRANSFERENCIA | C44: COMPROBANTE | D44: LINO GUTIERREZ LOPEZ | E44: PAGO ESTACIONAMIENTOS LINO Y SAID- MONTAJE DOTERRA 20OCT25 | F44: 350 | G44: 0 | H44: =SUM(F44:G44) -> 350 | I44: 45953 | J44: SI
A45: PAGADO | B45: TRANSFERENCIA | C45: N/A | D45: JUANA GARAY MONROY | E45: FINIQUITO HECHURA DE CORTINAS 2 22OCT25 | F45: 2750 | G45: 0 | H45: =SUM(F45:G45) -> 2750 | I45: 45953 | J45: SI
A46: PAGADO | B46: TRANSFERENCIA | C46: N/A | D46: EVODIO DE JESUS GOMEZ | E46: VIATICOS APOYO DOTERRA 22OCT25 | F46: 300 | G46: 0 | H46: =SUM(F46:G46) -> 300 | I46: 45953 | J46: SI
A47: PAGADO | B47: TRANSFERENCIA | C47: N/A | D47: TIRSO DE JESUS DE LA CRUZ | E47: VIATICOS APOYO DOTERRA 22OCT25 | F47: 300 | G47: 0 | H47: =SUM(F47:G47) -> 300 | I47: 45953 | J47: SI
A48: PAGADO | B48: TRANSFERENCIA | C48: N/A | D48: ISAIAS DE JESUS VALDES | E48: VIATICOS APOYO DOTERRA 22OCT25 | F48: 300 | G48: 0 | H48: =SUM(F48:G48) -> 300 | I48: 45953 | J48: SI
A49: PAGADO | B49: TRANSFERENCIA | C49: COMPROBANTE | D49: EDGAR OCTAVIO ALVARADO | E49: PAGO MANIOBRAS BRAYAN 20OCT25 | F49: 500 | G49: 0 | H49: =SUM(F49:G49) -> 500 | I49: 45953 | J49: SI
A50: PAGADO | B50: TRANSFERENCIA | C50: COMPROBANTE | D50: EDGAR OCTAVIO ALVARADO | E50: PAGO VIÁTICOS EDGAR OCTAVIO DEL 21OCT25 - DOTERRA | F50: 100 | G50: 0 | H50: =SUM(F50:G50) -> 100 | I50: 45953 | J50: SI
A51: PAGADO | B51: TRANSFERENCIA | C51: COMPROBANTE | D51: EDGAR OCTAVIO ALVARADO | E51: PAGO SUELDOS DE 11 MANIOBRISTAS EXTERNOS DEL 20OCT25 - DOTERRA | F51: 7700 | G51: 0 | H51: =SUM(F51:G51) -> 7700 | I51: 45953 | J51: SI | L51: TB EZ SANTANDER-AMEX $250,135.11 PROYECTOS VARIOS
A52: PAGADO | B52: AMEX | C52: FK41935 | D52: JOSE E ZEPEDA BURGOS | E52: INMOBILIARIA VALIANT RE NAUCALPAN DE JU/21 oct 2025 | F52: 896.55 | G52: =F52*16% -> 143.448 | H52: =SUM(F52:G52) -> 1039.998 | I52: PROCESO
A53: PAGADO | B53: AMEX | C53: FK41935 | D53: JOSE E ZEPEDA BURGOS | E53: INMOBILIARIA VALIANT RE NAUCALPAN DE JU/21 oct 2025 | F53: 12327.59 | G53: =F53*16% -> 1972.4144 | H53: =SUM(F53:G53) -> 14300.004 | I53: PROCESO
A54: PAGADO | B54: AMEX | C54: FK41935 | D54: JOSE E ZEPEDA BURGOS | E54: INMOBILIARIA VALIANT RE NAUCALPAN DE JU/21 oct 2025 | F54: 19109.33 | G54: 2890.67 | H54: =SUM(F54:G54) -> 22000 | I54: 45957
A55: PAGADO | B55: SANTANDER | C55: COMPROBANTE | D55: EDGAR OCTAVIO ALVARADO | E55: PAGO VIATICOS DESAYUNOS 21 Y 22OCT25 DOTERRA | F55: 200 | G55: 0 | H55: =SUM(F55:G55) -> 200 | I55: 45954 | J55: SI | L55: MANO DE OBRA SUAREZ
A56: PAGADO | B56: SANTANDER | C56: COMPROBANTE | D56: FRANCISCO JHOAN CHACON RUEDA | E56: PAGO VIÁTICOS CENA 21 Y 22OCT25 CONVENCIÓN DOTERRA | F56: 200 | G56: 0 | H56: =SUM(F56:G56) -> 200 | I56: 45954 | J56: SI | L56: =F65+F64+F63+F62+F11+F10+F9+F8 -> 200000
A57: PAGADO | B57: SANTANDER | C57: COMPROBANTE | D57: OMAR RAFAEL VICTOR GONZALEZ | E57: VIATICOS (CENA) OMAR MONTAJE DOTERRA 23OCT25 | F57: 100 | G57: 0 | H57: =SUM(F57:G57) -> 100 | I57: 45954 | J57: SI
A58: PAGADO | B58: SANTANDER | C58: COMPROBANTE | D58: ROGELIO VILCHIS | E58: VIATICOS ROGELIO MONTAJE DOTERRA 24OCT25 | F58: 300 | G58: 0 | H58: =SUM(F58:G58) -> 300 | I58: 45954 | J58: SI
A59: PAGADO | B59: SANTANDER | C59: COMPROBANTE | D59: DAVID CHACON | E59: VIATICOS DAVID MONTAJE DOTERRA 24OCT25 | F59: 300 | G59: 0 | H59: =SUM(F59:G59) -> 300 | I59: 45954 | J59: SI
A60: PAGADO | B60: SANTANDER | C60: COMPROBANTE | D60: FRANCISCO JHOAN CHACON RUEDA | E60: VIATICOS FRANCISCO MONTAJE DOTERRA 24OCT25 | F60: 300 | G60: 0 | H60: =SUM(F60:G60) -> 300 | I60: 45954 | J60: SI
A61: PAGADO | B61: TRANSFERENCIA | C61: COT WHATS | D61: MARIA DE LOURDES PASTRANA PEREZ | E61: FINIQUITO DEL 50% CABINA DE FOTOS CONVENCION DOTERRA | F61: 2000 | G61: 0 | H61: =SUM(F61:G61) -> 2000 | I61: 45954 | J61: SI
A62: PAGADO | B62: TRANSFERENCIA | C62: N/A | D62: ALBERTO SUÁREZ JIMENEZ | E62: MO TRABAJOS DOTERRA | F62: 30000 | G62: 0 | H62: =SUM(F62:G62) -> 30000 | I62: 45954 | J62: SI
A63: PAGADO | B63: TRANSFERENCIA | C63: N/A | D63: GUILLERMO SUÁREZ JIMENEZ | E63: MO TRABAJOS DOTERRA | F63: 30000 | G63: 0 | H63: =SUM(F63:G63) -> 30000 | I63: 45954 | J63: SI
A64: PAGADO | B64: TRANSFERENCIA | C64: N/A | D64: OSCAR SUÁREZ JIMENEZ | E64: MO TRABAJOS DOTERRA | F64: 30000 | G64: 0 | H64: =SUM(F64:G64) -> 30000 | I64: 45954 | J64: SI
A65: PAGADO | B65: TRANSFERENCIA | C65: N/A | D65: ALEJANDRO SUÁREZ JIMENEZ | E65: MO TRABAJOS DOTERRA | F65: 30000 | G65: 0 | H65: =SUM(F65:G65) -> 30000 | I65: 45954 | J65: SI
A66: PAGADO | B66: TRANSFERENCIA | C66: N/A | D66: DANIEL ARELLANO LAMA | E66: MO TRABAJOS DOTERRA | F66: 80000 | G66: 0 | H66: =SUM(F66:G66) -> 80000 | I66: 45954 | L66: MANO DE OBRA ARELLANO
A67: PAGADO | B67: TRANSFERENCIA | C67: PENDIENTE | D67: ALEJANDRO SANTA ANNA NIER | E67: ANTICIPO 50% LEVANTAMIENTO DE FOTO Y VIDEO, MONTAJE Y EVENTO DOTERRA, VIDEOMEMMORIAS EXPRESS Y VIDEOMEMORIA FINAL CLIENTE Y MADE | F67: 17000 | G67: 0 | H67: =SUM(F67:G67) -> 17000 | I67: 45954 | J67: SI | L67: 80000
A68: PAGADO | B68: SANTANDER | C68: PENDIENTE | D68: ERICK AXEL ESPINOZA HERNANDEZ | E68: FINIQUITO 50% PERFORMANCE | F68: 25000 | G68: 0 | H68: =SUM(F68:G68) -> 25000 | I68: 45955
A69: PAGADO | B69: SANTANDER | C69: COMPROBANTE | D69: LINO GUTIÉRREZ LOPEZ | E69: VIATICOS DESMONTAJE DOTERRA 25OCT25 GERARDO DOMINGUEZ | F69: 200 | G69: 0 | H69: =SUM(F69:G69) -> 200 | I69: 45955 | J69: SI
A70: PAGADO | B70: SANTANDER | C70: COMPROBANTE | D70: ROGELIO VILCHIS | E70: VIATICOS CENA Y DESAYUNO DESMONTAJE DOTERRA 25OCT25 | F70: 200 | G70: 0 | H70: =SUM(F70:G70) -> 200 | I70: 45955 | J70: SI
A71: PAGADO | B71: SANTANDER | C71: COMPROBANTE | D71: EDGAR OCTAVIO ALVARADO | E71: VIATICOS CENA Y DESAYUNO DESMONTAJE DOTERRA 25OCT25 | F71: 200 | G71: 0 | H71: =SUM(F71:G71) -> 200 | I71: 45955 | J71: SI
A72: PAGADO | B72: TARJETA SANTANDER | C72: TK110299 | D72: FANTASIAS MIGUEL | E72: LADRILLO, PLANTAS DE FORAJJE Y MACETA | F72: 2165.83 | G72: 0 | H72: =SUM(F72:G72) -> 2165.83 | I72: 45950
A73: PAGADO | B73: EFECTIVO | C73: FACTURA | D73: SUMINISTROS COMBUSTIBLES MORELOS | E73: PAGO COMBUSTIBLE DE GASOLINA RENE EFECTIVO 16OCT2025 | F73: 173.09 | G73: 26.91 | H73: =SUM(F73:G73) -> 200
A74: PAGADO | B74: EFECTIVO | C74: COMPROBANTE | D74: CRISMA TEMPLADO | E74: COMPRA DE ESPEJO 3MM | F74: 900 | G74: 0 | H74: =SUM(F74:G74) -> 900 | I74: 45946
A75: PAGADO | B75: EFECTIVO | C75: COMPROBANTE | D75: ANGIE PEREZ | E75: COMPRA DE FRUTA | F75: 330 | G75: 0 | H75: =SUM(F75:G75) -> 330 | I75: 45952
A76: PAGADO | B76: EFECTIVO | C76: COMPROBANTE | D76: CRISMA TEMPLADO | E76: 1 ESPEJO LUNA 450*1150 | F76: 687 | G76: 0 | H76: =SUM(F76:G76) -> 687 | I76: 45953
A77: PAGADO | B77: EFECTIVO | C77: TK | D77: THE HOME DEPOT | E77: BRIDA PARA TUBO CLOSET | F77: 340 | G77: 0 | H77: =SUM(F77:G77) -> 340 | I77: 45951
A78: PAGADO | B78: SANTANDER | C78: N/A | D78: ANGIE LIZEL PEREZ GUERRA | E78: REEMBOLSO PAGO MANIOBRAS | F78: 11200 | G78: 0 | H78: =SUM(F78:G78) -> 11200 | I78: 45957 | J78: SI
A79: PAGADO | B79: SANTANDER | C79: N/A | D79: EVODIO DE JESUS GOMEZ | E79: MO TRABAJOS APOYO DOTERRA | F79: 2125 | G79: 0 | H79: =SUM(F79:G79) -> 2125 | I79: 45957 | J79: SI
A80: PAGADO | B80: SANTANDER | C80: N/A | D80: TIRSO DE JESUS DE LA CRUZ | E80: MO TRABAJOS APOYO DOTERRA | F80: 2125 | G80: 0 | H80: =SUM(F80:G80) -> 2125 | I80: 45957 | J80: SI
A81: PAGADO | B81: TARJETA SANTANDER | C81: LWQ2587952 | D81: LIVERPOOL | E81: CAMBIADORES DE PAÑALES PARA AREA MATERNIDAD | F81: 4136.56 | G81: 661.84 | H81: =SUM(F81:G81) -> 4798.4 | I81: 45950
A82: PAGADO | B82: TRANSFERENCIA | C82: 4EC7CCE1 | D82: JESUS SANCHEZ GALICIA | E82: LIQUIDACION VOLUMETRICO EN FIBRA DE VIDRIO 60X36CM CONVENCION DOTERRA | F82: 13450 | G82: =F82*16% -> 2152 | H82: =SUM(F82:G82) -> 15602 | I82: 45957
A83: PAGADO | B83: SANTANDER | C83: N/A | D83: EVODIO DE JESUS GOMEZ | E83: APOYO EN EVENTO DOTERRA | F83: 3500 | G83: 0 | H83: =SUM(F83:G83) -> 3500 | I83: 45958
A84: PAGADO | B84: SANTANDER | C84: N/A | D84: TIRSO DE JESUS DE LA CRUZ | E84: APOYO EN EVENTO DOTERRA | F84: 3200 | G84: 0 | H84: =SUM(F84:G84) -> 3200 | I84: 45958
A85: PAGADO | B85: SANTANDER | C85: COMPROBANTE | D85: JORDAN LEAL | E85: VIATICOS DESAYUNO, COMIDA Y CENA DESMONTAJE DOTERRA 25OCT25 | F85: 300 | G85: 0 | H85: =SUM(F85:G85) -> 300 | I85: 45958
A86: PAGADO | B86: SANTANDER | C86: COMPROBANTE | D86: MANUEL MARTÍNEZ | E86: VIATICOS DESAYUNO, COMIDA Y CENA DESMONTAJE DOTERRA 25OCT25 | F86: 300 | G86: 0 | H86: =SUM(F86:G86) -> 300 | I86: 45958
A87: PAGADO | B87: SANTANDER | C87: COMPROBANTE | D87: LINO GUTIÉRREZ LOPEZ | E87: PAGO CHOFER DESMONTAJE DOTERRA 25OCT25 | F87: 1300 | G87: 0 | H87: =SUM(F87:G87) -> 1300 | I87: 45958
A88: PAGADO | B88: SANTANDER | C88: COMPROBANTE | D88: GERARDO DOMINGUEZ HERRERA | E88: PAGO CHOFER DESMONTAJE DOTERRA 25OCT25 | F88: 1300 | G88: 0 | H88: =SUM(F88:G88) -> 1300 | I88: 45958
A89: PAGADO | B89: SANTANDER | C89: COMPROBANTE | D89: LINO GUTIÉRREZ LOPEZ | E89: VIATICOS DESMONTAJE CENA Y DESAYUNO 25OCT25 | F89: 200 | G89: 0 | H89: =SUM(F89:G89) -> 200 | I89: 45958
A90: PAGADO | B90: SANTANDER | C90: COMPROBANTE | D90: ROGELIO VILCHIS | E90: REEMBOLSO ESTACIONAMIENTOS DOT2025-003, OBY2025-027, KCM2025-003 | F90: 538 | G90: 0 | H90: =SUM(F90:G90) -> 538 | I90: 45965 | L90: TB $546 DOT2028-003 $538 + OBY2025-027 $4.00 + KCM2025-003 $4.00
A91: PAGADO | B91: TRANSFERENCIA | C91: COMPROBANTE | D91: JONATAN DOMINGUEZ URBINA | E91: PAGO TRAILER DESMONTAJE DOTERRA 25OCT25 | F91: 9196 | G91: 0 | H91: =SUM(F91:G91) -> 9196 | I91: 45958
A92: PAGADO | B92: TRANSFERENCIA | C92: N/A | D92: LUIS ANTONIO MILLAN | E92: BANAMEX DOTERRA | F92: 15400 | H92: =SUM(F92:G92) -> 15400 | I92: 45958
A93: PAGADO | B93: TRANSFERENCIA | C93: N/A | D93: LUIS ANTONIO MILLAN | E93: AEROPUERTO - MENSAJERIA | F93: 2400 | H93: =SUM(F93:G93) -> 2400 | I93: 45958
A94: PAGADO | B94: SANTANDER | C94: COMPROBANTE | D94: LINO GUTIÉRREZ LOPEZ | E94: PAGO ESTACIONAMIENTO CHOFER EXTERNO LINO Y SAID MONTAJE DOTERRA 20OCT25 | F94: 500 | G94: 0 | H94: =SUM(F94:G94) -> 500 | I94: 45959
A95: PAGADO | B95: SANTANDER | C95: COMPROBANTES | D95: GUILLERMO MENDOZA | E95: COMPRA DE PLAYOS, CENA PERSONAL DESMONTAJE, CASETAS, ESTACIONAMIENTO | F95: 3344 | G95: 0 | H95: =SUM(F95:G95) -> 3344 | I95: 45959
A96: PAGADO | B96: TRANSFERENCIA | C96: COT WHATS | D96: EVELIA JIMENEZ LEGORRETA | E96: PAGO DE PLANOS ARQUITECTONICOS Y DRO CONVENCION DOTERRA | F96: 35000 | G96: 0 | H96: =SUM(F96:G96) -> 35000 | I96: 45960
A97: PAGADO | B97: TRANSFERENCIA | C97: 36A1286F-07F3-42CC-B39C-C87ED660DC7E | D97: IVAN EDUARDO MORENO | E97: LIQUIDACION DE IMPRESORAS CONVENCION DOTERRA | F97: 21448.28 | G97: 3896 | H97: =SUM(F97:G97) -> 25344.28 | I97: 45960
A98: PAGADO | B98: TRANSFERENCIA | C98: C247 | D98: LETICIA RUBI TÉLLEZ | E98: CAPELOS DOTERRA EN ACRILICOS CRISTAL 4MM | F98: 14643.1 | G98: =F98*16% -> 2342.896 | H98: =SUM(F98:G98) -> 16985.996 | I98: 45960
A99: PAGADO | B99: TRANSFERENCIA | C99: 6346 | D99: DESARROLLO CREATIVO EN PUBLICIDAD Y MARKETING | E99: PAGO DE BANDERAS ADICIONALES CONVENCION DOTERRA | F99: 5100 | G99: =F99*16% -> 816 | H99: =SUM(F99:G99) -> 5916 | I99: 45960
A100: PAGADO | B100: SANTANDER | C100: N/A | D100: INNOVACION VERDE | E100: CORTEZA DE ARBOL MACETA DOTERRA | F100: 450 | G100: 0 | H100: =SUM(F100:G100) -> 450 | I100: 45965
A101: PAGADO | B101: SANTANDER | C101: COMPROBANTES | D101: ELISA DANIELA NAVA TERAN | E101: REEMBOLSO TAXIS | F101: 544.9 | G101: 0 | H101: =SUM(F101:G101) -> 544.9 | I101: 45965
A102: PAGADO | B102: SANTANDER | C102: SOPORTE | D102: JESSICA GARCIA GONZALEZ | E102: REEMBOLSOS UBER CONVENCION DOTERRA | F102: 510.09 | G102: 0 | H102: =SUM(F102:G102) -> 510.09 | I102: 45965
A103: PAGADO | B103: SANTANDER | C103: COMPROBANTE | D103: LESLIE FLORES ETIENNE | E103: TRANSFERENCIA A ENRIQUE ZEPEDA DOTERRA 24OCT25 | F103: 1200 | G103: 0 | H103: =SUM(F103:G103) -> 1200 | I103: 45965
A104: PAGADO | B104: SANTANDER | C104: COMPROBANTE | D104: ROGELIO VILCHIS | E104: REEMBOLSO ESTACIONAMIENTOS DOTERRA | F104: 546 | G104: 0 | H104: =SUM(F104:G104) -> 546 | I104: 45965
...

Sheet COMBUSTIBLE  PEAJE
A5: COMBUSTIBLE / PEAJE
A6: Status | B6: Método de Pago | C6: No. Factura | D6: Proveedor / Razón Social | E6: Concepto | F6: Sub-Total | G6: I.V.A | H6: Monto a Pagar | I6: Fecha de Pago
A7: PAGADO | B7: TOKA LINO /ROGELIO | C7: W87660 | D7: AUTOMOTRIZ HF | E7: MONTAJE DOTERRA | F7: 1500.22 | G7: 234.98 | H7: =SUM(F7:G7) -> 1735.2 | I7: 45950
A8: PAGADO | B8: TOKA SAID/ROGELIO | C8: W87659 | D8: AUTOMOTRIZ HF | E8: MONTAJE DOTERRA | F8: 5360.98 | G8: 839.71 | H8: =SUM(F8:G8) -> 6200.69 | I8: 45950
A9: PAGADO | B9: TOKA SAID/ROGELIO | C9: W87744 | D9: AUTOMOTRIZ HF | E9: MONTAJE DOTERRA | F9: 864.58 | G9: 135.42 | H9: =SUM(F9:G9) -> 1000 | I9: 45951
A10: PAGADO | B10: TOKA SAID/ROGELIO | C10: W87745 | D10: AUTOMOTRIZ HF | E10: MONTAJE DOTERRA | F10: 491.38 | G10: 78.62 | H10: =SUM(F10:G10) -> 570 | I10: 45951
A11: PAGADO | B11: TOKA YAIR | C11: Z73108 | D11: SERVICIO CONSCRIPTO | E11: MONTAJE DOTERRA | F11: 865.47 | G11: 134.53 | H11: =SUM(F11:G11) -> 1000 | I11: 45953
A12: PAGADO | B12: TOKA YAIR | C12: W88113 | D12: AUTOMOTRIZ HF | E12: MONTAJE DOTERRA | F12: 692.28 | G12: 107.72 | H12: =SUM(F12:G12) -> 800 | I12: 45951
A13: PAGADO | B13: TOKA 9165 LINO | C13: W43289 | D13: SUPER SERVICIO NAUMEX | E13: DESMONTAJE DOTERRA | F13: 1729.06 | G13: 270.94 | H13: =SUM(F13:G13) -> 2000 | I13: 45956
A14: PAGADO | B14: TELEVIA | C14: CDEC-29789 | D14: OPERADORA CONCESIONARIA | E14: PEAJES DEL 1 AL 10OCT25 | F14: 95.69 | G14: =F14*16% -> 15.3104 | H14: =SUM(F14:G14) -> 111.0004 | I14: 45943
A15: PAGADO | B15: TELEVIA | C15: CDEC-29789 | D15: OPERADORA CONCESIONARIA | E15: PEAJES DEL 1 AL 10OCT25 | F15: 371.55 | G15: =F15*16% -> 59.448 | H15: =SUM(F15:G15) -> 430.998 | I15: 45943 | J15: EZ
A16: PAGADO | B16: TELEVIA | C16: CDEC-30974 | D16: OPERADORA CONCESIONARIA | E16: PEAJES DEL 21 AL 31OCT25 | F16: 5232.76 | G16: =F16*16% -> 837.2416 | H16: =SUM(F16:G16) -> 6070.0016 | I16: 45965
A17: PAGADO | B17: TOKA ROGELIO | C17: W88480 | D17: AUTOMOTRIZ HF | E17: ENTREGA DE MATERIALES Y HERRAMIENTAS EN DOTERRA ENTREGA DE MATERIALES Y HERRAMIENTAS EN SURA | F17: 1216.55 | G17: 189.31 | H17: =SUM(F17:G17) -> 1405.86 | I17: 45955
A18: PAGADO | B18: TOKA ROGELIO | C18: W88483 | D18: AUTOMOTRIZ HF | E18: RECOLECCIÓN PROMOCIONALES KRAKEN ENTREGA DE INSUMOS SURA ENTREGA DE VINILES CENTRO BANAMEX | F18: 213.22 | G18: 33.18 | H18: =SUM(F18:G18) -> 246.4 | I18: 45951 | J18: DOT03 / SUR02 / CCU03
A19: PAGADO | B19: TOKA ROGELIO | C19: W88481 | D19: AUTOMOTRIZ HF | E19: APOYO EN DOTERRA Y SURA (TRASLADO DE PERSONAL, ENTREGA DE HERRAMIENTAS Y VARIOS MATERIALES) | F19: 346.14 | G19: 53.86 | H19: =SUM(F19:G19) -> 400 | I19: 45952 | J19: DOT2025-003 Y SUR2025-002
A20: PAGADO | B20: TOKA ROGELIO | C20: W99438 | D20: EDGAR JOSE ARGUELLES DURAN | E20: APOYO DOTERRA VIERNES 24 | F20: 865.44 | G20: 134.56 | H20: =SUM(F20:G20) -> 1000 | I20: 45953
A21: PAGADO | B21: TOKA ROGELIO | C21: F60595 | D21: SERVICIO MIRUSA | E21: DESMONTAJE DOTERRA | F21: 1394.27 | G21: 216.7 | H21: =SUM(F21:G21) -> 1610.97 | I21: 45955
A22: PAGADO | B22: TOKA ROGELIO | C22: MMEI121231 | D22: OPERADORA DE MINIESTACIONES COMBUSERV | E22: DESMONTAJE DOTERRA | F22: 692.4 | G22: 107.6 | H22: =SUM(F22:G22) -> 800 | I22: 45951
A23: PAGADO | B23: TOKA ROGELIO | C23: W88482 | D23: AUTOMOTRIZ HF | E23: DESMONTAJE DOTERRA | F23: 504.63 | G23: 78.52 | H23: =SUM(F23:G23) -> 583.15 | I23: 45955
A24: PAGADO | B24: TOKA ROGELIO | C24: W87658 | D24: AUTOMOTRIZ HF | E24: DESMONTAJE DOTERRA | F24: 692.28 | G24: 107.72 | H24: =SUM(F24:G24) -> 800 | I24: 45950
A25: PAGADO | B25: TOKA ENRIQUE | C25: N/A | D25: SIN FACTURA | E25: MONTAJE DOTERRA | F25: 1499.81 | G25: 0 | H25: =SUM(F25:G25) -> 1499.81 | I25: 45951
A26: PAGADO | B26: TELEVIA | C26: CDEC-30974 | D26: OPERADORA CONCESIONARIA | E26: PEAJES DEL 21 AL 31OCT25 | F26: =183/2 -> 91.5 | G26: =F26*16% -> 14.64 | H26: =SUM(F26:G26) -> 106.14 | I26: 45965 | J26: SUR2025-001 Y DOT2025-003
A27: PAGADO | B27: TELEVIA | C27: CDEC-30974 | D27: OPERADORA CONCESIONARIA | E27: PEAJES DEL 21 AL 31OCT25 | F27: =294/2 -> 147 | G27: =F27*16% -> 23.52 | H27: =SUM(F27:G27) -> 170.52 | I27: 45965 | J27: SUR2025-001 Y DOT2025-003
A28: PAGADO | B28: TELEVIA | C28: CDEC-30164 | D28: OPERADORA CONCESIONARIA | E28: PEAJES DEL 11 AL 20 OCT25 | F28: 191.38 | G28: =F28*16% -> 30.6208 | H28: =SUM(F28:G28) -> 222.0008 | I28: 45953
A29: PAGADO | B29: TELEVIA | C29: CDEC-30164 | D29: OPERADORA CONCESIONARIA | E29: PEAJES DEL 11 AL 20 OCT25 | F29: 1196.59 | G29: =F29*16% -> 191.4544 | H29: =SUM(F29:G29) -> 1388.0444 | I29: 45953 | J29: EZ
A30: PAGADO | B30: TELEVIA | C30: CDEC 31779 | D30: OPERADORA CONCESIONARIA | E30: PEAJES DEL 11 AL 20NOV25 | F30: 172.41 | G30: =F30*16% -> 27.5856 | H30: =SUM(F30:G30) -> 199.9956 | I30: 45985 | J30: BFM2025-019 Y YMH2025-001
F34: 0 | G34: =F34*16% -> 0 | H34: =SUM(F34:G34) -> 0
A36: TOTAL EFECTIVO - CAJA CHICA - TOKA | F36: =SUM($F$7:$F$35) -> 26427.59 | G36: =SUM($G$7:$G$35) -> 3923.1908 | H36: =SUM($H$7:$H$35) -> 30350.781
B39: PAGADO | D39: =SUMIFS($H7:H$34,$A7:A$34,"PAGADO") -> 30350.781
B40: PENDIENTE DE PAGO | D40: =SUMIFS($H7:H$34,$A7:A$34,"PENDIENTE") -> 0
A607: PAGADO | B607: EFECTIVO
A608: PENDIENTE | B608: EDENRED
B609: TOKA

Sheet RH
A5: RH
A6: Status | B6: Método de Pago | C6: No. Factura | D6: Proveedor / Razón Social | E6: Concepto | F6: Sub-Total | G6: I.V.A | H6: Monto a Pagar | I6: Fecha de Pago
A7: PAGADO | B7: PAGADORA | C7: N/A | D7: KAWIR | E7: NOMINA SEMANAL DEL 15 AL 21SEP25 | F7: 761.9 | G7: 0 | H7: =SUM(F7:G7) -> 761.9 | I7: 45922
A8: PAGADO | B8: PAGADORA | C8: N/A | D8: KAWIR | E8: NOMINA SEMANAL DEL 22 AL 28SEP25 | F8: 1068.16 | G8: 0 | H8: =SUM(F8:G8) -> 1068.16 | I8: 45929
A9: PAGADO | B9: PAGADORA | C9: N/A | D9: KAWIR | E9: NOMINA SEMANAL DEL 29SEP AL 05OCT25 | F9: 1487.44 | G9: 0 | H9: =SUM(F9:G9) -> 1487.44 | I9: 45936
A10: PAGADO | B10: PAGADORA | C10: N/A | D10: KAWIR | E10: NOMINA SEMANAL DEL 6 AL 12OCT25 | F10: 989.34 | G10: 0 | H10: =SUM(F10:G10) -> 989.34 | I10: 45943
A11: PAGADO | B11: PAGADORA | C11: N/A | D11: KAWIR | E11: NOMINA SEMANAL DEL13 AL 19OCT25 | F11: =3269.49+47.62 -> 3317.11 | G11: 0 | H11: =SUM(F11:G11) -> 3317.11 | I11: 45950
A12: PAGADO | B12: PAGADORA | C12: N/A | D12: KAWIR | E12: NOMINA SEMANAL DEL 20 AL 26OCT25 | F12: 32735.28 | G12: 0 | H12: =SUM(F12:G12) -> 32735.28 | I12: 45957
A13: PAGADO | B13: PAGADORA | C13: N/A | D13: KAWIR | E13: NOMINA SEMANAL DEL 27OCT AL 02NOV25 | F13: 192.86 | G13: 0 | H13: =SUM(F13:G13) -> 192.86 | I13: 45964
F14: 0 | G14: =F14*16% -> 0 | H14: =SUM(F14:G14) -> 0
F15: 0 | G15: =F15*16% -> 0 | H15: =SUM(F15:G15) -> 0
F16: 0 | G16: =F16*16% -> 0 | H16: =SUM(F16:G16) -> 0
F17: 0 | G17: =F17*16% -> 0 | H17: =SUM(F17:G17) -> 0
F18: 0 | G18: =F18*16% -> 0 | H18: =SUM(F18:G18) -> 0
F19: 0 | G19: =F19*16% -> 0 | H19: =SUM(F19:G19) -> 0
F20: 0 | G20: =F20*16% -> 0 | H20: =SUM(F20:G20) -> 0
F21: 0 | G21: =F21*16% -> 0 | H21: =SUM(F21:G21) -> 0
F22: 0 | G22: =F22*16% -> 0 | H22: =SUM(F22:G22) -> 0
F23: 0 | G23: =F23*16% -> 0 | H23: =SUM(F23:G23) -> 0
F24: 0 | G24: =F24*16% -> 0 | H24: =SUM(F24:G24) -> 0
F25: 0 | G25: =F25*16% -> 0 | H25: =SUM(F25:G25) -> 0
... F29: 0 | G29: =F29*16% -> 0 | H29: =SUM(F29:G29) -> 0
A31: TOTAL RH - LOGÍSTICA | F31: =SUM($F$7:$F$30) -> 40552.09 | G31: =SUM($G$7:$G$30) -> 0 | H31: =SUM($H$7:$H$30) -> 40552.09
A34: PAGADO | D34: =SUMIFS($H7:H$29,$A7:A$29,"PAGADO") -> 40552.09
A35: PENDIENTE DE PAGO | D35: =SUMIFS($H7:H$29,$A7:A$29,"PENDIENTE") -> 0
A602: PAGADO | B602: PAGADORA
A603: PENDIENTE | B603: TOKA
B604: EFECTIVO

Sheet MATERIALES
A5: MATERIALES
A6: Status | B6: Método de Pago | C6: No. Factura | D6: Proveedor / Razón Social | E6: Concepto | F6: Costo Unitario | G6: Piezas | H6: Sub-Total | I6: I.V.A | J6: Monto a Pagar | K6: Fecha de Pago
A7: PAGADO | B7: TRANSFERENCIA | E7: TIRAS DE MADERA DE 4*2 | F7: 50.86 | G7: =25+30+60+75 -> 190 | H7: =F7*G7 -> 9663.4 | I7: =H7*16% -> 1546.144 | J7: =SUM(H7:I7) -> 11209.544 | K7: 8 Y 24SEP, 02 21OCT
A8: PAGADO | B8: TRANSFERENCIA | E8: HOJA DE MDF DE 6 MM | F8: 235.55 | G8: =50+4+7+27+2+29+5+2+16+10+23+6+7+13++6 -> 207 | H8: =F8*G8 -> 48758.85 | I8: =H8*16% -> 7801.416 | J8: =SUM(H8:I8) -> 56560.266 | K8: 8 12 17 18 19 23 25 26 29 30sep, 1 6 7 8 15 17 20oct
A9: PAGADO | B9: TRANSFERENCIA | E9: HOJA DE MDF DE 15MM | F9: 387.07 | G9: =36+2+20+4+7+5+3+12+6+10+11+22+10+4+15+5+2+2+12+2+4+3+22+27+12+8+1 -> 267 | H9: =F9*G9 -> 103347.69 | I9: =H9*16% -> 16535.63 | J9: =SUM(H9:I9) -> 119883.32 | K9: 8 17 18 19 23 24 25 26 29 Y 30sep, 01, 2, 3, 6, 7 8, 10 14 15 16 17 20oct
A10: PAGADO | B10: TRANSFERENCIA | E10: CLAVILLO Nº 25 | F10: 96.05 | G10: =1+2+1+2+1+1+2 -> 10 | H10: =F10*G10 -> 960.5 | I10: =H10*16% -> 153.68 | J10: =SUM(H10:I10) -> 1114.18 | K10: 8 18 23 24sep, 7 15 21oct
A11: PAGADO | B11: TRANSFERENCIA | E11: CLAVILLO Nº 40 | F11: 399 | G11: =1+2+1 -> 4 | H11: =F11*G11 -> 1596 | I11: =H11*16% -> 255.36 | J11: =SUM(H11:I11) -> 1851.36 | K11: 8 SEP Y 16 21OCT
A12: PAGADO | B12: TRANSFERENCIA | E12: BROCAS CON BALERO 1 1/4 NEGRA | F12: 245.77 | G12: =1+1+1+1+1+1+1+5 -> 12 | H12: =F12*G12 -> 2949.24 | I12: =H12*16% -> 471.8784 | J12: =SUM(H12:I12) -> 3421.1184 | K12: 8 18 y 23 24sep, 1, 2, 6 21OCT
A13: PAGADO | B13: TRANSFERENCIA | E13: RESISTOL 850 | F13: 82.11 | G13: =18+20+4 -> 42 | H13: =F13*G13 -> 3448.62 | I13: =H13*16% -> 551.7792 | J13: =SUM(H13:I13) -> 4000.3992 | K13: 8SEP Y 8 21OCT
A14: PAGADO | B14: TRANSFERENCIA | E14: PINTURA VINILICA BLANCA | F14: 163.52 | G14: =19+19+19 -> 57 | H14: =F14*G14 -> 9320.64 | I14: =H14*16% -> 1491.3024 | J14: =SUM(H14:I14) -> 10811.942 | K14: 17 19 y 30sep
A15: PAGADO | B15: TRANSFERENCIA | E15: FELPA CHICO | F15: 10.77 | G15: =3+2+2+1+1+2+2+3+2+6 -> 24 | H15: =F15*G15 -> 258.48 | I15: =H15*16% -> 41.3568 | J15: =SUM(H15:I15) -> 299.8368 | K15: 17 18 y 23 24 25sep, 1 Y 8 16 21OCT
A16: PAGADO | B16: TRANSFERENCIA | E16: FELPA GRANDE COMEX | F16: 33.62 | G16: =3+1+2+4+10 -> 20 | H16: =F16*G16 -> 672.4 | I16: =H16*16% -> 107.584 | J16: =SUM(H16:I16) -> 779.984 | K16: 17 23 SEP Y 8, 16 21OCT
A17: PAGADO | B17: TRANSFERENCIA | E17: SOLVENTE (THINNER) | F17: 32.5 | G17: =20+20+20+10 -> 70 | H17: =F17*G17 -> 2275 | I17: =H17*16% -> 364 | J17: =SUM(H17:I17) -> 2639 | K17: 17SEP, 2 y 6 21ocT
A18: PAGADO | B18: TRANSFERENCIA | E18: CLAVILLO Nº 38 | F18: 399 | G18: =1+1+1+1+1 -> 5 | H18: =F18*G18 -> 1995 | I18: =H18*16% -> 319.2 | J18: =SUM(H18:I18) -> 2314.2 | K18: 18 y 23sep, 15, 20oct25
A19: PAGADO | B19: TRANSFERENCIA | E19: HOJA DE MDF DE 12 MM | F19: 318.1 | G19: =15+10+8+10+6+6+2+28 -> 85 | H19: =F19*G19 -> 27038.5 | I19: =H19*16% -> 4326.16 | J19: =SUM(H19:I19) -> 31364.66 | K19: 18 19 23 29sep, 01 16 17 20oct
A20: PAGADO | B20: TRANSFERENCIA | E20: CLAVILLO Nº 20 | F20: 80 | G20: =1+1 -> 2 | H20: =F20*G20 -> 160 | I20: =H20*16% -> 25.6 | J20: =SUM(H20:I20) -> 185.6 | K20: 18 Y 24SEP
A21: PAGADO | B21: TRANSFERENCIA | E21: ESTOPA | F21: 111 | G21: =1+2 -> 3 | H21: =F21*G21 -> 333 | I21: =H21*16% -> 53.28 | J21: =SUM(H21:I21) -> 386.28 | K21: 18sep y 21oct
A22: PAGADO | B22: TRANSFERENCIA | E22: LIJAS AMARILLAS CON VELCRO GRADO 100 | F22: 10.3 | G22: =5+5+2+10+5+10 -> 37 | H22: =F22*G22 -> 381.1 | I22: =H22*16% -> 60.976 | J22: =SUM(H22:I22) -> 442.076 | K22: 18 23 26 29SEP, 03 21oct
A23: PAGADO | B23: TRANSFERENCIA | E23: NITROCELULOSA | F23: 186.13 | G23: =19+19+19+19+19 -> 95 | H23: =F23*G23 -> 17682.35 | I23: =H23*16% -> 2829.176 | J23: =SUM(H23:I23) -> 20511.526 | K23: 18, 24sep y 1 Y 8 17OCT
A24: PAGADO | B24: TRANSFERENCIA | E24: PIJA DE 1 1/2 | F24: 0.3 | G24: =400+300+100+700+12000 -> 13500 | H24: =F24*G24 -> 4050 | I24: =H24*16% -> 648 | J24: =SUM(H24:I24) -> 4698 | K24: 19 23 Y 29SEP, 17 21oct25
A25: PAGADO | B25: TRANSFERENCIA | E25: EMPAQUE PARA PISTOLA | F25: 10.12 | G25: =1+1+3 -> 5 | H25: =F25*G25 -> 50.6 | I25: =H25*16% -> 8.096 | J25: =SUM(H25:I25) -> 58.696 | K25: 19 Y 24SEP, 8OCT
A26: PAGADO | B26: TRANSFERENCIA | D26: SUSTITUCIÓN DE MATERIAL | E26: VINIL PARA IMPRECION | F26: 0 | G26: =2+2+1+3+3+1 -> 12 | H26: =F26*G26 -> 0 | I26: =H26*16% -> 0 | J26: =SUM(H26:I26) -> 0 | K26: 22sep, 1 2 8 14 17OCT
A27: PAGADO | B27: TRANSFERENCIA | D27: SUSTITUCIÓN DE MATERIAL | E27: CABEZAL CYAN/MAGENTA 836 | F27: 0 | G27: =1+2 -> 3 | H27: =F27*G27 -> 0 | I27: =H27*16% -> 0 | J27: =SUM(H27:I27) -> 0 | K27: 22SEP 8OCT
A28: PAGADO | B28: TRANSFERENCIA | D28: SUSTITUCIÓN DE MATERIAL | E28: CABEZAL OPTIMIZADOR 836 | F28: 0 | G28: 1 | H28: =F28*G28 -> 0 | I28: =H28*16% -> 0 | J28: =SUM(H28:I28) -> 0 | K28: 45922
A29: PAGADO | B29: TRANSFERENCIA | E29: TRAPOS | F29: 11.24 | G29: =2+1+4 -> 7 | H29: =F29*G29 -> 78.68 | I29: =H29*16% -> 12.5888 | J29: =SUM(H29:I29) -> 91.2688 | K29: 29sep y 24oct
A30: PAGADO | B30: TRANSFERENCIA | E30: SEGETAS PARA CALADORA GRUESA | F30: 18.97 | G30: =1+5 -> 6 | H30: =F30*G30 -> 113.82 | I30: =H30*16% -> 18.2112 | J30: =SUM(H30:I30) -> 132.0312 | K30: 23sep y 21oct
A31: PAGADO | B31: TRANSFERENCIA | E31: LIJAS AMARILLAS CON VELCRO GRADO 220 | F31: 6 | G31: =5+5+10 -> 20 | H31: =F31*G31 -> 120 | I31: =H31*16% -> 19.2 | J31: =SUM(H31:I31) -> 139.2 | K31: 23 Y 25SEP, 21oct
A32: PAGADO | B32: TRANSFERENCIA | E32: ESQUINEROS | F32: 11.02 | G32: =40+40 -> 80 | H32: =F32*G32 -> 881.6 | I32: =H32*16% -> 141.056 | J32: =SUM(H32:I32) -> 1022.656 | K32: 23sep y 7oct25
A33: PAGADO | B33: TRANSFERENCIA | E33: AVELLANADOR CON BROCA 8 | F33: 49.9 | G33: 1 | H33: =F33*G33 -> 49.9 | I33: =H33*16% -> 7.984 | J33: =SUM(H33:I33) -> 57.884 | K33: 45923
A34: PAGADO | B34: TRANSFERENCIA | E34: RESANADOR AUTOMOTRIZ | F34: 190.23 | G34: =1+1+1+4 -> 7 | H34: =F34*G34 -> 1331.61 | I34: =H34*16% -> 213.0576 | J34: =SUM(H34:I34) -> 1544.6676 | K34: 23 y 25sep y 17 21oct25
A35: PAGADO | B35: TRANSFERENCIA | E35: AVELLANADOR CON BROCA 10 | F35: 52.2 | G35: =1+1+1+1 -> 4 | H35: =F35*G35 -> 208.8 | I35: =H35*16% -> 33.408 | J35: =SUM(H35:I35) -> 242.208 | K35: 23 y 24sep, 17 20oct
A36: PAGADO | B36: TRANSFERENCIA | E36: CLAVILLO Nº 35 | F36: 91.38 | G36: 2 | H36: =F36*G36 -> 182.76 | I36: =H36*16% -> 29.2416 | J36: =SUM(H36:I36) -> 212.0016 | K36: 24//09/25
A37: PAGADO | B37: TRANSFERENCIA | E37: BISAGRA BIDIMENCIONAL RECTA | F37: 18 | G37: 16 | H37: =F37*G37 -> 288 | I37: =H37*16% -> 46.08 | J37: =SUM(H37:I37) -> 334.08 | K37: 24//09/25
A38: PAGADO | B38: TRANSFERENCIA | E38: LIJAS AMARILLAS CON VELCRO GRADO 80 | F38: 10.2 | G38: =5+3+5 -> 13 | H38: =F38*G38 -> 132.6 | I38: =H38*16% -> 21.216 | J38: =SUM(H38:I38) -> 153.816 | K38: 24 Y 25SEP, 03oct
A39: PAGADO | B39: TRANSFERENCIA | E39: TIRAS DE MADERA DE 8*2 | F39: 98 | G39: 15 | H39: =F39*G39 -> 1470 | I39: =H39*16% -> 235.2 | J39: =SUM(H39:I39) -> 1705.2 | K39: 24//09/25
A40: PAGADO | B40: TRANSFERENCIA | E40: LIJA NEGRA 80 | F40: 10 | G40: =5+3 -> 8 | H40: =F40*G40 -> 80 | I40: =H40*16% -> 12.8 | J40: =SUM(H40:I40) -> 92.8 | K40: 24SEP Y 16OCT
A41: PAGADO | B41: TRANSFERENCIA | E41: LIJA NEGRA 100 | F41: 10.5 | G41: =5+20 -> 25 | H41: =F41*G41 -> 262.5 | I41: =H41*16% -> 42 | J41: =SUM(H41:I41) -> 304.5 | K41: 29sep y 21oct
A42: PAGADO | B42: TRANSFERENCIA | E42: LIJA NEGRA 120 | F42: 10 | G42: =5+20 -> 25 | H42: =F42*G42 -> 250 | I42: =H42*16% -> 40 | J42: =SUM(H42:I42) -> 290 | K42: 24sep y 21oct
A43: PAGADO | B43: TRANSFERENCIA | E43: LIJA ROJA 100 | F43: 12.93 | G43: 3 | H43: =F43*G43 -> 38.79 | I43: =H43*16% -> 6.2064 | J43: =SUM(H43:I43) -> 44.9964 | K43: 45925
A44: PAGADO | B44: TRANSFERENCIA | E44: LACA BLANCA | F44: 204.53 | G44: 19 | H44: =F44*G44 -> 3886.07 | I44: =H44*16% -> 621.7712 | J44: =SUM(H44:I44) -> 4507.8412 | K44: 45925
A45: PAGADO | B45: TRANSFERENCIA | E45: MATIZANTE | F45: 1554.31 | G45: 4 | H45: =F45*G45 -> 6217.24 | I45: =H45*16% -> 994.7584 | J45: =SUM(H45:I45) -> 7211.9984 | K45: 45925
A46: PAGADO | B46: TRANSFERENCIA | E46: HOJA DE MDF DE 9 MM | F46: 249.14 | G46: =6+4+6+8+2 -> 26 | H46: =F46*G46 -> 6477.64 | I46: =H46*16% -> 1036.4224 | J46: =SUM(H46:I46) -> 7514.0624 | K46: 26 29 Y 30SEP, 16 21OCT
A47: PAGADO | B47: TRANSFERENCIA | D47: SUSTITUCIÓN DE MATERIAL | E47: TINTA 831 AMARILLA | F47: 0 | G47: =1+1+1 -> 3 | H47: =F47*G47 -> 0 | I47: =H47*16% -> 0 | J47: =SUM(H47:I47) -> 0 | K47: 26sep y 3 14oct
A48: PAGADO | B48: TRANSFERENCIA | D48: SUSTITUCIÓN DE MATERIAL | E48: TINTA 831 OPTIMIZADOR | F48: 0 | G48: =1+1 -> 2 | H48: =F48*G48 -> 0 | I48: =H48*16% -> 0 | J48: =SUM(H48:I48) -> 0 | K48: 26sep y 14oct25
A49: PAGADO | B49: TRANSFERENCIA | E49: PLAYO GRANDE | F49: 150 | G49: =2+3+2+1+2+3+6 -> 19 | H49: =F49*G49 -> 2850 | I49: =H49*16% -> 456 | J49: =SUM(H49:I49) -> 3306 | K49: 29 y 30sep, 3 7 8 17 20 21oct
A50: PAGADO | B50: TRANSFERENCIA | E50: PLAYO CHICO | F50: 80 | G50: =2+1+2 -> 5 | H50: =F50*G50 -> 400 | I50: =H50*16% -> 64 | J50: =SUM(H50:I50) -> 464 | K50: 29 30 SEP Y 8 17OCT
A51: PAGADO | B51: TRANSFERENCIA | E51: PERFIL DE 3/4 X 3/4 | F51: 148 | G51: =8+20 -> 28 | H51: =F51*G51 -> 4144 | I51: =H51*16% -> 663.04 | J51: =SUM(H51:I51) -> 4807.04 | K51: 30SEP, 02OCT
A52: PAGADO | B52: TRANSFERENCIA | E52: FLASH COAT NEGRA | F52: 274.14 | G52: =4+4+4 -> 12 | H52: =F52*G52 -> 3289.68 | I52: =H52*16% -> 526.3488 | J52: =SUM(H52:I52) -> 3816.0288 | K52: 30sep y 1 Y 8OCT
A53: PAGADO | B53: TRANSFERENCIA | E53: FLASH COAT NARANJA | F53: 257.32 | G53: 4 | H53: =F53*G53 -> 1029.28 | I53: =H53*16% -> 164.6848 | J53: =SUM(H53:I53) -> 1193.9648 | K53: 45946
A54: PAGADO | B54: TRANSFERENCIA | E54: RESANADOR BLANCO | F54: 195.86 | G54: =1+1+2 -> 4 | H54: =F54*G54 -> 783.44 | I54: =H54*16% -> 125.3504 | J54: =SUM(H54:I54) -> 908.7904 | K54: 30sep y 20 21oct
A55: PAGADO | B55: TRANSFERENCIA | E55: PINTURA VINILICA AZUL | F55: 188.15 | G55: =20+8 -> 28 | H55: =F55*G55 -> 5268.2 | I55: =H55*16% -> 842.912 | J55: =SUM(H55:I55) -> 6111.112 | K55: 1 Y 6OCT25
A56: PAGADO | B56: TRANSFERENCIA | D56: SUSTITUCIÓN DE MATERIAL | E56: TINTA 831 NEGRA | F56: 0 | G56: 1 | H56: =F56*G56 -> 0 | I56: =H56*16% -> 0 | J56: =SUM(H56:I56) -> 0 | K56: 45931
A57: PAGADO | B57: TRANSFERENCIA | D57: SUSTITUCIÓN DE MATERIAL | E57: TINTA 832 OVER COAT | F57: 0 | G57: 1 | H57: =F57*G57 -> 0 | I57: =H57*16% -> 0 | J57: =SUM(H57:I57) -> 0 | K57: 45931
A58: PAGADO | B58: TRANSFERENCIA | E58: TIRA LED BLANCA INTERIOR | F58: 85 | G58: =16+8 -> 24 | H58: =F58*G58 -> 2040 | I58: =H58*16% -> 326.4 | J58: =SUM(H58:I58) -> 2366.4 | K58: 1 2 6 y 7 8OCT25
A59: PAGADO | B59: TRANSFERENCIA | E59: ACRILICO BLANCO DE 3 MM | F59: 1900 | G59: 1 | H59: =F59*G59 -> 1900 | I59: =H59*16% -> 304 | J59: =SUM(H59:I59) -> 2204 | K59: 45931
A60: PAGADO | B60: TRANSFERENCIA | E60: DISCOS DE LIJA | F60: 58 | G60: 2 | H60: =F60*G60 -> 116 | I60: =H60*16% -> 18.56 | J60: =SUM(H60:I60) -> 134.56 | K60: 45931
A61: PAGADO | B61: TRANSFERENCIA | E61: DISCO DE CORTE ACERO DE 14´ | F61: 41.81 | G61: 1 | H61: =F61*G61 -> 41.81 | I61: =H61*16% -> 6.6896 | J61: =SUM(H61:I61) -> 48.4996 | K61: 45931
A62: PAGADO | B62: TRANSFERENCIA | E62: AEROSOL NEGRO | F62: 99 | G62: =1+3 -> 4 | H62: =F62*G62 -> 396 | I62: =H62*16% -> 63.36 | J62: =SUM(H62:I62) -> 459.36 | K62: 1 y 21oct
A63: PAGADO | B63: TRANSFERENCIA | E63: ELIMINADORES | F63: 249 | G63: 3 | H63: =F63*G63 -> 747 | I63: =H63*16% -> 119.52 | J63: =SUM(H63:I63) -> 866.52 | K63: 45932
A64: PAGADO | B64: TRANSFERENCIA | D64: SUSTITUCIÓN DE MATERIAL | E64: TINTA 832 LIGH MAGENTA | F64: 0 | G64: 1 | H64: =F64*G64 -> 0 | I64: =H64*16% -> 0 | J64: =SUM(H64:I64) -> 0 | K64: 45933
A65: PAGADO | B65: TRANSFERENCIA | E65: PIJA DE 5/8 | F65: 0.31 | G65: =100+500 -> 600 | H65: =F65*G65 -> 186 | I65: =H65*16% -> 29.76 | J65: =SUM(H65:I65) -> 215.76 | K65: 3 y 21oct
A66: PAGADO | B66: TRANSFERENCIA | E66: MASKIG DE 2´ | F66: 28 | G66: =2+2+3+8+3 -> 18 | H66: =F66*G66 -> 504 | I66: =H66*16% -> 80.64 | J66: =SUM(H66:I66) -> 584.64 | K66: 3 20 21 22oct25
A67: PAGADO | B67: TRANSFERENCIA | E67: CLAVILLO Nº 30 | F67: 85.5 | G67: 1 | H67: =F67*G67 -> 85.5 | I67: =H67*16% -> 13.68 | J67: =SUM(H67:I67) -> 99.18 | K67: 45936
A68: PAGADO | B68: TRANSFERENCIA | E68: SOLDADURA | F68: 35 | G68: =1+1 -> 2 | H68: =F68*G68 -> 70 | I68: =H68*16% -> 11.2 | J68: =SUM(H68:I68) -> 81.2 | K68: 6 Y 8OCT
A69: PAGADO | B69: TRANSFERENCIA | E69: NAVAJA PARA CUTTER GRANDE | F69: 2.93 | G69: =10+10+20 -> 40 | H69: =F69*G69 -> 117.2 | I69: =H69*16% -> 18.752 | J69: =SUM(H69:I69) -> 135.952 | K69: 6 17 y 21oct
A70: PAGADO | B70: TRANSFERENCIA | E70: MANGUERA NEON FLEX BLANCA | F70: 75 | G70: =2+6 -> 8 | H70: =F70*G70 -> 600 | I70: =H70*16% -> 96 | J70: =SUM(H70:I70) -> 696 | K70: 6 Y 22OCT
A71: PAGADO | B71: TRANSFERENCIA | E71: BROCHAS DE 1´´ | F71: 16.5 | G71: =1+3 -> 4 | H71: =F71*G71 -> 66 | I71: =H71*16% -> 10.56 | J71: =SUM(H71:I71) -> 76.56 | K71: 8 y 21oct
A72: PAGADO | B72: TRANSFERENCIA | E72: PASTA PARA SOLDAR | F72: 19.72 | G72: 1 | H72: =F72*G72 -> 19.72 | I72: =H72*16% -> 3.1552 | J72: =SUM(H72:I72) -> 22.8752 | K72: 45938
A73: PAGADO | B73: TRANSFERENCIA | E73: CABLE PROTOBOT # 22 ROJO | F73: 7.5 | G73: 70 | H73: =F73*G73 -> 525 | I73: =H73*16% -> 84 | J73: =SUM(H73:I73) -> 609 | K73: 45938
A74: PAGADO | B74: TRANSFERENCIA | E74: ALAMBRE PROTOBOT NEGRO 22 | F74: 7.5 | G74: 70 | H74: =F74*G74 -> 525 | I74: =H74*16% -> 84 | J74: =SUM(H74:I74) -> 609 | K74: 45938
A75: PAGADO | B75: TRANSFERENCIA | D75: SUSTITUCIÓN DE MATERIAL | E75: TINTA 832 LYAN CYAN | F75: 0 | G75: 1 | H75: =F75*G75 -> 0 | I75: =H75*16% -> 0 | J75: =SUM(H75:I75) -> 0 | K75: 45944
A76: PAGADO | B76: TRANSFERENCIA | E76: GRAPAS DE 1/4 ET-21 | F76: 20.68 | G76: =2+5 -> 7 | H76: =F76*G76 -> 144.76 | I76: =H76*16% -> 23.1616 | J76: =SUM(H76:I76) -> 167.9216 | K76: 14 y 21oct
A77: PAGADO | B77: TRANSFERENCIA | D77: SUSTITUCIÓN DE MATERIAL | E77: CABEZAL 831 CYAN BLACK | F77: 0 | G77: 1 | H77: =F77*G77 -> 0 | I77: =H77*16% -> 0 | J77: =SUM(H77:I77) -> 0 | K77: 45945
A78: PAGADO | B78: TRANSFERENCIA | E78: TRIPLAY FLEXIBLE 6MM | F78: 413.79 | G78: =4+1+1 -> 6 | H78: =F78*G78 -> 2482.74 | I78: =H78*16% -> 397.2384 | J78: =SUM(H78:I78) -> 2879.9784 | K78: 15 16 y 17oct
A79: PAGADO | B79: TRANSFERENCIA | E79: HOJA DE MDF DE 3 MM | F79: 128.44 | G79: 1 | H79: =F79*G79 -> 128.44 | I79: =H79*16% -> 20.5504 | J79: =SUM(H79:I79) -> 148.9904 | K79: 45946
A80: PAGADO | B80: TRANSFERENCIA | E80: LIJA MADERA 80 | F80: 6.41 | G80: 3 | H80: =F80*G80 -> 19.23 | I80: =H80*16% -> 3.0768 | J80: =SUM(H80:I80) -> 22.3068 | K80: 45946
A81: PAGADO | B81: TRANSFERENCIA | E81: LIJA NEGRA 180 | F81: 11 | G81: =3+5+10 -> 18 | H81: =F81*G81 -> 198 | I81: =H81*16% -> 31.68 | J81: =SUM(H81:I81) -> 229.68 | K81: 16 17 21oct25
A82: PAGADO | B82: TRANSFERENCIA | E82: LIJAS AMARILLAS CON VELCRO GRADO 180 | F82: 8.7 | G82: =6+5+10 -> 21 | H82: =F82*G82 -> 182.7 | I82: =H82*16% -> 29.232 | J82: =SUM(H82:I82) -> 211.932 | K82: 16 17 y 21oct
A83: PAGADO | B83: TRANSFERENCIA | E83: PINTURA VINILICA GRIS | F83: 163.52 | G83: 4 | H83: =F83*G83 -> 654.08 | I83: =H83*16% -> 104.6528 | J83: =SUM(H83:I83) -> 758.7328 | K83: 45946
A84: PAGADO | B84: TRANSFERENCIA | D84: PRUEBLA DE COLOR DOTERRA | E84: VINIL DE IMPRESIÓN 1 M2 | F84: 150 | G84: 1 | H84: =F84*G84 -> 150 | I84: =H84*16% -> 24 | J84: =SUM(H84:I84) -> 174 | K84: 45911
A85: PAGADO | B85: TRANSFERENCIA | D85: PRUEBAS DE COLOR DOTERRA | E85: VINIL DE IMPRESIÓN 2 M2 | F85: 150 | G85: 2 | H85: =F85*G85 -> 300 | I85: =H85*16% -> 48 | J85: =SUM(H85:I85) -> 348 | K85: 45918
A86: PAGADO | B86: TRANSFERENCIA | D86: IMPRESIÓN VINIL COUNTERS REGISTRO DOTERRA | E86: VINIL DE IMPRESIÓN 35 M2 | F86: 150 | G86: 35 | H86: =F86*G86 -> 5250 | I86: =H86*16% -> 840 | J86: =SUM(H86:I86) -> 6090 | K86: 45922
A87: PAGADO | B87: TRANSFERENCIA | D87: CALIBRACIÓN CABEZALES E IMPRESIÓN ETIQUETAS DOTERRA | E87: VINIL DE IMPRESIÓN 6 M2 | F87: 150 | G87: 6 | H87: =F87*G87 -> 900 | I87: =H87*16% -> 144 | J87: =SUM(H87:I87) -> 1044 | K87: 45922
A88: PAGADO | B88: TRANSFERENCIA | D88: IMPRESIÓN VINIL PANTONE 494 U 2 DOTERRA | E88: VINIL DE IMPRESIÓN 26 M2 | F88: 150 | G88: 26 | H88: =F88*G88 -> 3900 | I88: =H88*16% -> 624 | J88: =SUM(H88:I88) -> 4524 | K88: 45929
A89: PAGADO | B89: TRANSFERENCIA | D89: IMPRESIÓN DE VINIL PANTONE 965 U / 494 U DOTERRA | E89: VINIL DE IMPRESIÓN 44 M2 | F89: 150 | G89: 44 | H89: =F89*G89 -> 6600 | I89: =H89*16% -> 1056 | J89: =SUM(H89:I89) -> 7656 | K89: 45931
A90: PAGADO | B90: TRANSFERENCIA | D90: IMPRESIÓN DE VINIL DOTERRA | E90: VINIL DE IMPRESIÓN 21 M2 | F90: 150 | G90: 21 | H90: =F90*G90 -> 3150 | I90: =H90*16% -> 504 | J90: =SUM(H90:I90) -> 3654 | K90: 45932
A91: PAGADO | B91: TRANSFERENCIA | D91: IMPRESIÓN DE VINIL DOTERRA | E91: IMPRESIÓN DE VINIL 23 M2 | F91: 150 | G91: 23 | H91: =F91*G91 -> 3450 | I91: =H91*16% -> 552 | J91: =SUM(H91:I91) -> 4002 | K91: 45933
A92: PAGADO | B92: TRANSFERENCIA | D92: IMPRESIÓN TEXTURAS DOTERRA | E92: IMPRESIÓN DE VINIL 14 M2 | F92: 150 | G92: 14 | H92: =F92*G92 -> 2100 | I92: =H92*16% -> 336 | J92: =SUM(H92:I92) -> 2436 | K92: 45936
A93: PAGADO | B93: TRANSFERENCIA | D93: IMPRESIÓN DE VINIL DOTERRA | E93: IMPRESIÓN DE VINIL 1 M2 | F93: 150 | G93: 1 | H93: =F93*G93 -> 150 | I93: =H93*16% -> 24 | J93: =SUM(H93:I93) -> 174 | K93: 45937
A94: PAGADO | B94: TRANSFERENCIA | D94: IMPRESIÓN DE VINIL DOTERRA | E94: IMPRESIÓN DE VINIL 55 M2 | F94: 150 | G94: 55 | H94: =F94*G94 -> 8250 | I94: =H94*16% -> 1320 | J94: =SUM(H94:I94) -> 9570 | K94: 45938
A95: PAGADO | B95: TRANSFERENCIA | D95: IMPRESIÓN VINIL DOTERRA | E95: IMPRESIÓN DE VINIL 17 M2 | F95: 150 | G95: 17 | H95: =F95*G95 -> 2550 | I95: =H95*16% -> 408 | J95: =SUM(H95:I95) -> 2958 | K95: 45939
... A97: PAGADO | B97: TRANSFERENCIA | D97: IMPRESIÓN DE VINIL DOTERRA | E97: IMPRESIÓN DE VINIL 20 M2 | F97: 150 | G97: 20 | H97: =F97*G97 -> 3000 | I97: =H97*16% -> 480 | J97: =SUM(H97:I97) -> 3480 | K97: 45945
A98: PAGADO | B98: TRANSFERENCIA | D98: SUSTITUCIÓN DE MATERIAL | E98: VINIL PARA IMPRECION | F98: 0 | G98: =25*50 -> 1250 | H98: =F98*G98 -> 0 | I98: =H98*16% -> 0 | J98: =SUM(H98:I98) -> 0 | K98: 20 y 21oct
A99: PAGADO | B99: TRANSFERENCIA | E99: PISTOLAS DE GRAVEDAD | F99: 1114.22 | G99: 2 | H99: =F99*G99 -> 2228.44 | I99: =H99*16% -> 356.5504 | J99: =SUM(H99:I99) -> 2584.9904 | K99: 45947
A100: PAGADO | B100: TRANSFERENCIA | E100: PTR DE 3/4 | F100: 230.49 | G100: 1 | H100: =F100*G100 -> 230.49 | I100: =H100*16% -> 36.8784 | J100: =SUM(H100:I100) -> 267.3684 | K100: 45947
A101: PAGADO | B101: TRANSFERENCIA | E101: BROCHAS DE 2´´ | F101: 27 | G101: =2+6 -> 8 | H101: =F101*G101 -> 216 | I101: =H101*16% -> 34.56 | J101: =SUM(H101:I101) -> 250.56 | K101: 17 y 21oct
A102: PAGADO | B102: TRANSFERENCIA | E102: NAVAJA PARA CUTTER CHICA | F102: 2.07 | G102: =10+20 -> 30 | H102: =F102*G102 -> 62.1 | I102: =H102*16% -> 9.936 | J102: =SUM(H102:I102) -> 72.036 | K102: 17 y 21oct
A103: PAGADO | B103: TRANSFERENCIA | E103: LIJA NEGRA 240 | F103: 10 | G103: =4+20 -> 24 | H103: =F103*G103 -> 240 | I103: =H103*16% -> 38.4 | J103: =SUM(H103:I103) -> 278.4 | K103: 20 y 21oct
A104: PAGADO | B104: TRANSFERENCIA | E104: PVC BLANCO DE 3MM | F104: 239.36 | G104: 3 | H104: =F104*G104 -> 718.08 | I104: =H104*16% -> 114.8928 | J104: =SUM(H104:I104) -> 832.9728 | K104: 45951
A105: PAGADO | B105: TRANSFERENCIA | E105: PVC NEGRO DE 3MM | F105: 435.34 | G105: 3 | H105: =F105*G105 -> 1306.02 | I105: =H105*16% -> 208.9632 | J105: =SUM(H105:I105) -> 1514.9832 | K105: 45951
...

Sheet PROVISIONES
A7: PROVISIONES
A8: Proveedor / Razón Social | B8: Concepto | C8: Sub-Total | D8: I.V.A | E8: Monto a Pagar
A9: ALEJANDRO SANTA ANNA NIER | B9: VIDEOMEMORIA | C9: 17000 | D9: 0 | E9: =SUM(C9:D9) -> 17000 | F9: SP INGRESADA 24 NOV
A10: Amex Enrique | B10: Amazon, compra balones y canasta basquetball | C10: 1935 | D10: =C10*0% -> 0 | E10: =SUM(C10:D10) -> 1935
A11: LO COMPRA ENRIQUE | B11: VIDRIO .45 X 1.50 CM PARA SHOW ROOM | C11: 1050 | E11: =SUM(C11:D11) -> 1050 | F11: PENDIENTE REEMBOLSO ENRIQUE
A12: MIX PRO | B12: AUDIO, VIDEO E ILUMINACION | C12: 800000 | D12: =C12*0% -> 0 | E12: =SUM(C12:D12) -> 800000
A13: IMAXINARIO | B13: CABINAS | C13: 150000 | D13: =C13*0% -> 0 | E13: =SUM(C13:D13) -> 150000
A14: CUAUTEMOC | B14: DJ | C14: 4000 | D14: =C14*0% -> 0 | E14: =SUM(C14:D14) -> 4000
A15: SHELLY RIGGING / U OTRO | B15: STAGE DE TODAS LAS ZONAS | C15: 70000 | D15: =C15*0% -> 0 | E15: =SUM(C15:D15) -> 70000 | F15: PENDIENTE REEMBOLSO ENRIQUE
A16: CRISTIAN MORENO | B16: ANTICIPO IMPRESION Y COLOCACION | C16: 50000 | E16: =D16+C16 -> 50000 | F16: PENDIENTE REEMBOLSO ENRIQUE
A17: CRISTIAN MORENO | B17: IMPRESION Y COLOCACION VINIL | C17: =99391-C16 -> 49391 | D17: =C17*0% -> 0 | E17: =SUM(C17:D17) -> 49391 | F17: SP INGRESADA 26 NOV
B19: MO SUAREZ | C19: 150000 | D19: =C19*0% -> 0 | E19: =SUM(C19:D19) -> 150000
B20: MO DANIEL ARELLANO | C20: 30000 | D20: =C20*0% -> 0 | E20: =SUM(C20:D20) -> 30000
B21: LOGISTICA | C21: 4000 | D21: =C21*0% -> 0 | E21: =SUM(C21:D21) -> 4000
B22: STAFF OPERACION 4 PAX | C22: =1200*3*4 -> 14400 | D22: =C22*0% -> 0 | E22: =SUM(C22:D22) -> 14400
B23: GASTO POR VENTA 1 | C23: 80000 | D23: =C23*0% -> 0 | E23: =SUM(C23:D23) -> 80000
B24: MANIOBRA EXTERNA | C24: 2500 | D24: =C24*0% -> 0 | E24: =SUM(C24:D24) -> 2500
A25: ENRIQUE ZEPEDA | B25: CENA STAFF MONTAJE 20 OCT | C25: 1800 | D25: =C25*0% -> 0 | E25: =SUM(C25:D25) -> 1800 | F25: REEMBOLSO ENRIQUE
A26: OSCAR ARRIAGA QUINTANA | B26: ANTICIPO APOYO DE TRABAJOS DOTERRA | C26: 2000 | D26: =C26*0% -> 0 | E26: =SUM(C26:D26) -> 2000
A27: PROVISION | B27: MANIOBRAS 25 DE OCTUBRE | C27: 7000 | D27: 0 | E27: =C27+D27 -> 7000 | F27: REEMBOLSO ENRIQUE
A28: PROVISION | B28: VIATICOS | C28: 15000 | D28: 0 | E28: =C28+D28 -> 15000 | F28: REEMBOLSO ENRIQUE
A29: PROVISION | B29: VIATICOS ALEJANDRO | C29: 7000 | D29: 0 | E29: =C29+D29 -> 7000 | F29: REEMBOLSO ENRIQUE
A31: LESLIE FLORES ETIENNE | B31: GASTOS VARIOS REEMBOLSO | C31: 35672.79 | D31: 0 | E31: =C31+D31 -> 35672.79 | F31: SP INGRESADA 24 NOV
A32: PROVISION | B32: COMPRA TENIS CASSANDRA | C32: 1682.85 | E32: =C32+D32 -> 1682.85 | F32: PENDIENTE POR QUE AMEX NO PASO
A33: CUAUHTEMOC ORTEGA AVILÉS | B33: DJ DOTERRA | C33: 5000 | E33: =C33+D33 -> 5000
A34: ANGIE LIZEL PEREZ GUERRA | B34: REEMBOLSO PAGO DE TINTORERIA | C34: 1539 | D34: 0 | E34: =C34+D34 -> 1539
D35: =C35*16% -> 0 | E35: =C35+D35 -> 0
D36: =C36*16% -> 0 | E36: =C36+D36 -> 0
D37: =C37*16% -> 0 | E37: =C37+D37 -> 0
D38: =C38*16% -> 0 | E38: =C38+D38 -> 0
D39: =C39*16% -> 0 | E39: =C39+D39 -> 0
D40: =C40*16% -> 0 | E40: =C40+D40 -> 0
D41: =C41*16% -> 0 | E41: =C41+D41 -> 0
D42: =C42*16% -> 0 | E42: =C42+D42 -> 0
D43: =C43*16% -> 0 | E43: =C43+D43 -> 0
D44: =C44*16% -> 0 | E44: =C44+D44 -> 0
D45: =C45*16% -> 0 | E45: =C45+D45 -> 0
D46: =C46*16% -> 0 | E46: =C46+D46 -> 0
D47: =C47*16% -> 0 | E47: =C47+D47 -> 0
A48: MERCADAZO | B48: MAQUINAS FRAPPE (3 maquinas) | D48: =C48*0% -> 0 | E48: =SUM(C48:D48) -> 0
A49: ALBERTO GARCIA MORENO | B49: blasfer de confeti | D49: =C49*0% -> 0 | E49: =SUM(C49:D49) -> 0 | F49: SE LE VA A DEBER A MIX / PAGADO 11NOV25 JESSI
A50: ERICK ESPINOSA | B50: FINIQUITO PERFOMANCE | D50: 0 | E50: =SUM(C50:D50) -> 0
A51: MEXICO VALLE | B51: HOTEL STAFF | D51: =C51*0% -> 0 | E51: =SUM(C51:D51) -> 0 | F51: POR PAGAR CON TDC ENRIQUE
A53: TOTAL DE PROVISIONES | C53: =SUM(C9:C51) -> 1500970.6 | D53: =SUM(D9:D51) -> 0 | E53: =SUM(E9:E51) -> 1500970.6
