Workbook
Name eventos_cerrados: #REF!

Sheet RESUMEN
A1: CIERRE INTERNO
E2: CLIENTE: | F2: MEDTRONIC
E3: CLAVE EVENTO | F3: MTC2025-002 | G3: MTC2025-002
E4: FECHAS DEL EVENTO: | F4: SEPTIEMBRE
E5: SEDE:
E6: CIUDAD:
E7: ASESOR TERRESTRE:
E8: VENDEDOR DE GRUPOS:
A11: INGRESOS
A12: Status | B12: No. Factura | C12: Proveedor / Razón Social | D12: Concepto | E12: Otra Moneda | F12: Sub-Total | G12: I.V.A | H12: Monto a Pagar
A13: PENDIENTE | B13: PENDIENTE | C13: MEDTRONIC | D13: Exhibición Neurociencias Congreso Angeles | F13: 150 | G13: =+F13*0.16 -> 24 | H13: =+SUM(F13:G13) -> 174
A14: PENDIENTE | B14: PENDIENTE | C14: MEDTRONIC | D14: Stand 6x3 Congreso Angeles. | F14: 350 | G14: =+F14*0.16 -> 56 | H14: =+SUM(F14:G14) -> 406
A15: PENDIENTE | B15: PENDIENTE | C15: MEDTRONIC | D15: Flete y gastos operacionales Stand Congreso Angeles. | F15: 200 | G15: =+F15*0.16 -> 32 | H15: =+SUM(F15:G15) -> 232
A16: PENDIENTE | B16: PENDIENTE | C16: MEDTRONIC | D16: Stand Hugo RAS Congreso Angeles. | G16: =+F16*0.16 -> 0 | H16: =+SUM(F16:G16) -> 0
A18: TOTAL INGRESOS | F18: =+SUM(F13:F16) -> 700 | G18: =+SUM(G13:G16) -> 112 | H18: =+SUM(H13:H16) -> 812
A20: RESUMEN GASTOS
A21: Concepto | B21: Sub-Total | C21: I.V.A | D21: Total | E21: Porcentaje
A22: SP´S | B22: =+SUMIFS(GASTOS!G:G,GASTOS!A:A,$A22) -> 0 | C22: =+SUMIFS(GASTOS!H:H,GASTOS!$A:$A,$A22) -> 0 | D22: =+SUMIFS(GASTOS!I:I,GASTOS!$A:$A,$A22) -> 0 | E22: =+D22/$D$27 -> 0
A23: COMBUSTIBLE / PEAJE | B23: =+SUMIFS(GASTOS!G:G,GASTOS!A:A,$A23) -> 50 | C23: =+SUMIFS(GASTOS!H:H,GASTOS!$A:$A,$A23) -> 8 | D23: =+SUMIFS(GASTOS!I:I,GASTOS!$A:$A,$A23) -> 58 | E23: =+D23/$D$27 -> 0.11627907
A24: RH | B24: =+SUMIFS(GASTOS!G:G,GASTOS!A:A,$A24) -> 220 | C24: =+SUMIFS(GASTOS!H:H,GASTOS!$A:$A,$A24) -> 35.2 | D24: =+SUMIFS(GASTOS!I:I,GASTOS!$A:$A,$A24) -> 255.2 | E24: =+D24/$D$27 -> 0.51162791
A25: MATERIALES | B25: =+SUMIFS(GASTOS!G:G,GASTOS!A:A,$A25) -> 160 | C25: =+SUMIFS(GASTOS!H:H,GASTOS!$A:$A,$A25) -> 25.6 | D25: =+SUMIFS(GASTOS!I:I,GASTOS!$A:$A,$A25) -> 185.6 | E25: =+D25/$D$27 -> 0.37209302
A27: TOTAL EGRESOS | B27: =+SUM(B22:B25) -> 430 | C27: =+SUM(C22:C25) -> 68.8 | D27: =+SUM(D22:D25) -> 498.8 | E27: =+SUM(E22:E25) -> 1
A29: RESUMEN PROVISIONES
A30: Concepto | B30: Sub-Total | C30: I.V.A | D30: Total | E30: Porcentaje
A31: PROVISIONES | B31: =+SUMIFS(PROVISIONES!E:E,PROVISIONES!$B:$B,"PENDIENTE") -> 220 | C31: =+SUMIFS(PROVISIONES!F:F,PROVISIONES!$B:$B,"PENDIENTE") -> 35.2 | D31: =+SUMIFS(PROVISIONES!G:G,PROVISIONES!$B:$B,"PENDIENTE") -> 255.2 | E31: =+PROVISIONES!$C$84 -> 0.51162791
A33: TOTAL PROVISIONES | B33: =+SUM(B31) -> 220 | C33: =+SUM(C31) -> 35.2 | D33: =+SUM(D31) -> 255.2 | E33: 0.4063
A35: RESUMEN UTILIDAD
A36: CONCEPTO | B36: MONTO | C36: PORCENTAJE
A37: SUMA DE INGRESOS | B37: =+F18 -> 700 | C37: =+SUM(C38:C40) -> 1
A38: SUMA DE EGRESOS | B38: =+B27+B33 -> 650 | C38: =+B38/B37 -> 0.92857143
A40: UTILIDAD | B40: =B37-B38 -> 50 | C40: =+B40/B37 -> 0.071428571

Sheet GASTOS
A1: Tipo de Gasto | B1: Status | C1: Método de Pago | D1: No. Factura | E1: Proveedor / Razón Social | F1: Concepto | G1: Sub-Total | H1: I.V.A | I1: Monto a Pagar | J1: Fecha de Pago
A2: RH | B2: PAGADO | C2: TRANSFERENCIA | D2: FAC 2265 | E2: CEDECOM SA DE CV | F2: PAGO DE SERVICIO INTERNET PARA STAND MEDTRONIC | G2: 100 | H2: =+G2*0.16 -> 16 | I2: =+SUM(G2:H2) -> 116 | J2: 45925
A3: COMBUSTIBLE / PEAJE | B3: PAGADO | C3: TRANSFERENCIA | D3: FAC 2265 | E3: CEDECOM SA DE CV | F3: PAGO DE SERVICIO INTERNET PARA STAND MEDTRONIC | G3: 50 | H3: =+G3*0.16 -> 8 | I3: =+SUM(G3:H3) -> 58 | J3: 45925
A4: RH | B4: PAGADO | C4: TRANSFERENCIA | D4: FAC 2265 | E4: CEDECOM SA DE CV | F4: PAGO DE SERVICIO INTERNET PARA STAND MEDTRONIC | G4: 120 | H4: =+G4*0.16 -> 19.2 | I4: =+SUM(G4:H4) -> 139.2 | J4: 45925
A5: MATERIALES | B5: PAGADO | C5: TRANSFERENCIA | D5: FAC 2265 | E5: CEDECOM SA DE CV | F5: PAGO DE SERVICIO INTERNET PARA STAND MEDTRONIC | G5: 160 | H5: =+G5*0.16 -> 25.6 | I5: =+SUM(G5:H5) -> 185.6 | J5: 45925

Sheet PROVISIONES
A1: Tipo de Provision | B1: EROGADA | C1: Proveedor / Razón Social | D1: Concepto | E1: Sub-Total | F1: I.V.A | G1: Monto a Pagar
A2: SP´S | B2: PENDIENTE | C2: CEDECOM SA DE CV | D2: PAGO DE SERVICIO INTERNET PARA STAND MEDTRONIC | E2: 100 | F2: =+E2*0.16 -> 16 | G2: =+SUM(E2:F2) -> 116
A3: COMBUSTIBLE / PEAJE | B3: PAGADA | C3: CEDECOM SA DE CV | D3: PAGO DE SERVICIO INTERNET PARA STAND MEDTRONIC | E3: 50 | F3: =+E3*0.16 -> 8 | G3: =+SUM(E3:F3) -> 58
A4: RH | B4: PENDIENTE | C4: CEDECOM SA DE CV | D4: PAGO DE SERVICIO INTERNET PARA STAND MEDTRONIC | E4: 120 | F4: =+E4*0.16 -> 19.2 | G4: =+SUM(E4:F4) -> 139.2
A5: MATERIALES | B5: PAGADA | C5: CEDECOM SA DE CV | D5: PAGO DE SERVICIO INTERNET PARA STAND MEDTRONIC | E5: 160 | F5: =+E5*0.16 -> 25.6 | G5: =+SUM(E5:F5) -> 185.6
D21: TOTAL DE PROVISIONES | E21: =+SUM(E2:E20) -> 430 | F21: =+SUM(F2:F20) -> 68.8 | G21: =+SUM(G2:G20) -> 498.8
A84: PENDIENTE | B84: =+SUMIFS(E1:E19,B1:B19,A84) -> 220 | C84: =+B84/E21 -> 0.51162791
A85: PAGADA | B85: =+SUMIFS(E2:E20,B2:B20,A85) -> 210
